Workbook
Name _____del1: {"Page1",#N/A,FALSE,"7979";"Page2",#N/A,FALSE,"7979";"Page3",#N/A,FALSE,"7979"}
Name ___del1: {"Page1",#N/A,FALSE,"7979";"Page2",#N/A,FALSE,"7979";"Page3",#N/A,FALSE,"7979"}
Name __123Graph_X: [1]Sheet3!#REF!
Name __del1: {"Page1",#N/A,FALSE,"7979";"Page2",#N/A,FALSE,"7979";"Page3",#N/A,FALSE,"7979"}
Name __FDS_HYPERLINK_TOGGLE_STATE__: "ON"
Name __IntlFixup: TRUE
Name _1_0_S: '[2]1999 BUDGET'!#REF!
Name _2_0_0_F: '[2]1999 BUDGET'!#REF!
Name _3_0_0_S: '[3]1999 BUDGET'!#REF!
Name _3_0_S: '[2]1999 BUDGET'!#REF!
Name _6_0_0_F: '[2]1999 BUDGET'!#REF!
Name _9_0_0_S: '[3]1999 BUDGET'!#REF!
Name _a2: {#N/A,#N/A,FALSE,"Sheet1"}
Name _a3: {#N/A,#N/A,FALSE,"Sheet1"}
Name _ATPRegress_Dlg_Results: {2;#N/A;"R13C16:R17C16";#N/A;"R13C14:R17C15";FALSE;FALSE;FALSE;95;#N/A;#N/A;"R13C19";#N/A;FALSE;FALSE;FALSE;FALSE;#N/A;"";#N/A;FALSE;"";"";#N/A;#N/A;#N/A}
Name _ATPRegress_Dlg_Types: {"EXCELHLP.HLP!1802";5;10;5;10;13;13;13;8;5;5;10;14;13;13;13;13;5;10;14;13;5;10;1;2;24}
Name _ATPRegress_Range4: "="
Name _ATPRegress_Range5: "="
Name _bdm.27B19874CAD649FA9C5B9A2AEE728DA3.edm: #REF!
Name _del1: {"Page1",#N/A,FALSE,"7979";"Page2",#N/A,FALSE,"7979";"Page3",#N/A,FALSE,"7979"}
Name _Dist_Values: #REF!
Name _Fil1: '[4]Current 9-02'!$A$6:$A$166
Name _Fill: #REF!
Name _Key1: #REF!
Name _Key10: #REF!
Name _Key2: #REF!
Name _Key5: #REF!
Name _Key6: #REF!
Name _Key8: #REF!
Name _Key9: '[4]Current 9-02'!#REF!
Name _Order1: 0
Name _Order2: 255
Name _Regression_Int: 1
Name _Regression_Out: #REF!
Name _Regression_X: #REF!
Name _Regression_Y: #REF!
Name _Sort: #REF!
Name _Table1_In1: #REF!
Name _Table1_Out: #REF!
Name _Table2_In1: #REF!
Name _Table2_Out: #REF!
Name aa: {"1999 Cash Budget",#N/A,FALSE,"99 Cash";"1999 Cash Budget YTD",#N/A,FALSE,"99 Cash";"1999 Cash Actual/Forcast",#N/A,FALSE,"99 Cash";"1999 Cash Actual/Forcast YTD",#N/A,FALSE,"99 Cash"}
Name aaa: #REF!
Name AAA_DOCTOPS: "AAA_SET"
Name AAA_duser: "OFF"
Name AAAA: #REF!
Name aaaa1: {"1999 Cash Budget",#N/A,FALSE,"99 Cash";"1999 Cash Budget YTD",#N/A,FALSE,"99 Cash";"1999 Cash Actual/Forcast",#N/A,FALSE,"99 Cash";"1999 Cash Actual/Forcast YTD",#N/A,FALSE,"99 Cash"}
Name aaaaa: {"Income Budget",#N/A,FALSE,"98 Income";"Running GAAP Budget Income",#N/A,FALSE,"98 Income";"GAAP Actual",#N/A,FALSE,"98 Income";"GAAP Varinance",#N/A,FALSE,"98 Income"}
Name aaaaaa: {"Cash Budget",#N/A,FALSE,"98 Cash";"Running Cash Budget",#N/A,FALSE,"98 Cash";"Actual Cash",#N/A,FALSE,"98 Cash";"Update Cash Budget",#N/A,FALSE,"98 Cash"}
Name aaaaaaa: {"Cash Budget",#N/A,FALSE,"98 Cash";"Running Cash Budget",#N/A,FALSE,"98 Cash";"Actual Cash",#N/A,FALSE,"98 Cash";"Update Cash Budget",#N/A,FALSE,"98 Cash"}
Name aaaaaaaa: {"Income Budget",#N/A,FALSE,"98 Income";"Running GAAP Budget Income",#N/A,FALSE,"98 Income";"GAAP Actual",#N/A,FALSE,"98 Income";"GAAP Varinance",#N/A,FALSE,"98 Income"}
Name aaaaaaaaaa: {"Cash Budget",#N/A,FALSE,"98 Cash";"Running Cash Budget",#N/A,FALSE,"98 Cash";"Actual Cash",#N/A,FALSE,"98 Cash";"Update Cash Budget",#N/A,FALSE,"98 Cash"}
Name AAB_Addin5: "AAB_Description for addin 5,Description for addin 5,Description for addin 5,Description for addin 5,Description for addin 5,Description for addin 5"
Name AAB_GSPPG: "AAB_Goldman Sachs PPG Chart Utilities 1.0g"
Name AccessDatabase: "C:\Due Diligence\Takeover.mdb"
Name Acq: [5]Control!$C$13
Name Acq_Acid_Multiplier: '[6]REG Seneca'!$C$169
Name Acq_Biodiesel_lbs_gallons: '[6]REG Seneca'!$C$170
Name Acq_Feedstock_Yield: '[6]REG Seneca'!$C$162
Name Acq_KOH_Multiplier: '[6]REG Seneca'!$C$168

Sheet Dashboard
C3: Cash Available to dividend CHART / Paid out vs reinvested stacked | U3: Capex Deployed | AM3: EPC Value
C15: 0 | D15: =1+C15 -> 1 | E15: =1+D15 -> 2 | F15: =1+E15 -> 3 | G15: =1+F15 -> 4 | H15: =1+G15 -> 5 | I15: =1+H15 -> 6 | J15: =1+I15 -> 7 | K15: =1+J15 -> 8 | ... R15: =1+Q15 -> 15 | U15: 0 | V15: =1+U15 -> 1 | W15: =1+V15 -> 2 | X15: =1+W15 -> 3 | Y15: =1+X15 -> 4 | Z15: =1+Y15 -> 5 | AA15: =1+Z15 -> 6 | AB15: =1+AA15 -> 7 | AC15: =1+AB15 -> 8 | ... AJ15: =1+AI15 -> 15 | AM15: 0 | AN15: =1+AM15 -> 1 | AO15: =1+AN15 -> 2 | AP15: =1+AO15 -> 3 | AQ15: =1+AP15 -> 4 | AR15: =1+AQ15 -> 5 | AS15: =1+AR15 -> 6 | AT15: =1+AS15 -> 7 | AU15: =1+AT15 -> 8 | ... BB15: =1+BA15 -> 15
A16: 0.27 | B16: Foundation | C16: =$A16*SUMIF('Project DIV'!E$3:E$200, "<>#N/A") -> 0 | D16: =$A16*SUMIF('Project DIV'!F$3:F$200, "<>#N/A") -> 19.200338 | E16: =$A16*SUMIF('Project DIV'!G$3:G$200, "<>#N/A") -> 29.42135 | F16: =$A16*SUMIF('Project DIV'!H$3:H$200, "<>#N/A") -> 159.4353 | G16: =$A16*SUMIF('Project DIV'!I$3:I$200, "<>#N/A") -> 217.42013 | H16: =$A16*SUMIF('Project DIV'!J$3:J$200, "<>#N/A") -> 249.49381 | I16: =$A16*SUMIF('Project DIV'!K$3:K$200, "<>#N/A") -> 288.65635 | J16: =$A16*SUMIF('Project DIV'!L$3:L$200, "<>#N/A") -> 297.24939 | ... R16: =$A16*SUMIF('Project DIV'!T$3:T$200, "<>#N/A") -> 343.02726 | T16: Nat Gas | U16: =SUMIFS('Project CAPEX'!E$3:E$200, 'Project CAPEX'!$B$3:$B$200, Dashboard!$T16)*(-1) -> 0 | V16: =SUMIFS('Project CAPEX'!F$3:F$200, 'Project CAPEX'!$B$3:$B$200, Dashboard!$T16)*(-1) -> 33.611111 | W16: =SUMIFS('Project CAPEX'!G$3:G$200, 'Project CAPEX'!$B$3:$B$200, Dashboard!$T16)*(-1) -> 36.666667 | X16: =SUMIFS('Project CAPEX'!H$3:H$200, 'Project CAPEX'!$B$3:$B$200, Dashboard!$T16)*(-1) -> 36.666667 | Y16: =SUMIFS('Project CAPEX'!I$3:I$200, 'Project CAPEX'!$B$3:$B$200, Dashboard!$T16)*(-1) -> 3.0555556 | Z16: =SUMIFS('Project CAPEX'!J$3:J$200, 'Project CAPEX'!$B$3:$B$200, Dashboard!$T16)*(-1) -> 0 | AA16: =SUMIFS('Project CAPEX'!K$3:K$200, 'Project CAPEX'!$B$3:$B$200, Dashboard!$T16)*(-1) -> 0 | AB16: =SUMIFS('Project CAPEX'!L$3:L$200, 'Project CAPEX'!$B$3:$B$200, Dashboard!$T16)*(-1) -> 0 | ... AJ16: =SUMIFS('Project CAPEX'!T$3:T$200, 'Project CAPEX'!$B$3:$B$200, Dashboard!$T16)*(-1) -> 0 | AL16: Nat Gas | AM16: =SUMIFS('Project EPC'!E:E, 'Project EPC'!$B:$B, Dashboard!$AL16) -> 0 | AN16: =SUMIFS('Project EPC'!F:F, 'Project EPC'!$B:$B, Dashboard!$AL16) -> 1.6805556 | AO16: =SUMIFS('Project EPC'!G:G, 'Project EPC'!$B:$B, Dashboard!$AL16) -> 1.8333333 | AP16: =SUMIFS('Project EPC'!H:H, 'Project EPC'!$B:$B, Dashboard!$AL16) -> 1.8333333 | AQ16: =SUMIFS('Project EPC'!I:I, 'Project EPC'!$B:$B, Dashboard!$AL16) -> 0.15277778 | AR16: =SUMIFS('Project EPC'!J:J, 'Project EPC'!$B:$B, Dashboard!$AL16) -> 0 | AS16: =SUMIFS('Project EPC'!K:K, 'Project EPC'!$B:$B, Dashboard!$AL16) -> 0 | AT16: =SUMIFS('Project EPC'!L:L, 'Project EPC'!$B:$B, Dashboard!$AL16) -> 0 | AU16: =SUMIFS('Project EPC'!M:M, 'Project EPC'!$B:$B, Dashboard!$AL16) -> 0 | AV16: =SUMIFS('Project EPC'!N:N, 'Project EPC'!$B:$B, Dashboard!$AL16) -> 0 | AW16: =SUMIFS('Project EPC'!O:O, 'Project EPC'!$B:$B, Dashboard!$AL16) -> 0 | AX16: =SUMIFS('Project EPC'!P:P, 'Project EPC'!$B:$B, Dashboard!$AL16) -> 0 | AY16: =SUMIFS('Project EPC'!Q:Q, 'Project EPC'!$B:$B, Dashboard!$AL16) -> 0 | AZ16: =SUMIFS('Project EPC'!R:R, 'Project EPC'!$B:$B, Dashboard!$AL16) -> 0 | BA16: =SUMIFS('Project EPC'!S:S, 'Project EPC'!$B:$B, Dashboard!$AL16) -> 0 | BB16: =SUMIFS('Project EPC'!T:T, 'Project EPC'!$B:$B, Dashboard!$AL16) -> 0
A17: =1-A16 -> 0.73 | B17: SENS | C17: =$A17*SUMIF('Project DIV'!E$3:E$200, "<>#N/A") -> 0 | D17: =$A17*SUMIF('Project DIV'!F$3:F$200, "<>#N/A") -> 51.912026 | E17: =$A17*SUMIF('Project DIV'!G$3:G$200, "<>#N/A") -> 79.546614 | F17: =$A17*SUMIF('Project DIV'!H$3:H$200, "<>#N/A") -> 431.06581 | G17: =$A17*SUMIF('Project DIV'!I$3:I$200, "<>#N/A") -> 587.83961 | H17: =$A17*SUMIF('Project DIV'!J$3:J$200, "<>#N/A") -> 674.55733 | I17: =$A17*SUMIF('Project DIV'!K$3:K$200, "<>#N/A") -> 780.44124 | J17: =$A17*SUMIF('Project DIV'!L$3:L$200, "<>#N/A") -> 803.67427 | ... R17: =$A17*SUMIF('Project DIV'!T$3:T$200, "<>#N/A") -> 927.44406 | T17: Solar | U17: =SUMIFS('Project CAPEX'!E$3:E$200, 'Project CAPEX'!$B$3:$B$200, Dashboard!$T17)*(-1) -> 51.333333 | V17: =SUMIFS('Project CAPEX'!F$3:F$200, 'Project CAPEX'!$B$3:$B$200, Dashboard!$T17)*(-1) -> 32.666667 | W17: =SUMIFS('Project CAPEX'!G$3:G$200, 'Project CAPEX'!$B$3:$B$200, Dashboard!$T17)*(-1) -> 0 | X17: =SUMIFS('Project CAPEX'!H$3:H$200, 'Project CAPEX'!$B$3:$B$200, Dashboard!$T17)*(-1) -> 0 | Y17: =SUMIFS('Project CAPEX'!I$3:I$200, 'Project CAPEX'!$B$3:$B$200, Dashboard!$T17)*(-1) -> 0 | Z17: =SUMIFS('Project CAPEX'!J$3:J$200, 'Project CAPEX'!$B$3:$B$200, Dashboard!$T17)*(-1) -> 0 | AA17: =SUMIFS('Project CAPEX'!K$3:K$200, 'Project CAPEX'!$B$3:$B$200, Dashboard!$T17)*(-1) -> 0 | AB17: =SUMIFS('Project CAPEX'!L$3:L$200, 'Project CAPEX'!$B$3:$B$200, Dashboard!$T17)*(-1) -> 0 | ... AJ17: =SUMIFS('Project CAPEX'!T$3:T$200, 'Project CAPEX'!$B$3:$B$200, Dashboard!$T17)*(-1) -> 0 | AL17: Solar | AM17: =SUMIFS('Project EPC'!E:E, 'Project EPC'!$B:$B, Dashboard!$AL17) -> 2.5666667 | AN17: =SUMIFS('Project EPC'!F:F, 'Project EPC'!$B:$B, Dashboard!$AL17) -> 1.6333333 | AO17: =SUMIFS('Project EPC'!G:G, 'Project EPC'!$B:$B, Dashboard!$AL17) -> 0 | AP17: =SUMIFS('Project EPC'!H:H, 'Project EPC'!$B:$B, Dashboard!$AL17) -> 0 | AQ17: =SUMIFS('Project EPC'!I:I, 'Project EPC'!$B:$B, Dashboard!$AL17) -> 0 | AR17: =SUMIFS('Project EPC'!J:J, 'Project EPC'!$B:$B, Dashboard!$AL17) -> 0 | AS17: =SUMIFS('Project EPC'!K:K, 'Project EPC'!$B:$B, Dashboard!$AL17) -> 0 | AT17: =SUMIFS('Project EPC'!L:L, 'Project EPC'!$B:$B, Dashboard!$AL17) -> 0 | AU17: =SUMIFS('Project EPC'!M:M, 'Project EPC'!$B:$B, Dashboard!$AL17) -> 0 | AV17: =SUMIFS('Project EPC'!N:N, 'Project EPC'!$B:$B, Dashboard!$AL17) -> 0 | AW17: =SUMIFS('Project EPC'!O:O, 'Project EPC'!$B:$B, Dashboard!$AL17) -> 0 | AX17: =SUMIFS('Project EPC'!P:P, 'Project EPC'!$B:$B, Dashboard!$AL17) -> 0 | AY17: =SUMIFS('Project EPC'!Q:Q, 'Project EPC'!$B:$B, Dashboard!$AL17) -> 0 | AZ17: =SUMIFS('Project EPC'!R:R, 'Project EPC'!$B:$B, Dashboard!$AL17) -> 0 | BA17: =SUMIFS('Project EPC'!S:S, 'Project EPC'!$B:$B, Dashboard!$AL17) -> 0 | BB17: =SUMIFS('Project EPC'!T:T, 'Project EPC'!$B:$B, Dashboard!$AL17) -> 0
T18: BESS | U18: =SUMIFS('Project CAPEX'!E$3:E$200, 'Project CAPEX'!$B$3:$B$200, Dashboard!$T18)*(-1) -> 0 | V18: =SUMIFS('Project CAPEX'!F$3:F$200, 'Project CAPEX'!$B$3:$B$200, Dashboard!$T18)*(-1) -> 52.708333 | W18: =SUMIFS('Project CAPEX'!G$3:G$200, 'Project CAPEX'!$B$3:$B$200, Dashboard!$T18)*(-1) -> 4.7916667 | X18: =SUMIFS('Project CAPEX'!H$3:H$200, 'Project CAPEX'!$B$3:$B$200, Dashboard!$T18)*(-1) -> 0 | Y18: =SUMIFS('Project CAPEX'!I$3:I$200, 'Project CAPEX'!$B$3:$B$200, Dashboard!$T18)*(-1) -> 0 | Z18: =SUMIFS('Project CAPEX'!J$3:J$200, 'Project CAPEX'!$B$3:$B$200, Dashboard!$T18)*(-1) -> 0 | AA18: =SUMIFS('Project CAPEX'!K$3:K$200, 'Project CAPEX'!$B$3:$B$200, Dashboard!$T18)*(-1) -> 0 | AB18: =SUMIFS('Project CAPEX'!L$3:L$200, 'Project CAPEX'!$B$3:$B$200, Dashboard!$T18)*(-1) -> 0 | ... AJ18: =SUMIFS('Project CAPEX'!T$3:T$200, 'Project CAPEX'!$B$3:$B$200, Dashboard!$T18)*(-1) -> 0 | AL18: BESS | AM18: =SUMIFS('Project EPC'!E:E, 'Project EPC'!$B:$B, Dashboard!$AL18) -> 0 | AN18: =SUMIFS('Project EPC'!F:F, 'Project EPC'!$B:$B, Dashboard!$AL18) -> 2.6354167 | AO18: =SUMIFS('Project EPC'!G:G, 'Project EPC'!$B:$B, Dashboard!$AL18) -> 0.23958333 | AP18: =SUMIFS('Project EPC'!H:H, 'Project EPC'!$B:$B, Dashboard!$AL18) -> 0 | AQ18: =SUMIFS('Project EPC'!I:I, 'Project EPC'!$B:$B, Dashboard!$AL18) -> 0 | AR18: =SUMIFS('Project EPC'!J:J, 'Project EPC'!$B:$B, Dashboard!$AL18) -> 0 | AS18: =SUMIFS('Project EPC'!K:K, 'Project EPC'!$B:$B, Dashboard!$AL18) -> 0 | AT18: =SUMIFS('Project EPC'!L:L, 'Project EPC'!$B:$B, Dashboard!$AL18) -> 0 | AU18: =SUMIFS('Project EPC'!M:M, 'Project EPC'!$B:$B, Dashboard!$AL18) -> 0 | AV18: =SUMIFS('Project EPC'!N:N, 'Project EPC'!$B:$B, Dashboard!$AL18) -> 0 | AW18: =SUMIFS('Project EPC'!O:O, 'Project EPC'!$B:$B, Dashboard!$AL18) -> 0 | AX18: =SUMIFS('Project EPC'!P:P, 'Project EPC'!$B:$B, Dashboard!$AL18) -> 0 | AY18: =SUMIFS('Project EPC'!Q:Q, 'Project EPC'!$B:$B, Dashboard!$AL18) -> 0 | AZ18: =SUMIFS('Project EPC'!R:R, 'Project EPC'!$B:$B, Dashboard!$AL18) -> 0 | BA18: =SUMIFS('Project EPC'!S:S, 'Project EPC'!$B:$B, Dashboard!$AL18) -> 0 | BB18: =SUMIFS('Project EPC'!T:T, 'Project EPC'!$B:$B, Dashboard!$AL18) -> 0
B19: Cumulative | C19: =SUM(C16:C17) -> 0 | D19: =SUM(D16:D17)+C19 -> 71.112365 | E19: =SUM(E16:E17)+D19 -> 180.08033 | F19: =SUM(F16:F17)+E19 -> 770.58144 | G19: =SUM(G16:G17)+F19 -> 1575.8412 | H19: =SUM(H16:H17)+G19 -> 2499.8923 | I19: =SUM(I16:I17)+H19 -> 3568.9899 | J19: =SUM(J16:J17)+I19 -> 4669.9136 | K19: =SUM(K16:K17)+J19 -> 5790.641 | ... R19: =SUM(R16:R17)+Q19 -> 14223.273 | T19: Carbon | U19: =SUMIFS('Project CAPEX'!E$3:E$200, 'Project CAPEX'!$B$3:$B$200, Dashboard!$T19)*(-1) -> 0 | V19: =SUMIFS('Project CAPEX'!F$3:F$200, 'Project CAPEX'!$B$3:$B$200, Dashboard!$T19)*(-1) -> 330 | W19: =SUMIFS('Project CAPEX'!G$3:G$200, 'Project CAPEX'!$B$3:$B$200, Dashboard!$T19)*(-1) -> 360 | X19: =SUMIFS('Project CAPEX'!H$3:H$200, 'Project CAPEX'!$B$3:$B$200, Dashboard!$T19)*(-1) -> 360 | Y19: =SUMIFS('Project CAPEX'!I$3:I$200, 'Project CAPEX'!$B$3:$B$200, Dashboard!$T19)*(-1) -> 360 | Z19: =SUMIFS('Project CAPEX'!J$3:J$200, 'Project CAPEX'!$B$3:$B$200, Dashboard!$T19)*(-1) -> 30 | AA19: =SUMIFS('Project CAPEX'!K$3:K$200, 'Project CAPEX'!$B$3:$B$200, Dashboard!$T19)*(-1) -> 0 | AB19: =SUMIFS('Project CAPEX'!L$3:L$200, 'Project CAPEX'!$B$3:$B$200, Dashboard!$T19)*(-1) -> 0 | ... AJ19: =SUMIFS('Project CAPEX'!T$3:T$200, 'Project CAPEX'!$B$3:$B$200, Dashboard!$T19)*(-1) -> 0 | AL19: Carbon | AM19: =SUMIFS('Project EPC'!E:E, 'Project EPC'!$B:$B, Dashboard!$AL19) -> 0 | AN19: =SUMIFS('Project EPC'!F:F, 'Project EPC'!$B:$B, Dashboard!$AL19) -> 16.5 | AO19: =SUMIFS('Project EPC'!G:G, 'Project EPC'!$B:$B, Dashboard!$AL19) -> 18 | AP19: =SUMIFS('Project EPC'!H:H, 'Project EPC'!$B:$B, Dashboard!$AL19) -> 18 | AQ19: =SUMIFS('Project EPC'!I:I, 'Project EPC'!$B:$B, Dashboard!$AL19) -> 18 | AR19: =SUMIFS('Project EPC'!J:J, 'Project EPC'!$B:$B, Dashboard!$AL19) -> 1.5 | AS19: =SUMIFS('Project EPC'!K:K, 'Project EPC'!$B:$B, Dashboard!$AL19) -> 0 | AT19: =SUMIFS('Project EPC'!L:L, 'Project EPC'!$B:$B, Dashboard!$AL19) -> 0 | AU19: =SUMIFS('Project EPC'!M:M, 'Project EPC'!$B:$B, Dashboard!$AL19) -> 0 | AV19: =SUMIFS('Project EPC'!N:N, 'Project EPC'!$B:$B, Dashboard!$AL19) -> 0 | AW19: =SUMIFS('Project EPC'!O:O, 'Project EPC'!$B:$B, Dashboard!$AL19) -> 0 | AX19: =SUMIFS('Project EPC'!P:P, 'Project EPC'!$B:$B, Dashboard!$AL19) -> 0 | AY19: =SUMIFS('Project EPC'!Q:Q, 'Project EPC'!$B:$B, Dashboard!$AL19) -> 0 | AZ19: =SUMIFS('Project EPC'!R:R, 'Project EPC'!$B:$B, Dashboard!$AL19) -> 0 | BA19: =SUMIFS('Project EPC'!S:S, 'Project EPC'!$B:$B, Dashboard!$AL19) -> 0 | BB19: =SUMIFS('Project EPC'!T:T, 'Project EPC'!$B:$B, Dashboard!$AL19) -> 0
B20: C - Foundation | C20: =C16 -> 0 | D20: =D16+C20 -> 19.200338 | E20: =E16+D20 -> 48.621689 | F20: =F16+E20 -> 208.05699 | G20: =G16+F20 -> 425.47712 | H20: =H16+G20 -> 674.97092 | I20: =I16+H20 -> 963.62727 | J20: =J16+I20 -> 1260.8767 | K20: =K16+J20 -> 1563.4731 | ... R20: =R16+Q20 -> 3840.2838 | T20: SENS - Coal | U20: =SUMIFS('Project CAPEX'!E$3:E$200, 'Project CAPEX'!$B$3:$B$200, Dashboard!$T20)*(-1) -> 0 | V20: =SUMIFS('Project CAPEX'!F$3:F$200, 'Project CAPEX'!$B$3:$B$200, Dashboard!$T20)*(-1) -> 0 | W20: =SUMIFS('Project CAPEX'!G$3:G$200, 'Project CAPEX'!$B$3:$B$200, Dashboard!$T20)*(-1) -> 660 | X20: =SUMIFS('Project CAPEX'!H$3:H$200, 'Project CAPEX'!$B$3:$B$200, Dashboard!$T20)*(-1) -> 60 | Y20: =SUMIFS('Project CAPEX'!I$3:I$200, 'Project CAPEX'!$B$3:$B$200, Dashboard!$T20)*(-1) -> 0 | Z20: =SUMIFS('Project CAPEX'!J$3:J$200, 'Project CAPEX'!$B$3:$B$200, Dashboard!$T20)*(-1) -> 0 | AA20: =SUMIFS('Project CAPEX'!K$3:K$200, 'Project CAPEX'!$B$3:$B$200, Dashboard!$T20)*(-1) -> 0 | AB20: =SUMIFS('Project CAPEX'!L$3:L$200, 'Project CAPEX'!$B$3:$B$200, Dashboard!$T20)*(-1) -> 0 | ... AJ20: =SUMIFS('Project CAPEX'!T$3:T$200, 'Project CAPEX'!$B$3:$B$200, Dashboard!$T20)*(-1) -> 0 | AL20: SENS - Coal | AM20: =SUMIFS('Project EPC'!E:E, 'Project EPC'!$B:$B, Dashboard!$AL20) -> 0 | AN20: =SUMIFS('Project EPC'!F:F, 'Project EPC'!$B:$B, Dashboard!$AL20) -> 0 | AO20: =SUMIFS('Project EPC'!G:G, 'Project EPC'!$B:$B, Dashboard!$AL20) -> 33 | AP20: =SUMIFS('Project EPC'!H:H, 'Project EPC'!$B:$B, Dashboard!$AL20) -> 3 | AQ20: =SUMIFS('Project EPC'!I:I, 'Project EPC'!$B:$B, Dashboard!$AL20) -> 0 | AR20: =SUMIFS('Project EPC'!J:J, 'Project EPC'!$B:$B, Dashboard!$AL20) -> 0 | AS20: =SUMIFS('Project EPC'!K:K, 'Project EPC'!$B:$B, Dashboard!$AL20) -> 0 | AT20: =SUMIFS('Project EPC'!L:L, 'Project EPC'!$B:$B, Dashboard!$AL20) -> 0 | AU20: =SUMIFS('Project EPC'!M:M, 'Project EPC'!$B:$B, Dashboard!$AL20) -> 0 | AV20: =SUMIFS('Project EPC'!N:N, 'Project EPC'!$B:$B, Dashboard!$AL20) -> 0 | AW20: =SUMIFS('Project EPC'!O:O, 'Project EPC'!$B:$B, Dashboard!$AL20) -> 0 | AX20: =SUMIFS('Project EPC'!P:P, 'Project EPC'!$B:$B, Dashboard!$AL20) -> 0 | AY20: =SUMIFS('Project EPC'!Q:Q, 'Project EPC'!$B:$B, Dashboard!$AL20) -> 0 | AZ20: =SUMIFS('Project EPC'!R:R, 'Project EPC'!$B:$B, Dashboard!$AL20) -> 0 | BA20: =SUMIFS('Project EPC'!S:S, 'Project EPC'!$B:$B, Dashboard!$AL20) -> 0 | BB20: =SUMIFS('Project EPC'!T:T, 'Project EPC'!$B:$B, Dashboard!$AL20) -> 0
B21: C - SENS | C21: =C17 -> 0 | D21: =D17+C21 -> 51.912026 | E21: =E17+D21 -> 131.45864 | F21: =F17+E21 -> 562.52445 | G21: =G17+F21 -> 1150.3641 | H21: =H17+G21 -> 1824.9214 | I21: =I17+H21 -> 2605.3626 | J21: =J17+I21 -> 3409.0369 | K21: =K17+J21 -> 4227.1679 | ... R21: =R17+Q21 -> 10382.99 | T21: SENS - Tires | U21: =SUMIFS('Project CAPEX'!E$3:E$200, 'Project CAPEX'!$B$3:$B$200, Dashboard!$T21)*(-1) -> 103.125 | V21: =SUMIFS('Project CAPEX'!F$3:F$200, 'Project CAPEX'!$B$3:$B$200, Dashboard!$T21)*(-1) -> 9.375 | W21: =SUMIFS('Project CAPEX'!G$3:G$200, 'Project CAPEX'!$B$3:$B$200, Dashboard!$T21)*(-1) -> 0 | X21: =SUMIFS('Project CAPEX'!H$3:H$200, 'Project CAPEX'!$B$3:$B$200, Dashboard!$T21)*(-1) -> 0 | Y21: =SUMIFS('Project CAPEX'!I$3:I$200, 'Project CAPEX'!$B$3:$B$200, Dashboard!$T21)*(-1) -> 0 | Z21: =SUMIFS('Project CAPEX'!J$3:J$200, 'Project CAPEX'!$B$3:$B$200, Dashboard!$T21)*(-1) -> 0 | AA21: =SUMIFS('Project CAPEX'!K$3:K$200, 'Project CAPEX'!$B$3:$B$200, Dashboard!$T21)*(-1) -> 0 | AB21: =SUMIFS('Project CAPEX'!L$3:L$200, 'Project CAPEX'!$B$3:$B$200, Dashboard!$T21)*(-1) -> 0 | ... AJ21: =SUMIFS('Project CAPEX'!T$3:T$200, 'Project CAPEX'!$B$3:$B$200, Dashboard!$T21)*(-1) -> 0 | AL21: SENS - Tires | AM21: =SUMIFS('Project EPC'!E:E, 'Project EPC'!$B:$B, Dashboard!$AL21) -> 5.15625 | AN21: =SUMIFS('Project EPC'!F:F, 'Project EPC'!$B:$B, Dashboard!$AL21) -> 0.46875 | AO21: =SUMIFS('Project EPC'!G:G, 'Project EPC'!$B:$B, Dashboard!$AL21) -> 0 | AP21: =SUMIFS('Project EPC'!H:H, 'Project EPC'!$B:$B, Dashboard!$AL21) -> 0 | AQ21: =SUMIFS('Project EPC'!I:I, 'Project EPC'!$B:$B, Dashboard!$AL21) -> 0 | AR21: =SUMIFS('Project EPC'!J:J, 'Project EPC'!$B:$B, Dashboard!$AL21) -> 0 | AS21: =SUMIFS('Project EPC'!K:K, 'Project EPC'!$B:$B, Dashboard!$AL21) -> 0 | AT21: =SUMIFS('Project EPC'!L:L, 'Project EPC'!$B:$B, Dashboard!$AL21) -> 0 | AU21: =SUMIFS('Project EPC'!M:M, 'Project EPC'!$B:$B, Dashboard!$AL21) -> 0 | AV21: =SUMIFS('Project EPC'!N:N, 'Project EPC'!$B:$B, Dashboard!$AL21) -> 0 | AW21: =SUMIFS('Project EPC'!O:O, 'Project EPC'!$B:$B, Dashboard!$AL21) -> 0 | AX21: =SUMIFS('Project EPC'!P:P, 'Project EPC'!$B:$B, Dashboard!$AL21) -> 0 | AY21: =SUMIFS('Project EPC'!Q:Q, 'Project EPC'!$B:$B, Dashboard!$AL21) -> 0 | AZ21: =SUMIFS('Project EPC'!R:R, 'Project EPC'!$B:$B, Dashboard!$AL21) -> 0 | BA21: =SUMIFS('Project EPC'!S:S, 'Project EPC'!$B:$B, Dashboard!$AL21) -> 0 | BB21: =SUMIFS('Project EPC'!T:T, 'Project EPC'!$B:$B, Dashboard!$AL21) -> 0
C23: CAPEX DEPLOYED | F23: ACTIVE PROCESSORS | I23: TOTAL PROJECTS | L23: INSTALLED CAPACITY (MW) | O23: DIVIDENDS PAID | T23: CAPEX Available | U23: ='Project List References'!D13 -> 2057.1429 | V23: =IF(V26="yes", $U$23+U24, 0)+U25 -> 1902.6845 | W23: =IF(W26="yes", $U$23+V24, 0)+V25 -> 1444.3234 | X23: =IF(X26="yes", $U$23+W24, 0)+W25 -> 382.86508 | Y23: =IF(Y26="yes", $U$23+X24, 0)+X25 -> 0 | Z23: =IF(Z26="yes", $U$23+Y24, 0)+Y25 -> 0 | AA23: =IF(AA26="yes", $U$23+Z24, 0)+Z25 -> 0 | AB23: =IF(AB26="yes", $U$23+AA24, 0)+AA25 -> 0 | AC23: =IF(AC26="yes", $U$23+AB24, 0)+AB25 -> 0 | ... AJ23: =IF(AJ26="yes", $U$23+AI24, 0)+AI25 -> 0
C24: =SUM(U16:AJ21) -> 2524 | F24: =AJ66+AJ67 -> 42 | I24: =COUNTIF('Project Master Sheet'!A3:A3000, "*") -> 0 | L24: =SUM(BB84:BB87) -> 620 | O24: =R19 -> 14223.273 | T24: New Capex Required | U24: =IF(U25=0,SUM(U16:U21)-U23, 0) -> 0 | V24: =IF(V25=0,SUM(V16:V21)-V23, 0) -> 0 | W24: =IF(W25=0,SUM(W16:W21)-W23, 0) -> 0 | X24: =IF(X25=0,SUM(X16:X21)-X23, 0) -> 73.801587 | Y24: =IF(Y25=0,SUM(Y16:Y21)-Y23, 0) -> 363.05556 | Z24: =IF(Z25=0,SUM(Z16:Z21)-Z23, 0) -> 30 | AA24: =IF(AA25=0,SUM(AA16:AA21)-AA23, 0) -> 0 | AB24: =IF(AB25=0,SUM(AB16:AB21)-AB23, 0) -> 0 | ... AJ24: =IF(AJ25=0,SUM(AJ16:AJ21)-AJ23, 0) -> 0
T25: Unused CapEx | U25: =IF(U23-SUM(U16:U21)<0, 0, U23-SUM(U16:U21)) -> 1902.6845 | V25: =IF(V23-SUM(V16:V21)<0, 0, V23-SUM(V16:V21)) -> 1444.3234 | W25: =IF(W23-SUM(W16:W21)<0, 0, W23-SUM(W16:W21)) -> 382.86508 | X25: =IF(X23-SUM(X16:X21)<0, 0, X23-SUM(X16:X21)) -> 0 | Y25: =IF(Y23-SUM(Y16:Y21)<0, 0, Y23-SUM(Y16:Y21)) -> 0 | Z25: =IF(Z23-SUM(Z16:Z21)<0, 0, Z23-SUM(Z16:Z21)) -> 0 | AA25: =IF(AA23-SUM(AA16:AA21)<0, 0, AA23-SUM(AA16:AA21)) -> 0 | AB25: =IF(AB23-SUM(AB16:AB21)<0, 0, AB23-SUM(AB16:AB21)) -> 0 | ... AJ25: =IF(AJ23-SUM(AJ16:AJ21)<0, 0, AJ23-SUM(AJ16:AJ21)) -> 0
C26: CAPEX AVAILABLE | F26: PEAK PROCESS VOL - TIRES | I26: PEAK PROCESS VOL - COAL | L26: COAL REQ FOR GEN | O26: EPC MARGIN | T26: Roll SBLC | V26: No | W26: No | X26: No | Y26: No | Z26: No | AA26: No | AB26: No | AC26: No | AD26: No | AE26: No | AF26: No | AG26: No | AH26: No | AI26: No | AJ26: No
C27: =AJ23 -> 0 | F27: =R67 -> 0.0883008 | I27: =R66 -> 5.298048 | L27: =R68 -> 5.2257992 | O27: =SUM(AM16:BB21) -> 126.2 | T27: New SBLC Value | U27: =U24*0.1 -> 0 | V27: =V24*0.1 -> 0 | W27: =W24*0.1 -> 0 | X27: =X24*0.1 -> 7.3801587 | Y27: =Y24*0.1 -> 36.305556 | Z27: =Z24*0.1 -> 3 | AA27: =AA24*0.1 -> 0 | AB27: =AB24*0.1 -> 0 | ... AJ27: =AJ24*0.1 -> 0
C32: Opex | U32: Net
AM34: Asset Value
C44: 0 | D44: =1+C44 -> 1 | E44: =1+D44 -> 2 | F44: =1+E44 -> 3 | G44: =1+F44 -> 4 | H44: =1+G44 -> 5 | I44: =1+H44 -> 6 | J44: =1+I44 -> 7 | K44: =1+J44 -> 8 | ... R44: =1+Q44 -> 15 | U44: 0 | V44: =1+U44 -> 1 | W44: =1+V44 -> 2 | X44: =1+W44 -> 3 | Y44: =1+X44 -> 4 | Z44: =1+Y44 -> 5 | AA44: =1+Z44 -> 6 | AB44: =1+AA44 -> 7 | AC44: =1+AB44 -> 8 | ... AJ44: =1+AI44 -> 15 | AM44: 0 | AN44: =1+AM44 -> 1 | AO44: =1+AN44 -> 2 | AP44: =1+AO44 -> 3 | AQ44: =1+AP44 -> 4 | AR44: =1+AQ44 -> 5 | AS44: =1+AR44 -> 6 | AT44: =1+AS44 -> 7 | AU44: =1+AT44 -> 8 | ... BB44: =1+BA44 -> 15
B45: Nat Gas | C45: =SUMIFS('Project OPEX'!E$3:E$200, 'Project OPEX'!$B$3:$B$200, Dashboard!$B45) -> 0 | D45: =SUMIFS('Project OPEX'!F$3:F$200, 'Project OPEX'!$B$3:$B$200, Dashboard!$B45) -> 0 | E45: =SUMIFS('Project OPEX'!G$3:G$200, 'Project OPEX'!$B$3:$B$200, Dashboard!$B45) -> 0 | F45: =SUMIFS('Project OPEX'!H$3:H$200, 'Project OPEX'!$B$3:$B$200, Dashboard!$B45) -> 0 | G45: =SUMIFS('Project OPEX'!I$3:I$200, 'Project OPEX'!$B$3:$B$200, Dashboard!$B45) -> 14.790982 | H45: =SUMIFS('Project OPEX'!J$3:J$200, 'Project OPEX'!$B$3:$B$200, Dashboard!$B45) -> 22.23766 | I45: =SUMIFS('Project OPEX'!K$3:K$200, 'Project OPEX'!$B$3:$B$200, Dashboard!$B45) -> 22.239182 | J45: =SUMIFS('Project OPEX'!L$3:L$200, 'Project OPEX'!$B$3:$B$200, Dashboard!$B45) -> 22.242415 | ... R45: =SUMIFS('Project OPEX'!T$3:T$200, 'Project OPEX'!$B$3:$B$200, Dashboard!$B45) -> 22.335788 | T45: Nat Gas | U45: =SUMIFS('Project NET'!E$3:E$200, 'Project NET'!$B$3:$B$200, Dashboard!$T45) -> 0 | V45: =SUMIFS('Project NET'!F$3:F$200, 'Project NET'!$B$3:$B$200, Dashboard!$T45) -> 0 | W45: =SUMIFS('Project NET'!G$3:G$200, 'Project NET'!$B$3:$B$200, Dashboard!$T45) -> 0 | X45: =SUMIFS('Project NET'!H$3:H$200, 'Project NET'!$B$3:$B$200, Dashboard!$T45) -> 0 | Y45: =SUMIFS('Project NET'!I$3:I$200, 'Project NET'!$B$3:$B$200, Dashboard!$T45) -> 16.851287 | Z45: =SUMIFS('Project NET'!J$3:J$200, 'Project NET'!$B$3:$B$200, Dashboard!$T45) -> 26.17501 | AA45: =SUMIFS('Project NET'!K$3:K$200, 'Project NET'!$B$3:$B$200, Dashboard!$T45) -> 27.018289 | AB45: =SUMIFS('Project NET'!L$3:L$200, 'Project NET'!$B$3:$B$200, Dashboard!$T45) -> 27.8746 | ... AJ45: =SUMIFS('Project NET'!T$3:T$200, 'Project NET'!$B$3:$B$200, Dashboard!$T45) -> 35.220106 | AL45: Nat Gas | AM45: =SUMIFS('Project ASSET'!E$3:E$200, 'Project ASSET'!$B$3:$B$200, $AL45) -> 0 | AN45: =SUMIFS('Project ASSET'!F$3:F$200, 'Project ASSET'!$B$3:$B$200, $AL45) -> 33.611111 | AO45: =SUMIFS('Project ASSET'!G$3:G$200, 'Project ASSET'!$B$3:$B$200, $AL45) -> 70.277778 | AP45: =SUMIFS('Project ASSET'!H$3:H$200, 'Project ASSET'!$B$3:$B$200, $AL45) -> 106.94444 | AQ45: =SUMIFS('Project ASSET'!I$3:I$200, 'Project ASSET'!$B$3:$B$200, $AL45) -> 110 | AR45: =SUMIFS('Project ASSET'!J$3:J$200, 'Project ASSET'!$B$3:$B$200, $AL45) -> 105.82 | AS45: =SUMIFS('Project ASSET'!K$3:K$200, 'Project ASSET'!$B$3:$B$200, $AL45) -> 101.64 | AT45: =SUMIFS('Project ASSET'!L$3:L$200, 'Project ASSET'!$B$3:$B$200, $AL45) -> 97.46 | ... BB45: =SUMIFS('Project ASSET'!T$3:T$200, 'Project ASSET'!$B$3:$B$200, $AL45) -> 64.02
B46: Solar | C46: =SUMIFS('Project OPEX'!E$3:E$200, 'Project OPEX'!$B$3:$B$200, Dashboard!$B46) -> 0 | D46: =SUMIFS('Project OPEX'!F$3:F$200, 'Project OPEX'!$B$3:$B$200, Dashboard!$B46) -> 0.86216381 | E46: =SUMIFS('Project OPEX'!G$3:G$200, 'Project OPEX'!$B$3:$B$200, Dashboard!$B46) -> 0.88802872 | F46: =SUMIFS('Project OPEX'!H$3:H$200, 'Project OPEX'!$B$3:$B$200, Dashboard!$B46) -> 0.91466958 | G46: =SUMIFS('Project OPEX'!I$3:I$200, 'Project OPEX'!$B$3:$B$200, Dashboard!$B46) -> 0.94210967 | H46: =SUMIFS('Project OPEX'!J$3:J$200, 'Project OPEX'!$B$3:$B$200, Dashboard!$B46) -> 0.97037296 | I46: =SUMIFS('Project OPEX'!K$3:K$200, 'Project OPEX'!$B$3:$B$200, Dashboard!$B46) -> 0.99948415 | J46: =SUMIFS('Project OPEX'!L$3:L$200, 'Project OPEX'!$B$3:$B$200, Dashboard!$B46) -> 1.0294687 | ... R46: =SUMIFS('Project OPEX'!T$3:T$200, 'Project OPEX'!$B$3:$B$200, Dashboard!$B46) -> 1.3041001 | T46: Solar | U46: =SUMIFS('Project NET'!E$3:E$200, 'Project NET'!$B$3:$B$200, Dashboard!$T46) -> 0 | V46: =SUMIFS('Project NET'!F$3:F$200, 'Project NET'!$B$3:$B$200, Dashboard!$T46) -> 1.6396922 | W46: =SUMIFS('Project NET'!G$3:G$200, 'Project NET'!$B$3:$B$200, Dashboard!$T46) -> 6.7103049 | X46: =SUMIFS('Project NET'!H$3:H$200, 'Project NET'!$B$3:$B$200, Dashboard!$T46) -> 6.7581277 | Y46: =SUMIFS('Project NET'!I$3:I$200, 'Project NET'!$B$3:$B$200, Dashboard!$T46) -> 6.8056834 | Z46: =SUMIFS('Project NET'!J$3:J$200, 'Project NET'!$B$3:$B$200, Dashboard!$T46) -> 6.8529473 | AA46: =SUMIFS('Project NET'!K$3:K$200, 'Project NET'!$B$3:$B$200, Dashboard!$T46) -> 6.899894 | AB46: =SUMIFS('Project NET'!L$3:L$200, 'Project NET'!$B$3:$B$200, Dashboard!$T46) -> 6.9464969 | ... AJ46: =SUMIFS('Project NET'!T$3:T$200, 'Project NET'!$B$3:$B$200, Dashboard!$T46) -> 7.3034688 | AL46: Solar | AM46: =SUMIFS('Project ASSET'!E$3:E$200, 'Project ASSET'!$B$3:$B$200, $AL46) -> 51.333333 | AN46: =SUMIFS('Project ASSET'!F$3:F$200, 'Project ASSET'!$B$3:$B$200, $AL46) -> 84 | AO46: =SUMIFS('Project ASSET'!G$3:G$200, 'Project ASSET'!$B$3:$B$200, $AL46) -> 80.808 | AP46: =SUMIFS('Project ASSET'!H$3:H$200, 'Project ASSET'!$B$3:$B$200, $AL46) -> 77.616 | AQ46: =SUMIFS('Project ASSET'!I$3:I$200, 'Project ASSET'!$B$3:$B$200, $AL46) -> 74.424 | AR46: =SUMIFS('Project ASSET'!J$3:J$200, 'Project ASSET'!$B$3:$B$200, $AL46) -> 71.232 | AS46: =SUMIFS('Project ASSET'!K$3:K$200, 'Project ASSET'!$B$3:$B$200, $AL46) -> 68.04 | AT46: =SUMIFS('Project ASSET'!L$3:L$200, 'Project ASSET'!$B$3:$B$200, $AL46) -> 64.848 | ... BB46: =SUMIFS('Project ASSET'!T$3:T$200, 'Project ASSET'!$B$3:$B$200, $AL46) -> 39.312
B47: BESS | C47: =SUMIFS('Project OPEX'!E$3:E$200, 'Project OPEX'!$B$3:$B$200, Dashboard!$B47) -> 0 | D47: =SUMIFS('Project OPEX'!F$3:F$200, 'Project OPEX'!$B$3:$B$200, Dashboard!$B47) -> 0 | E47: =SUMIFS('Project OPEX'!G$3:G$200, 'Project OPEX'!$B$3:$B$200, Dashboard!$B47) -> 0.26 | F47: =SUMIFS('Project OPEX'!H$3:H$200, 'Project OPEX'!$B$3:$B$200, Dashboard!$B47) -> 0.2678 | G47: =SUMIFS('Project OPEX'!I$3:I$200, 'Project OPEX'!$B$3:$B$200, Dashboard!$B47) -> 0.275834 | H47: =SUMIFS('Project OPEX'!J$3:J$200, 'Project OPEX'!$B$3:$B$200, Dashboard!$B47) -> 0.28410902 | I47: =SUMIFS('Project OPEX'!K$3:K$200, 'Project OPEX'!$B$3:$B$200, Dashboard!$B47) -> 0.29263229 | J47: =SUMIFS('Project OPEX'!L$3:L$200, 'Project OPEX'!$B$3:$B$200, Dashboard!$B47) -> 0.30141126 | ... R47: =SUMIFS('Project OPEX'!T$3:T$200, 'Project OPEX'!$B$3:$B$200, Dashboard!$B47) -> 0.38181877 | T47: BESS | U47: =SUMIFS('Project NET'!E$3:E$200, 'Project NET'!$B$3:$B$200, Dashboard!$T47) -> 0 | V47: =SUMIFS('Project NET'!F$3:F$200, 'Project NET'!$B$3:$B$200, Dashboard!$T47) -> 0 | W47: =SUMIFS('Project NET'!G$3:G$200, 'Project NET'!$B$3:$B$200, Dashboard!$T47) -> 2.462244 | X47: =SUMIFS('Project NET'!H$3:H$200, 'Project NET'!$B$3:$B$200, Dashboard!$T47) -> 3.0531568 | Y47: =SUMIFS('Project NET'!I$3:I$200, 'Project NET'!$B$3:$B$200, Dashboard!$T47) -> 3.1115419 | Z47: =SUMIFS('Project NET'!J$3:J$200, 'Project NET'!$B$3:$B$200, Dashboard!$T47) -> 3.1710144 | AA47: =SUMIFS('Project NET'!K$3:K$200, 'Project NET'!$B$3:$B$200, Dashboard!$T47) -> 3.2315936 | AB47: =SUMIFS('Project NET'!L$3:L$200, 'Project NET'!$B$3:$B$200, Dashboard!$T47) -> 3.2932992 | ... AJ47: =SUMIFS('Project NET'!T$3:T$200, 'Project NET'!$B$3:$B$200, Dashboard!$T47) -> 3.8299574 | AL47: BESS | AM47: =SUMIFS('Project ASSET'!E$3:E$200, 'Project ASSET'!$B$3:$B$200, $AL47) -> 0 | AN47: =SUMIFS('Project ASSET'!F$3:F$200, 'Project ASSET'!$B$3:$B$200, $AL47) -> 52.708333 | AO47: =SUMIFS('Project ASSET'!G$3:G$200, 'Project ASSET'!$B$3:$B$200, $AL47) -> 57.5 | AP47: =SUMIFS('Project ASSET'!H$3:H$200, 'Project ASSET'!$B$3:$B$200, $AL47) -> 55.315 | AQ47: =SUMIFS('Project ASSET'!I$3:I$200, 'Project ASSET'!$B$3:$B$200, $AL47) -> 53.13 | AR47: =SUMIFS('Project ASSET'!J$3:J$200, 'Project ASSET'!$B$3:$B$200, $AL47) -> 50.945 | AS47: =SUMIFS('Project ASSET'!K$3:K$200, 'Project ASSET'!$B$3:$B$200, $AL47) -> 48.76 | AT47: =SUMIFS('Project ASSET'!L$3:L$200, 'Project ASSET'!$B$3:$B$200, $AL47) -> 46.575 | ... BB47: =SUMIFS('Project ASSET'!T$3:T$200, 'Project ASSET'!$B$3:$B$200, $AL47) -> 29.095
B48: Carbon | C48: =SUMIFS('Project OPEX'!E$3:E$200, 'Project OPEX'!$B$3:$B$200, Dashboard!$B48) -> 0 | D48: =SUMIFS('Project OPEX'!F$3:F$200, 'Project OPEX'!$B$3:$B$200, Dashboard!$B48) -> 0 | E48: =SUMIFS('Project OPEX'!G$3:G$200, 'Project OPEX'!$B$3:$B$200, Dashboard!$B48) -> 0 | F48: =SUMIFS('Project OPEX'!H$3:H$200, 'Project OPEX'!$B$3:$B$200, Dashboard!$B48) -> 0 | G48: =SUMIFS('Project OPEX'!I$3:I$200, 'Project OPEX'!$B$3:$B$200, Dashboard!$B48) -> 0 | H48: =SUMIFS('Project OPEX'!J$3:J$200, 'Project OPEX'!$B$3:$B$200, Dashboard!$B48) -> 49.169243 | I48: =SUMIFS('Project OPEX'!K$3:K$200, 'Project OPEX'!$B$3:$B$200, Dashboard!$B48) -> 59.527068 | J48: =SUMIFS('Project OPEX'!L$3:L$200, 'Project OPEX'!$B$3:$B$200, Dashboard!$B48) -> 60.181651 | ... R48: =SUMIFS('Project OPEX'!T$3:T$200, 'Project OPEX'!$B$3:$B$200, Dashboard!$B48) -> 66.285689 | T48: Carbon | U48: =SUMIFS('Project NET'!E$3:E$200, 'Project NET'!$B$3:$B$200, Dashboard!$T48) -> 0 | V48: =SUMIFS('Project NET'!F$3:F$200, 'Project NET'!$B$3:$B$200, Dashboard!$T48) -> 0 | W48: =SUMIFS('Project NET'!G$3:G$200, 'Project NET'!$B$3:$B$200, Dashboard!$T48) -> 0 | X48: =SUMIFS('Project NET'!H$3:H$200, 'Project NET'!$B$3:$B$200, Dashboard!$T48) -> 0 | Y48: =SUMIFS('Project NET'!I$3:I$200, 'Project NET'!$B$3:$B$200, Dashboard!$T48) -> 0 | Z48: =SUMIFS('Project NET'!J$3:J$200, 'Project NET'!$B$3:$B$200, Dashboard!$T48) -> 123.7666 | AA48: =SUMIFS('Project NET'!K$3:K$200, 'Project NET'!$B$3:$B$200, Dashboard!$T48) -> 151.44316 | AB48: =SUMIFS('Project NET'!L$3:L$200, 'Project NET'!$B$3:$B$200, Dashboard!$T48) -> 154.47001 | ... AJ48: =SUMIFS('Project NET'!T$3:T$200, 'Project NET'!$B$3:$B$200, Dashboard!$T48) -> 180.22677 | AL48: Carbon | AM48: =SUMIFS('Project ASSET'!E$3:E$200, 'Project ASSET'!$B$3:$B$200, $AL48) -> 0 | AN48: =SUMIFS('Project ASSET'!F$3:F$200, 'Project ASSET'!$B$3:$B$200, $AL48) -> 330 | AO48: =SUMIFS('Project ASSET'!G$3:G$200, 'Project ASSET'!$B$3:$B$200, $AL48) -> 690 | AP48: =SUMIFS('Project ASSET'!H$3:H$200, 'Project ASSET'!$B$3:$B$200, $AL48) -> 1050 | AQ48: =SUMIFS('Project ASSET'!I$3:I$200, 'Project ASSET'!$B$3:$B$200, $AL48) -> 1410 | AR48: =SUMIFS('Project ASSET'!J$3:J$200, 'Project ASSET'!$B$3:$B$200, $AL48) -> 1440 | AS48: =SUMIFS('Project ASSET'!K$3:K$200, 'Project ASSET'!$B$3:$B$200, $AL48) -> 1385.28 | AT48: =SUMIFS('Project ASSET'!L$3:L$200, 'Project ASSET'!$B$3:$B$200, $AL48) -> 1330.56 | ... BB48: =SUMIFS('Project ASSET'!T$3:T$200, 'Project ASSET'!$B$3:$B$200, $AL48) -> 892.8
B49: SENS - Coal | C49: =SUMIFS('Project OPEX'!E$3:E$200, 'Project OPEX'!$B$3:$B$200, Dashboard!$B49) -> 0 | D49: =SUMIFS('Project OPEX'!F$3:F$200, 'Project OPEX'!$B$3:$B$200, Dashboard!$B49) -> 0 | E49: =SUMIFS('Project OPEX'!G$3:G$200, 'Project OPEX'!$B$3:$B$200, Dashboard!$B49) -> 0 | F49: =SUMIFS('Project OPEX'!H$3:H$200, 'Project OPEX'!$B$3:$B$200, Dashboard!$B49) -> 104.19707 | G49: =SUMIFS('Project OPEX'!I$3:I$200, 'Project OPEX'!$B$3:$B$200, Dashboard!$B49) -> 139.57765 | H49: =SUMIFS('Project OPEX'!J$3:J$200, 'Project OPEX'!$B$3:$B$200, Dashboard!$B49) -> 140.21238 | I49: =SUMIFS('Project OPEX'!K$3:K$200, 'Project OPEX'!$B$3:$B$200, Dashboard!$B49) -> 141.53955 | J49: =SUMIFS('Project OPEX'!L$3:L$200, 'Project OPEX'!$B$3:$B$200, Dashboard!$B49) -> 142.38937 | ... R49: =SUMIFS('Project OPEX'!T$3:T$200, 'Project OPEX'!$B$3:$B$200, Dashboard!$B49) -> 148.45439 | T49: SENS - Coal | U49: =SUMIFS('Project NET'!E$3:E$200, 'Project NET'!$B$3:$B$200, Dashboard!$T49) -> 0 | V49: =SUMIFS('Project NET'!F$3:F$200, 'Project NET'!$B$3:$B$200, Dashboard!$T49) -> 0 | W49: d | X49: =SUMIFS('Project NET'!H$3:H$200, 'Project NET'!$B$3:$B$200, Dashboard!$T49) -> 636.41914 | Y49: =SUMIFS('Project NET'!I$3:I$200, 'Project NET'!$B$3:$B$200, Dashboard!$T49) -> 867.40451 | Z49: =SUMIFS('Project NET'!J$3:J$200, 'Project NET'!$B$3:$B$200, Dashboard!$T49) -> 886.65353 | AA49: =SUMIFS('Project NET'!K$3:K$200, 'Project NET'!$B$3:$B$200, Dashboard!$T49) -> 976.6631 | AB49: =SUMIFS('Project NET'!L$3:L$200, 'Project NET'!$B$3:$B$200, Dashboard!$T49) -> 1012.936 | AC49: =SUMIFS('Project NET'!M$3:M$200, 'Project NET'!$B$3:$B$200, Dashboard!$T49) -> 1033.0797 | AD49: =SUMIFS('Project NET'!N$3:N$200, 'Project NET'!$B$3:$B$200, Dashboard!$T49) -> 1053.6318 | AE49: =SUMIFS('Project NET'!O$3:O$200, 'Project NET'!$B$3:$B$200, Dashboard!$T49) -> 1074.6005 | ... AJ49: =SUMIFS('Project NET'!T$3:T$200, 'Project NET'!$B$3:$B$200, Dashboard!$T49) -> 1185.9902 | AL49: SENS - Coal | AM49: =SUMIFS('Project ASSET'!E$3:E$200, 'Project ASSET'!$B$3:$B$200, $AL49) -> 0 | AN49: =SUMIFS('Project ASSET'!F$3:F$200, 'Project ASSET'!$B$3:$B$200, $AL49) -> 0 | AO49: =SUMIFS('Project ASSET'!G$3:G$200, 'Project ASSET'!$B$3:$B$200, $AL49) -> 660 | AP49: =SUMIFS('Project ASSET'!H$3:H$200, 'Project ASSET'!$B$3:$B$200, $AL49) -> 720 | AQ49: =SUMIFS('Project ASSET'!I$3:I$200, 'Project ASSET'!$B$3:$B$200, $AL49) -> 692.64 | AR49: =SUMIFS('Project ASSET'!J$3:J$200, 'Project ASSET'!$B$3:$B$200, $AL49) -> 665.28 | AS49: =SUMIFS('Project ASSET'!K$3:K$200, 'Project ASSET'!$B$3:$B$200, $AL49) -> 637.92 | AT49: =SUMIFS('Project ASSET'!L$3:L$200, 'Project ASSET'!$B$3:$B$200, $AL49) -> 610.56 | ... BB49: =SUMIFS('Project ASSET'!T$3:T$200, 'Project ASSET'!$B$3:$B$200, $AL49) -> 391.68
B50: SENS - Tires | C50: =SUMIFS('Project OPEX'!E$3:E$200, 'Project OPEX'!$B$3:$B$200, Dashboard!$B50) -> 0 | D50: =SUMIFS('Project OPEX'!F$3:F$200, 'Project OPEX'!$B$3:$B$200, Dashboard!$B50) -> 19.150496 | E50: =SUMIFS('Project OPEX'!G$3:G$200, 'Project OPEX'!$B$3:$B$200, Dashboard!$B50) -> 25.676104 | F50: =SUMIFS('Project OPEX'!H$3:H$200, 'Project OPEX'!$B$3:$B$200, Dashboard!$B50) -> 25.799435 | G50: =SUMIFS('Project OPEX'!I$3:I$200, 'Project OPEX'!$B$3:$B$200, Dashboard!$B50) -> 25.900043 | H50: =SUMIFS('Project OPEX'!J$3:J$200, 'Project OPEX'!$B$3:$B$200, Dashboard!$B50) -> 26.04886 | I50: =SUMIFS('Project OPEX'!K$3:K$200, 'Project OPEX'!$B$3:$B$200, Dashboard!$B50) -> 26.208631 | J50: =SUMIFS('Project OPEX'!L$3:L$200, 'Project OPEX'!$B$3:$B$200, Dashboard!$B50) -> 26.371602 | ... R50: =SUMIFS('Project OPEX'!T$3:T$200, 'Project OPEX'!$B$3:$B$200, Dashboard!$B50) -> 27.798575 | T50: SENS - Tires | U50: =SUMIFS('Project NET'!E$3:E$200, 'Project NET'!$B$3:$B$200, Dashboard!$T50) -> 0 | V50: =SUMIFS('Project NET'!F$3:F$200, 'Project NET'!$B$3:$B$200, Dashboard!$T50) -> 93.198657 | W50: =SUMIFS('Project NET'!G$3:G$200, 'Project NET'!$B$3:$B$200, Dashboard!$T50) -> 126.28437 | X50: =SUMIFS('Project NET'!H$3:H$200, 'Project NET'!$B$3:$B$200, Dashboard!$T50) -> 128.36588 | Y50: =SUMIFS('Project NET'!I$3:I$200, 'Project NET'!$B$3:$B$200, Dashboard!$T50) -> 130.5142 | Z50: =SUMIFS('Project NET'!J$3:J$200, 'Project NET'!$B$3:$B$200, Dashboard!$T50) -> 132.65929 | AA50: =SUMIFS('Project NET'!K$3:K$200, 'Project NET'!$B$3:$B$200, Dashboard!$T50) -> 134.83931 | AB50: =SUMIFS('Project NET'!L$3:L$200, 'Project NET'!$B$3:$B$200, Dashboard!$T50) -> 137.06293 | ... AJ50: =SUMIFS('Project NET'!T$3:T$200, 'Project NET'!$B$3:$B$200, Dashboard!$T50) -> 156.52962 | AL50: SENS - Tires | AM50: =SUMIFS('Project ASSET'!E$3:E$200, 'Project ASSET'!$B$3:$B$200, $AL50) -> 103.125 | AN50: =SUMIFS('Project ASSET'!F$3:F$200, 'Project ASSET'!$B$3:$B$200, $AL50) -> 112.5 | AO50: =SUMIFS('Project ASSET'!G$3:G$200, 'Project ASSET'!$B$3:$B$200, $AL50) -> 108.225 | AP50: =SUMIFS('Project ASSET'!H$3:H$200, 'Project ASSET'!$B$3:$B$200, $AL50) -> 103.95 | AQ50: =SUMIFS('Project ASSET'!I$3:I$200, 'Project ASSET'!$B$3:$B$200, $AL50) -> 99.675 | AR50: =SUMIFS('Project ASSET'!J$3:J$200, 'Project ASSET'!$B$3:$B$200, $AL50) -> 95.4 | AS50: =SUMIFS('Project ASSET'!K$3:K$200, 'Project ASSET'!$B$3:$B$200, $AL50) -> 91.125 | AT50: =SUMIFS('Project ASSET'!L$3:L$200, 'Project ASSET'!$B$3:$B$200, $AL50) -> 86.85 | ... BB50: =SUMIFS('Project ASSET'!T$3:T$200, 'Project ASSET'!$B$3:$B$200, $AL50) -> 52.65
C53: SENS Volume | U53: SENS Machines Deployed | AM53: Power Production (TWh)
C65: 0 | D65: =1+C65 -> 1 | E65: =1+D65 -> 2 | F65: =1+E65 -> 3 | G65: =1+F65 -> 4 | H65: =1+G65 -> 5 | I65: =1+H65 -> 6 | J65: =1+I65 -> 7 | K65: =1+J65 -> 8 | ... R65: =1+Q65 -> 15 | U65: 0 | V65: =1+U65 -> 1 | W65: =1+V65 -> 2 | X65: =1+W65 -> 3 | Y65: =1+X65 -> 4 | Z65: =1+Y65 -> 5 | AA65: =1+Z65 -> 6 | AB65: =1+AA65 -> 7 | AC65: =1+AB65 -> 8 | ... AJ65: =1+AI65 -> 15 | AM65: 0 | AN65: =1+AM65 -> 1 | AO65: =1+AN65 -> 2 | AP65: =1+AO65 -> 3 | AQ65: =1+AP65 -> 4 | AR65: =1+AQ65 -> 5 | AS65: =1+AR65 -> 6 | AT65: =1+AS65 -> 7 | AU65: =1+AT65 -> 8 | ... BB65: =1+BA65 -> 15
B66: SENS - Coal | C66: =SUMIFS('Project SVOL'!E$3:E$200, 'Project SVOL'!$B$3:$B$200, Dashboard!$T66) -> 0 | D66: =SUMIFS('Project SVOL'!F$3:F$200, 'Project SVOL'!$B$3:$B$200, Dashboard!$T66) -> 0 | E66: =SUMIFS('Project SVOL'!G$3:G$200, 'Project SVOL'!$B$3:$B$200, Dashboard!$T66) -> 0 | F66: =SUMIFS('Project SVOL'!H$3:H$200, 'Project SVOL'!$B$3:$B$200, Dashboard!$T66) -> 3.973536 | G66: =SUMIFS('Project SVOL'!I$3:I$200, 'Project SVOL'!$B$3:$B$200, Dashboard!$T66) -> 5.298048 | H66: =SUMIFS('Project SVOL'!J$3:J$200, 'Project SVOL'!$B$3:$B$200, Dashboard!$T66) -> 5.298048 | I66: =SUMIFS('Project SVOL'!K$3:K$200, 'Project SVOL'!$B$3:$B$200, Dashboard!$T66) -> 5.298048 | J66: =SUMIFS('Project SVOL'!L$3:L$200, 'Project SVOL'!$B$3:$B$200, Dashboard!$T66) -> 5.298048 | ... R66: =SUMIFS('Project SVOL'!T$3:T$200, 'Project SVOL'!$B$3:$B$200, Dashboard!$T66) -> 5.298048 | T66: SENS - Coal | U66: =SUMIFS('Project SMACH'!E$3:E$200, 'Project SMACH'!$B$3:$B$200, Dashboard!$T66) -> 0 | V66: =SUMIFS('Project SMACH'!F$3:F$200, 'Project SMACH'!$B$3:$B$200, Dashboard!$T66) -> 0 | W66: =SUMIFS('Project SMACH'!G$3:G$200, 'Project SMACH'!$B$3:$B$200, Dashboard!$T66) -> 0 | X66: =SUMIFS('Project SMACH'!H$3:H$200, 'Project SMACH'!$B$3:$B$200, Dashboard!$T66) -> 36 | Y66: =SUMIFS('Project SMACH'!I$3:I$200, 'Project SMACH'!$B$3:$B$200, Dashboard!$T66) -> 36 | Z66: =SUMIFS('Project SMACH'!J$3:J$200, 'Project SMACH'!$B$3:$B$200, Dashboard!$T66) -> 36 | AA66: =SUMIFS('Project SMACH'!K$3:K$200, 'Project SMACH'!$B$3:$B$200, Dashboard!$T66) -> 36 | AB66: =SUMIFS('Project SMACH'!L$3:L$200, 'Project SMACH'!$B$3:$B$200, Dashboard!$T66) -> 36 | ... AJ66: =SUMIFS('Project SMACH'!T$3:T$200, 'Project SMACH'!$B$3:$B$200, Dashboard!$T66) -> 36 | AL66: Nat Gas | AM66: =SUMIFS('Project PGEN'!E:E, 'Project PGEN'!$B:$B, Dashboard!$AL66)/1000 -> 0 | AN66: =SUMIFS('Project PGEN'!F:F, 'Project PGEN'!$B:$B, Dashboard!$AL66)/1000 -> 0 | AO66: =SUMIFS('Project PGEN'!G:G, 'Project PGEN'!$B:$B, Dashboard!$AL66)/1000 -> 0 | AP66: =SUMIFS('Project PGEN'!H:H, 'Project PGEN'!$B:$B, Dashboard!$AL66)/1000 -> 0 | AQ66: =SUMIFS('Project PGEN'!I:I, 'Project PGEN'!$B:$B, Dashboard!$AL66)/1000 -> 496.9536 | AR66: =SUMIFS('Project PGEN'!J:J, 'Project PGEN'!$B:$B, Dashboard!$AL66)/1000 -> 745.4304 | AS66: =SUMIFS('Project PGEN'!K:K, 'Project PGEN'!$B:$B, Dashboard!$AL66)/1000 -> 743.56682 | AT66: =SUMIFS('Project PGEN'!L:L, 'Project PGEN'!$B:$B, Dashboard!$AL66)/1000 -> 741.70791 | AU66: =SUMIFS('Project PGEN'!M:M, 'Project PGEN'!$B:$B, Dashboard!$AL66)/1000 -> 739.85364 | AV66: =SUMIFS('Project PGEN'!N:N, 'Project PGEN'!$B:$B, Dashboard!$AL66)/1000 -> 738.004 | AW66: =SUMIFS('Project PGEN'!O:O, 'Project PGEN'!$B:$B, Dashboard!$AL66)/1000 -> 736.15899 | AX66: =SUMIFS('Project PGEN'!P:P, 'Project PGEN'!$B:$B, Dashboard!$AL66)/1000 -> 734.3186 | AY66: =SUMIFS('Project PGEN'!Q:Q, 'Project PGEN'!$B:$B, Dashboard!$AL66)/1000 -> 732.4828 | AZ66: =SUMIFS('Project PGEN'!R:R, 'Project PGEN'!$B:$B, Dashboard!$AL66)/1000 -> 730.65159 | BA66: =SUMIFS('Project PGEN'!S:S, 'Project PGEN'!$B:$B, Dashboard!$AL66)/1000 -> 728.82496 | BB66: =SUMIFS('Project PGEN'!T:T, 'Project PGEN'!$B:$B, Dashboard!$AL66)/1000 -> 727.0029
B67: SENS - Tires | C67: =SUMIFS('Project SVOL'!E$3:E$200, 'Project SVOL'!$B$3:$B$200, Dashboard!$T67) -> 0 | D67: =SUMIFS('Project SVOL'!F$3:F$200, 'Project SVOL'!$B$3:$B$200, Dashboard!$T67) -> 0.0662256 | E67: =SUMIFS('Project SVOL'!G$3:G$200, 'Project SVOL'!$B$3:$B$200, Dashboard!$T67) -> 0.0883008 | F67: =SUMIFS('Project SVOL'!H$3:H$200, 'Project SVOL'!$B$3:$B$200, Dashboard!$T67) -> 0.0883008 | G67: =SUMIFS('Project SVOL'!I$3:I$200, 'Project SVOL'!$B$3:$B$200, Dashboard!$T67) -> 0.0883008 | H67: =SUMIFS('Project SVOL'!J$3:J$200, 'Project SVOL'!$B$3:$B$200, Dashboard!$T67) -> 0.0883008 | I67: =SUMIFS('Project SVOL'!K$3:K$200, 'Project SVOL'!$B$3:$B$200, Dashboard!$T67) -> 0.0883008 | J67: =SUMIFS('Project SVOL'!L$3:L$200, 'Project SVOL'!$B$3:$B$200, Dashboard!$T67) -> 0.0883008 | ... R67: =SUMIFS('Project SVOL'!T$3:T$200, 'Project SVOL'!$B$3:$B$200, Dashboard!$T67) -> 0.0883008 | T67: SENS - Tires | U67: =SUMIFS('Project SMACH'!E$3:E$200, 'Project SMACH'!$B$3:$B$200, Dashboard!$T67) -> 0 | V67: =SUMIFS('Project SMACH'!F$3:F$200, 'Project SMACH'!$B$3:$B$200, Dashboard!$T67) -> 6 | W67: =SUMIFS('Project SMACH'!G$3:G$200, 'Project SMACH'!$B$3:$B$200, Dashboard!$T67) -> 6 | X67: =SUMIFS('Project SMACH'!H$3:H$200, 'Project SMACH'!$B$3:$B$200, Dashboard!$T67) -> 6 | Y67: =SUMIFS('Project SMACH'!I$3:I$200, 'Project SMACH'!$B$3:$B$200, Dashboard!$T67) -> 6 | Z67: =SUMIFS('Project SMACH'!J$3:J$200, 'Project SMACH'!$B$3:$B$200, Dashboard!$T67) -> 6 | AA67: =SUMIFS('Project SMACH'!K$3:K$200, 'Project SMACH'!$B$3:$B$200, Dashboard!$T67) -> 6 | AB67: =SUMIFS('Project SMACH'!L$3:L$200, 'Project SMACH'!$B$3:$B$200, Dashboard!$T67) -> 6 | ... AJ67: =SUMIFS('Project SMACH'!T$3:T$200, 'Project SMACH'!$B$3:$B$200, Dashboard!$T67) -> 6 | AL67: Solar | AM67: =SUMIFS('Project PGEN'!E:E, 'Project PGEN'!$B:$B, Dashboard!$AL67)/1000 -> 0 | AN67: =SUMIFS('Project PGEN'!F:F, 'Project PGEN'!$B:$B, Dashboard!$AL67)/1000 -> 40.88 | AO67: =SUMIFS('Project PGEN'!G:G, 'Project PGEN'!$B:$B, Dashboard!$AL67)/1000 -> 121.72135 | AP67: =SUMIFS('Project PGEN'!H:H, 'Project PGEN'!$B:$B, Dashboard!$AL67)/1000 -> 120.50414 | AQ67: =SUMIFS('Project PGEN'!I:I, 'Project PGEN'!$B:$B, Dashboard!$AL67)/1000 -> 119.29605 | AR67: =SUMIFS('Project PGEN'!J:J, 'Project PGEN'!$B:$B, Dashboard!$AL67)/1000 -> 118.09704 | AS67: =SUMIFS('Project PGEN'!K:K, 'Project PGEN'!$B:$B, Dashboard!$AL67)/1000 -> 116.90703 | AT67: =SUMIFS('Project PGEN'!L:L, 'Project PGEN'!$B:$B, Dashboard!$AL67)/1000 -> 115.72597 | AU67: =SUMIFS('Project PGEN'!M:M, 'Project PGEN'!$B:$B, Dashboard!$AL67)/1000 -> 114.55379 | AV67: =SUMIFS('Project PGEN'!N:N, 'Project PGEN'!$B:$B, Dashboard!$AL67)/1000 -> 113.39045 | AW67: =SUMIFS('Project PGEN'!O:O, 'Project PGEN'!$B:$B, Dashboard!$AL67)/1000 -> 112.23588 | AX67: =SUMIFS('Project PGEN'!P:P, 'Project PGEN'!$B:$B, Dashboard!$AL67)/1000 -> 111.09001 | AY67: =SUMIFS('Project PGEN'!Q:Q, 'Project PGEN'!$B:$B, Dashboard!$AL67)/1000 -> 109.9528 | AZ67: =SUMIFS('Project PGEN'!R:R, 'Project PGEN'!$B:$B, Dashboard!$AL67)/1000 -> 108.82419 | BA67: =SUMIFS('Project PGEN'!S:S, 'Project PGEN'!$B:$B, Dashboard!$AL67)/1000 -> 107.70411 | BB67: =SUMIFS('Project PGEN'!T:T, 'Project PGEN'!$B:$B, Dashboard!$AL67)/1000 -> 106.59251
B68: Carbon | C68: =SUMIFS('Project SVOL'!E$3:E$200, 'Project SVOL'!$B$3:$B$200, $B68) -> 0 | D68: =SUMIFS('Project SVOL'!F$3:F$200, 'Project SVOL'!$B$3:$B$200, $B68) -> 0 | E68: =SUMIFS('Project SVOL'!G$3:G$200, 'Project SVOL'!$B$3:$B$200, $B68) -> 0 | F68: =SUMIFS('Project SVOL'!H$3:H$200, 'Project SVOL'!$B$3:$B$200, $B68) -> 0 | G68: =SUMIFS('Project SVOL'!I$3:I$200, 'Project SVOL'!$B$3:$B$200, $B68) -> 0 | H68: =SUMIFS('Project SVOL'!J$3:J$200, 'Project SVOL'!$B$3:$B$200, $B68) -> 5.2257992 | I68: =SUMIFS('Project SVOL'!K$3:K$200, 'Project SVOL'!$B$3:$B$200, $B68) -> 5.2257992 | J68: =SUMIFS('Project SVOL'!L$3:L$200, 'Project SVOL'!$B$3:$B$200, $B68) -> 5.2257992 | ... R68: =SUMIFS('Project SVOL'!T$3:T$200, 'Project SVOL'!$B$3:$B$200, $B68) -> 5.2257992 | T68: SENS - Coal Needed | U68: =IF(C69<0, ROUNDUP(-C69/('Assumptions & Inputs'!$L$109/1000000), 0), 0) -> 0 | V68: =IF(D69<0, ROUNDUP(-D69/('Assumptions & Inputs'!$L$109/1000000), 0), 0) -> 0 | W68: =IF(E69<0, ROUNDUP(-E69/('Assumptions & Inputs'!$L$109/1000000), 0), 0) -> 0 | X68: =IF(F69<0, ROUNDUP(-F69/('Assumptions & Inputs'!$L$109/1000000), 0), 0) -> 0 | Y68: =IF(G69<0, ROUNDUP(-G69/('Assumptions & Inputs'!$L$109/1000000), 0), 0) -> 0 | Z68: =IF(H69<0, ROUNDUP(-H69/('Assumptions & Inputs'!$L$109/1000000), 0), 0) -> 0 | AA68: =IF(I69<0, ROUNDUP(-I69/('Assumptions & Inputs'!$L$109/1000000), 0), 0) -> 0 | AB68: =IF(J69<0, ROUNDUP(-J69/('Assumptions & Inputs'!$L$109/1000000), 0), 0) -> 0 | ... AJ68: =IF(R69<0, ROUNDUP(-R69/('Assumptions & Inputs'!$L$109/1000000), 0), 0) -> 0 | AL68: BESS | AM68: =SUMIFS('Project PGEN'!E:E, 'Project PGEN'!$B:$B, Dashboard!$AL68)/1000 -> 0 | AN68: =SUMIFS('Project PGEN'!F:F, 'Project PGEN'!$B:$B, Dashboard!$AL68)/1000 -> 0 | AO68: =SUMIFS('Project PGEN'!G:G, 'Project PGEN'!$B:$B, Dashboard!$AL68)/1000 -> 44.481111 | AP68: =SUMIFS('Project PGEN'!H:H, 'Project PGEN'!$B:$B, Dashboard!$AL68)/1000 -> 53.2 | AQ68: =SUMIFS('Project PGEN'!I:I, 'Project PGEN'!$B:$B, Dashboard!$AL68)/1000 -> 53.2 | AR68: =SUMIFS('Project PGEN'!J:J, 'Project PGEN'!$B:$B, Dashboard!$AL68)/1000 -> 53.2 | AS68: =SUMIFS('Project PGEN'!K:K, 'Project PGEN'!$B:$B, Dashboard!$AL68)/1000 -> 53.2 | AT68: =SUMIFS('Project PGEN'!L:L, 'Project PGEN'!$B:$B, Dashboard!$AL68)/1000 -> 53.2 | AU68: =SUMIFS('Project PGEN'!M:M, 'Project PGEN'!$B:$B, Dashboard!$AL68)/1000 -> 53.2 | AV68: =SUMIFS('Project PGEN'!N:N, 'Project PGEN'!$B:$B, Dashboard!$AL68)/1000 -> 53.2 | AW68: =SUMIFS('Project PGEN'!O:O, 'Project PGEN'!$B:$B, Dashboard!$AL68)/1000 -> 53.2 | AX68: =SUMIFS('Project PGEN'!P:P, 'Project PGEN'!$B:$B, Dashboard!$AL68)/1000 -> 53.2 | AY68: =SUMIFS('Project PGEN'!Q:Q, 'Project PGEN'!$B:$B, Dashboard!$AL68)/1000 -> 53.2 | AZ68: =SUMIFS('Project PGEN'!R:R, 'Project PGEN'!$B:$B, Dashboard!$AL68)/1000 -> 53.2 | BA68: =SUMIFS('Project PGEN'!S:S, 'Project PGEN'!$B:$B, Dashboard!$AL68)/1000 -> 53.2 | BB68: =SUMIFS('Project PGEN'!T:T, 'Project PGEN'!$B:$B, Dashboard!$AL68)/1000 -> 53.2
B69: SENS Coal Net Gen | C69: =C66-C68 -> 0 | D69: =D66-D68 -> 0 | E69: =E66-E68 -> 0 | F69: =F66-F68 -> 3.973536 | G69: =G66-G68 -> 5.298048 | H69: =H66-H68 -> 0.072248778 | I69: =I66-I68 -> 0.072248778 | J69: =J66-J68 -> 0.072248778 | ... R69: =R66-R68 -> 0.072248778 | AL69: Carbon | AM69: =SUMIFS('Project PGEN'!E:E, 'Project PGEN'!$B:$B, Dashboard!$AL69)/1000 -> 0 | AN69: =SUMIFS('Project PGEN'!F:F, 'Project PGEN'!$B:$B, Dashboard!$AL69)/1000 -> 0 | AO69: =SUMIFS('Project PGEN'!G:G, 'Project PGEN'!$B:$B, Dashboard!$AL69)/1000 -> 0 | AP69: =SUMIFS('Project PGEN'!H:H, 'Project PGEN'!$B:$B, Dashboard!$AL69)/1000 -> 0 | AQ69: =SUMIFS('Project PGEN'!I:I, 'Project PGEN'!$B:$B, Dashboard!$AL69)/1000 -> 0 | AR69: =SUMIFS('Project PGEN'!J:J, 'Project PGEN'!$B:$B, Dashboard!$AL69)/1000 -> 2662.7664 | AS69: =SUMIFS('Project PGEN'!K:K, 'Project PGEN'!$B:$B, Dashboard!$AL69)/1000 -> 3184.704 | AT69: =SUMIFS('Project PGEN'!L:L, 'Project PGEN'!$B:$B, Dashboard!$AL69)/1000 -> 3176.7422 | AU69: =SUMIFS('Project PGEN'!M:M, 'Project PGEN'!$B:$B, Dashboard!$AL69)/1000 -> 3168.8004 | AV69: =SUMIFS('Project PGEN'!N:N, 'Project PGEN'!$B:$B, Dashboard!$AL69)/1000 -> 3160.8784 | AW69: =SUMIFS('Project PGEN'!O:O, 'Project PGEN'!$B:$B, Dashboard!$AL69)/1000 -> 3152.9762 | AX69: =SUMIFS('Project PGEN'!P:P, 'Project PGEN'!$B:$B, Dashboard!$AL69)/1000 -> 3145.0937 | AY69: =SUMIFS('Project PGEN'!Q:Q, 'Project PGEN'!$B:$B, Dashboard!$AL69)/1000 -> 3137.231 | AZ69: =SUMIFS('Project PGEN'!R:R, 'Project PGEN'!$B:$B, Dashboard!$AL69)/1000 -> 3129.3879 | BA69: =SUMIFS('Project PGEN'!S:S, 'Project PGEN'!$B:$B, Dashboard!$AL69)/1000 -> 3121.5645 | BB69: =SUMIFS('Project PGEN'!T:T, 'Project PGEN'!$B:$B, Dashboard!$AL69)/1000 -> 3113.7606
AM83: 0 | AN83: =1+AM83 -> 1 | AO83: =1+AN83 -> 2 | AP83: =1+AO83 -> 3 | AQ83: =1+AP83 -> 4 | AR83: =1+AQ83 -> 5 | AS83: =1+AR83 -> 6 | AT83: =1+AS83 -> 7 | AU83: =1+AT83 -> 8 | ... BB83: =1+BA83 -> 15
AL84: Nat Gas | AM84: =SUMIFS('Project Master Sheet'!$E:$E, 'Project Master Sheet'!$D:$D, Dashboard!$AL84, 'Project Master Sheet'!$I:$I, "<="&Dashboard!AM$83) -> 0 | AN84: =SUMIFS('Project Master Sheet'!$E:$E, 'Project Master Sheet'!$D:$D, Dashboard!$AL84, 'Project Master Sheet'!$I:$I, "<="&Dashboard!AN$83) -> 100 | AO84: =SUMIFS('Project Master Sheet'!$E:$E, 'Project Master Sheet'!$D:$D, Dashboard!$AL84, 'Project Master Sheet'!$I:$I, "<="&Dashboard!AO$83) -> 100 | AP84: =SUMIFS('Project Master Sheet'!$E:$E, 'Project Master Sheet'!$D:$D, Dashboard!$AL84, 'Project Master Sheet'!$I:$I, "<="&Dashboard!AP$83) -> 100 | AQ84: =SUMIFS('Project Master Sheet'!$E:$E, 'Project Master Sheet'!$D:$D, Dashboard!$AL84, 'Project Master Sheet'!$I:$I, "<="&Dashboard!AQ$83) -> 100 | AR84: =SUMIFS('Project Master Sheet'!$E:$E, 'Project Master Sheet'!$D:$D, Dashboard!$AL84, 'Project Master Sheet'!$I:$I, "<="&Dashboard!AR$83) -> 100 | AS84: =SUMIFS('Project Master Sheet'!$E:$E, 'Project Master Sheet'!$D:$D, Dashboard!$AL84, 'Project Master Sheet'!$I:$I, "<="&Dashboard!AS$83) -> 100 | AT84: =SUMIFS('Project Master Sheet'!$E:$E, 'Project Master Sheet'!$D:$D, Dashboard!$AL84, 'Project Master Sheet'!$I:$I, "<="&Dashboard!AT$83) -> 100 | ... BB84: =SUMIFS('Project Master Sheet'!$E:$E, 'Project Master Sheet'!$D:$D, Dashboard!$AL84, 'Project Master Sheet'!$I:$I, "<="&Dashboard!BB$83) -> 100
C85: 0 | D85: =1+C85 -> 1 | E85: =1+D85 -> 2 | F85: =1+E85 -> 3 | G85: =1+F85 -> 4 | H85: =1+G85 -> 5 | I85: =1+H85 -> 6 | J85: =1+I85 -> 7 | K85: =1+J85 -> 8 | ... R85: =1+Q85 -> 15 | AL85: Solar | AM85: =SUMIFS('Project Master Sheet'!$E:$E, 'Project Master Sheet'!$D:$D, Dashboard!$AL85, 'Project Master Sheet'!$I:$I, "<="&Dashboard!AM$83) -> 70 | AN85: =SUMIFS('Project Master Sheet'!$E:$E, 'Project Master Sheet'!$D:$D, Dashboard!$AL85, 'Project Master Sheet'!$I:$I, "<="&Dashboard!AN$83) -> 70 | AO85: =SUMIFS('Project Master Sheet'!$E:$E, 'Project Master Sheet'!$D:$D, Dashboard!$AL85, 'Project Master Sheet'!$I:$I, "<="&Dashboard!AO$83) -> 70 | AP85: =SUMIFS('Project Master Sheet'!$E:$E, 'Project Master Sheet'!$D:$D, Dashboard!$AL85, 'Project Master Sheet'!$I:$I, "<="&Dashboard!AP$83) -> 70 | AQ85: =SUMIFS('Project Master Sheet'!$E:$E, 'Project Master Sheet'!$D:$D, Dashboard!$AL85, 'Project Master Sheet'!$I:$I, "<="&Dashboard!AQ$83) -> 70 | AR85: =SUMIFS('Project Master Sheet'!$E:$E, 'Project Master Sheet'!$D:$D, Dashboard!$AL85, 'Project Master Sheet'!$I:$I, "<="&Dashboard!AR$83) -> 70 | AS85: =SUMIFS('Project Master Sheet'!$E:$E, 'Project Master Sheet'!$D:$D, Dashboard!$AL85, 'Project Master Sheet'!$I:$I, "<="&Dashboard!AS$83) -> 70 | AT85: =SUMIFS('Project Master Sheet'!$E:$E, 'Project Master Sheet'!$D:$D, Dashboard!$AL85, 'Project Master Sheet'!$I:$I, "<="&Dashboard!AT$83) -> 70 | ... BB85: =SUMIFS('Project Master Sheet'!$E:$E, 'Project Master Sheet'!$D:$D, Dashboard!$AL85, 'Project Master Sheet'!$I:$I, "<="&Dashboard!BB$83) -> 70
B86: Nat Gas | C86: =SUMIFS('Project LAND'!E:E, 'Project LAND'!$B:$B, Dashboard!$B86) -> 0 | D86: =SUMIFS('Project LAND'!F:F, 'Project LAND'!$B:$B, Dashboard!$B86) -> 1.1478421 | E86: =SUMIFS('Project LAND'!G:G, 'Project LAND'!$B:$B, Dashboard!$B86) -> 1.1478421 | F86: =SUMIFS('Project LAND'!H:H, 'Project LAND'!$B:$B, Dashboard!$B86) -> 1.1478421 | G86: =SUMIFS('Project LAND'!I:I, 'Project LAND'!$B:$B, Dashboard!$B86) -> 1.1478421 | H86: =SUMIFS('Project LAND'!J:J, 'Project LAND'!$B:$B, Dashboard!$B86) -> 1.1478421 | I86: =SUMIFS('Project LAND'!K:K, 'Project LAND'!$B:$B, Dashboard!$B86) -> 1.1478421 | J86: =SUMIFS('Project LAND'!L:L, 'Project LAND'!$B:$B, Dashboard!$B86) -> 1.1478421 | K86: =SUMIFS('Project LAND'!M:M, 'Project LAND'!$B:$B, Dashboard!$B86) -> 1.1478421 | L86: =SUMIFS('Project LAND'!N:N, 'Project LAND'!$B:$B, Dashboard!$B86) -> 1.1478421 | M86: =SUMIFS('Project LAND'!O:O, 'Project LAND'!$B:$B, Dashboard!$B86) -> 1.1478421 | N86: =SUMIFS('Project LAND'!P:P, 'Project LAND'!$B:$B, Dashboard!$B86) -> 1.1478421 | O86: =SUMIFS('Project LAND'!Q:Q, 'Project LAND'!$B:$B, Dashboard!$B86) -> 1.1478421 | P86: =SUMIFS('Project LAND'!R:R, 'Project LAND'!$B:$B, Dashboard!$B86) -> 1.1478421 | Q86: =SUMIFS('Project LAND'!S:S, 'Project LAND'!$B:$B, Dashboard!$B86) -> 1.1478421 | R86: =SUMIFS('Project LAND'!T:T, 'Project LAND'!$B:$B, Dashboard!$B86) -> 1.1478421 | AL86: BESS | AM86: =SUMIFS('Project Master Sheet'!$E:$E, 'Project Master Sheet'!$D:$D, Dashboard!$AL86, 'Project Master Sheet'!$I:$I, "<="&Dashboard!AM$83) -> 0 | AN86: =SUMIFS('Project Master Sheet'!$E:$E, 'Project Master Sheet'!$D:$D, Dashboard!$AL86, 'Project Master Sheet'!$I:$I, "<="&Dashboard!AN$83) -> 50 | AO86: =SUMIFS('Project Master Sheet'!$E:$E, 'Project Master Sheet'!$D:$D, Dashboard!$AL86, 'Project Master Sheet'!$I:$I, "<="&Dashboard!AO$83) -> 50 | AP86: =SUMIFS('Project Master Sheet'!$E:$E, 'Project Master Sheet'!$D:$D, Dashboard!$AL86, 'Project Master Sheet'!$I:$I, "<="&Dashboard!AP$83) -> 50 | AQ86: =SUMIFS('Project Master Sheet'!$E:$E, 'Project Master Sheet'!$D:$D, Dashboard!$AL86, 'Project Master Sheet'!$I:$I, "<="&Dashboard!AQ$83) -> 50 | AR86: =SUMIFS('Project Master Sheet'!$E:$E, 'Project Master Sheet'!$D:$D, Dashboard!$AL86, 'Project Master Sheet'!$I:$I, "<="&Dashboard!AR$83) -> 50 | AS86: =SUMIFS('Project Master Sheet'!$E:$E, 'Project Master Sheet'!$D:$D, Dashboard!$AL86, 'Project Master Sheet'!$I:$I, "<="&Dashboard!AS$83) -> 50 | AT86: =SUMIFS('Project Master Sheet'!$E:$E, 'Project Master Sheet'!$D:$D, Dashboard!$AL86, 'Project Master Sheet'!$I:$I, "<="&Dashboard!AT$83) -> 50 | ... BB86: =SUMIFS('Project Master Sheet'!$E:$E, 'Project Master Sheet'!$D:$D, Dashboard!$AL86, 'Project Master Sheet'!$I:$I, "<="&Dashboard!BB$83) -> 50
B87: Solar | C87: =SUMIFS('Project LAND'!E:E, 'Project LAND'!$B:$B, Dashboard!$B87) -> 700 | D87: =SUMIFS('Project LAND'!F:F, 'Project LAND'!$B:$B, Dashboard!$B87) -> 700 | E87: =SUMIFS('Project LAND'!G:G, 'Project LAND'!$B:$B, Dashboard!$B87) -> 700 | F87: =SUMIFS('Project LAND'!H:H, 'Project LAND'!$B:$B, Dashboard!$B87) -> 700 | G87: =SUMIFS('Project LAND'!I:I, 'Project LAND'!$B:$B, Dashboard!$B87) -> 700 | H87: =SUMIFS('Project LAND'!J:J, 'Project LAND'!$B:$B, Dashboard!$B87) -> 700 | I87: =SUMIFS('Project LAND'!K:K, 'Project LAND'!$B:$B, Dashboard!$B87) -> 700 | J87: =SUMIFS('Project LAND'!L:L, 'Project LAND'!$B:$B, Dashboard!$B87) -> 700 | K87: =SUMIFS('Project LAND'!M:M, 'Project LAND'!$B:$B, Dashboard!$B87) -> 700 | L87: =SUMIFS('Project LAND'!N:N, 'Project LAND'!$B:$B, Dashboard!$B87) -> 700 | M87: =SUMIFS('Project LAND'!O:O, 'Project LAND'!$B:$B, Dashboard!$B87) -> 700 | N87: =SUMIFS('Project LAND'!P:P, 'Project LAND'!$B:$B, Dashboard!$B87) -> 700 | O87: =SUMIFS('Project LAND'!Q:Q, 'Project LAND'!$B:$B, Dashboard!$B87) -> 700 | P87: =SUMIFS('Project LAND'!R:R, 'Project LAND'!$B:$B, Dashboard!$B87) -> 700 | Q87: =SUMIFS('Project LAND'!S:S, 'Project LAND'!$B:$B, Dashboard!$B87) -> 700 | R87: =SUMIFS('Project LAND'!T:T, 'Project LAND'!$B:$B, Dashboard!$B87) -> 700 | AL87: Carbon | AM87: =SUMIFS('Project Master Sheet'!$E:$E, 'Project Master Sheet'!$D:$D, Dashboard!$AL87, 'Project Master Sheet'!$I:$I, "<="&Dashboard!AM$83) -> 0 | AN87: =SUMIFS('Project Master Sheet'!$E:$E, 'Project Master Sheet'!$D:$D, Dashboard!$AL87, 'Project Master Sheet'!$I:$I, "<="&Dashboard!AN$83) -> 400 | AO87: =SUMIFS('Project Master Sheet'!$E:$E, 'Project Master Sheet'!$D:$D, Dashboard!$AL87, 'Project Master Sheet'!$I:$I, "<="&Dashboard!AO$83) -> 400 | AP87: =SUMIFS('Project Master Sheet'!$E:$E, 'Project Master Sheet'!$D:$D, Dashboard!$AL87, 'Project Master Sheet'!$I:$I, "<="&Dashboard!AP$83) -> 400 | AQ87: =SUMIFS('Project Master Sheet'!$E:$E, 'Project Master Sheet'!$D:$D, Dashboard!$AL87, 'Project Master Sheet'!$I:$I, "<="&Dashboard!AQ$83) -> 400 | AR87: =SUMIFS('Project Master Sheet'!$E:$E, 'Project Master Sheet'!$D:$D, Dashboard!$AL87, 'Project Master Sheet'!$I:$I, "<="&Dashboard!AR$83) -> 400 | AS87: =SUMIFS('Project Master Sheet'!$E:$E, 'Project Master Sheet'!$D:$D, Dashboard!$AL87, 'Project Master Sheet'!$I:$I, "<="&Dashboard!AS$83) -> 400 | AT87: =SUMIFS('Project Master Sheet'!$E:$E, 'Project Master Sheet'!$D:$D, Dashboard!$AL87, 'Project Master Sheet'!$I:$I, "<="&Dashboard!AT$83) -> 400 | ... BB87: =SUMIFS('Project Master Sheet'!$E:$E, 'Project Master Sheet'!$D:$D, Dashboard!$AL87, 'Project Master Sheet'!$I:$I, "<="&Dashboard!BB$83) -> 400
B88: BESS | C88: =SUMIFS('Project LAND'!E:E, 'Project LAND'!$B:$B, Dashboard!$B88) -> 0 | D88: =SUMIFS('Project LAND'!F:F, 'Project LAND'!$B:$B, Dashboard!$B88) -> 0.60240964 | E88: =SUMIFS('Project LAND'!G:G, 'Project LAND'!$B:$B, Dashboard!$B88) -> 0.60240964 | F88: =SUMIFS('Project LAND'!H:H, 'Project LAND'!$B:$B, Dashboard!$B88) -> 0.60240964 | G88: =SUMIFS('Project LAND'!I:I, 'Project LAND'!$B:$B, Dashboard!$B88) -> 0.60240964 | H88: =SUMIFS('Project LAND'!J:J, 'Project LAND'!$B:$B, Dashboard!$B88) -> 0.60240964 | I88: =SUMIFS('Project LAND'!K:K, 'Project LAND'!$B:$B, Dashboard!$B88) -> 0.60240964 | J88: =SUMIFS('Project LAND'!L:L, 'Project LAND'!$B:$B, Dashboard!$B88) -> 0.60240964 | K88: =SUMIFS('Project LAND'!M:M, 'Project LAND'!$B:$B, Dashboard!$B88) -> 0.60240964 | L88: =SUMIFS('Project LAND'!N:N, 'Project LAND'!$B:$B, Dashboard!$B88) -> 0.60240964 | M88: =SUMIFS('Project LAND'!O:O, 'Project LAND'!$B:$B, Dashboard!$B88) -> 0.60240964 | N88: =SUMIFS('Project LAND'!P:P, 'Project LAND'!$B:$B, Dashboard!$B88) -> 0.60240964 | O88: =SUMIFS('Project LAND'!Q:Q, 'Project LAND'!$B:$B, Dashboard!$B88) -> 0.60240964 | P88: =SUMIFS('Project LAND'!R:R, 'Project LAND'!$B:$B, Dashboard!$B88) -> 0.60240964 | Q88: =SUMIFS('Project LAND'!S:S, 'Project LAND'!$B:$B, Dashboard!$B88) -> 0.60240964 | R88: =SUMIFS('Project LAND'!T:T, 'Project LAND'!$B:$B, Dashboard!$B88) -> 0.60240964
B89: Carbon | C89: =SUMIFS('Project LAND'!E:E, 'Project LAND'!$B:$B, Dashboard!$B89) -> 0 | D89: =SUMIFS('Project LAND'!F:F, 'Project LAND'!$B:$B, Dashboard!$B89) -> 200 | E89: =SUMIFS('Project LAND'!G:G, 'Project LAND'!$B:$B, Dashboard!$B89) -> 200 | F89: =SUMIFS('Project LAND'!H:H, 'Project LAND'!$B:$B, Dashboard!$B89) -> 200 | G89: =SUMIFS('Project LAND'!I:I, 'Project LAND'!$B:$B, Dashboard!$B89) -> 200 | H89: =SUMIFS('Project LAND'!J:J, 'Project LAND'!$B:$B, Dashboard!$B89) -> 200 | I89: =SUMIFS('Project LAND'!K:K, 'Project LAND'!$B:$B, Dashboard!$B89) -> 200 | J89: =SUMIFS('Project LAND'!L:L, 'Project LAND'!$B:$B, Dashboard!$B89) -> 200 | K89: =SUMIFS('Project LAND'!M:M, 'Project LAND'!$B:$B, Dashboard!$B89) -> 200 | L89: =SUMIFS('Project LAND'!N:N, 'Project LAND'!$B:$B, Dashboard!$B89) -> 200 | M89: =SUMIFS('Project LAND'!O:O, 'Project LAND'!$B:$B, Dashboard!$B89) -> 200 | N89: =SUMIFS('Project LAND'!P:P, 'Project LAND'!$B:$B, Dashboard!$B89) -> 200 | O89: =SUMIFS('Project LAND'!Q:Q, 'Project LAND'!$B:$B, Dashboard!$B89) -> 200 | P89: =SUMIFS('Project LAND'!R:R, 'Project LAND'!$B:$B, Dashboard!$B89) -> 200 | Q89: =SUMIFS('Project LAND'!S:S, 'Project LAND'!$B:$B, Dashboard!$B89) -> 200 | R89: =SUMIFS('Project LAND'!T:T, 'Project LAND'!$B:$B, Dashboard!$B89) -> 200
B90: SENS - Coal | C90: =SUMIFS('Project LAND'!E:E, 'Project LAND'!$B:$B, Dashboard!$B90) -> 0 | D90: =SUMIFS('Project LAND'!F:F, 'Project LAND'!$B:$B, Dashboard!$B90) -> 0 | E90: =SUMIFS('Project LAND'!G:G, 'Project LAND'!$B:$B, Dashboard!$B90) -> 36 | F90: =SUMIFS('Project LAND'!H:H, 'Project LAND'!$B:$B, Dashboard!$B90) -> 36 | G90: =SUMIFS('Project LAND'!I:I, 'Project LAND'!$B:$B, Dashboard!$B90) -> 36 | H90: =SUMIFS('Project LAND'!J:J, 'Project LAND'!$B:$B, Dashboard!$B90) -> 36 | I90: =SUMIFS('Project LAND'!K:K, 'Project LAND'!$B:$B, Dashboard!$B90) -> 36 | J90: =SUMIFS('Project LAND'!L:L, 'Project LAND'!$B:$B, Dashboard!$B90) -> 36 | K90: =SUMIFS('Project LAND'!M:M, 'Project LAND'!$B:$B, Dashboard!$B90) -> 36 | L90: =SUMIFS('Project LAND'!N:N, 'Project LAND'!$B:$B, Dashboard!$B90) -> 36 | M90: =SUMIFS('Project LAND'!O:O, 'Project LAND'!$B:$B, Dashboard!$B90) -> 36 | N90: =SUMIFS('Project LAND'!P:P, 'Project LAND'!$B:$B, Dashboard!$B90) -> 36 | O90: =SUMIFS('Project LAND'!Q:Q, 'Project LAND'!$B:$B, Dashboard!$B90) -> 36 | P90: =SUMIFS('Project LAND'!R:R, 'Project LAND'!$B:$B, Dashboard!$B90) -> 36 | Q90: =SUMIFS('Project LAND'!S:S, 'Project LAND'!$B:$B, Dashboard!$B90) -> 36 | R90: =SUMIFS('Project LAND'!T:T, 'Project LAND'!$B:$B, Dashboard!$B90) -> 36
B91: SENS - Tires | C91: =SUMIFS('Project LAND'!E:E, 'Project LAND'!$B:$B, Dashboard!$B91) -> 6 | D91: =SUMIFS('Project LAND'!F:F, 'Project LAND'!$B:$B, Dashboard!$B91) -> 6 | E91: =SUMIFS('Project LAND'!G:G, 'Project LAND'!$B:$B, Dashboard!$B91) -> 6 | F91: =SUMIFS('Project LAND'!H:H, 'Project LAND'!$B:$B, Dashboard!$B91) -> 6 | G91: =SUMIFS('Project LAND'!I:I, 'Project LAND'!$B:$B, Dashboard!$B91) -> 6 | H91: =SUMIFS('Project LAND'!J:J, 'Project LAND'!$B:$B, Dashboard!$B91) -> 6 | I91: =SUMIFS('Project LAND'!K:K, 'Project LAND'!$B:$B, Dashboard!$B91) -> 6 | J91: =SUMIFS('Project LAND'!L:L, 'Project LAND'!$B:$B, Dashboard!$B91) -> 6 | K91: =SUMIFS('Project LAND'!M:M, 'Project LAND'!$B:$B, Dashboard!$B91) -> 6 | L91: =SUMIFS('Project LAND'!N:N, 'Project LAND'!$B:$B, Dashboard!$B91) -> 6 | M91: =SUMIFS('Project LAND'!O:O, 'Project LAND'!$B:$B, Dashboard!$B91) -> 6 | N91: =SUMIFS('Project LAND'!P:P, 'Project LAND'!$B:$B, Dashboard!$B91) -> 6 | O91: =SUMIFS('Project LAND'!Q:Q, 'Project LAND'!$B:$B, Dashboard!$B91) -> 6 | P91: =SUMIFS('Project LAND'!R:R, 'Project LAND'!$B:$B, Dashboard!$B91) -> 6 | Q91: =SUMIFS('Project LAND'!S:S, 'Project LAND'!$B:$B, Dashboard!$B91) -> 6 | R91: =SUMIFS('Project LAND'!T:T, 'Project LAND'!$B:$B, Dashboard!$B91) -> 6

Sheet Project Master Sheet
A1: Projects | J1: Project Start Year
A2: Reference Number | B2: Project Name | C2: Project State | D2: Type | E2: Volume MW | F2: Volume Machines | G2: JV Capex Contribution | H2: ISCM Capex Contribution | I2: START DATE >> | J2: 0 | K2: 1 | L2: 2 | M2: 3 | N2: 4 | O2: 5 | P2: 6 | Q2: 7 | R2: 8 | S2: 9 | T2: 10 | U2: 11 | V2: 12 | W2: 13 | X2: 14 | Y2: 15
A3: 1 | D3: Carbon | E3: 400 | G3: 0 | H3: =1-G3 -> 1 | I3: 1 | J3: =IF($I3>J$2, 0, 1) -> 0 | K3: =IF($I3>K$2, 0, 1) -> 1 | L3: =IF($I3>L$2, 0, 1) -> 1 | M3: =IF($I3>M$2, 0, 1) -> 1 | N3: =IF($I3>N$2, 0, 1) -> 1 | O3: =IF($I3>O$2, 0, 1) -> 1 | P3: =IF($I3>P$2, 0, 1) -> 1 | Q3: =IF($I3>Q$2, 0, 1) -> 1 | ... Y3: =IF($I3>Y$2, 0, 1) -> 1
A4: 2 | D4: BESS | E4: 50 | G4: 0 | H4: =1-G4 -> 1 | I4: 1 | J4: =IF($I4>J$2, 0, 1) -> 0 | K4: =IF($I4>K$2, 0, 1) -> 1 | L4: =IF($I4>L$2, 0, 1) -> 1 | M4: =IF($I4>M$2, 0, 1) -> 1 | N4: =IF($I4>N$2, 0, 1) -> 1 | O4: =IF($I4>O$2, 0, 1) -> 1 | P4: =IF($I4>P$2, 0, 1) -> 1 | Q4: =IF($I4>Q$2, 0, 1) -> 1 | ... Y4: =IF($I4>Y$2, 0, 1) -> 1
A5: 3 | D5: SENS - Coal | F5: 36 | G5: 0 | H5: =1-G5 -> 1 | I5: 2 | J5: =IF($I5>J$2, 0, 1) -> 0 | K5: =IF($I5>K$2, 0, 1) -> 0 | L5: =IF($I5>L$2, 0, 1) -> 1 | M5: =IF($I5>M$2, 0, 1) -> 1 | N5: =IF($I5>N$2, 0, 1) -> 1 | O5: =IF($I5>O$2, 0, 1) -> 1 | P5: =IF($I5>P$2, 0, 1) -> 1 | Q5: =IF($I5>Q$2, 0, 1) -> 1 | ... Y5: =IF($I5>Y$2, 0, 1) -> 1
A6: 4 | D6: SENS - Tires | F6: 6 | G6: 0 | H6: =1-G6 -> 1 | I6: 0 | J6: =IF($I6>J$2, 0, 1) -> 1 | K6: =IF($I6>K$2, 0, 1) -> 1 | L6: 1 | M6: 1 | N6: =IF($I6>N$2, 0, 1) -> 1 | O6: =IF($I6>O$2, 0, 1) -> 1 | P6: =IF($I6>P$2, 0, 1) -> 1 | Q6: =IF($I6>Q$2, 0, 1) -> 1 | R6: =IF($I6>R$2, 0, 1) -> 1 | S6: =IF($I6>S$2, 0, 1) -> 1 | T6: =IF($I6>T$2, 0, 1) -> 1 | U6: =IF($I6>U$2, 0, 1) -> 1 | ... Y6: =IF($I6>Y$2, 0, 1) -> 1
A7: 5 | D7: Solar | E7: 70 | G7: 0 | H7: =1-G7 -> 1 | I7: 0 | J7: =IF($I7>J$2, 0, 1) -> 1 | K7: =IF($I7>K$2, 0, 1) -> 1 | L7: =IF($I7>L$2, 0, 1) -> 1 | M7: =IF($I7>M$2, 0, 1) -> 1 | N7: =IF($I7>N$2, 0, 1) -> 1 | O7: =IF($I7>O$2, 0, 1) -> 1 | P7: =IF($I7>P$2, 0, 1) -> 1 | Q7: =IF($I7>Q$2, 0, 1) -> 1 | ... Y7: =IF($I7>Y$2, 0, 1) -> 1
J8: =IF($I8>J$2, 0, 1) -> 1 | K8: =IF($I8>K$2, 0, 1) -> 1 | L8: =IF($I8>L$2, 0, 1) -> 1 | M8: =IF($I8>M$2, 0, 1) -> 1 | N8: =IF($I8>N$2, 0, 1) -> 1 | O8: =IF($I8>O$2, 0, 1) -> 1 | P8: =IF($I8>P$2, 0, 1) -> 1 | Q8: =IF($I8>Q$2, 0, 1) -> 1 | ... Y8: =IF($I8>Y$2, 0, 1) -> 1
A9: 7 | D9: Nat Gas | E9: 100 | G9: 0 | H9: =1-G9 -> 1 | I9: 1 | J9: =IF($I9>J$2, 0, 1) -> 0 | K9: =IF($I9>K$2, 0, 1) -> 1 | L9: =IF($I9>L$2, 0, 1) -> 1 | M9: =IF($I9>M$2, 0, 1) -> 1 | N9: =IF($I9>N$2, 0, 1) -> 1 | O9: =IF($I9>O$2, 0, 1) -> 1 | P9: =IF($I9>P$2, 0, 1) -> 1 | Q9: =IF($I9>Q$2, 0, 1) -> 1 | ... Y9: =IF($I9>Y$2, 0, 1) -> 1
G10: 0 | H10: =1-G10 -> 1 | J10: =IF($I10>J$2, 0, 1) -> 1 | K10: =IF($I10>K$2, 0, 1) -> 1 | L10: =IF($I10>L$2, 0, 1) -> 1 | M10: =IF($I10>M$2, 0, 1) -> 1 | N10: =IF($I10>N$2, 0, 1) -> 1 | O10: =IF($I10>O$2, 0, 1) -> 1 | P10: =IF($I10>P$2, 0, 1) -> 1 | Q10: =IF($I10>Q$2, 0, 1) -> 1 | ... Y10: =IF($I10>Y$2, 0, 1) -> 1
G11: 0 | H11: =1-G11 -> 1 | J11: =IF($I11>J$2, 0, 1) -> 1 | K11: =IF($I11>K$2, 0, 1) -> 1 | L11: =IF($I11>L$2, 0, 1) -> 1 | M11: =IF($I11>M$2, 0, 1) -> 1 | N11: =IF($I11>N$2, 0, 1) -> 1 | O11: =IF($I11>O$2, 0, 1) -> 1 | P11: =IF($I11>P$2, 0, 1) -> 1 | Q11: =IF($I11>Q$2, 0, 1) -> 1 | ... Y11: =IF($I11>Y$2, 0, 1) -> 1
G12: 0 | H12: =1-G12 -> 1 | J12: =IF($I12>J$2, 0, 1) -> 1 | K12: =IF($I12>K$2, 0, 1) -> 1 | L12: =IF($I12>L$2, 0, 1) -> 1 | M12: =IF($I12>M$2, 0, 1) -> 1 | N12: =IF($I12>N$2, 0, 1) -> 1 | O12: =IF($I12>O$2, 0, 1) -> 1 | P12: =IF($I12>P$2, 0, 1) -> 1 | Q12: =IF($I12>Q$2, 0, 1) -> 1 | ... Y12: =IF($I12>Y$2, 0, 1) -> 1
G13: 0 | H13: =1-G13 -> 1 | J13: =IF($I13>J$2, 0, 1) -> 1 | K13: =IF($I13>K$2, 0, 1) -> 1 | L13: =IF($I13>L$2, 0, 1) -> 1 | M13: =IF($I13>M$2, 0, 1) -> 1 | N13: =IF($I13>N$2, 0, 1) -> 1 | O13: =IF($I13>O$2, 0, 1) -> 1 | P13: =IF($I13>P$2, 0, 1) -> 1 | Q13: =IF($I13>Q$2, 0, 1) -> 1 | ... Y13: =IF($I13>Y$2, 0, 1) -> 1
J14: =IF($I14>J$2, 0, 1) -> 1 | K14: =IF($I14>K$2, 0, 1) -> 1 | L14: =IF($I14>L$2, 0, 1) -> 1 | M14: =IF($I14>M$2, 0, 1) -> 1 | N14: =IF($I14>N$2, 0, 1) -> 1 | O14: =IF($I14>O$2, 0, 1) -> 1 | P14: =IF($I14>P$2, 0, 1) -> 1 | Q14: =IF($I14>Q$2, 0, 1) -> 1 | ... Y14: =IF($I14>Y$2, 0, 1) -> 1
J15: =IF($I15>J$2, 0, 1) -> 1 | K15: =IF($I15>K$2, 0, 1) -> 1 | L15: =IF($I15>L$2, 0, 1) -> 1 | M15: =IF($I15>M$2, 0, 1) -> 1 | N15: =IF($I15>N$2, 0, 1) -> 1 | O15: =IF($I15>O$2, 0, 1) -> 1 | P15: =IF($I15>P$2, 0, 1) -> 1 | Q15: =IF($I15>Q$2, 0, 1) -> 1 | ... Y15: =IF($I15>Y$2, 0, 1) -> 1
J16: =IF($I16>J$2, 0, 1) -> 1 | K16: =IF($I16>K$2, 0, 1) -> 1 | L16: =IF($I16>L$2, 0, 1) -> 1 | M16: =IF($I16>M$2, 0, 1) -> 1 | N16: =IF($I16>N$2, 0, 1) -> 1 | O16: =IF($I16>O$2, 0, 1) -> 1 | P16: =IF($I16>P$2, 0, 1) -> 1 | Q16: =IF($I16>Q$2, 0, 1) -> 1 | ... Y16: =IF($I16>Y$2, 0, 1) -> 1
J17: =IF($I17>J$2, 0, 1) -> 1 | K17: =IF($I17>K$2, 0, 1) -> 1 | L17: =IF($I17>L$2, 0, 1) -> 1 | M17: =IF($I17>M$2, 0, 1) -> 1 | N17: =IF($I17>N$2, 0, 1) -> 1 | O17: =IF($I17>O$2, 0, 1) -> 1 | P17: =IF($I17>P$2, 0, 1) -> 1 | Q17: =IF($I17>Q$2, 0, 1) -> 1 | ... Y17: =IF($I17>Y$2, 0, 1) -> 1
J18: =IF($I18>J$2, 0, 1) -> 1 | K18: =IF($I18>K$2, 0, 1) -> 1 | L18: =IF($I18>L$2, 0, 1) -> 1 | M18: =IF($I18>M$2, 0, 1) -> 1 | N18: =IF($I18>N$2, 0, 1) -> 1 | O18: =IF($I18>O$2, 0, 1) -> 1 | P18: =IF($I18>P$2, 0, 1) -> 1 | Q18: =IF($I18>Q$2, 0, 1) -> 1 | ... Y18: =IF($I18>Y$2, 0, 1) -> 1
J19: =IF($I19>J$2, 0, 1) -> 1 | K19: =IF($I19>K$2, 0, 1) -> 1 | L19: =IF($I19>L$2, 0, 1) -> 1 | M19: =IF($I19>M$2, 0, 1) -> 1 | N19: =IF($I19>N$2, 0, 1) -> 1 | O19: =IF($I19>O$2, 0, 1) -> 1 | P19: =IF($I19>P$2, 0, 1) -> 1 | Q19: =IF($I19>Q$2, 0, 1) -> 1 | ... Y19: =IF($I19>Y$2, 0, 1) -> 1
J20: =IF($I20>J$2, 0, 1) -> 1 | K20: =IF($I20>K$2, 0, 1) -> 1 | L20: =IF($I20>L$2, 0, 1) -> 1 | M20: =IF($I20>M$2, 0, 1) -> 1 | N20: =IF($I20>N$2, 0, 1) -> 1 | O20: =IF($I20>O$2, 0, 1) -> 1 | P20: =IF($I20>P$2, 0, 1) -> 1 | Q20: =IF($I20>Q$2, 0, 1) -> 1 | ... Y20: =IF($I20>Y$2, 0, 1) -> 1
J21: =IF($I21>J$2, 0, 1) -> 1 | K21: =IF($I21>K$2, 0, 1) -> 1 | L21: =IF($I21>L$2, 0, 1) -> 1 | M21: =IF($I21>M$2, 0, 1) -> 1 | N21: =IF($I21>N$2, 0, 1) -> 1 | O21: =IF($I21>O$2, 0, 1) -> 1 | P21: =IF($I21>P$2, 0, 1) -> 1 | Q21: =IF($I21>Q$2, 0, 1) -> 1 | ... Y21: =IF($I21>Y$2, 0, 1) -> 1
G22: 0 | H22: =1-G22 -> 1 | J22: =IF($I22>J$2, 0, 1) -> 1 | K22: =IF($I22>K$2, 0, 1) -> 1 | L22: =IF($I22>L$2, 0, 1) -> 1 | M22: =IF($I22>M$2, 0, 1) -> 1 | N22: =IF($I22>N$2, 0, 1) -> 1 | O22: =IF($I22>O$2, 0, 1) -> 1 | P22: =IF($I22>P$2, 0, 1) -> 1 | Q22: =IF($I22>Q$2, 0, 1) -> 1 | ... Y22: =IF($I22>Y$2, 0, 1) -> 1
J23: =IF($I23>J$2, 0, 1) -> 1 | K23: =IF($I23>K$2, 0, 1) -> 1 | L23: =IF($I23>L$2, 0, 1) -> 1 | M23: =IF($I23>M$2, 0, 1) -> 1 | N23: =IF($I23>N$2, 0, 1) -> 1 | O23: =IF($I23>O$2, 0, 1) -> 1 | P23: =IF($I23>P$2, 0, 1) -> 1 | Q23: =IF($I23>Q$2, 0, 1) -> 1 | ... Y23: =IF($I23>Y$2, 0, 1) -> 1
J24: =IF($I24>J$2, 0, 1) -> 1 | K24: =IF($I24>K$2, 0, 1) -> 1 | L24: =IF($I24>L$2, 0, 1) -> 1 | M24: =IF($I24>M$2, 0, 1) -> 1 | N24: =IF($I24>N$2, 0, 1) -> 1 | O24: =IF($I24>O$2, 0, 1) -> 1 | P24: =IF($I24>P$2, 0, 1) -> 1 | Q24: =IF($I24>Q$2, 0, 1) -> 1 | ... Y24: =IF($I24>Y$2, 0, 1) -> 1
J25: =IF($I25>J$2, 0, 1) -> 1 | K25: =IF($I25>K$2, 0, 1) -> 1 | L25: =IF($I25>L$2, 0, 1) -> 1 | M25: =IF($I25>M$2, 0, 1) -> 1 | N25: =IF($I25>N$2, 0, 1) -> 1 | O25: =IF($I25>O$2, 0, 1) -> 1 | P25: =IF($I25>P$2, 0, 1) -> 1 | Q25: =IF($I25>Q$2, 0, 1) -> 1 | ... Y25: =IF($I25>Y$2, 0, 1) -> 1
J26: =IF($I26>J$2, 0, 1) -> 1 | K26: =IF($I26>K$2, 0, 1) -> 1 | L26: =IF($I26>L$2, 0, 1) -> 1 | M26: =IF($I26>M$2, 0, 1) -> 1 | N26: =IF($I26>N$2, 0, 1) -> 1 | O26: =IF($I26>O$2, 0, 1) -> 1 | P26: =IF($I26>P$2, 0, 1) -> 1 | Q26: =IF($I26>Q$2, 0, 1) -> 1 | ... Y26: =IF($I26>Y$2, 0, 1) -> 1
J27: =IF($I27>J$2, 0, 1) -> 1 | K27: =IF($I27>K$2, 0, 1) -> 1 | L27: =IF($I27>L$2, 0, 1) -> 1 | M27: =IF($I27>M$2, 0, 1) -> 1 | N27: =IF($I27>N$2, 0, 1) -> 1 | O27: =IF($I27>O$2, 0, 1) -> 1 | P27: =IF($I27>P$2, 0, 1) -> 1 | Q27: =IF($I27>Q$2, 0, 1) -> 1 | ... Y27: =IF($I27>Y$2, 0, 1) -> 1
J28: =IF($I28>J$2, 0, 1) -> 1 | K28: =IF($I28>K$2, 0, 1) -> 1 | L28: =IF($I28>L$2, 0, 1) -> 1 | M28: =IF($I28>M$2, 0, 1) -> 1 | N28: =IF($I28>N$2, 0, 1) -> 1 | O28: =IF($I28>O$2, 0, 1) -> 1 | P28: =IF($I28>P$2, 0, 1) -> 1 | Q28: =IF($I28>Q$2, 0, 1) -> 1 | ... Y28: =IF($I28>Y$2, 0, 1) -> 1
J29: =IF($I29>J$2, 0, 1) -> 1 | K29: =IF($I29>K$2, 0, 1) -> 1 | L29: =IF($I29>L$2, 0, 1) -> 1 | M29: =IF($I29>M$2, 0, 1) -> 1 | N29: =IF($I29>N$2, 0, 1) -> 1 | O29: =IF($I29>O$2, 0, 1) -> 1 | P29: =IF($I29>P$2, 0, 1) -> 1 | Q29: =IF($I29>Q$2, 0, 1) -> 1 | ... Y29: =IF($I29>Y$2, 0, 1) -> 1
J30: =IF($I30>J$2, 0, 1) -> 1 | K30: =IF($I30>K$2, 0, 1) -> 1 | L30: =IF($I30>L$2, 0, 1) -> 1 | M30: =IF($I30>M$2, 0, 1) -> 1 | N30: =IF($I30>N$2, 0, 1) -> 1 | O30: =IF($I30>O$2, 0, 1) -> 1 | P30: =IF($I30>P$2, 0, 1) -> 1 | Q30: =IF($I30>Q$2, 0, 1) -> 1 | ... Y30: =IF($I30>Y$2, 0, 1) -> 1
J31: =IF($I31>J$2, 0, 1) -> 1 | K31: =IF($I31>K$2, 0, 1) -> 1 | L31: =IF($I31>L$2, 0, 1) -> 1 | M31: =IF($I31>M$2, 0, 1) -> 1 | N31: =IF($I31>N$2, 0, 1) -> 1 | O31: =IF($I31>O$2, 0, 1) -> 1 | P31: =IF($I31>P$2, 0, 1) -> 1 | Q31: =IF($I31>Q$2, 0, 1) -> 1 | ... Y31: =IF($I31>Y$2, 0, 1) -> 1
J32: =IF($I32>J$2, 0, 1) -> 1 | K32: =IF($I32>K$2, 0, 1) -> 1 | L32: =IF($I32>L$2, 0, 1) -> 1 | M32: =IF($I32>M$2, 0, 1) -> 1 | N32: =IF($I32>N$2, 0, 1) -> 1 | O32: =IF($I32>O$2, 0, 1) -> 1 | P32: =IF($I32>P$2, 0, 1) -> 1 | Q32: =IF($I32>Q$2, 0, 1) -> 1 | ... Y32: =IF($I32>Y$2, 0, 1) -> 1
J33: =IF($I33>J$2, 0, 1) -> 1 | K33: =IF($I33>K$2, 0, 1) -> 1 | L33: =IF($I33>L$2, 0, 1) -> 1 | M33: =IF($I33>M$2, 0, 1) -> 1 | N33: =IF($I33>N$2, 0, 1) -> 1 | O33: =IF($I33>O$2, 0, 1) -> 1 | P33: =IF($I33>P$2, 0, 1) -> 1 | Q33: =IF($I33>Q$2, 0, 1) -> 1 | ... Y33: =IF($I33>Y$2, 0, 1) -> 1
J34: =IF($I34>J$2, 0, 1) -> 1 | K34: =IF($I34>K$2, 0, 1) -> 1 | L34: =IF($I34>L$2, 0, 1) -> 1 | M34: =IF($I34>M$2, 0, 1) -> 1 | N34: =IF($I34>N$2, 0, 1) -> 1 | O34: =IF($I34>O$2, 0, 1) -> 1 | P34: =IF($I34>P$2, 0, 1) -> 1 | Q34: =IF($I34>Q$2, 0, 1) -> 1 | ... Y34: =IF($I34>Y$2, 0, 1) -> 1
... J64: =IF($I64>J$2, 0, 1) -> 1 | K64: =IF($I64>K$2, 0, 1) -> 1 | L64: =IF($I64>L$2, 0, 1) -> 1 | M64: =IF($I64>M$2, 0, 1) -> 1 | N64: =IF($I64>N$2, 0, 1) -> 1 | O64: =IF($I64>O$2, 0, 1) -> 1 | P64: =IF($I64>P$2, 0, 1) -> 1 | Q64: =IF($I64>Q$2, 0, 1) -> 1 | ... Y64: =IF($I64>Y$2, 0, 1) -> 1

Sheet Project CAPEX
A1: Project CapEx ($M) | E1: Project Start Year
A2: Project Reference | B2: Type | C2: Start Date | E2: 0 | F2: =E2+1 -> 1 | G2: =F2+1 -> 2 | H2: =G2+1 -> 3 | I2: =H2+1 -> 4 | J2: =I2+1 -> 5 | K2: =J2+1 -> 6 | L2: =K2+1 -> 7 | M2: =L2+1 -> 8 | ... T2: =S2+1 -> 15
A3: =IF(ISBLANK('Project Master Sheet'!A3)=FALSE, 'Project Master Sheet'!A3, "") -> 1 | B3: =_xlfn.IFNA(_xlfn.XLOOKUP(A3, 'Project Master Sheet'!A:A, 'Project Master Sheet'!D:D), "") -> Carbon | C3: =_xlfn.XLOOKUP(A3, 'Project Master Sheet'!A:A, 'Project Master Sheet'!I:I) -> 1 | E3: =IF($B3='Project List References'!$B$3, _xlfn.IFNA(_xlfn.XLOOKUP(E$2-$C3, 'GEN-CCGT'!$D$7:$AW$7, 'GEN-CCGT'!$D$24:$AW$24), 0), IF($B3='Project List References'!$B$4, _xlfn.IFNA(_xlfn.XLOOKUP(E$2-$C3, 'GEN-SOLAR'!$D$7:$AW$7, 'GEN-SOLAR'!$D$24:$AW$24), 0), IF($B3='Project List References'!$B$5, _xlfn.IFNA(_xlfn.XLOOKUP(E$2-$C3, 'GEN-BESS'!$D$7:$AW$7, 'GEN-BESS'!$D$24:$AW$24), 0), IF($B3='Project List References'!$B$6, _xlfn.IFNA(_xlfn.XLOOKUP(E$2-$C3, 'GEN-CARBON'!$D$7:$AW$7, 'GEN-CARBON'!$D$24:$AW$24), 0), IF($B3='Project List References'!$B$7, _xlfn.IFNA(_xlfn.XLOOKUP(E$2-$C3, 'SENS Coal'!$D$7:$AW$7, 'SENS Coal'!$D$24:$AW$24), 0), IF($B3='Project List References'!$B$8, _xlfn.IFNA(_xlfn.XLOOKUP(E$2-$C3, 'SENS Tires'!$D$7:$AW$7, 'SENS Tires'!$D$24:$AW$24), 0)))))))/_xlfn.XLOOKUP($B3, 'Assumptions & Inputs'!$F$76:$L$76, 'Assumptions & Inputs'!$F$77:$L$77)*IF(OR($B3='Project List References'!$B$3, $B3='Project List References'!$B$4, $B3='Project List References'!$B$5, $B3='Project List References'!$B$6), 'Project Master Sheet'!$E3, 'Project Master Sheet'!$F3) -> 0 | F3: =IF($B3='Project List References'!$B$3, _xlfn.IFNA(_xlfn.XLOOKUP(F$2-$C3, 'GEN-CCGT'!$D$7:$AW$7, 'GEN-CCGT'!$D$24:$AW$24), 0), IF($B3='Project List References'!$B$4, _xlfn.IFNA(_xlfn.XLOOKUP(F$2-$C3, 'GEN-SOLAR'!$D$7:$AW$7, 'GEN-SOLAR'!$D$24:$AW$24), 0), IF($B3='Project List References'!$B$5, _xlfn.IFNA(_xlfn.XLOOKUP(F$2-$C3, 'GEN-BESS'!$D$7:$AW$7, 'GEN-BESS'!$D$24:$AW$24), 0), IF($B3='Project List References'!$B$6, _xlfn.IFNA(_xlfn.XLOOKUP(F$2-$C3, 'GEN-CARBON'!$D$7:$AW$7, 'GEN-CARBON'!$D$24:$AW$24), 0), IF($B3='Project List References'!$B$7, _xlfn.IFNA(_xlfn.XLOOKUP(F$2-$C3, 'SENS Coal'!$D$7:$AW$7, 'SENS Coal'!$D$24:$AW$24), 0), IF($B3='Project List References'!$B$8, _xlfn.IFNA(_xlfn.XLOOKUP(F$2-$C3, 'SENS Tires'!$D$7:$AW$7, 'SENS Tires'!$D$24:$AW$24), 0)))))))/_xlfn.XLOOKUP($B3, 'Assumptions & Inputs'!$F$76:$L$76, 'Assumptions & Inputs'!$F$77:$L$77)*IF(OR($B3='Project List References'!$B$3, $B3='Project List References'!$B$4, $B3='Project List References'!$B$5, $B3='Project List References'!$B$6), 'Project Master Sheet'!$E3, 'Project Master Sheet'!$F3) -> -330 | G3: =IF($B3='Project List References'!$B$3, _xlfn.IFNA(_xlfn.XLOOKUP(G$2-$C3, 'GEN-CCGT'!$D$7:$AW$7, 'GEN-CCGT'!$D$24:$AW$24), 0), IF($B3='Project List References'!$B$4, _xlfn.IFNA(_xlfn.XLOOKUP(G$2-$C3, 'GEN-SOLAR'!$D$7:$AW$7, 'GEN-SOLAR'!$D$24:$AW$24), 0), IF($B3='Project List References'!$B$5, _xlfn.IFNA(_xlfn.XLOOKUP(G$2-$C3, 'GEN-BESS'!$D$7:$AW$7, 'GEN-BESS'!$D$24:$AW$24), 0), IF($B3='Project List References'!$B$6, _xlfn.IFNA(_xlfn.XLOOKUP(G$2-$C3, 'GEN-CARBON'!$D$7:$AW$7, 'GEN-CARBON'!$D$24:$AW$24), 0), IF($B3='Project List References'!$B$7, _xlfn.IFNA(_xlfn.XLOOKUP(G$2-$C3, 'SENS Coal'!$D$7:$AW$7, 'SENS Coal'!$D$24:$AW$24), 0), IF($B3='Project List References'!$B$8, _xlfn.IFNA(_xlfn.XLOOKUP(G$2-$C3, 'SENS Tires'!$D$7:$AW$7, 'SENS Tires'!$D$24:$AW$24), 0)))))))/_xlfn.XLOOKUP($B3, 'Assumptions & Inputs'!$F$76:$L$76, 'Assumptions & Inputs'!$F$77:$L$77)*IF(OR($B3='Project List References'!$B$3, $B3='Project List References'!$B$4, $B3='Project List References'!$B$5, $B3='Project List References'!$B$6), 'Project Master Sheet'!$E3, 'Project Master Sheet'!$F3) -> -360 | H3: =IF($B3='Project List References'!$B$3, _xlfn.IFNA(_xlfn.XLOOKUP(H$2-$C3, 'GEN-CCGT'!$D$7:$AW$7, 'GEN-CCGT'!$D$24:$AW$24), 0), IF($B3='Project List References'!$B$4, _xlfn.IFNA(_xlfn.XLOOKUP(H$2-$C3, 'GEN-SOLAR'!$D$7:$AW$7, 'GEN-SOLAR'!$D$24:$AW$24), 0), IF($B3='Project List References'!$B$5, _xlfn.IFNA(_xlfn.XLOOKUP(H$2-$C3, 'GEN-BESS'!$D$7:$AW$7, 'GEN-BESS'!$D$24:$AW$24), 0), IF($B3='Project List References'!$B$6, _xlfn.IFNA(_xlfn.XLOOKUP(H$2-$C3, 'GEN-CARBON'!$D$7:$AW$7, 'GEN-CARBON'!$D$24:$AW$24), 0), IF($B3='Project List References'!$B$7, _xlfn.IFNA(_xlfn.XLOOKUP(H$2-$C3, 'SENS Coal'!$D$7:$AW$7, 'SENS Coal'!$D$24:$AW$24), 0), IF($B3='Project List References'!$B$8, _xlfn.IFNA(_xlfn.XLOOKUP(H$2-$C3, 'SENS Tires'!$D$7:$AW$7, 'SENS Tires'!$D$24:$AW$24), 0)))))))/_xlfn.XLOOKUP($B3, 'Assumptions & Inputs'!$F$76:$L$76, 'Assumptions & Inputs'!$F$77:$L$77)*IF(OR($B3='Project List References'!$B$3, $B3='Project List References'!$B$4, $B3='Project List References'!$B$5, $B3='Project List References'!$B$6), 'Project Master Sheet'!$E3, 'Project Master Sheet'!$F3) -> -360 | I3: =IF($B3='Project List References'!$B$3, _xlfn.IFNA(_xlfn.XLOOKUP(I$2-$C3, 'GEN-CCGT'!$D$7:$AW$7, 'GEN-CCGT'!$D$24:$AW$24), 0), IF($B3='Project List References'!$B$4, _xlfn.IFNA(_xlfn.XLOOKUP(I$2-$C3, 'GEN-SOLAR'!$D$7:$AW$7, 'GEN-SOLAR'!$D$24:$AW$24), 0), IF($B3='Project List References'!$B$5, _xlfn.IFNA(_xlfn.XLOOKUP(I$2-$C3, 'GEN-BESS'!$D$7:$AW$7, 'GEN-BESS'!$D$24:$AW$24), 0), IF($B3='Project List References'!$B$6, _xlfn.IFNA(_xlfn.XLOOKUP(I$2-$C3, 'GEN-CARBON'!$D$7:$AW$7, 'GEN-CARBON'!$D$24:$AW$24), 0), IF($B3='Project List References'!$B$7, _xlfn.IFNA(_xlfn.XLOOKUP(I$2-$C3, 'SENS Coal'!$D$7:$AW$7, 'SENS Coal'!$D$24:$AW$24), 0), IF($B3='Project List References'!$B$8, _xlfn.IFNA(_xlfn.XLOOKUP(I$2-$C3, 'SENS Tires'!$D$7:$AW$7, 'SENS Tires'!$D$24:$AW$24), 0)))))))/_xlfn.XLOOKUP($B3, 'Assumptions & Inputs'!$F$76:$L$76, 'Assumptions & Inputs'!$F$77:$L$77)*IF(OR($B3='Project List References'!$B$3, $B3='Project List References'!$B$4, $B3='Project List References'!$B$5, $B3='Project List References'!$B$6), 'Project Master Sheet'!$E3, 'Project Master Sheet'!$F3) -> -360 | J3: =IF($B3='Project List References'!$B$3, _xlfn.IFNA(_xlfn.XLOOKUP(J$2-$C3, 'GEN-CCGT'!$D$7:$AW$7, 'GEN-CCGT'!$D$24:$AW$24), 0), IF($B3='Project List References'!$B$4, _xlfn.IFNA(_xlfn.XLOOKUP(J$2-$C3, 'GEN-SOLAR'!$D$7:$AW$7, 'GEN-SOLAR'!$D$24:$AW$24), 0), IF($B3='Project List References'!$B$5, _xlfn.IFNA(_xlfn.XLOOKUP(J$2-$C3, 'GEN-BESS'!$D$7:$AW$7, 'GEN-BESS'!$D$24:$AW$24), 0), IF($B3='Project List References'!$B$6, _xlfn.IFNA(_xlfn.XLOOKUP(J$2-$C3, 'GEN-CARBON'!$D$7:$AW$7, 'GEN-CARBON'!$D$24:$AW$24), 0), IF($B3='Project List References'!$B$7, _xlfn.IFNA(_xlfn.XLOOKUP(J$2-$C3, 'SENS Coal'!$D$7:$AW$7, 'SENS Coal'!$D$24:$AW$24), 0), IF($B3='Project List References'!$B$8, _xlfn.IFNA(_xlfn.XLOOKUP(J$2-$C3, 'SENS Tires'!$D$7:$AW$7, 'SENS Tires'!$D$24:$AW$24), 0)))))))/_xlfn.XLOOKUP($B3, 'Assumptions & Inputs'!$F$76:$L$76, 'Assumptions & Inputs'!$F$77:$L$77)*IF(OR($B3='Project List References'!$B$3, $B3='Project List References'!$B$4, $B3='Project List References'!$B$5, $B3='Project List References'!$B$6), 'Project Master Sheet'!$E3, 'Project Master Sheet'!$F3) -> -30 | K3: =IF($B3='Project List References'!$B$3, _xlfn.IFNA(_xlfn.XLOOKUP(K$2-$C3, 'GEN-CCGT'!$D$7:$AW$7, 'GEN-CCGT'!$D$24:$AW$24), 0), IF($B3='Project List References'!$B$4, _xlfn.IFNA(_xlfn.XLOOKUP(K$2-$C3, 'GEN-SOLAR'!$D$7:$AW$7, 'GEN-SOLAR'!$D$24:$AW$24), 0), IF($B3='Project List References'!$B$5, _xlfn.IFNA(_xlfn.XLOOKUP(K$2-$C3, 'GEN-BESS'!$D$7:$AW$7, 'GEN-BESS'!$D$24:$AW$24), 0), IF($B3='Project List References'!$B$6, _xlfn.IFNA(_xlfn.XLOOKUP(K$2-$C3, 'GEN-CARBON'!$D$7:$AW$7, 'GEN-CARBON'!$D$24:$AW$24), 0), IF($B3='Project List References'!$B$7, _xlfn.IFNA(_xlfn.XLOOKUP(K$2-$C3, 'SENS Coal'!$D$7:$AW$7, 'SENS Coal'!$D$24:$AW$24), 0), IF($B3='Project List References'!$B$8, _xlfn.IFNA(_xlfn.XLOOKUP(K$2-$C3, 'SENS Tires'!$D$7:$AW$7, 'SENS Tires'!$D$24:$AW$24), 0)))))))/_xlfn.XLOOKUP($B3, 'Assumptions & Inputs'!$F$76:$L$76, 'Assumptions & Inputs'!$F$77:$L$77)*IF(OR($B3='Project List References'!$B$3, $B3='Project List References'!$B$4, $B3='Project List References'!$B$5, $B3='Project List References'!$B$6), 'Project Master Sheet'!$E3, 'Project Master Sheet'!$F3) -> 0 | L3: =IF($B3='Project List References'!$B$3, _xlfn.IFNA(_xlfn.XLOOKUP(L$2-$C3, 'GEN-CCGT'!$D$7:$AW$7, 'GEN-CCGT'!$D$24:$AW$24), 0), IF($B3='Project List References'!$B$4, _xlfn.IFNA(_xlfn.XLOOKUP(L$2-$C3, 'GEN-SOLAR'!$D$7:$AW$7, 'GEN-SOLAR'!$D$24:$AW$24), 0), IF($B3='Project List References'!$B$5, _xlfn.IFNA(_xlfn.XLOOKUP(L$2-$C3, 'GEN-BESS'!$D$7:$AW$7, 'GEN-BESS'!$D$24:$AW$24), 0), IF($B3='Project List References'!$B$6, _xlfn.IFNA(_xlfn.XLOOKUP(L$2-$C3, 'GEN-CARBON'!$D$7:$AW$7, 'GEN-CARBON'!$D$24:$AW$24), 0), IF($B3='Project List References'!$B$7, _xlfn.IFNA(_xlfn.XLOOKUP(L$2-$C3, 'SENS Coal'!$D$7:$AW$7, 'SENS Coal'!$D$24:$AW$24), 0), IF($B3='Project List References'!$B$8, _xlfn.IFNA(_xlfn.XLOOKUP(L$2-$C3, 'SENS Tires'!$D$7:$AW$7, 'SENS Tires'!$D$24:$AW$24), 0)))))))/_xlfn.XLOOKUP($B3, 'Assumptions & Inputs'!$F$76:$L$76, 'Assumptions & Inputs'!$F$77:$L$77)*IF(OR($B3='Project List References'!$B$3, $B3='Project List References'!$B$4, $B3='Project List References'!$B$5, $B3='Project List References'!$B$6), 'Project Master Sheet'!$E3, 'Project Master Sheet'!$F3) -> 0 | ... T3: =IF($B3='Project List References'!$B$3, _xlfn.IFNA(_xlfn.XLOOKUP(T$2-$C3, 'GEN-CCGT'!$D$7:$AW$7, 'GEN-CCGT'!$D$24:$AW$24), 0), IF($B3='Project List References'!$B$4, _xlfn.IFNA(_xlfn.XLOOKUP(T$2-$C3, 'GEN-SOLAR'!$D$7:$AW$7, 'GEN-SOLAR'!$D$24:$AW$24), 0), IF($B3='Project List References'!$B$5, _xlfn.IFNA(_xlfn.XLOOKUP(T$2-$C3, 'GEN-BESS'!$D$7:$AW$7, 'GEN-BESS'!$D$24:$AW$24), 0), IF($B3='Project List References'!$B$6, _xlfn.IFNA(_xlfn.XLOOKUP(T$2-$C3, 'GEN-CARBON'!$D$7:$AW$7, 'GEN-CARBON'!$D$24:$AW$24), 0), IF($B3='Project List References'!$B$7, _xlfn.IFNA(_xlfn.XLOOKUP(T$2-$C3, 'SENS Coal'!$D$7:$AW$7, 'SENS Coal'!$D$24:$AW$24), 0), IF($B3='Project List References'!$B$8, _xlfn.IFNA(_xlfn.XLOOKUP(T$2-$C3, 'SENS Tires'!$D$7:$AW$7, 'SENS Tires'!$D$24:$AW$24), 0)))))))/_xlfn.XLOOKUP($B3, 'Assumptions & Inputs'!$F$76:$L$76, 'Assumptions & Inputs'!$F$77:$L$77)*IF(OR($B3='Project List References'!$B$3, $B3='Project List References'!$B$4, $B3='Project List References'!$B$5, $B3='Project List References'!$B$6), 'Project Master Sheet'!$E3, 'Project Master Sheet'!$F3) -> 0
A4: =IF(ISBLANK('Project Master Sheet'!A4)=FALSE, 'Project Master Sheet'!A4, "") -> 2 | B4: =_xlfn.IFNA(_xlfn.XLOOKUP(A4, 'Project Master Sheet'!A:A, 'Project Master Sheet'!D:D), "") -> BESS | C4: =_xlfn.XLOOKUP(A4, 'Project Master Sheet'!A:A, 'Project Master Sheet'!I:I) -> 1 | E4: =IF($B4='Project List References'!$B$3, _xlfn.IFNA(_xlfn.XLOOKUP(E$2-$C4, 'GEN-CCGT'!$D$7:$AW$7, 'GEN-CCGT'!$D$24:$AW$24), 0), IF($B4='Project List References'!$B$4, _xlfn.IFNA(_xlfn.XLOOKUP(E$2-$C4, 'GEN-SOLAR'!$D$7:$AW$7, 'GEN-SOLAR'!$D$24:$AW$24), 0), IF($B4='Project List References'!$B$5, _xlfn.IFNA(_xlfn.XLOOKUP(E$2-$C4, 'GEN-BESS'!$D$7:$AW$7, 'GEN-BESS'!$D$24:$AW$24), 0), IF($B4='Project List References'!$B$6, _xlfn.IFNA(_xlfn.XLOOKUP(E$2-$C4, 'GEN-CARBON'!$D$7:$AW$7, 'GEN-CARBON'!$D$24:$AW$24), 0), IF($B4='Project List References'!$B$7, _xlfn.IFNA(_xlfn.XLOOKUP(E$2-$C4, 'SENS Coal'!$D$7:$AW$7, 'SENS Coal'!$D$24:$AW$24), 0), IF($B4='Project List References'!$B$8, _xlfn.IFNA(_xlfn.XLOOKUP(E$2-$C4, 'SENS Tires'!$D$7:$AW$7, 'SENS Tires'!$D$24:$AW$24), 0)))))))/_xlfn.XLOOKUP($B4, 'Assumptions & Inputs'!$F$76:$L$76, 'Assumptions & Inputs'!$F$77:$L$77)*IF(OR($B4='Project List References'!$B$3, $B4='Project List References'!$B$4, $B4='Project List References'!$B$5, $B4='Project List References'!$B$6), 'Project Master Sheet'!$E4, 'Project Master Sheet'!$F4) -> 0 | F4: =IF($B4='Project List References'!$B$3, _xlfn.IFNA(_xlfn.XLOOKUP(F$2-$C4, 'GEN-CCGT'!$D$7:$AW$7, 'GEN-CCGT'!$D$24:$AW$24), 0), IF($B4='Project List References'!$B$4, _xlfn.IFNA(_xlfn.XLOOKUP(F$2-$C4, 'GEN-SOLAR'!$D$7:$AW$7, 'GEN-SOLAR'!$D$24:$AW$24), 0), IF($B4='Project List References'!$B$5, _xlfn.IFNA(_xlfn.XLOOKUP(F$2-$C4, 'GEN-BESS'!$D$7:$AW$7, 'GEN-BESS'!$D$24:$AW$24), 0), IF($B4='Project List References'!$B$6, _xlfn.IFNA(_xlfn.XLOOKUP(F$2-$C4, 'GEN-CARBON'!$D$7:$AW$7, 'GEN-CARBON'!$D$24:$AW$24), 0), IF($B4='Project List References'!$B$7, _xlfn.IFNA(_xlfn.XLOOKUP(F$2-$C4, 'SENS Coal'!$D$7:$AW$7, 'SENS Coal'!$D$24:$AW$24), 0), IF($B4='Project List References'!$B$8, _xlfn.IFNA(_xlfn.XLOOKUP(F$2-$C4, 'SENS Tires'!$D$7:$AW$7, 'SENS Tires'!$D$24:$AW$24), 0)))))))/_xlfn.XLOOKUP($B4, 'Assumptions & Inputs'!$F$76:$L$76, 'Assumptions & Inputs'!$F$77:$L$77)*IF(OR($B4='Project List References'!$B$3, $B4='Project List References'!$B$4, $B4='Project List References'!$B$5, $B4='Project List References'!$B$6), 'Project Master Sheet'!$E4, 'Project Master Sheet'!$F4) -> -52.708333 | G4: =IF($B4='Project List References'!$B$3, _xlfn.IFNA(_xlfn.XLOOKUP(G$2-$C4, 'GEN-CCGT'!$D$7:$AW$7, 'GEN-CCGT'!$D$24:$AW$24), 0), IF($B4='Project List References'!$B$4, _xlfn.IFNA(_xlfn.XLOOKUP(G$2-$C4, 'GEN-SOLAR'!$D$7:$AW$7, 'GEN-SOLAR'!$D$24:$AW$24), 0), IF($B4='Project List References'!$B$5, _xlfn.IFNA(_xlfn.XLOOKUP(G$2-$C4, 'GEN-BESS'!$D$7:$AW$7, 'GEN-BESS'!$D$24:$AW$24), 0), IF($B4='Project List References'!$B$6, _xlfn.IFNA(_xlfn.XLOOKUP(G$2-$C4, 'GEN-CARBON'!$D$7:$AW$7, 'GEN-CARBON'!$D$24:$AW$24), 0), IF($B4='Project List References'!$B$7, _xlfn.IFNA(_xlfn.XLOOKUP(G$2-$C4, 'SENS Coal'!$D$7:$AW$7, 'SENS Coal'!$D$24:$AW$24), 0), IF($B4='Project List References'!$B$8, _xlfn.IFNA(_xlfn.XLOOKUP(G$2-$C4, 'SENS Tires'!$D$7:$AW$7, 'SENS Tires'!$D$24:$AW$24), 0)))))))/_xlfn.XLOOKUP($B4, 'Assumptions & Inputs'!$F$76:$L$76, 'Assumptions & Inputs'!$F$77:$L$77)*IF(OR($B4='Project List References'!$B$3, $B4='Project List References'!$B$4, $B4='Project List References'!$B$5, $B4='Project List References'!$B$6), 'Project Master Sheet'!$E4, 'Project Master Sheet'!$F4) -> -4.7916667 | H4: =IF($B4='Project List References'!$B$3, _xlfn.IFNA(_xlfn.XLOOKUP(H$2-$C4, 'GEN-CCGT'!$D$7:$AW$7, 'GEN-CCGT'!$D$24:$AW$24), 0), IF($B4='Project List References'!$B$4, _xlfn.IFNA(_xlfn.XLOOKUP(H$2-$C4, 'GEN-SOLAR'!$D$7:$AW$7, 'GEN-SOLAR'!$D$24:$AW$24), 0), IF($B4='Project List References'!$B$5, _xlfn.IFNA(_xlfn.XLOOKUP(H$2-$C4, 'GEN-BESS'!$D$7:$AW$7, 'GEN-BESS'!$D$24:$AW$24), 0), IF($B4='Project List References'!$B$6, _xlfn.IFNA(_xlfn.XLOOKUP(H$2-$C4, 'GEN-CARBON'!$D$7:$AW$7, 'GEN-CARBON'!$D$24:$AW$24), 0), IF($B4='Project List References'!$B$7, _xlfn.IFNA(_xlfn.XLOOKUP(H$2-$C4, 'SENS Coal'!$D$7:$AW$7, 'SENS Coal'!$D$24:$AW$24), 0), IF($B4='Project List References'!$B$8, _xlfn.IFNA(_xlfn.XLOOKUP(H$2-$C4, 'SENS Tires'!$D$7:$AW$7, 'SENS Tires'!$D$24:$AW$24), 0)))))))/_xlfn.XLOOKUP($B4, 'Assumptions & Inputs'!$F$76:$L$76, 'Assumptions & Inputs'!$F$77:$L$77)*IF(OR($B4='Project List References'!$B$3, $B4='Project List References'!$B$4, $B4='Project List References'!$B$5, $B4='Project List References'!$B$6), 'Project Master Sheet'!$E4, 'Project Master Sheet'!$F4) -> 0 | I4: =IF($B4='Project List References'!$B$3, _xlfn.IFNA(_xlfn.XLOOKUP(I$2-$C4, 'GEN-CCGT'!$D$7:$AW$7, 'GEN-CCGT'!$D$24:$AW$24), 0), IF($B4='Project List References'!$B$4, _xlfn.IFNA(_xlfn.XLOOKUP(I$2-$C4, 'GEN-SOLAR'!$D$7:$AW$7, 'GEN-SOLAR'!$D$24:$AW$24), 0), IF($B4='Project List References'!$B$5, _xlfn.IFNA(_xlfn.XLOOKUP(I$2-$C4, 'GEN-BESS'!$D$7:$AW$7, 'GEN-BESS'!$D$24:$AW$24), 0), IF($B4='Project List References'!$B$6, _xlfn.IFNA(_xlfn.XLOOKUP(I$2-$C4, 'GEN-CARBON'!$D$7:$AW$7, 'GEN-CARBON'!$D$24:$AW$24), 0), IF($B4='Project List References'!$B$7, _xlfn.IFNA(_xlfn.XLOOKUP(I$2-$C4, 'SENS Coal'!$D$7:$AW$7, 'SENS Coal'!$D$24:$AW$24), 0), IF($B4='Project List References'!$B$8, _xlfn.IFNA(_xlfn.XLOOKUP(I$2-$C4, 'SENS Tires'!$D$7:$AW$7, 'SENS Tires'!$D$24:$AW$24), 0)))))))/_xlfn.XLOOKUP($B4, 'Assumptions & Inputs'!$F$76:$L$76, 'Assumptions & Inputs'!$F$77:$L$77)*IF(OR($B4='Project List References'!$B$3, $B4='Project List References'!$B$4, $B4='Project List References'!$B$5, $B4='Project List References'!$B$6), 'Project Master Sheet'!$E4, 'Project Master Sheet'!$F4) -> 0 | J4: =IF($B4='Project List References'!$B$3, _xlfn.IFNA(_xlfn.XLOOKUP(J$2-$C4, 'GEN-CCGT'!$D$7:$AW$7, 'GEN-CCGT'!$D$24:$AW$24), 0), IF($B4='Project List References'!$B$4, _xlfn.IFNA(_xlfn.XLOOKUP(J$2-$C4, 'GEN-SOLAR'!$D$7:$AW$7, 'GEN-SOLAR'!$D$24:$AW$24), 0), IF($B4='Project List References'!$B$5, _xlfn.IFNA(_xlfn.XLOOKUP(J$2-$C4, 'GEN-BESS'!$D$7:$AW$7, 'GEN-BESS'!$D$24:$AW$24), 0), IF($B4='Project List References'!$B$6, _xlfn.IFNA(_xlfn.XLOOKUP(J$2-$C4, 'GEN-CARBON'!$D$7:$AW$7, 'GEN-CARBON'!$D$24:$AW$24), 0), IF($B4='Project List References'!$B$7, _xlfn.IFNA(_xlfn.XLOOKUP(J$2-$C4, 'SENS Coal'!$D$7:$AW$7, 'SENS Coal'!$D$24:$AW$24), 0), IF($B4='Project List References'!$B$8, _xlfn.IFNA(_xlfn.XLOOKUP(J$2-$C4, 'SENS Tires'!$D$7:$AW$7, 'SENS Tires'!$D$24:$AW$24), 0)))))))/_xlfn.XLOOKUP($B4, 'Assumptions & Inputs'!$F$76:$L$76, 'Assumptions & Inputs'!$F$77:$L$77)*IF(OR($B4='Project List References'!$B$3, $B4='Project List References'!$B$4, $B4='Project List References'!$B$5, $B4='Project List References'!$B$6), 'Project Master Sheet'!$E4, 'Project Master Sheet'!$F4) -> 0 | K4: =IF($B4='Project List References'!$B$3, _xlfn.IFNA(_xlfn.XLOOKUP(K$2-$C4, 'GEN-CCGT'!$D$7:$AW$7, 'GEN-CCGT'!$D$24:$AW$24), 0), IF($B4='Project List References'!$B$4, _xlfn.IFNA(_xlfn.XLOOKUP(K$2-$C4, 'GEN-SOLAR'!$D$7:$AW$7, 'GEN-SOLAR'!$D$24:$AW$24), 0), IF($B4='Project List References'!$B$5, _xlfn.IFNA(_xlfn.XLOOKUP(K$2-$C4, 'GEN-BESS'!$D$7:$AW$7, 'GEN-BESS'!$D$24:$AW$24), 0), IF($B4='Project List References'!$B$6, _xlfn.IFNA(_xlfn.XLOOKUP(K$2-$C4, 'GEN-CARBON'!$D$7:$AW$7, 'GEN-CARBON'!$D$24:$AW$24), 0), IF($B4='Project List References'!$B$7, _xlfn.IFNA(_xlfn.XLOOKUP(K$2-$C4, 'SENS Coal'!$D$7:$AW$7, 'SENS Coal'!$D$24:$AW$24), 0), IF($B4='Project List References'!$B$8, _xlfn.IFNA(_xlfn.XLOOKUP(K$2-$C4, 'SENS Tires'!$D$7:$AW$7, 'SENS Tires'!$D$24:$AW$24), 0)))))))/_xlfn.XLOOKUP($B4, 'Assumptions & Inputs'!$F$76:$L$76, 'Assumptions & Inputs'!$F$77:$L$77)*IF(OR($B4='Project List References'!$B$3, $B4='Project List References'!$B$4, $B4='Project List References'!$B$5, $B4='Project List References'!$B$6), 'Project Master Sheet'!$E4, 'Project Master Sheet'!$F4) -> 0 | L4: =IF($B4='Project List References'!$B$3, _xlfn.IFNA(_xlfn.XLOOKUP(L$2-$C4, 'GEN-CCGT'!$D$7:$AW$7, 'GEN-CCGT'!$D$24:$AW$24), 0), IF($B4='Project List References'!$B$4, _xlfn.IFNA(_xlfn.XLOOKUP(L$2-$C4, 'GEN-SOLAR'!$D$7:$AW$7, 'GEN-SOLAR'!$D$24:$AW$24), 0), IF($B4='Project List References'!$B$5, _xlfn.IFNA(_xlfn.XLOOKUP(L$2-$C4, 'GEN-BESS'!$D$7:$AW$7, 'GEN-BESS'!$D$24:$AW$24), 0), IF($B4='Project List References'!$B$6, _xlfn.IFNA(_xlfn.XLOOKUP(L$2-$C4, 'GEN-CARBON'!$D$7:$AW$7, 'GEN-CARBON'!$D$24:$AW$24), 0), IF($B4='Project List References'!$B$7, _xlfn.IFNA(_xlfn.XLOOKUP(L$2-$C4, 'SENS Coal'!$D$7:$AW$7, 'SENS Coal'!$D$24:$AW$24), 0), IF($B4='Project List References'!$B$8, _xlfn.IFNA(_xlfn.XLOOKUP(L$2-$C4, 'SENS Tires'!$D$7:$AW$7, 'SENS Tires'!$D$24:$AW$24), 0)))))))/_xlfn.XLOOKUP($B4, 'Assumptions & Inputs'!$F$76:$L$76, 'Assumptions & Inputs'!$F$77:$L$77)*IF(OR($B4='Project List References'!$B$3, $B4='Project List References'!$B$4, $B4='Project List References'!$B$5, $B4='Project List References'!$B$6), 'Project Master Sheet'!$E4, 'Project Master Sheet'!$F4) -> 0 | ... T4: =IF($B4='Project List References'!$B$3, _xlfn.IFNA(_xlfn.XLOOKUP(T$2-$C4, 'GEN-CCGT'!$D$7:$AW$7, 'GEN-CCGT'!$D$24:$AW$24), 0), IF($B4='Project List References'!$B$4, _xlfn.IFNA(_xlfn.XLOOKUP(T$2-$C4, 'GEN-SOLAR'!$D$7:$AW$7, 'GEN-SOLAR'!$D$24:$AW$24), 0), IF($B4='Project List References'!$B$5, _xlfn.IFNA(_xlfn.XLOOKUP(T$2-$C4, 'GEN-BESS'!$D$7:$AW$7, 'GEN-BESS'!$D$24:$AW$24), 0), IF($B4='Project List References'!$B$6, _xlfn.IFNA(_xlfn.XLOOKUP(T$2-$C4, 'GEN-CARBON'!$D$7:$AW$7, 'GEN-CARBON'!$D$24:$AW$24), 0), IF($B4='Project List References'!$B$7, _xlfn.IFNA(_xlfn.XLOOKUP(T$2-$C4, 'SENS Coal'!$D$7:$AW$7, 'SENS Coal'!$D$24:$AW$24), 0), IF($B4='Project List References'!$B$8, _xlfn.IFNA(_xlfn.XLOOKUP(T$2-$C4, 'SENS Tires'!$D$7:$AW$7, 'SENS Tires'!$D$24:$AW$24), 0)))))))/_xlfn.XLOOKUP($B4, 'Assumptions & Inputs'!$F$76:$L$76, 'Assumptions & Inputs'!$F$77:$L$77)*IF(OR($B4='Project List References'!$B$3, $B4='Project List References'!$B$4, $B4='Project List References'!$B$5, $B4='Project List References'!$B$6), 'Project Master Sheet'!$E4, 'Project Master Sheet'!$F4) -> 0
A5: =IF(ISBLANK('Project Master Sheet'!A5)=FALSE, 'Project Master Sheet'!A5, "") -> 3 | B5: =_xlfn.IFNA(_xlfn.XLOOKUP(A5, 'Project Master Sheet'!A:A, 'Project Master Sheet'!D:D), "") -> SENS - Coal | C5: =_xlfn.XLOOKUP(A5, 'Project Master Sheet'!A:A, 'Project Master Sheet'!I:I) -> 2 | E5: =IF($B5='Project List References'!$B$3, _xlfn.IFNA(_xlfn.XLOOKUP(E$2-$C5, 'GEN-CCGT'!$D$7:$AW$7, 'GEN-CCGT'!$D$24:$AW$24), 0), IF($B5='Project List References'!$B$4, _xlfn.IFNA(_xlfn.XLOOKUP(E$2-$C5, 'GEN-SOLAR'!$D$7:$AW$7, 'GEN-SOLAR'!$D$24:$AW$24), 0), IF($B5='Project List References'!$B$5, _xlfn.IFNA(_xlfn.XLOOKUP(E$2-$C5, 'GEN-BESS'!$D$7:$AW$7, 'GEN-BESS'!$D$24:$AW$24), 0), IF($B5='Project List References'!$B$6, _xlfn.IFNA(_xlfn.XLOOKUP(E$2-$C5, 'GEN-CARBON'!$D$7:$AW$7, 'GEN-CARBON'!$D$24:$AW$24), 0), IF($B5='Project List References'!$B$7, _xlfn.IFNA(_xlfn.XLOOKUP(E$2-$C5, 'SENS Coal'!$D$7:$AW$7, 'SENS Coal'!$D$24:$AW$24), 0), IF($B5='Project List References'!$B$8, _xlfn.IFNA(_xlfn.XLOOKUP(E$2-$C5, 'SENS Tires'!$D$7:$AW$7, 'SENS Tires'!$D$24:$AW$24), 0)))))))/_xlfn.XLOOKUP($B5, 'Assumptions & Inputs'!$F$76:$L$76, 'Assumptions & Inputs'!$F$77:$L$77)*IF(OR($B5='Project List References'!$B$3, $B5='Project List References'!$B$4, $B5='Project List References'!$B$5, $B5='Project List References'!$B$6), 'Project Master Sheet'!$E5, 'Project Master Sheet'!$F5) -> 0 | F5: =IF($B5='Project List References'!$B$3, _xlfn.IFNA(_xlfn.XLOOKUP(F$2-$C5, 'GEN-CCGT'!$D$7:$AW$7, 'GEN-CCGT'!$D$24:$AW$24), 0), IF($B5='Project List References'!$B$4, _xlfn.IFNA(_xlfn.XLOOKUP(F$2-$C5, 'GEN-SOLAR'!$D$7:$AW$7, 'GEN-SOLAR'!$D$24:$AW$24), 0), IF($B5='Project List References'!$B$5, _xlfn.IFNA(_xlfn.XLOOKUP(F$2-$C5, 'GEN-BESS'!$D$7:$AW$7, 'GEN-BESS'!$D$24:$AW$24), 0), IF($B5='Project List References'!$B$6, _xlfn.IFNA(_xlfn.XLOOKUP(F$2-$C5, 'GEN-CARBON'!$D$7:$AW$7, 'GEN-CARBON'!$D$24:$AW$24), 0), IF($B5='Project List References'!$B$7, _xlfn.IFNA(_xlfn.XLOOKUP(F$2-$C5, 'SENS Coal'!$D$7:$AW$7, 'SENS Coal'!$D$24:$AW$24), 0), IF($B5='Project List References'!$B$8, _xlfn.IFNA(_xlfn.XLOOKUP(F$2-$C5, 'SENS Tires'!$D$7:$AW$7, 'SENS Tires'!$D$24:$AW$24), 0)))))))/_xlfn.XLOOKUP($B5, 'Assumptions & Inputs'!$F$76:$L$76, 'Assumptions & Inputs'!$F$77:$L$77)*IF(OR($B5='Project List References'!$B$3, $B5='Project List References'!$B$4, $B5='Project List References'!$B$5, $B5='Project List References'!$B$6), 'Project Master Sheet'!$E5, 'Project Master Sheet'!$F5) -> 0 | G5: =IF($B5='Project List References'!$B$3, _xlfn.IFNA(_xlfn.XLOOKUP(G$2-$C5, 'GEN-CCGT'!$D$7:$AW$7, 'GEN-CCGT'!$D$24:$AW$24), 0), IF($B5='Project List References'!$B$4, _xlfn.IFNA(_xlfn.XLOOKUP(G$2-$C5, 'GEN-SOLAR'!$D$7:$AW$7, 'GEN-SOLAR'!$D$24:$AW$24), 0), IF($B5='Project List References'!$B$5, _xlfn.IFNA(_xlfn.XLOOKUP(G$2-$C5, 'GEN-BESS'!$D$7:$AW$7, 'GEN-BESS'!$D$24:$AW$24), 0), IF($B5='Project List References'!$B$6, _xlfn.IFNA(_xlfn.XLOOKUP(G$2-$C5, 'GEN-CARBON'!$D$7:$AW$7, 'GEN-CARBON'!$D$24:$AW$24), 0), IF($B5='Project List References'!$B$7, _xlfn.IFNA(_xlfn.XLOOKUP(G$2-$C5, 'SENS Coal'!$D$7:$AW$7, 'SENS Coal'!$D$24:$AW$24), 0), IF($B5='Project List References'!$B$8, _xlfn.IFNA(_xlfn.XLOOKUP(G$2-$C5, 'SENS Tires'!$D$7:$AW$7, 'SENS Tires'!$D$24:$AW$24), 0)))))))/_xlfn.XLOOKUP($B5, 'Assumptions & Inputs'!$F$76:$L$76, 'Assumptions & Inputs'!$F$77:$L$77)*IF(OR($B5='Project List References'!$B$3, $B5='Project List References'!$B$4, $B5='Project List References'!$B$5, $B5='Project List References'!$B$6), 'Project Master Sheet'!$E5, 'Project Master Sheet'!$F5) -> -660 | H5: =IF($B5='Project List References'!$B$3, _xlfn.IFNA(_xlfn.XLOOKUP(H$2-$C5, 'GEN-CCGT'!$D$7:$AW$7, 'GEN-CCGT'!$D$24:$AW$24), 0), IF($B5='Project List References'!$B$4, _xlfn.IFNA(_xlfn.XLOOKUP(H$2-$C5, 'GEN-SOLAR'!$D$7:$AW$7, 'GEN-SOLAR'!$D$24:$AW$24), 0), IF($B5='Project List References'!$B$5, _xlfn.IFNA(_xlfn.XLOOKUP(H$2-$C5, 'GEN-BESS'!$D$7:$AW$7, 'GEN-BESS'!$D$24:$AW$24), 0), IF($B5='Project List References'!$B$6, _xlfn.IFNA(_xlfn.XLOOKUP(H$2-$C5, 'GEN-CARBON'!$D$7:$AW$7, 'GEN-CARBON'!$D$24:$AW$24), 0), IF($B5='Project List References'!$B$7, _xlfn.IFNA(_xlfn.XLOOKUP(H$2-$C5, 'SENS Coal'!$D$7:$AW$7, 'SENS Coal'!$D$24:$AW$24), 0), IF($B5='Project List References'!$B$8, _xlfn.IFNA(_xlfn.XLOOKUP(H$2-$C5, 'SENS Tires'!$D$7:$AW$7, 'SENS Tires'!$D$24:$AW$24), 0)))))))/_xlfn.XLOOKUP($B5, 'Assumptions & Inputs'!$F$76:$L$76, 'Assumptions & Inputs'!$F$77:$L$77)*IF(OR($B5='Project List References'!$B$3, $B5='Project List References'!$B$4, $B5='Project List References'!$B$5, $B5='Project List References'!$B$6), 'Project Master Sheet'!$E5, 'Project Master Sheet'!$F5) -> -60 | I5: =IF($B5='Project List References'!$B$3, _xlfn.IFNA(_xlfn.XLOOKUP(I$2-$C5, 'GEN-CCGT'!$D$7:$AW$7, 'GEN-CCGT'!$D$24:$AW$24), 0), IF($B5='Project List References'!$B$4, _xlfn.IFNA(_xlfn.XLOOKUP(I$2-$C5, 'GEN-SOLAR'!$D$7:$AW$7, 'GEN-SOLAR'!$D$24:$AW$24), 0), IF($B5='Project List References'!$B$5, _xlfn.IFNA(_xlfn.XLOOKUP(I$2-$C5, 'GEN-BESS'!$D$7:$AW$7, 'GEN-BESS'!$D$24:$AW$24), 0), IF($B5='Project List References'!$B$6, _xlfn.IFNA(_xlfn.XLOOKUP(I$2-$C5, 'GEN-CARBON'!$D$7:$AW$7, 'GEN-CARBON'!$D$24:$AW$24), 0), IF($B5='Project List References'!$B$7, _xlfn.IFNA(_xlfn.XLOOKUP(I$2-$C5, 'SENS Coal'!$D$7:$AW$7, 'SENS Coal'!$D$24:$AW$24), 0), IF($B5='Project List References'!$B$8, _xlfn.IFNA(_xlfn.XLOOKUP(I$2-$C5, 'SENS Tires'!$D$7:$AW$7, 'SENS Tires'!$D$24:$AW$24), 0)))))))/_xlfn.XLOOKUP($B5, 'Assumptions & Inputs'!$F$76:$L$76, 'Assumptions & Inputs'!$F$77:$L$77)*IF(OR($B5='Project List References'!$B$3, $B5='Project List References'!$B$4, $B5='Project List References'!$B$5, $B5='Project List References'!$B$6), 'Project Master Sheet'!$E5, 'Project Master Sheet'!$F5) -> 0 | J5: =IF($B5='Project List References'!$B$3, _xlfn.IFNA(_xlfn.XLOOKUP(J$2-$C5, 'GEN-CCGT'!$D$7:$AW$7, 'GEN-CCGT'!$D$24:$AW$24), 0), IF($B5='Project List References'!$B$4, _xlfn.IFNA(_xlfn.XLOOKUP(J$2-$C5, 'GEN-SOLAR'!$D$7:$AW$7, 'GEN-SOLAR'!$D$24:$AW$24), 0), IF($B5='Project List References'!$B$5, _xlfn.IFNA(_xlfn.XLOOKUP(J$2-$C5, 'GEN-BESS'!$D$7:$AW$7, 'GEN-BESS'!$D$24:$AW$24), 0), IF($B5='Project List References'!$B$6, _xlfn.IFNA(_xlfn.XLOOKUP(J$2-$C5, 'GEN-CARBON'!$D$7:$AW$7, 'GEN-CARBON'!$D$24:$AW$24), 0), IF($B5='Project List References'!$B$7, _xlfn.IFNA(_xlfn.XLOOKUP(J$2-$C5, 'SENS Coal'!$D$7:$AW$7, 'SENS Coal'!$D$24:$AW$24), 0), IF($B5='Project List References'!$B$8, _xlfn.IFNA(_xlfn.XLOOKUP(J$2-$C5, 'SENS Tires'!$D$7:$AW$7, 'SENS Tires'!$D$24:$AW$24), 0)))))))/_xlfn.XLOOKUP($B5, 'Assumptions & Inputs'!$F$76:$L$76, 'Assumptions & Inputs'!$F$77:$L$77)*IF(OR($B5='Project List References'!$B$3, $B5='Project List References'!$B$4, $B5='Project List References'!$B$5, $B5='Project List References'!$B$6), 'Project Master Sheet'!$E5, 'Project Master Sheet'!$F5) -> 0 | K5: =IF($B5='Project List References'!$B$3, _xlfn.IFNA(_xlfn.XLOOKUP(K$2-$C5, 'GEN-CCGT'!$D$7:$AW$7, 'GEN-CCGT'!$D$24:$AW$24), 0), IF($B5='Project List References'!$B$4, _xlfn.IFNA(_xlfn.XLOOKUP(K$2-$C5, 'GEN-SOLAR'!$D$7:$AW$7, 'GEN-SOLAR'!$D$24:$AW$24), 0), IF($B5='Project List References'!$B$5, _xlfn.IFNA(_xlfn.XLOOKUP(K$2-$C5, 'GEN-BESS'!$D$7:$AW$7, 'GEN-BESS'!$D$24:$AW$24), 0), IF($B5='Project List References'!$B$6, _xlfn.IFNA(_xlfn.XLOOKUP(K$2-$C5, 'GEN-CARBON'!$D$7:$AW$7, 'GEN-CARBON'!$D$24:$AW$24), 0), IF($B5='Project List References'!$B$7, _xlfn.IFNA(_xlfn.XLOOKUP(K$2-$C5, 'SENS Coal'!$D$7:$AW$7, 'SENS Coal'!$D$24:$AW$24), 0), IF($B5='Project List References'!$B$8, _xlfn.IFNA(_xlfn.XLOOKUP(K$2-$C5, 'SENS Tires'!$D$7:$AW$7, 'SENS Tires'!$D$24:$AW$24), 0)))))))/_xlfn.XLOOKUP($B5, 'Assumptions & Inputs'!$F$76:$L$76, 'Assumptions & Inputs'!$F$77:$L$77)*IF(OR($B5='Project List References'!$B$3, $B5='Project List References'!$B$4, $B5='Project List References'!$B$5, $B5='Project List References'!$B$6), 'Project Master Sheet'!$E5, 'Project Master Sheet'!$F5) -> 0 | L5: =IF($B5='Project List References'!$B$3, _xlfn.IFNA(_xlfn.XLOOKUP(L$2-$C5, 'GEN-CCGT'!$D$7:$AW$7, 'GEN-CCGT'!$D$24:$AW$24), 0), IF($B5='Project List References'!$B$4, _xlfn.IFNA(_xlfn.XLOOKUP(L$2-$C5, 'GEN-SOLAR'!$D$7:$AW$7, 'GEN-SOLAR'!$D$24:$AW$24), 0), IF($B5='Project List References'!$B$5, _xlfn.IFNA(_xlfn.XLOOKUP(L$2-$C5, 'GEN-BESS'!$D$7:$AW$7, 'GEN-BESS'!$D$24:$AW$24), 0), IF($B5='Project List References'!$B$6, _xlfn.IFNA(_xlfn.XLOOKUP(L$2-$C5, 'GEN-CARBON'!$D$7:$AW$7, 'GEN-CARBON'!$D$24:$AW$24), 0), IF($B5='Project List References'!$B$7, _xlfn.IFNA(_xlfn.XLOOKUP(L$2-$C5, 'SENS Coal'!$D$7:$AW$7, 'SENS Coal'!$D$24:$AW$24), 0), IF($B5='Project List References'!$B$8, _xlfn.IFNA(_xlfn.XLOOKUP(L$2-$C5, 'SENS Tires'!$D$7:$AW$7, 'SENS Tires'!$D$24:$AW$24), 0)))))))/_xlfn.XLOOKUP($B5, 'Assumptions & Inputs'!$F$76:$L$76, 'Assumptions & Inputs'!$F$77:$L$77)*IF(OR($B5='Project List References'!$B$3, $B5='Project List References'!$B$4, $B5='Project List References'!$B$5, $B5='Project List References'!$B$6), 'Project Master Sheet'!$E5, 'Project Master Sheet'!$F5) -> 0 | ... T5: =IF($B5='Project List References'!$B$3, _xlfn.IFNA(_xlfn.XLOOKUP(T$2-$C5, 'GEN-CCGT'!$D$7:$AW$7, 'GEN-CCGT'!$D$24:$AW$24), 0), IF($B5='Project List References'!$B$4, _xlfn.IFNA(_xlfn.XLOOKUP(T$2-$C5, 'GEN-SOLAR'!$D$7:$AW$7, 'GEN-SOLAR'!$D$24:$AW$24), 0), IF($B5='Project List References'!$B$5, _xlfn.IFNA(_xlfn.XLOOKUP(T$2-$C5, 'GEN-BESS'!$D$7:$AW$7, 'GEN-BESS'!$D$24:$AW$24), 0), IF($B5='Project List References'!$B$6, _xlfn.IFNA(_xlfn.XLOOKUP(T$2-$C5, 'GEN-CARBON'!$D$7:$AW$7, 'GEN-CARBON'!$D$24:$AW$24), 0), IF($B5='Project List References'!$B$7, _xlfn.IFNA(_xlfn.XLOOKUP(T$2-$C5, 'SENS Coal'!$D$7:$AW$7, 'SENS Coal'!$D$24:$AW$24), 0), IF($B5='Project List References'!$B$8, _xlfn.IFNA(_xlfn.XLOOKUP(T$2-$C5, 'SENS Tires'!$D$7:$AW$7, 'SENS Tires'!$D$24:$AW$24), 0)))))))/_xlfn.XLOOKUP($B5, 'Assumptions & Inputs'!$F$76:$L$76, 'Assumptions & Inputs'!$F$77:$L$77)*IF(OR($B5='Project List References'!$B$3, $B5='Project List References'!$B$4, $B5='Project List References'!$B$5, $B5='Project List References'!$B$6), 'Project Master Sheet'!$E5, 'Project Master Sheet'!$F5) -> 0
A6: =IF(ISBLANK('Project Master Sheet'!A6)=FALSE, 'Project Master Sheet'!A6, "") -> 4 | B6: =_xlfn.IFNA(_xlfn.XLOOKUP(A6, 'Project Master Sheet'!A:A, 'Project Master Sheet'!D:D), "") -> SENS - Tires | C6: =_xlfn.XLOOKUP(A6, 'Project Master Sheet'!A:A, 'Project Master Sheet'!I:I) -> 0 | E6: =IF($B6='Project List References'!$B$3, _xlfn.IFNA(_xlfn.XLOOKUP(E$2-$C6, 'GEN-CCGT'!$D$7:$AW$7, 'GEN-CCGT'!$D$24:$AW$24), 0), IF($B6='Project List References'!$B$4, _xlfn.IFNA(_xlfn.XLOOKUP(E$2-$C6, 'GEN-SOLAR'!$D$7:$AW$7, 'GEN-SOLAR'!$D$24:$AW$24), 0), IF($B6='Project List References'!$B$5, _xlfn.IFNA(_xlfn.XLOOKUP(E$2-$C6, 'GEN-BESS'!$D$7:$AW$7, 'GEN-BESS'!$D$24:$AW$24), 0), IF($B6='Project List References'!$B$6, _xlfn.IFNA(_xlfn.XLOOKUP(E$2-$C6, 'GEN-CARBON'!$D$7:$AW$7, 'GEN-CARBON'!$D$24:$AW$24), 0), IF($B6='Project List References'!$B$7, _xlfn.IFNA(_xlfn.XLOOKUP(E$2-$C6, 'SENS Coal'!$D$7:$AW$7, 'SENS Coal'!$D$24:$AW$24), 0), IF($B6='Project List References'!$B$8, _xlfn.IFNA(_xlfn.XLOOKUP(E$2-$C6, 'SENS Tires'!$D$7:$AW$7, 'SENS Tires'!$D$24:$AW$24), 0)))))))/_xlfn.XLOOKUP($B6, 'Assumptions & Inputs'!$F$76:$L$76, 'Assumptions & Inputs'!$F$77:$L$77)*IF(OR($B6='Project List References'!$B$3, $B6='Project List References'!$B$4, $B6='Project List References'!$B$5, $B6='Project List References'!$B$6), 'Project Master Sheet'!$E6, 'Project Master Sheet'!$F6) -> -103.125 | F6: =IF($B6='Project List References'!$B$3, _xlfn.IFNA(_xlfn.XLOOKUP(F$2-$C6, 'GEN-CCGT'!$D$7:$AW$7, 'GEN-CCGT'!$D$24:$AW$24), 0), IF($B6='Project List References'!$B$4, _xlfn.IFNA(_xlfn.XLOOKUP(F$2-$C6, 'GEN-SOLAR'!$D$7:$AW$7, 'GEN-SOLAR'!$D$24:$AW$24), 0), IF($B6='Project List References'!$B$5, _xlfn.IFNA(_xlfn.XLOOKUP(F$2-$C6, 'GEN-BESS'!$D$7:$AW$7, 'GEN-BESS'!$D$24:$AW$24), 0), IF($B6='Project List References'!$B$6, _xlfn.IFNA(_xlfn.XLOOKUP(F$2-$C6, 'GEN-CARBON'!$D$7:$AW$7, 'GEN-CARBON'!$D$24:$AW$24), 0), IF($B6='Project List References'!$B$7, _xlfn.IFNA(_xlfn.XLOOKUP(F$2-$C6, 'SENS Coal'!$D$7:$AW$7, 'SENS Coal'!$D$24:$AW$24), 0), IF($B6='Project List References'!$B$8, _xlfn.IFNA(_xlfn.XLOOKUP(F$2-$C6, 'SENS Tires'!$D$7:$AW$7, 'SENS Tires'!$D$24:$AW$24), 0)))))))/_xlfn.XLOOKUP($B6, 'Assumptions & Inputs'!$F$76:$L$76, 'Assumptions & Inputs'!$F$77:$L$77)*IF(OR($B6='Project List References'!$B$3, $B6='Project List References'!$B$4, $B6='Project List References'!$B$5, $B6='Project List References'!$B$6), 'Project Master Sheet'!$E6, 'Project Master Sheet'!$F6) -> -9.375 | G6: =IF($B6='Project List References'!$B$3, _xlfn.IFNA(_xlfn.XLOOKUP(G$2-$C6, 'GEN-CCGT'!$D$7:$AW$7, 'GEN-CCGT'!$D$24:$AW$24), 0), IF($B6='Project List References'!$B$4, _xlfn.IFNA(_xlfn.XLOOKUP(G$2-$C6, 'GEN-SOLAR'!$D$7:$AW$7, 'GEN-SOLAR'!$D$24:$AW$24), 0), IF($B6='Project List References'!$B$5, _xlfn.IFNA(_xlfn.XLOOKUP(G$2-$C6, 'GEN-BESS'!$D$7:$AW$7, 'GEN-BESS'!$D$24:$AW$24), 0), IF($B6='Project List References'!$B$6, _xlfn.IFNA(_xlfn.XLOOKUP(G$2-$C6, 'GEN-CARBON'!$D$7:$AW$7, 'GEN-CARBON'!$D$24:$AW$24), 0), IF($B6='Project List References'!$B$7, _xlfn.IFNA(_xlfn.XLOOKUP(G$2-$C6, 'SENS Coal'!$D$7:$AW$7, 'SENS Coal'!$D$24:$AW$24), 0), IF($B6='Project List References'!$B$8, _xlfn.IFNA(_xlfn.XLOOKUP(G$2-$C6, 'SENS Tires'!$D$7:$AW$7, 'SENS Tires'!$D$24:$AW$24), 0)))))))/_xlfn.XLOOKUP($B6, 'Assumptions & Inputs'!$F$76:$L$76, 'Assumptions & Inputs'!$F$77:$L$77)*IF(OR($B6='Project List References'!$B$3, $B6='Project List References'!$B$4, $B6='Project List References'!$B$5, $B6='Project List References'!$B$6), 'Project Master Sheet'!$E6, 'Project Master Sheet'!$F6) -> 0 | H6: =IF($B6='Project List References'!$B$3, _xlfn.IFNA(_xlfn.XLOOKUP(H$2-$C6, 'GEN-CCGT'!$D$7:$AW$7, 'GEN-CCGT'!$D$24:$AW$24), 0), IF($B6='Project List References'!$B$4, _xlfn.IFNA(_xlfn.XLOOKUP(H$2-$C6, 'GEN-SOLAR'!$D$7:$AW$7, 'GEN-SOLAR'!$D$24:$AW$24), 0), IF($B6='Project List References'!$B$5, _xlfn.IFNA(_xlfn.XLOOKUP(H$2-$C6, 'GEN-BESS'!$D$7:$AW$7, 'GEN-BESS'!$D$24:$AW$24), 0), IF($B6='Project List References'!$B$6, _xlfn.IFNA(_xlfn.XLOOKUP(H$2-$C6, 'GEN-CARBON'!$D$7:$AW$7, 'GEN-CARBON'!$D$24:$AW$24), 0), IF($B6='Project List References'!$B$7, _xlfn.IFNA(_xlfn.XLOOKUP(H$2-$C6, 'SENS Coal'!$D$7:$AW$7, 'SENS Coal'!$D$24:$AW$24), 0), IF($B6='Project List References'!$B$8, _xlfn.IFNA(_xlfn.XLOOKUP(H$2-$C6, 'SENS Tires'!$D$7:$AW$7, 'SENS Tires'!$D$24:$AW$24), 0)))))))/_xlfn.XLOOKUP($B6, 'Assumptions & Inputs'!$F$76:$L$76, 'Assumptions & Inputs'!$F$77:$L$77)*IF(OR($B6='Project List References'!$B$3, $B6='Project List References'!$B$4, $B6='Project List References'!$B$5, $B6='Project List References'!$B$6), 'Project Master Sheet'!$E6, 'Project Master Sheet'!$F6) -> 0 | I6: =IF($B6='Project List References'!$B$3, _xlfn.IFNA(_xlfn.XLOOKUP(I$2-$C6, 'GEN-CCGT'!$D$7:$AW$7, 'GEN-CCGT'!$D$24:$AW$24), 0), IF($B6='Project List References'!$B$4, _xlfn.IFNA(_xlfn.XLOOKUP(I$2-$C6, 'GEN-SOLAR'!$D$7:$AW$7, 'GEN-SOLAR'!$D$24:$AW$24), 0), IF($B6='Project List References'!$B$5, _xlfn.IFNA(_xlfn.XLOOKUP(I$2-$C6, 'GEN-BESS'!$D$7:$AW$7, 'GEN-BESS'!$D$24:$AW$24), 0), IF($B6='Project List References'!$B$6, _xlfn.IFNA(_xlfn.XLOOKUP(I$2-$C6, 'GEN-CARBON'!$D$7:$AW$7, 'GEN-CARBON'!$D$24:$AW$24), 0), IF($B6='Project List References'!$B$7, _xlfn.IFNA(_xlfn.XLOOKUP(I$2-$C6, 'SENS Coal'!$D$7:$AW$7, 'SENS Coal'!$D$24:$AW$24), 0), IF($B6='Project List References'!$B$8, _xlfn.IFNA(_xlfn.XLOOKUP(I$2-$C6, 'SENS Tires'!$D$7:$AW$7, 'SENS Tires'!$D$24:$AW$24), 0)))))))/_xlfn.XLOOKUP($B6, 'Assumptions & Inputs'!$F$76:$L$76, 'Assumptions & Inputs'!$F$77:$L$77)*IF(OR($B6='Project List References'!$B$3, $B6='Project List References'!$B$4, $B6='Project List References'!$B$5, $B6='Project List References'!$B$6), 'Project Master Sheet'!$E6, 'Project Master Sheet'!$F6) -> 0 | J6: =IF($B6='Project List References'!$B$3, _xlfn.IFNA(_xlfn.XLOOKUP(J$2-$C6, 'GEN-CCGT'!$D$7:$AW$7, 'GEN-CCGT'!$D$24:$AW$24), 0), IF($B6='Project List References'!$B$4, _xlfn.IFNA(_xlfn.XLOOKUP(J$2-$C6, 'GEN-SOLAR'!$D$7:$AW$7, 'GEN-SOLAR'!$D$24:$AW$24), 0), IF($B6='Project List References'!$B$5, _xlfn.IFNA(_xlfn.XLOOKUP(J$2-$C6, 'GEN-BESS'!$D$7:$AW$7, 'GEN-BESS'!$D$24:$AW$24), 0), IF($B6='Project List References'!$B$6, _xlfn.IFNA(_xlfn.XLOOKUP(J$2-$C6, 'GEN-CARBON'!$D$7:$AW$7, 'GEN-CARBON'!$D$24:$AW$24), 0), IF($B6='Project List References'!$B$7, _xlfn.IFNA(_xlfn.XLOOKUP(J$2-$C6, 'SENS Coal'!$D$7:$AW$7, 'SENS Coal'!$D$24:$AW$24), 0), IF($B6='Project List References'!$B$8, _xlfn.IFNA(_xlfn.XLOOKUP(J$2-$C6, 'SENS Tires'!$D$7:$AW$7, 'SENS Tires'!$D$24:$AW$24), 0)))))))/_xlfn.XLOOKUP($B6, 'Assumptions & Inputs'!$F$76:$L$76, 'Assumptions & Inputs'!$F$77:$L$77)*IF(OR($B6='Project List References'!$B$3, $B6='Project List References'!$B$4, $B6='Project List References'!$B$5, $B6='Project List References'!$B$6), 'Project Master Sheet'!$E6, 'Project Master Sheet'!$F6) -> 0 | K6: =IF($B6='Project List References'!$B$3, _xlfn.IFNA(_xlfn.XLOOKUP(K$2-$C6, 'GEN-CCGT'!$D$7:$AW$7, 'GEN-CCGT'!$D$24:$AW$24), 0), IF($B6='Project List References'!$B$4, _xlfn.IFNA(_xlfn.XLOOKUP(K$2-$C6, 'GEN-SOLAR'!$D$7:$AW$7, 'GEN-SOLAR'!$D$24:$AW$24), 0), IF($B6='Project List References'!$B$5, _xlfn.IFNA(_xlfn.XLOOKUP(K$2-$C6, 'GEN-BESS'!$D$7:$AW$7, 'GEN-BESS'!$D$24:$AW$24), 0), IF($B6='Project List References'!$B$6, _xlfn.IFNA(_xlfn.XLOOKUP(K$2-$C6, 'GEN-CARBON'!$D$7:$AW$7, 'GEN-CARBON'!$D$24:$AW$24), 0), IF($B6='Project List References'!$B$7, _xlfn.IFNA(_xlfn.XLOOKUP(K$2-$C6, 'SENS Coal'!$D$7:$AW$7, 'SENS Coal'!$D$24:$AW$24), 0), IF($B6='Project List References'!$B$8, _xlfn.IFNA(_xlfn.XLOOKUP(K$2-$C6, 'SENS Tires'!$D$7:$AW$7, 'SENS Tires'!$D$24:$AW$24), 0)))))))/_xlfn.XLOOKUP($B6, 'Assumptions & Inputs'!$F$76:$L$76, 'Assumptions & Inputs'!$F$77:$L$77)*IF(OR($B6='Project List References'!$B$3, $B6='Project List References'!$B$4, $B6='Project List References'!$B$5, $B6='Project List References'!$B$6), 'Project Master Sheet'!$E6, 'Project Master Sheet'!$F6) -> 0 | L6: =IF($B6='Project List References'!$B$3, _xlfn.IFNA(_xlfn.XLOOKUP(L$2-$C6, 'GEN-CCGT'!$D$7:$AW$7, 'GEN-CCGT'!$D$24:$AW$24), 0), IF($B6='Project List References'!$B$4, _xlfn.IFNA(_xlfn.XLOOKUP(L$2-$C6, 'GEN-SOLAR'!$D$7:$AW$7, 'GEN-SOLAR'!$D$24:$AW$24), 0), IF($B6='Project List References'!$B$5, _xlfn.IFNA(_xlfn.XLOOKUP(L$2-$C6, 'GEN-BESS'!$D$7:$AW$7, 'GEN-BESS'!$D$24:$AW$24), 0), IF($B6='Project List References'!$B$6, _xlfn.IFNA(_xlfn.XLOOKUP(L$2-$C6, 'GEN-CARBON'!$D$7:$AW$7, 'GEN-CARBON'!$D$24:$AW$24), 0), IF($B6='Project List References'!$B$7, _xlfn.IFNA(_xlfn.XLOOKUP(L$2-$C6, 'SENS Coal'!$D$7:$AW$7, 'SENS Coal'!$D$24:$AW$24), 0), IF($B6='Project List References'!$B$8, _xlfn.IFNA(_xlfn.XLOOKUP(L$2-$C6, 'SENS Tires'!$D$7:$AW$7, 'SENS Tires'!$D$24:$AW$24), 0)))))))/_xlfn.XLOOKUP($B6, 'Assumptions & Inputs'!$F$76:$L$76, 'Assumptions & Inputs'!$F$77:$L$77)*IF(OR($B6='Project List References'!$B$3, $B6='Project List References'!$B$4, $B6='Project List References'!$B$5, $B6='Project List References'!$B$6), 'Project Master Sheet'!$E6, 'Project Master Sheet'!$F6) -> 0 | ... T6: =IF($B6='Project List References'!$B$3, _xlfn.IFNA(_xlfn.XLOOKUP(T$2-$C6, 'GEN-CCGT'!$D$7:$AW$7, 'GEN-CCGT'!$D$24:$AW$24), 0), IF($B6='Project List References'!$B$4, _xlfn.IFNA(_xlfn.XLOOKUP(T$2-$C6, 'GEN-SOLAR'!$D$7:$AW$7, 'GEN-SOLAR'!$D$24:$AW$24), 0), IF($B6='Project List References'!$B$5, _xlfn.IFNA(_xlfn.XLOOKUP(T$2-$C6, 'GEN-BESS'!$D$7:$AW$7, 'GEN-BESS'!$D$24:$AW$24), 0), IF($B6='Project List References'!$B$6, _xlfn.IFNA(_xlfn.XLOOKUP(T$2-$C6, 'GEN-CARBON'!$D$7:$AW$7, 'GEN-CARBON'!$D$24:$AW$24), 0), IF($B6='Project List References'!$B$7, _xlfn.IFNA(_xlfn.XLOOKUP(T$2-$C6, 'SENS Coal'!$D$7:$AW$7, 'SENS Coal'!$D$24:$AW$24), 0), IF($B6='Project List References'!$B$8, _xlfn.IFNA(_xlfn.XLOOKUP(T$2-$C6, 'SENS Tires'!$D$7:$AW$7, 'SENS Tires'!$D$24:$AW$24), 0)))))))/_xlfn.XLOOKUP($B6, 'Assumptions & Inputs'!$F$76:$L$76, 'Assumptions & Inputs'!$F$77:$L$77)*IF(OR($B6='Project List References'!$B$3, $B6='Project List References'!$B$4, $B6='Project List References'!$B$5, $B6='Project List References'!$B$6), 'Project Master Sheet'!$E6, 'Project Master Sheet'!$F6) -> 0
A7: =IF(ISBLANK('Project Master Sheet'!A7)=FALSE, 'Project Master Sheet'!A7, "") -> 5 | B7: =_xlfn.IFNA(_xlfn.XLOOKUP(A7, 'Project Master Sheet'!A:A, 'Project Master Sheet'!D:D), "") -> Solar | C7: =_xlfn.XLOOKUP(A7, 'Project Master Sheet'!A:A, 'Project Master Sheet'!I:I) -> 0 | E7: =IF($B7='Project List References'!$B$3, _xlfn.IFNA(_xlfn.XLOOKUP(E$2-$C7, 'GEN-CCGT'!$D$7:$AW$7, 'GEN-CCGT'!$D$24:$AW$24), 0), IF($B7='Project List References'!$B$4, _xlfn.IFNA(_xlfn.XLOOKUP(E$2-$C7, 'GEN-SOLAR'!$D$7:$AW$7, 'GEN-SOLAR'!$D$24:$AW$24), 0), IF($B7='Project List References'!$B$5, _xlfn.IFNA(_xlfn.XLOOKUP(E$2-$C7, 'GEN-BESS'!$D$7:$AW$7, 'GEN-BESS'!$D$24:$AW$24), 0), IF($B7='Project List References'!$B$6, _xlfn.IFNA(_xlfn.XLOOKUP(E$2-$C7, 'GEN-CARBON'!$D$7:$AW$7, 'GEN-CARBON'!$D$24:$AW$24), 0), IF($B7='Project List References'!$B$7, _xlfn.IFNA(_xlfn.XLOOKUP(E$2-$C7, 'SENS Coal'!$D$7:$AW$7, 'SENS Coal'!$D$24:$AW$24), 0), IF($B7='Project List References'!$B$8, _xlfn.IFNA(_xlfn.XLOOKUP(E$2-$C7, 'SENS Tires'!$D$7:$AW$7, 'SENS Tires'!$D$24:$AW$24), 0)))))))/_xlfn.XLOOKUP($B7, 'Assumptions & Inputs'!$F$76:$L$76, 'Assumptions & Inputs'!$F$77:$L$77)*IF(OR($B7='Project List References'!$B$3, $B7='Project List References'!$B$4, $B7='Project List References'!$B$5, $B7='Project List References'!$B$6), 'Project Master Sheet'!$E7, 'Project Master Sheet'!$F7) -> -51.333333 | F7: =IF($B7='Project List References'!$B$3, _xlfn.IFNA(_xlfn.XLOOKUP(F$2-$C7, 'GEN-CCGT'!$D$7:$AW$7, 'GEN-CCGT'!$D$24:$AW$24), 0), IF($B7='Project List References'!$B$4, _xlfn.IFNA(_xlfn.XLOOKUP(F$2-$C7, 'GEN-SOLAR'!$D$7:$AW$7, 'GEN-SOLAR'!$D$24:$AW$24), 0), IF($B7='Project List References'!$B$5, _xlfn.IFNA(_xlfn.XLOOKUP(F$2-$C7, 'GEN-BESS'!$D$7:$AW$7, 'GEN-BESS'!$D$24:$AW$24), 0), IF($B7='Project List References'!$B$6, _xlfn.IFNA(_xlfn.XLOOKUP(F$2-$C7, 'GEN-CARBON'!$D$7:$AW$7, 'GEN-CARBON'!$D$24:$AW$24), 0), IF($B7='Project List References'!$B$7, _xlfn.IFNA(_xlfn.XLOOKUP(F$2-$C7, 'SENS Coal'!$D$7:$AW$7, 'SENS Coal'!$D$24:$AW$24), 0), IF($B7='Project List References'!$B$8, _xlfn.IFNA(_xlfn.XLOOKUP(F$2-$C7, 'SENS Tires'!$D$7:$AW$7, 'SENS Tires'!$D$24:$AW$24), 0)))))))/_xlfn.XLOOKUP($B7, 'Assumptions & Inputs'!$F$76:$L$76, 'Assumptions & Inputs'!$F$77:$L$77)*IF(OR($B7='Project List References'!$B$3, $B7='Project List References'!$B$4, $B7='Project List References'!$B$5, $B7='Project List References'!$B$6), 'Project Master Sheet'!$E7, 'Project Master Sheet'!$F7) -> -32.666667 | G7: =IF($B7='Project List References'!$B$3, _xlfn.IFNA(_xlfn.XLOOKUP(G$2-$C7, 'GEN-CCGT'!$D$7:$AW$7, 'GEN-CCGT'!$D$24:$AW$24), 0), IF($B7='Project List References'!$B$4, _xlfn.IFNA(_xlfn.XLOOKUP(G$2-$C7, 'GEN-SOLAR'!$D$7:$AW$7, 'GEN-SOLAR'!$D$24:$AW$24), 0), IF($B7='Project List References'!$B$5, _xlfn.IFNA(_xlfn.XLOOKUP(G$2-$C7, 'GEN-BESS'!$D$7:$AW$7, 'GEN-BESS'!$D$24:$AW$24), 0), IF($B7='Project List References'!$B$6, _xlfn.IFNA(_xlfn.XLOOKUP(G$2-$C7, 'GEN-CARBON'!$D$7:$AW$7, 'GEN-CARBON'!$D$24:$AW$24), 0), IF($B7='Project List References'!$B$7, _xlfn.IFNA(_xlfn.XLOOKUP(G$2-$C7, 'SENS Coal'!$D$7:$AW$7, 'SENS Coal'!$D$24:$AW$24), 0), IF($B7='Project List References'!$B$8, _xlfn.IFNA(_xlfn.XLOOKUP(G$2-$C7, 'SENS Tires'!$D$7:$AW$7, 'SENS Tires'!$D$24:$AW$24), 0)))))))/_xlfn.XLOOKUP($B7, 'Assumptions & Inputs'!$F$76:$L$76, 'Assumptions & Inputs'!$F$77:$L$77)*IF(OR($B7='Project List References'!$B$3, $B7='Project List References'!$B$4, $B7='Project List References'!$B$5, $B7='Project List References'!$B$6), 'Project Master Sheet'!$E7, 'Project Master Sheet'!$F7) -> 0 | H7: =IF($B7='Project List References'!$B$3, _xlfn.IFNA(_xlfn.XLOOKUP(H$2-$C7, 'GEN-CCGT'!$D$7:$AW$7, 'GEN-CCGT'!$D$24:$AW$24), 0), IF($B7='Project List References'!$B$4, _xlfn.IFNA(_xlfn.XLOOKUP(H$2-$C7, 'GEN-SOLAR'!$D$7:$AW$7, 'GEN-SOLAR'!$D$24:$AW$24), 0), IF($B7='Project List References'!$B$5, _xlfn.IFNA(_xlfn.XLOOKUP(H$2-$C7, 'GEN-BESS'!$D$7:$AW$7, 'GEN-BESS'!$D$24:$AW$24), 0), IF($B7='Project List References'!$B$6, _xlfn.IFNA(_xlfn.XLOOKUP(H$2-$C7, 'GEN-CARBON'!$D$7:$AW$7, 'GEN-CARBON'!$D$24:$AW$24), 0), IF($B7='Project List References'!$B$7, _xlfn.IFNA(_xlfn.XLOOKUP(H$2-$C7, 'SENS Coal'!$D$7:$AW$7, 'SENS Coal'!$D$24:$AW$24), 0), IF($B7='Project List References'!$B$8, _xlfn.IFNA(_xlfn.XLOOKUP(H$2-$C7, 'SENS Tires'!$D$7:$AW$7, 'SENS Tires'!$D$24:$AW$24), 0)))))))/_xlfn.XLOOKUP($B7, 'Assumptions & Inputs'!$F$76:$L$76, 'Assumptions & Inputs'!$F$77:$L$77)*IF(OR($B7='Project List References'!$B$3, $B7='Project List References'!$B$4, $B7='Project List References'!$B$5, $B7='Project List References'!$B$6), 'Project Master Sheet'!$E7, 'Project Master Sheet'!$F7) -> 0 | I7: =IF($B7='Project List References'!$B$3, _xlfn.IFNA(_xlfn.XLOOKUP(I$2-$C7, 'GEN-CCGT'!$D$7:$AW$7, 'GEN-CCGT'!$D$24:$AW$24), 0), IF($B7='Project List References'!$B$4, _xlfn.IFNA(_xlfn.XLOOKUP(I$2-$C7, 'GEN-SOLAR'!$D$7:$AW$7, 'GEN-SOLAR'!$D$24:$AW$24), 0), IF($B7='Project List References'!$B$5, _xlfn.IFNA(_xlfn.XLOOKUP(I$2-$C7, 'GEN-BESS'!$D$7:$AW$7, 'GEN-BESS'!$D$24:$AW$24), 0), IF($B7='Project List References'!$B$6, _xlfn.IFNA(_xlfn.XLOOKUP(I$2-$C7, 'GEN-CARBON'!$D$7:$AW$7, 'GEN-CARBON'!$D$24:$AW$24), 0), IF($B7='Project List References'!$B$7, _xlfn.IFNA(_xlfn.XLOOKUP(I$2-$C7, 'SENS Coal'!$D$7:$AW$7, 'SENS Coal'!$D$24:$AW$24), 0), IF($B7='Project List References'!$B$8, _xlfn.IFNA(_xlfn.XLOOKUP(I$2-$C7, 'SENS Tires'!$D$7:$AW$7, 'SENS Tires'!$D$24:$AW$24), 0)))))))/_xlfn.XLOOKUP($B7, 'Assumptions & Inputs'!$F$76:$L$76, 'Assumptions & Inputs'!$F$77:$L$77)*IF(OR($B7='Project List References'!$B$3, $B7='Project List References'!$B$4, $B7='Project List References'!$B$5, $B7='Project List References'!$B$6), 'Project Master Sheet'!$E7, 'Project Master Sheet'!$F7) -> 0 | J7: =IF($B7='Project List References'!$B$3, _xlfn.IFNA(_xlfn.XLOOKUP(J$2-$C7, 'GEN-CCGT'!$D$7:$AW$7, 'GEN-CCGT'!$D$24:$AW$24), 0), IF($B7='Project List References'!$B$4, _xlfn.IFNA(_xlfn.XLOOKUP(J$2-$C7, 'GEN-SOLAR'!$D$7:$AW$7, 'GEN-SOLAR'!$D$24:$AW$24), 0), IF($B7='Project List References'!$B$5, _xlfn.IFNA(_xlfn.XLOOKUP(J$2-$C7, 'GEN-BESS'!$D$7:$AW$7, 'GEN-BESS'!$D$24:$AW$24), 0), IF($B7='Project List References'!$B$6, _xlfn.IFNA(_xlfn.XLOOKUP(J$2-$C7, 'GEN-CARBON'!$D$7:$AW$7, 'GEN-CARBON'!$D$24:$AW$24), 0), IF($B7='Project List References'!$B$7, _xlfn.IFNA(_xlfn.XLOOKUP(J$2-$C7, 'SENS Coal'!$D$7:$AW$7, 'SENS Coal'!$D$24:$AW$24), 0), IF($B7='Project List References'!$B$8, _xlfn.IFNA(_xlfn.XLOOKUP(J$2-$C7, 'SENS Tires'!$D$7:$AW$7, 'SENS Tires'!$D$24:$AW$24), 0)))))))/_xlfn.XLOOKUP($B7, 'Assumptions & Inputs'!$F$76:$L$76, 'Assumptions & Inputs'!$F$77:$L$77)*IF(OR($B7='Project List References'!$B$3, $B7='Project List References'!$B$4, $B7='Project List References'!$B$5, $B7='Project List References'!$B$6), 'Project Master Sheet'!$E7, 'Project Master Sheet'!$F7) -> 0 | K7: =IF($B7='Project List References'!$B$3, _xlfn.IFNA(_xlfn.XLOOKUP(K$2-$C7, 'GEN-CCGT'!$D$7:$AW$7, 'GEN-CCGT'!$D$24:$AW$24), 0), IF($B7='Project List References'!$B$4, _xlfn.IFNA(_xlfn.XLOOKUP(K$2-$C7, 'GEN-SOLAR'!$D$7:$AW$7, 'GEN-SOLAR'!$D$24:$AW$24), 0), IF($B7='Project List References'!$B$5, _xlfn.IFNA(_xlfn.XLOOKUP(K$2-$C7, 'GEN-BESS'!$D$7:$AW$7, 'GEN-BESS'!$D$24:$AW$24), 0), IF($B7='Project List References'!$B$6, _xlfn.IFNA(_xlfn.XLOOKUP(K$2-$C7, 'GEN-CARBON'!$D$7:$AW$7, 'GEN-CARBON'!$D$24:$AW$24), 0), IF($B7='Project List References'!$B$7, _xlfn.IFNA(_xlfn.XLOOKUP(K$2-$C7, 'SENS Coal'!$D$7:$AW$7, 'SENS Coal'!$D$24:$AW$24), 0), IF($B7='Project List References'!$B$8, _xlfn.IFNA(_xlfn.XLOOKUP(K$2-$C7, 'SENS Tires'!$D$7:$AW$7, 'SENS Tires'!$D$24:$AW$24), 0)))))))/_xlfn.XLOOKUP($B7, 'Assumptions & Inputs'!$F$76:$L$76, 'Assumptions & Inputs'!$F$77:$L$77)*IF(OR($B7='Project List References'!$B$3, $B7='Project List References'!$B$4, $B7='Project List References'!$B$5, $B7='Project List References'!$B$6), 'Project Master Sheet'!$E7, 'Project Master Sheet'!$F7) -> 0 | L7: =IF($B7='Project List References'!$B$3, _xlfn.IFNA(_xlfn.XLOOKUP(L$2-$C7, 'GEN-CCGT'!$D$7:$AW$7, 'GEN-CCGT'!$D$24:$AW$24), 0), IF($B7='Project List References'!$B$4, _xlfn.IFNA(_xlfn.XLOOKUP(L$2-$C7, 'GEN-SOLAR'!$D$7:$AW$7, 'GEN-SOLAR'!$D$24:$AW$24), 0), IF($B7='Project List References'!$B$5, _xlfn.IFNA(_xlfn.XLOOKUP(L$2-$C7, 'GEN-BESS'!$D$7:$AW$7, 'GEN-BESS'!$D$24:$AW$24), 0), IF($B7='Project List References'!$B$6, _xlfn.IFNA(_xlfn.XLOOKUP(L$2-$C7, 'GEN-CARBON'!$D$7:$AW$7, 'GEN-CARBON'!$D$24:$AW$24), 0), IF($B7='Project List References'!$B$7, _xlfn.IFNA(_xlfn.XLOOKUP(L$2-$C7, 'SENS Coal'!$D$7:$AW$7, 'SENS Coal'!$D$24:$AW$24), 0), IF($B7='Project List References'!$B$8, _xlfn.IFNA(_xlfn.XLOOKUP(L$2-$C7, 'SENS Tires'!$D$7:$AW$7, 'SENS Tires'!$D$24:$AW$24), 0)))))))/_xlfn.XLOOKUP($B7, 'Assumptions & Inputs'!$F$76:$L$76, 'Assumptions & Inputs'!$F$77:$L$77)*IF(OR($B7='Project List References'!$B$3, $B7='Project List References'!$B$4, $B7='Project List References'!$B$5, $B7='Project List References'!$B$6), 'Project Master Sheet'!$E7, 'Project Master Sheet'!$F7) -> 0 | ... T7: =IF($B7='Project List References'!$B$3, _xlfn.IFNA(_xlfn.XLOOKUP(T$2-$C7, 'GEN-CCGT'!$D$7:$AW$7, 'GEN-CCGT'!$D$24:$AW$24), 0), IF($B7='Project List References'!$B$4, _xlfn.IFNA(_xlfn.XLOOKUP(T$2-$C7, 'GEN-SOLAR'!$D$7:$AW$7, 'GEN-SOLAR'!$D$24:$AW$24), 0), IF($B7='Project List References'!$B$5, _xlfn.IFNA(_xlfn.XLOOKUP(T$2-$C7, 'GEN-BESS'!$D$7:$AW$7, 'GEN-BESS'!$D$24:$AW$24), 0), IF($B7='Project List References'!$B$6, _xlfn.IFNA(_xlfn.XLOOKUP(T$2-$C7, 'GEN-CARBON'!$D$7:$AW$7, 'GEN-CARBON'!$D$24:$AW$24), 0), IF($B7='Project List References'!$B$7, _xlfn.IFNA(_xlfn.XLOOKUP(T$2-$C7, 'SENS Coal'!$D$7:$AW$7, 'SENS Coal'!$D$24:$AW$24), 0), IF($B7='Project List References'!$B$8, _xlfn.IFNA(_xlfn.XLOOKUP(T$2-$C7, 'SENS Tires'!$D$7:$AW$7, 'SENS Tires'!$D$24:$AW$24), 0)))))))/_xlfn.XLOOKUP($B7, 'Assumptions & Inputs'!$F$76:$L$76, 'Assumptions & Inputs'!$F$77:$L$77)*IF(OR($B7='Project List References'!$B$3, $B7='Project List References'!$B$4, $B7='Project List References'!$B$5, $B7='Project List References'!$B$6), 'Project Master Sheet'!$E7, 'Project Master Sheet'!$F7) -> 0
A8: =IF(ISBLANK('Project Master Sheet'!A8)=FALSE, 'Project Master Sheet'!A8, "") | B8: =_xlfn.IFNA(_xlfn.XLOOKUP(A8, 'Project Master Sheet'!A:A, 'Project Master Sheet'!D:D), "") | C8: =_xlfn.XLOOKUP(A8, 'Project Master Sheet'!A:A, 'Project Master Sheet'!I:I) -> #N/A | E8: =IF($B8='Project List References'!$B$3, _xlfn.IFNA(_xlfn.XLOOKUP(E$2-$C8, 'GEN-CCGT'!$D$7:$AW$7, 'GEN-CCGT'!$D$24:$AW$24), 0), IF($B8='Project List References'!$B$4, _xlfn.IFNA(_xlfn.XLOOKUP(E$2-$C8, 'GEN-SOLAR'!$D$7:$AW$7, 'GEN-SOLAR'!$D$24:$AW$24), 0), IF($B8='Project List References'!$B$5, _xlfn.IFNA(_xlfn.XLOOKUP(E$2-$C8, 'GEN-BESS'!$D$7:$AW$7, 'GEN-BESS'!$D$24:$AW$24), 0), IF($B8='Project List References'!$B$6, _xlfn.IFNA(_xlfn.XLOOKUP(E$2-$C8, 'GEN-CARBON'!$D$7:$AW$7, 'GEN-CARBON'!$D$24:$AW$24), 0), IF($B8='Project List References'!$B$7, _xlfn.IFNA(_xlfn.XLOOKUP(E$2-$C8, 'SENS Coal'!$D$7:$AW$7, 'SENS Coal'!$D$24:$AW$24), 0), IF($B8='Project List References'!$B$8, _xlfn.IFNA(_xlfn.XLOOKUP(E$2-$C8, 'SENS Tires'!$D$7:$AW$7, 'SENS Tires'!$D$24:$AW$24), 0)))))))/_xlfn.XLOOKUP($B8, 'Assumptions & Inputs'!$F$76:$L$76, 'Assumptions & Inputs'!$F$77:$L$77)*IF(OR($B8='Project List References'!$B$3, $B8='Project List References'!$B$4, $B8='Project List References'!$B$5, $B8='Project List References'!$B$6), 'Project Master Sheet'!$E8, 'Project Master Sheet'!$F8) -> #N/A | F8: =IF($B8='Project List References'!$B$3, _xlfn.IFNA(_xlfn.XLOOKUP(F$2-$C8, 'GEN-CCGT'!$D$7:$AW$7, 'GEN-CCGT'!$D$24:$AW$24), 0), IF($B8='Project List References'!$B$4, _xlfn.IFNA(_xlfn.XLOOKUP(F$2-$C8, 'GEN-SOLAR'!$D$7:$AW$7, 'GEN-SOLAR'!$D$24:$AW$24), 0), IF($B8='Project List References'!$B$5, _xlfn.IFNA(_xlfn.XLOOKUP(F$2-$C8, 'GEN-BESS'!$D$7:$AW$7, 'GEN-BESS'!$D$24:$AW$24), 0), IF($B8='Project List References'!$B$6, _xlfn.IFNA(_xlfn.XLOOKUP(F$2-$C8, 'GEN-CARBON'!$D$7:$AW$7, 'GEN-CARBON'!$D$24:$AW$24), 0), IF($B8='Project List References'!$B$7, _xlfn.IFNA(_xlfn.XLOOKUP(F$2-$C8, 'SENS Coal'!$D$7:$AW$7, 'SENS Coal'!$D$24:$AW$24), 0), IF($B8='Project List References'!$B$8, _xlfn.IFNA(_xlfn.XLOOKUP(F$2-$C8, 'SENS Tires'!$D$7:$AW$7, 'SENS Tires'!$D$24:$AW$24), 0)))))))/_xlfn.XLOOKUP($B8, 'Assumptions & Inputs'!$F$76:$L$76, 'Assumptions & Inputs'!$F$77:$L$77)*IF(OR($B8='Project List References'!$B$3, $B8='Project List References'!$B$4, $B8='Project List References'!$B$5, $B8='Project List References'!$B$6), 'Project Master Sheet'!$E8, 'Project Master Sheet'!$F8) -> #N/A | G8: =IF($B8='Project List References'!$B$3, _xlfn.IFNA(_xlfn.XLOOKUP(G$2-$C8, 'GEN-CCGT'!$D$7:$AW$7, 'GEN-CCGT'!$D$24:$AW$24), 0), IF($B8='Project List References'!$B$4, _xlfn.IFNA(_xlfn.XLOOKUP(G$2-$C8, 'GEN-SOLAR'!$D$7:$AW$7, 'GEN-SOLAR'!$D$24:$AW$24), 0), IF($B8='Project List References'!$B$5, _xlfn.IFNA(_xlfn.XLOOKUP(G$2-$C8, 'GEN-BESS'!$D$7:$AW$7, 'GEN-BESS'!$D$24:$AW$24), 0), IF($B8='Project List References'!$B$6, _xlfn.IFNA(_xlfn.XLOOKUP(G$2-$C8, 'GEN-CARBON'!$D$7:$AW$7, 'GEN-CARBON'!$D$24:$AW$24), 0), IF($B8='Project List References'!$B$7, _xlfn.IFNA(_xlfn.XLOOKUP(G$2-$C8, 'SENS Coal'!$D$7:$AW$7, 'SENS Coal'!$D$24:$AW$24), 0), IF($B8='Project List References'!$B$8, _xlfn.IFNA(_xlfn.XLOOKUP(G$2-$C8, 'SENS Tires'!$D$7:$AW$7, 'SENS Tires'!$D$24:$AW$24), 0)))))))/_xlfn.XLOOKUP($B8, 'Assumptions & Inputs'!$F$76:$L$76, 'Assumptions & Inputs'!$F$77:$L$77)*IF(OR($B8='Project List References'!$B$3, $B8='Project List References'!$B$4, $B8='Project List References'!$B$5, $B8='Project List References'!$B$6), 'Project Master Sheet'!$E8, 'Project Master Sheet'!$F8) -> #N/A | H8: =IF($B8='Project List References'!$B$3, _xlfn.IFNA(_xlfn.XLOOKUP(H$2-$C8, 'GEN-CCGT'!$D$7:$AW$7, 'GEN-CCGT'!$D$24:$AW$24), 0), IF($B8='Project List References'!$B$4, _xlfn.IFNA(_xlfn.XLOOKUP(H$2-$C8, 'GEN-SOLAR'!$D$7:$AW$7, 'GEN-SOLAR'!$D$24:$AW$24), 0), IF($B8='Project List References'!$B$5, _xlfn.IFNA(_xlfn.XLOOKUP(H$2-$C8, 'GEN-BESS'!$D$7:$AW$7, 'GEN-BESS'!$D$24:$AW$24), 0), IF($B8='Project List References'!$B$6, _xlfn.IFNA(_xlfn.XLOOKUP(H$2-$C8, 'GEN-CARBON'!$D$7:$AW$7, 'GEN-CARBON'!$D$24:$AW$24), 0), IF($B8='Project List References'!$B$7, _xlfn.IFNA(_xlfn.XLOOKUP(H$2-$C8, 'SENS Coal'!$D$7:$AW$7, 'SENS Coal'!$D$24:$AW$24), 0), IF($B8='Project List References'!$B$8, _xlfn.IFNA(_xlfn.XLOOKUP(H$2-$C8, 'SENS Tires'!$D$7:$AW$7, 'SENS Tires'!$D$24:$AW$24), 0)))))))/_xlfn.XLOOKUP($B8, 'Assumptions & Inputs'!$F$76:$L$76, 'Assumptions & Inputs'!$F$77:$L$77)*IF(OR($B8='Project List References'!$B$3, $B8='Project List References'!$B$4, $B8='Project List References'!$B$5, $B8='Project List References'!$B$6), 'Project Master Sheet'!$E8, 'Project Master Sheet'!$F8) -> #N/A | I8: =IF($B8='Project List References'!$B$3, _xlfn.IFNA(_xlfn.XLOOKUP(I$2-$C8, 'GEN-CCGT'!$D$7:$AW$7, 'GEN-CCGT'!$D$24:$AW$24), 0), IF($B8='Project List References'!$B$4, _xlfn.IFNA(_xlfn.XLOOKUP(I$2-$C8, 'GEN-SOLAR'!$D$7:$AW$7, 'GEN-SOLAR'!$D$24:$AW$24), 0), IF($B8='Project List References'!$B$5, _xlfn.IFNA(_xlfn.XLOOKUP(I$2-$C8, 'GEN-BESS'!$D$7:$AW$7, 'GEN-BESS'!$D$24:$AW$24), 0), IF($B8='Project List References'!$B$6, _xlfn.IFNA(_xlfn.XLOOKUP(I$2-$C8, 'GEN-CARBON'!$D$7:$AW$7, 'GEN-CARBON'!$D$24:$AW$24), 0), IF($B8='Project List References'!$B$7, _xlfn.IFNA(_xlfn.XLOOKUP(I$2-$C8, 'SENS Coal'!$D$7:$AW$7, 'SENS Coal'!$D$24:$AW$24), 0), IF($B8='Project List References'!$B$8, _xlfn.IFNA(_xlfn.XLOOKUP(I$2-$C8, 'SENS Tires'!$D$7:$AW$7, 'SENS Tires'!$D$24:$AW$24), 0)))))))/_xlfn.XLOOKUP($B8, 'Assumptions & Inputs'!$F$76:$L$76, 'Assumptions & Inputs'!$F$77:$L$77)*IF(OR($B8='Project List References'!$B$3, $B8='Project List References'!$B$4, $B8='Project List References'!$B$5, $B8='Project List References'!$B$6), 'Project Master Sheet'!$E8, 'Project Master Sheet'!$F8) -> #N/A | J8: =IF($B8='Project List References'!$B$3, _xlfn.IFNA(_xlfn.XLOOKUP(J$2-$C8, 'GEN-CCGT'!$D$7:$AW$7, 'GEN-CCGT'!$D$24:$AW$24), 0), IF($B8='Project List References'!$B$4, _xlfn.IFNA(_xlfn.XLOOKUP(J$2-$C8, 'GEN-SOLAR'!$D$7:$AW$7, 'GEN-SOLAR'!$D$24:$AW$24), 0), IF($B8='Project List References'!$B$5, _xlfn.IFNA(_xlfn.XLOOKUP(J$2-$C8, 'GEN-BESS'!$D$7:$AW$7, 'GEN-BESS'!$D$24:$AW$24), 0), IF($B8='Project List References'!$B$6, _xlfn.IFNA(_xlfn.XLOOKUP(J$2-$C8, 'GEN-CARBON'!$D$7:$AW$7, 'GEN-CARBON'!$D$24:$AW$24), 0), IF($B8='Project List References'!$B$7, _xlfn.IFNA(_xlfn.XLOOKUP(J$2-$C8, 'SENS Coal'!$D$7:$AW$7, 'SENS Coal'!$D$24:$AW$24), 0), IF($B8='Project List References'!$B$8, _xlfn.IFNA(_xlfn.XLOOKUP(J$2-$C8, 'SENS Tires'!$D$7:$AW$7, 'SENS Tires'!$D$24:$AW$24), 0)))))))/_xlfn.XLOOKUP($B8, 'Assumptions & Inputs'!$F$76:$L$76, 'Assumptions & Inputs'!$F$77:$L$77)*IF(OR($B8='Project List References'!$B$3, $B8='Project List References'!$B$4, $B8='Project List References'!$B$5, $B8='Project List References'!$B$6), 'Project Master Sheet'!$E8, 'Project Master Sheet'!$F8) -> #N/A | K8: =IF($B8='Project List References'!$B$3, _xlfn.IFNA(_xlfn.XLOOKUP(K$2-$C8, 'GEN-CCGT'!$D$7:$AW$7, 'GEN-CCGT'!$D$24:$AW$24), 0), IF($B8='Project List References'!$B$4, _xlfn.IFNA(_xlfn.XLOOKUP(K$2-$C8, 'GEN-SOLAR'!$D$7:$AW$7, 'GEN-SOLAR'!$D$24:$AW$24), 0), IF($B8='Project List References'!$B$5, _xlfn.IFNA(_xlfn.XLOOKUP(K$2-$C8, 'GEN-BESS'!$D$7:$AW$7, 'GEN-BESS'!$D$24:$AW$24), 0), IF($B8='Project List References'!$B$6, _xlfn.IFNA(_xlfn.XLOOKUP(K$2-$C8, 'GEN-CARBON'!$D$7:$AW$7, 'GEN-CARBON'!$D$24:$AW$24), 0), IF($B8='Project List References'!$B$7, _xlfn.IFNA(_xlfn.XLOOKUP(K$2-$C8, 'SENS Coal'!$D$7:$AW$7, 'SENS Coal'!$D$24:$AW$24), 0), IF($B8='Project List References'!$B$8, _xlfn.IFNA(_xlfn.XLOOKUP(K$2-$C8, 'SENS Tires'!$D$7:$AW$7, 'SENS Tires'!$D$24:$AW$24), 0)))))))/_xlfn.XLOOKUP($B8, 'Assumptions & Inputs'!$F$76:$L$76, 'Assumptions & Inputs'!$F$77:$L$77)*IF(OR($B8='Project List References'!$B$3, $B8='Project List References'!$B$4, $B8='Project List References'!$B$5, $B8='Project List References'!$B$6), 'Project Master Sheet'!$E8, 'Project Master Sheet'!$F8) -> #N/A | L8: =IF($B8='Project List References'!$B$3, _xlfn.IFNA(_xlfn.XLOOKUP(L$2-$C8, 'GEN-CCGT'!$D$7:$AW$7, 'GEN-CCGT'!$D$24:$AW$24), 0), IF($B8='Project List References'!$B$4, _xlfn.IFNA(_xlfn.XLOOKUP(L$2-$C8, 'GEN-SOLAR'!$D$7:$AW$7, 'GEN-SOLAR'!$D$24:$AW$24), 0), IF($B8='Project List References'!$B$5, _xlfn.IFNA(_xlfn.XLOOKUP(L$2-$C8, 'GEN-BESS'!$D$7:$AW$7, 'GEN-BESS'!$D$24:$AW$24), 0), IF($B8='Project List References'!$B$6, _xlfn.IFNA(_xlfn.XLOOKUP(L$2-$C8, 'GEN-CARBON'!$D$7:$AW$7, 'GEN-CARBON'!$D$24:$AW$24), 0), IF($B8='Project List References'!$B$7, _xlfn.IFNA(_xlfn.XLOOKUP(L$2-$C8, 'SENS Coal'!$D$7:$AW$7, 'SENS Coal'!$D$24:$AW$24), 0), IF($B8='Project List References'!$B$8, _xlfn.IFNA(_xlfn.XLOOKUP(L$2-$C8, 'SENS Tires'!$D$7:$AW$7, 'SENS Tires'!$D$24:$AW$24), 0)))))))/_xlfn.XLOOKUP($B8, 'Assumptions & Inputs'!$F$76:$L$76, 'Assumptions & Inputs'!$F$77:$L$77)*IF(OR($B8='Project List References'!$B$3, $B8='Project List References'!$B$4, $B8='Project List References'!$B$5, $B8='Project List References'!$B$6), 'Project Master Sheet'!$E8, 'Project Master Sheet'!$F8) -> #N/A | ... T8: =IF($B8='Project List References'!$B$3, _xlfn.IFNA(_xlfn.XLOOKUP(T$2-$C8, 'GEN-CCGT'!$D$7:$AW$7, 'GEN-CCGT'!$D$24:$AW$24), 0), IF($B8='Project List References'!$B$4, _xlfn.IFNA(_xlfn.XLOOKUP(T$2-$C8, 'GEN-SOLAR'!$D$7:$AW$7, 'GEN-SOLAR'!$D$24:$AW$24), 0), IF($B8='Project List References'!$B$5, _xlfn.IFNA(_xlfn.XLOOKUP(T$2-$C8, 'GEN-BESS'!$D$7:$AW$7, 'GEN-BESS'!$D$24:$AW$24), 0), IF($B8='Project List References'!$B$6, _xlfn.IFNA(_xlfn.XLOOKUP(T$2-$C8, 'GEN-CARBON'!$D$7:$AW$7, 'GEN-CARBON'!$D$24:$AW$24), 0), IF($B8='Project List References'!$B$7, _xlfn.IFNA(_xlfn.XLOOKUP(T$2-$C8, 'SENS Coal'!$D$7:$AW$7, 'SENS Coal'!$D$24:$AW$24), 0), IF($B8='Project List References'!$B$8, _xlfn.IFNA(_xlfn.XLOOKUP(T$2-$C8, 'SENS Tires'!$D$7:$AW$7, 'SENS Tires'!$D$24:$AW$24), 0)))))))/_xlfn.XLOOKUP($B8, 'Assumptions & Inputs'!$F$76:$L$76, 'Assumptions & Inputs'!$F$77:$L$77)*IF(OR($B8='Project List References'!$B$3, $B8='Project List References'!$B$4, $B8='Project List References'!$B$5, $B8='Project List References'!$B$6), 'Project Master Sheet'!$E8, 'Project Master Sheet'!$F8) -> #N/A
A9: =IF(ISBLANK('Project Master Sheet'!A9)=FALSE, 'Project Master Sheet'!A9, "") -> 7 | B9: =_xlfn.IFNA(_xlfn.XLOOKUP(A9, 'Project Master Sheet'!A:A, 'Project Master Sheet'!D:D), "") -> Nat Gas | C9: =_xlfn.XLOOKUP(A9, 'Project Master Sheet'!A:A, 'Project Master Sheet'!I:I) -> 1 | E9: =IF($B9='Project List References'!$B$3, _xlfn.IFNA(_xlfn.XLOOKUP(E$2-$C9, 'GEN-CCGT'!$D$7:$AW$7, 'GEN-CCGT'!$D$24:$AW$24), 0), IF($B9='Project List References'!$B$4, _xlfn.IFNA(_xlfn.XLOOKUP(E$2-$C9, 'GEN-SOLAR'!$D$7:$AW$7, 'GEN-SOLAR'!$D$24:$AW$24), 0), IF($B9='Project List References'!$B$5, _xlfn.IFNA(_xlfn.XLOOKUP(E$2-$C9, 'GEN-BESS'!$D$7:$AW$7, 'GEN-BESS'!$D$24:$AW$24), 0), IF($B9='Project List References'!$B$6, _xlfn.IFNA(_xlfn.XLOOKUP(E$2-$C9, 'GEN-CARBON'!$D$7:$AW$7, 'GEN-CARBON'!$D$24:$AW$24), 0), IF($B9='Project List References'!$B$7, _xlfn.IFNA(_xlfn.XLOOKUP(E$2-$C9, 'SENS Coal'!$D$7:$AW$7, 'SENS Coal'!$D$24:$AW$24), 0), IF($B9='Project List References'!$B$8, _xlfn.IFNA(_xlfn.XLOOKUP(E$2-$C9, 'SENS Tires'!$D$7:$AW$7, 'SENS Tires'!$D$24:$AW$24), 0)))))))/_xlfn.XLOOKUP($B9, 'Assumptions & Inputs'!$F$76:$L$76, 'Assumptions & Inputs'!$F$77:$L$77)*IF(OR($B9='Project List References'!$B$3, $B9='Project List References'!$B$4, $B9='Project List References'!$B$5, $B9='Project List References'!$B$6), 'Project Master Sheet'!$E9, 'Project Master Sheet'!$F9) -> 0 | F9: =IF($B9='Project List References'!$B$3, _xlfn.IFNA(_xlfn.XLOOKUP(F$2-$C9, 'GEN-CCGT'!$D$7:$AW$7, 'GEN-CCGT'!$D$24:$AW$24), 0), IF($B9='Project List References'!$B$4, _xlfn.IFNA(_xlfn.XLOOKUP(F$2-$C9, 'GEN-SOLAR'!$D$7:$AW$7, 'GEN-SOLAR'!$D$24:$AW$24), 0), IF($B9='Project List References'!$B$5, _xlfn.IFNA(_xlfn.XLOOKUP(F$2-$C9, 'GEN-BESS'!$D$7:$AW$7, 'GEN-BESS'!$D$24:$AW$24), 0), IF($B9='Project List References'!$B$6, _xlfn.IFNA(_xlfn.XLOOKUP(F$2-$C9, 'GEN-CARBON'!$D$7:$AW$7, 'GEN-CARBON'!$D$24:$AW$24), 0), IF($B9='Project List References'!$B$7, _xlfn.IFNA(_xlfn.XLOOKUP(F$2-$C9, 'SENS Coal'!$D$7:$AW$7, 'SENS Coal'!$D$24:$AW$24), 0), IF($B9='Project List References'!$B$8, _xlfn.IFNA(_xlfn.XLOOKUP(F$2-$C9, 'SENS Tires'!$D$7:$AW$7, 'SENS Tires'!$D$24:$AW$24), 0)))))))/_xlfn.XLOOKUP($B9, 'Assumptions & Inputs'!$F$76:$L$76, 'Assumptions & Inputs'!$F$77:$L$77)*IF(OR($B9='Project List References'!$B$3, $B9='Project List References'!$B$4, $B9='Project List References'!$B$5, $B9='Project List References'!$B$6), 'Project Master Sheet'!$E9, 'Project Master Sheet'!$F9) -> -33.611111 | G9: =IF($B9='Project List References'!$B$3, _xlfn.IFNA(_xlfn.XLOOKUP(G$2-$C9, 'GEN-CCGT'!$D$7:$AW$7, 'GEN-CCGT'!$D$24:$AW$24), 0), IF($B9='Project List References'!$B$4, _xlfn.IFNA(_xlfn.XLOOKUP(G$2-$C9, 'GEN-SOLAR'!$D$7:$AW$7, 'GEN-SOLAR'!$D$24:$AW$24), 0), IF($B9='Project List References'!$B$5, _xlfn.IFNA(_xlfn.XLOOKUP(G$2-$C9, 'GEN-BESS'!$D$7:$AW$7, 'GEN-BESS'!$D$24:$AW$24), 0), IF($B9='Project List References'!$B$6, _xlfn.IFNA(_xlfn.XLOOKUP(G$2-$C9, 'GEN-CARBON'!$D$7:$AW$7, 'GEN-CARBON'!$D$24:$AW$24), 0), IF($B9='Project List References'!$B$7, _xlfn.IFNA(_xlfn.XLOOKUP(G$2-$C9, 'SENS Coal'!$D$7:$AW$7, 'SENS Coal'!$D$24:$AW$24), 0), IF($B9='Project List References'!$B$8, _xlfn.IFNA(_xlfn.XLOOKUP(G$2-$C9, 'SENS Tires'!$D$7:$AW$7, 'SENS Tires'!$D$24:$AW$24), 0)))))))/_xlfn.XLOOKUP($B9, 'Assumptions & Inputs'!$F$76:$L$76, 'Assumptions & Inputs'!$F$77:$L$77)*IF(OR($B9='Project List References'!$B$3, $B9='Project List References'!$B$4, $B9='Project List References'!$B$5, $B9='Project List References'!$B$6), 'Project Master Sheet'!$E9, 'Project Master Sheet'!$F9) -> -36.666667 | H9: =IF($B9='Project List References'!$B$3, _xlfn.IFNA(_xlfn.XLOOKUP(H$2-$C9, 'GEN-CCGT'!$D$7:$AW$7, 'GEN-CCGT'!$D$24:$AW$24), 0), IF($B9='Project List References'!$B$4, _xlfn.IFNA(_xlfn.XLOOKUP(H$2-$C9, 'GEN-SOLAR'!$D$7:$AW$7, 'GEN-SOLAR'!$D$24:$AW$24), 0), IF($B9='Project List References'!$B$5, _xlfn.IFNA(_xlfn.XLOOKUP(H$2-$C9, 'GEN-BESS'!$D$7:$AW$7, 'GEN-BESS'!$D$24:$AW$24), 0), IF($B9='Project List References'!$B$6, _xlfn.IFNA(_xlfn.XLOOKUP(H$2-$C9, 'GEN-CARBON'!$D$7:$AW$7, 'GEN-CARBON'!$D$24:$AW$24), 0), IF($B9='Project List References'!$B$7, _xlfn.IFNA(_xlfn.XLOOKUP(H$2-$C9, 'SENS Coal'!$D$7:$AW$7, 'SENS Coal'!$D$24:$AW$24), 0), IF($B9='Project List References'!$B$8, _xlfn.IFNA(_xlfn.XLOOKUP(H$2-$C9, 'SENS Tires'!$D$7:$AW$7, 'SENS Tires'!$D$24:$AW$24), 0)))))))/_xlfn.XLOOKUP($B9, 'Assumptions & Inputs'!$F$76:$L$76, 'Assumptions & Inputs'!$F$77:$L$77)*IF(OR($B9='Project List References'!$B$3, $B9='Project List References'!$B$4, $B9='Project List References'!$B$5, $B9='Project List References'!$B$6), 'Project Master Sheet'!$E9, 'Project Master Sheet'!$F9) -> -36.666667 | I9: =IF($B9='Project List References'!$B$3, _xlfn.IFNA(_xlfn.XLOOKUP(I$2-$C9, 'GEN-CCGT'!$D$7:$AW$7, 'GEN-CCGT'!$D$24:$AW$24), 0), IF($B9='Project List References'!$B$4, _xlfn.IFNA(_xlfn.XLOOKUP(I$2-$C9, 'GEN-SOLAR'!$D$7:$AW$7, 'GEN-SOLAR'!$D$24:$AW$24), 0), IF($B9='Project List References'!$B$5, _xlfn.IFNA(_xlfn.XLOOKUP(I$2-$C9, 'GEN-BESS'!$D$7:$AW$7, 'GEN-BESS'!$D$24:$AW$24), 0), IF($B9='Project List References'!$B$6, _xlfn.IFNA(_xlfn.XLOOKUP(I$2-$C9, 'GEN-CARBON'!$D$7:$AW$7, 'GEN-CARBON'!$D$24:$AW$24), 0), IF($B9='Project List References'!$B$7, _xlfn.IFNA(_xlfn.XLOOKUP(I$2-$C9, 'SENS Coal'!$D$7:$AW$7, 'SENS Coal'!$D$24:$AW$24), 0), IF($B9='Project List References'!$B$8, _xlfn.IFNA(_xlfn.XLOOKUP(I$2-$C9, 'SENS Tires'!$D$7:$AW$7, 'SENS Tires'!$D$24:$AW$24), 0)))))))/_xlfn.XLOOKUP($B9, 'Assumptions & Inputs'!$F$76:$L$76, 'Assumptions & Inputs'!$F$77:$L$77)*IF(OR($B9='Project List References'!$B$3, $B9='Project List References'!$B$4, $B9='Project List References'!$B$5, $B9='Project List References'!$B$6), 'Project Master Sheet'!$E9, 'Project Master Sheet'!$F9) -> -3.0555556 | J9: =IF($B9='Project List References'!$B$3, _xlfn.IFNA(_xlfn.XLOOKUP(J$2-$C9, 'GEN-CCGT'!$D$7:$AW$7, 'GEN-CCGT'!$D$24:$AW$24), 0), IF($B9='Project List References'!$B$4, _xlfn.IFNA(_xlfn.XLOOKUP(J$2-$C9, 'GEN-SOLAR'!$D$7:$AW$7, 'GEN-SOLAR'!$D$24:$AW$24), 0), IF($B9='Project List References'!$B$5, _xlfn.IFNA(_xlfn.XLOOKUP(J$2-$C9, 'GEN-BESS'!$D$7:$AW$7, 'GEN-BESS'!$D$24:$AW$24), 0), IF($B9='Project List References'!$B$6, _xlfn.IFNA(_xlfn.XLOOKUP(J$2-$C9, 'GEN-CARBON'!$D$7:$AW$7, 'GEN-CARBON'!$D$24:$AW$24), 0), IF($B9='Project List References'!$B$7, _xlfn.IFNA(_xlfn.XLOOKUP(J$2-$C9, 'SENS Coal'!$D$7:$AW$7, 'SENS Coal'!$D$24:$AW$24), 0), IF($B9='Project List References'!$B$8, _xlfn.IFNA(_xlfn.XLOOKUP(J$2-$C9, 'SENS Tires'!$D$7:$AW$7, 'SENS Tires'!$D$24:$AW$24), 0)))))))/_xlfn.XLOOKUP($B9, 'Assumptions & Inputs'!$F$76:$L$76, 'Assumptions & Inputs'!$F$77:$L$77)*IF(OR($B9='Project List References'!$B$3, $B9='Project List References'!$B$4, $B9='Project List References'!$B$5, $B9='Project List References'!$B$6), 'Project Master Sheet'!$E9, 'Project Master Sheet'!$F9) -> 0 | K9: =IF($B9='Project List References'!$B$3, _xlfn.IFNA(_xlfn.XLOOKUP(K$2-$C9, 'GEN-CCGT'!$D$7:$AW$7, 'GEN-CCGT'!$D$24:$AW$24), 0), IF($B9='Project List References'!$B$4, _xlfn.IFNA(_xlfn.XLOOKUP(K$2-$C9, 'GEN-SOLAR'!$D$7:$AW$7, 'GEN-SOLAR'!$D$24:$AW$24), 0), IF($B9='Project List References'!$B$5, _xlfn.IFNA(_xlfn.XLOOKUP(K$2-$C9, 'GEN-BESS'!$D$7:$AW$7, 'GEN-BESS'!$D$24:$AW$24), 0), IF($B9='Project List References'!$B$6, _xlfn.IFNA(_xlfn.XLOOKUP(K$2-$C9, 'GEN-CARBON'!$D$7:$AW$7, 'GEN-CARBON'!$D$24:$AW$24), 0), IF($B9='Project List References'!$B$7, _xlfn.IFNA(_xlfn.XLOOKUP(K$2-$C9, 'SENS Coal'!$D$7:$AW$7, 'SENS Coal'!$D$24:$AW$24), 0), IF($B9='Project List References'!$B$8, _xlfn.IFNA(_xlfn.XLOOKUP(K$2-$C9, 'SENS Tires'!$D$7:$AW$7, 'SENS Tires'!$D$24:$AW$24), 0)))))))/_xlfn.XLOOKUP($B9, 'Assumptions & Inputs'!$F$76:$L$76, 'Assumptions & Inputs'!$F$77:$L$77)*IF(OR($B9='Project List References'!$B$3, $B9='Project List References'!$B$4, $B9='Project List References'!$B$5, $B9='Project List References'!$B$6), 'Project Master Sheet'!$E9, 'Project Master Sheet'!$F9) -> 0 | L9: =IF($B9='Project List References'!$B$3, _xlfn.IFNA(_xlfn.XLOOKUP(L$2-$C9, 'GEN-CCGT'!$D$7:$AW$7, 'GEN-CCGT'!$D$24:$AW$24), 0), IF($B9='Project List References'!$B$4, _xlfn.IFNA(_xlfn.XLOOKUP(L$2-$C9, 'GEN-SOLAR'!$D$7:$AW$7, 'GEN-SOLAR'!$D$24:$AW$24), 0), IF($B9='Project List References'!$B$5, _xlfn.IFNA(_xlfn.XLOOKUP(L$2-$C9, 'GEN-BESS'!$D$7:$AW$7, 'GEN-BESS'!$D$24:$AW$24), 0), IF($B9='Project List References'!$B$6, _xlfn.IFNA(_xlfn.XLOOKUP(L$2-$C9, 'GEN-CARBON'!$D$7:$AW$7, 'GEN-CARBON'!$D$24:$AW$24), 0), IF($B9='Project List References'!$B$7, _xlfn.IFNA(_xlfn.XLOOKUP(L$2-$C9, 'SENS Coal'!$D$7:$AW$7, 'SENS Coal'!$D$24:$AW$24), 0), IF($B9='Project List References'!$B$8, _xlfn.IFNA(_xlfn.XLOOKUP(L$2-$C9, 'SENS Tires'!$D$7:$AW$7, 'SENS Tires'!$D$24:$AW$24), 0)))))))/_xlfn.XLOOKUP($B9, 'Assumptions & Inputs'!$F$76:$L$76, 'Assumptions & Inputs'!$F$77:$L$77)*IF(OR($B9='Project List References'!$B$3, $B9='Project List References'!$B$4, $B9='Project List References'!$B$5, $B9='Project List References'!$B$6), 'Project Master Sheet'!$E9, 'Project Master Sheet'!$F9) -> 0 | ... T9: =IF($B9='Project List References'!$B$3, _xlfn.IFNA(_xlfn.XLOOKUP(T$2-$C9, 'GEN-CCGT'!$D$7:$AW$7, 'GEN-CCGT'!$D$24:$AW$24), 0), IF($B9='Project List References'!$B$4, _xlfn.IFNA(_xlfn.XLOOKUP(T$2-$C9, 'GEN-SOLAR'!$D$7:$AW$7, 'GEN-SOLAR'!$D$24:$AW$24), 0), IF($B9='Project List References'!$B$5, _xlfn.IFNA(_xlfn.XLOOKUP(T$2-$C9, 'GEN-BESS'!$D$7:$AW$7, 'GEN-BESS'!$D$24:$AW$24), 0), IF($B9='Project List References'!$B$6, _xlfn.IFNA(_xlfn.XLOOKUP(T$2-$C9, 'GEN-CARBON'!$D$7:$AW$7, 'GEN-CARBON'!$D$24:$AW$24), 0), IF($B9='Project List References'!$B$7, _xlfn.IFNA(_xlfn.XLOOKUP(T$2-$C9, 'SENS Coal'!$D$7:$AW$7, 'SENS Coal'!$D$24:$AW$24), 0), IF($B9='Project List References'!$B$8, _xlfn.IFNA(_xlfn.XLOOKUP(T$2-$C9, 'SENS Tires'!$D$7:$AW$7, 'SENS Tires'!$D$24:$AW$24), 0)))))))/_xlfn.XLOOKUP($B9, 'Assumptions & Inputs'!$F$76:$L$76, 'Assumptions & Inputs'!$F$77:$L$77)*IF(OR($B9='Project List References'!$B$3, $B9='Project List References'!$B$4, $B9='Project List References'!$B$5, $B9='Project List References'!$B$6), 'Project Master Sheet'!$E9, 'Project Master Sheet'!$F9) -> 0
A10: =IF(ISBLANK('Project Master Sheet'!A10)=FALSE, 'Project Master Sheet'!A10, "") | B10: =_xlfn.IFNA(_xlfn.XLOOKUP(A10, 'Project Master Sheet'!A:A, 'Project Master Sheet'!D:D), "") | C10: =_xlfn.XLOOKUP(A10, 'Project Master Sheet'!A:A, 'Project Master Sheet'!I:I) -> #N/A | E10: =IF($B10='Project List References'!$B$3, _xlfn.IFNA(_xlfn.XLOOKUP(E$2-$C10, 'GEN-CCGT'!$D$7:$AW$7, 'GEN-CCGT'!$D$24:$AW$24), 0), IF($B10='Project List References'!$B$4, _xlfn.IFNA(_xlfn.XLOOKUP(E$2-$C10, 'GEN-SOLAR'!$D$7:$AW$7, 'GEN-SOLAR'!$D$24:$AW$24), 0), IF($B10='Project List References'!$B$5, _xlfn.IFNA(_xlfn.XLOOKUP(E$2-$C10, 'GEN-BESS'!$D$7:$AW$7, 'GEN-BESS'!$D$24:$AW$24), 0), IF($B10='Project List References'!$B$6, _xlfn.IFNA(_xlfn.XLOOKUP(E$2-$C10, 'GEN-CARBON'!$D$7:$AW$7, 'GEN-CARBON'!$D$24:$AW$24), 0), IF($B10='Project List References'!$B$7, _xlfn.IFNA(_xlfn.XLOOKUP(E$2-$C10, 'SENS Coal'!$D$7:$AW$7, 'SENS Coal'!$D$24:$AW$24), 0), IF($B10='Project List References'!$B$8, _xlfn.IFNA(_xlfn.XLOOKUP(E$2-$C10, 'SENS Tires'!$D$7:$AW$7, 'SENS Tires'!$D$24:$AW$24), 0)))))))/_xlfn.XLOOKUP($B10, 'Assumptions & Inputs'!$F$76:$L$76, 'Assumptions & Inputs'!$F$77:$L$77)*IF(OR($B10='Project List References'!$B$3, $B10='Project List References'!$B$4, $B10='Project List References'!$B$5, $B10='Project List References'!$B$6), 'Project Master Sheet'!$E10, 'Project Master Sheet'!$F10) -> #N/A | F10: =IF($B10='Project List References'!$B$3, _xlfn.IFNA(_xlfn.XLOOKUP(F$2-$C10, 'GEN-CCGT'!$D$7:$AW$7, 'GEN-CCGT'!$D$24:$AW$24), 0), IF($B10='Project List References'!$B$4, _xlfn.IFNA(_xlfn.XLOOKUP(F$2-$C10, 'GEN-SOLAR'!$D$7:$AW$7, 'GEN-SOLAR'!$D$24:$AW$24), 0), IF($B10='Project List References'!$B$5, _xlfn.IFNA(_xlfn.XLOOKUP(F$2-$C10, 'GEN-BESS'!$D$7:$AW$7, 'GEN-BESS'!$D$24:$AW$24), 0), IF($B10='Project List References'!$B$6, _xlfn.IFNA(_xlfn.XLOOKUP(F$2-$C10, 'GEN-CARBON'!$D$7:$AW$7, 'GEN-CARBON'!$D$24:$AW$24), 0), IF($B10='Project List References'!$B$7, _xlfn.IFNA(_xlfn.XLOOKUP(F$2-$C10, 'SENS Coal'!$D$7:$AW$7, 'SENS Coal'!$D$24:$AW$24), 0), IF($B10='Project List References'!$B$8, _xlfn.IFNA(_xlfn.XLOOKUP(F$2-$C10, 'SENS Tires'!$D$7:$AW$7, 'SENS Tires'!$D$24:$AW$24), 0)))))))/_xlfn.XLOOKUP($B10, 'Assumptions & Inputs'!$F$76:$L$76, 'Assumptions & Inputs'!$F$77:$L$77)*IF(OR($B10='Project List References'!$B$3, $B10='Project List References'!$B$4, $B10='Project List References'!$B$5, $B10='Project List References'!$B$6), 'Project Master Sheet'!$E10, 'Project Master Sheet'!$F10) -> #N/A | G10: =IF($B10='Project List References'!$B$3, _xlfn.IFNA(_xlfn.XLOOKUP(G$2-$C10, 'GEN-CCGT'!$D$7:$AW$7, 'GEN-CCGT'!$D$24:$AW$24), 0), IF($B10='Project List References'!$B$4, _xlfn.IFNA(_xlfn.XLOOKUP(G$2-$C10, 'GEN-SOLAR'!$D$7:$AW$7, 'GEN-SOLAR'!$D$24:$AW$24), 0), IF($B10='Project List References'!$B$5, _xlfn.IFNA(_xlfn.XLOOKUP(G$2-$C10, 'GEN-BESS'!$D$7:$AW$7, 'GEN-BESS'!$D$24:$AW$24), 0), IF($B10='Project List References'!$B$6, _xlfn.IFNA(_xlfn.XLOOKUP(G$2-$C10, 'GEN-CARBON'!$D$7:$AW$7, 'GEN-CARBON'!$D$24:$AW$24), 0), IF($B10='Project List References'!$B$7, _xlfn.IFNA(_xlfn.XLOOKUP(G$2-$C10, 'SENS Coal'!$D$7:$AW$7, 'SENS Coal'!$D$24:$AW$24), 0), IF($B10='Project List References'!$B$8, _xlfn.IFNA(_xlfn.XLOOKUP(G$2-$C10, 'SENS Tires'!$D$7:$AW$7, 'SENS Tires'!$D$24:$AW$24), 0)))))))/_xlfn.XLOOKUP($B10, 'Assumptions & Inputs'!$F$76:$L$76, 'Assumptions & Inputs'!$F$77:$L$77)*IF(OR($B10='Project List References'!$B$3, $B10='Project List References'!$B$4, $B10='Project List References'!$B$5, $B10='Project List References'!$B$6), 'Project Master Sheet'!$E10, 'Project Master Sheet'!$F10) -> #N/A | H10: =IF($B10='Project List References'!$B$3, _xlfn.IFNA(_xlfn.XLOOKUP(H$2-$C10, 'GEN-CCGT'!$D$7:$AW$7, 'GEN-CCGT'!$D$24:$AW$24), 0), IF($B10='Project List References'!$B$4, _xlfn.IFNA(_xlfn.XLOOKUP(H$2-$C10, 'GEN-SOLAR'!$D$7:$AW$7, 'GEN-SOLAR'!$D$24:$AW$24), 0), IF($B10='Project List References'!$B$5, _xlfn.IFNA(_xlfn.XLOOKUP(H$2-$C10, 'GEN-BESS'!$D$7:$AW$7, 'GEN-BESS'!$D$24:$AW$24), 0), IF($B10='Project List References'!$B$6, _xlfn.IFNA(_xlfn.XLOOKUP(H$2-$C10, 'GEN-CARBON'!$D$7:$AW$7, 'GEN-CARBON'!$D$24:$AW$24), 0), IF($B10='Project List References'!$B$7, _xlfn.IFNA(_xlfn.XLOOKUP(H$2-$C10, 'SENS Coal'!$D$7:$AW$7, 'SENS Coal'!$D$24:$AW$24), 0), IF($B10='Project List References'!$B$8, _xlfn.IFNA(_xlfn.XLOOKUP(H$2-$C10, 'SENS Tires'!$D$7:$AW$7, 'SENS Tires'!$D$24:$AW$24), 0)))))))/_xlfn.XLOOKUP($B10, 'Assumptions & Inputs'!$F$76:$L$76, 'Assumptions & Inputs'!$F$77:$L$77)*IF(OR($B10='Project List References'!$B$3, $B10='Project List References'!$B$4, $B10='Project List References'!$B$5, $B10='Project List References'!$B$6), 'Project Master Sheet'!$E10, 'Project Master Sheet'!$F10) -> #N/A | I10: =IF($B10='Project List References'!$B$3, _xlfn.IFNA(_xlfn.XLOOKUP(I$2-$C10, 'GEN-CCGT'!$D$7:$AW$7, 'GEN-CCGT'!$D$24:$AW$24), 0), IF($B10='Project List References'!$B$4, _xlfn.IFNA(_xlfn.XLOOKUP(I$2-$C10, 'GEN-SOLAR'!$D$7:$AW$7, 'GEN-SOLAR'!$D$24:$AW$24), 0), IF($B10='Project List References'!$B$5, _xlfn.IFNA(_xlfn.XLOOKUP(I$2-$C10, 'GEN-BESS'!$D$7:$AW$7, 'GEN-BESS'!$D$24:$AW$24), 0), IF($B10='Project List References'!$B$6, _xlfn.IFNA(_xlfn.XLOOKUP(I$2-$C10, 'GEN-CARBON'!$D$7:$AW$7, 'GEN-CARBON'!$D$24:$AW$24), 0), IF($B10='Project List References'!$B$7, _xlfn.IFNA(_xlfn.XLOOKUP(I$2-$C10, 'SENS Coal'!$D$7:$AW$7, 'SENS Coal'!$D$24:$AW$24), 0), IF($B10='Project List References'!$B$8, _xlfn.IFNA(_xlfn.XLOOKUP(I$2-$C10, 'SENS Tires'!$D$7:$AW$7, 'SENS Tires'!$D$24:$AW$24), 0)))))))/_xlfn.XLOOKUP($B10, 'Assumptions & Inputs'!$F$76:$L$76, 'Assumptions & Inputs'!$F$77:$L$77)*IF(OR($B10='Project List References'!$B$3, $B10='Project List References'!$B$4, $B10='Project List References'!$B$5, $B10='Project List References'!$B$6), 'Project Master Sheet'!$E10, 'Project Master Sheet'!$F10) -> #N/A | J10: =IF($B10='Project List References'!$B$3, _xlfn.IFNA(_xlfn.XLOOKUP(J$2-$C10, 'GEN-CCGT'!$D$7:$AW$7, 'GEN-CCGT'!$D$24:$AW$24), 0), IF($B10='Project List References'!$B$4, _xlfn.IFNA(_xlfn.XLOOKUP(J$2-$C10, 'GEN-SOLAR'!$D$7:$AW$7, 'GEN-SOLAR'!$D$24:$AW$24), 0), IF($B10='Project List References'!$B$5, _xlfn.IFNA(_xlfn.XLOOKUP(J$2-$C10, 'GEN-BESS'!$D$7:$AW$7, 'GEN-BESS'!$D$24:$AW$24), 0), IF($B10='Project List References'!$B$6, _xlfn.IFNA(_xlfn.XLOOKUP(J$2-$C10, 'GEN-CARBON'!$D$7:$AW$7, 'GEN-CARBON'!$D$24:$AW$24), 0), IF($B10='Project List References'!$B$7, _xlfn.IFNA(_xlfn.XLOOKUP(J$2-$C10, 'SENS Coal'!$D$7:$AW$7, 'SENS Coal'!$D$24:$AW$24), 0), IF($B10='Project List References'!$B$8, _xlfn.IFNA(_xlfn.XLOOKUP(J$2-$C10, 'SENS Tires'!$D$7:$AW$7, 'SENS Tires'!$D$24:$AW$24), 0)))))))/_xlfn.XLOOKUP($B10, 'Assumptions & Inputs'!$F$76:$L$76, 'Assumptions & Inputs'!$F$77:$L$77)*IF(OR($B10='Project List References'!$B$3, $B10='Project List References'!$B$4, $B10='Project List References'!$B$5, $B10='Project List References'!$B$6), 'Project Master Sheet'!$E10, 'Project Master Sheet'!$F10) -> #N/A | K10: =IF($B10='Project List References'!$B$3, _xlfn.IFNA(_xlfn.XLOOKUP(K$2-$C10, 'GEN-CCGT'!$D$7:$AW$7, 'GEN-CCGT'!$D$24:$AW$24), 0), IF($B10='Project List References'!$B$4, _xlfn.IFNA(_xlfn.XLOOKUP(K$2-$C10, 'GEN-SOLAR'!$D$7:$AW$7, 'GEN-SOLAR'!$D$24:$AW$24), 0), IF($B10='Project List References'!$B$5, _xlfn.IFNA(_xlfn.XLOOKUP(K$2-$C10, 'GEN-BESS'!$D$7:$AW$7, 'GEN-BESS'!$D$24:$AW$24), 0), IF($B10='Project List References'!$B$6, _xlfn.IFNA(_xlfn.XLOOKUP(K$2-$C10, 'GEN-CARBON'!$D$7:$AW$7, 'GEN-CARBON'!$D$24:$AW$24), 0), IF($B10='Project List References'!$B$7, _xlfn.IFNA(_xlfn.XLOOKUP(K$2-$C10, 'SENS Coal'!$D$7:$AW$7, 'SENS Coal'!$D$24:$AW$24), 0), IF($B10='Project List References'!$B$8, _xlfn.IFNA(_xlfn.XLOOKUP(K$2-$C10, 'SENS Tires'!$D$7:$AW$7, 'SENS Tires'!$D$24:$AW$24), 0)))))))/_xlfn.XLOOKUP($B10, 'Assumptions & Inputs'!$F$76:$L$76, 'Assumptions & Inputs'!$F$77:$L$77)*IF(OR($B10='Project List References'!$B$3, $B10='Project List References'!$B$4, $B10='Project List References'!$B$5, $B10='Project List References'!$B$6), 'Project Master Sheet'!$E10, 'Project Master Sheet'!$F10) -> #N/A | L10: =IF($B10='Project List References'!$B$3, _xlfn.IFNA(_xlfn.XLOOKUP(L$2-$C10, 'GEN-CCGT'!$D$7:$AW$7, 'GEN-CCGT'!$D$24:$AW$24), 0), IF($B10='Project List References'!$B$4, _xlfn.IFNA(_xlfn.XLOOKUP(L$2-$C10, 'GEN-SOLAR'!$D$7:$AW$7, 'GEN-SOLAR'!$D$24:$AW$24), 0), IF($B10='Project List References'!$B$5, _xlfn.IFNA(_xlfn.XLOOKUP(L$2-$C10, 'GEN-BESS'!$D$7:$AW$7, 'GEN-BESS'!$D$24:$AW$24), 0), IF($B10='Project List References'!$B$6, _xlfn.IFNA(_xlfn.XLOOKUP(L$2-$C10, 'GEN-CARBON'!$D$7:$AW$7, 'GEN-CARBON'!$D$24:$AW$24), 0), IF($B10='Project List References'!$B$7, _xlfn.IFNA(_xlfn.XLOOKUP(L$2-$C10, 'SENS Coal'!$D$7:$AW$7, 'SENS Coal'!$D$24:$AW$24), 0), IF($B10='Project List References'!$B$8, _xlfn.IFNA(_xlfn.XLOOKUP(L$2-$C10, 'SENS Tires'!$D$7:$AW$7, 'SENS Tires'!$D$24:$AW$24), 0)))))))/_xlfn.XLOOKUP($B10, 'Assumptions & Inputs'!$F$76:$L$76, 'Assumptions & Inputs'!$F$77:$L$77)*IF(OR($B10='Project List References'!$B$3, $B10='Project List References'!$B$4, $B10='Project List References'!$B$5, $B10='Project List References'!$B$6), 'Project Master Sheet'!$E10, 'Project Master Sheet'!$F10) -> #N/A | ... T10: =IF($B10='Project List References'!$B$3, _xlfn.IFNA(_xlfn.XLOOKUP(T$2-$C10, 'GEN-CCGT'!$D$7:$AW$7, 'GEN-CCGT'!$D$24:$AW$24), 0), IF($B10='Project List References'!$B$4, _xlfn.IFNA(_xlfn.XLOOKUP(T$2-$C10, 'GEN-SOLAR'!$D$7:$AW$7, 'GEN-SOLAR'!$D$24:$AW$24), 0), IF($B10='Project List References'!$B$5, _xlfn.IFNA(_xlfn.XLOOKUP(T$2-$C10, 'GEN-BESS'!$D$7:$AW$7, 'GEN-BESS'!$D$24:$AW$24), 0), IF($B10='Project List References'!$B$6, _xlfn.IFNA(_xlfn.XLOOKUP(T$2-$C10, 'GEN-CARBON'!$D$7:$AW$7, 'GEN-CARBON'!$D$24:$AW$24), 0), IF($B10='Project List References'!$B$7, _xlfn.IFNA(_xlfn.XLOOKUP(T$2-$C10, 'SENS Coal'!$D$7:$AW$7, 'SENS Coal'!$D$24:$AW$24), 0), IF($B10='Project List References'!$B$8, _xlfn.IFNA(_xlfn.XLOOKUP(T$2-$C10, 'SENS Tires'!$D$7:$AW$7, 'SENS Tires'!$D$24:$AW$24), 0)))))))/_xlfn.XLOOKUP($B10, 'Assumptions & Inputs'!$F$76:$L$76, 'Assumptions & Inputs'!$F$77:$L$77)*IF(OR($B10='Project List References'!$B$3, $B10='Project List References'!$B$4, $B10='Project List References'!$B$5, $B10='Project List References'!$B$6), 'Project Master Sheet'!$E10, 'Project Master Sheet'!$F10) -> #N/A
A11: =IF(ISBLANK('Project Master Sheet'!A11)=FALSE, 'Project Master Sheet'!A11, "") | B11: =_xlfn.IFNA(_xlfn.XLOOKUP(A11, 'Project Master Sheet'!A:A, 'Project Master Sheet'!D:D), "") | C11: =_xlfn.XLOOKUP(A11, 'Project Master Sheet'!A:A, 'Project Master Sheet'!I:I) -> #N/A | E11: =IF($B11='Project List References'!$B$3, _xlfn.IFNA(_xlfn.XLOOKUP(E$2-$C11, 'GEN-CCGT'!$D$7:$AW$7, 'GEN-CCGT'!$D$24:$AW$24), 0), IF($B11='Project List References'!$B$4, _xlfn.IFNA(_xlfn.XLOOKUP(E$2-$C11, 'GEN-SOLAR'!$D$7:$AW$7, 'GEN-SOLAR'!$D$24:$AW$24), 0), IF($B11='Project List References'!$B$5, _xlfn.IFNA(_xlfn.XLOOKUP(E$2-$C11, 'GEN-BESS'!$D$7:$AW$7, 'GEN-BESS'!$D$24:$AW$24), 0), IF($B11='Project List References'!$B$6, _xlfn.IFNA(_xlfn.XLOOKUP(E$2-$C11, 'GEN-CARBON'!$D$7:$AW$7, 'GEN-CARBON'!$D$24:$AW$24), 0), IF($B11='Project List References'!$B$7, _xlfn.IFNA(_xlfn.XLOOKUP(E$2-$C11, 'SENS Coal'!$D$7:$AW$7, 'SENS Coal'!$D$24:$AW$24), 0), IF($B11='Project List References'!$B$8, _xlfn.IFNA(_xlfn.XLOOKUP(E$2-$C11, 'SENS Tires'!$D$7:$AW$7, 'SENS Tires'!$D$24:$AW$24), 0)))))))/_xlfn.XLOOKUP($B11, 'Assumptions & Inputs'!$F$76:$L$76, 'Assumptions & Inputs'!$F$77:$L$77)*IF(OR($B11='Project List References'!$B$3, $B11='Project List References'!$B$4, $B11='Project List References'!$B$5, $B11='Project List References'!$B$6), 'Project Master Sheet'!$E11, 'Project Master Sheet'!$F11) -> #N/A | F11: =IF($B11='Project List References'!$B$3, _xlfn.IFNA(_xlfn.XLOOKUP(F$2-$C11, 'GEN-CCGT'!$D$7:$AW$7, 'GEN-CCGT'!$D$24:$AW$24), 0), IF($B11='Project List References'!$B$4, _xlfn.IFNA(_xlfn.XLOOKUP(F$2-$C11, 'GEN-SOLAR'!$D$7:$AW$7, 'GEN-SOLAR'!$D$24:$AW$24), 0), IF($B11='Project List References'!$B$5, _xlfn.IFNA(_xlfn.XLOOKUP(F$2-$C11, 'GEN-BESS'!$D$7:$AW$7, 'GEN-BESS'!$D$24:$AW$24), 0), IF($B11='Project List References'!$B$6, _xlfn.IFNA(_xlfn.XLOOKUP(F$2-$C11, 'GEN-CARBON'!$D$7:$AW$7, 'GEN-CARBON'!$D$24:$AW$24), 0), IF($B11='Project List References'!$B$7, _xlfn.IFNA(_xlfn.XLOOKUP(F$2-$C11, 'SENS Coal'!$D$7:$AW$7, 'SENS Coal'!$D$24:$AW$24), 0), IF($B11='Project List References'!$B$8, _xlfn.IFNA(_xlfn.XLOOKUP(F$2-$C11, 'SENS Tires'!$D$7:$AW$7, 'SENS Tires'!$D$24:$AW$24), 0)))))))/_xlfn.XLOOKUP($B11, 'Assumptions & Inputs'!$F$76:$L$76, 'Assumptions & Inputs'!$F$77:$L$77)*IF(OR($B11='Project List References'!$B$3, $B11='Project List References'!$B$4, $B11='Project List References'!$B$5, $B11='Project List References'!$B$6), 'Project Master Sheet'!$E11, 'Project Master Sheet'!$F11) -> #N/A | G11: =IF($B11='Project List References'!$B$3, _xlfn.IFNA(_xlfn.XLOOKUP(G$2-$C11, 'GEN-CCGT'!$D$7:$AW$7, 'GEN-CCGT'!$D$24:$AW$24), 0), IF($B11='Project List References'!$B$4, _xlfn.IFNA(_xlfn.XLOOKUP(G$2-$C11, 'GEN-SOLAR'!$D$7:$AW$7, 'GEN-SOLAR'!$D$24:$AW$24), 0), IF($B11='Project List References'!$B$5, _xlfn.IFNA(_xlfn.XLOOKUP(G$2-$C11, 'GEN-BESS'!$D$7:$AW$7, 'GEN-BESS'!$D$24:$AW$24), 0), IF($B11='Project List References'!$B$6, _xlfn.IFNA(_xlfn.XLOOKUP(G$2-$C11, 'GEN-CARBON'!$D$7:$AW$7, 'GEN-CARBON'!$D$24:$AW$24), 0), IF($B11='Project List References'!$B$7, _xlfn.IFNA(_xlfn.XLOOKUP(G$2-$C11, 'SENS Coal'!$D$7:$AW$7, 'SENS Coal'!$D$24:$AW$24), 0), IF($B11='Project List References'!$B$8, _xlfn.IFNA(_xlfn.XLOOKUP(G$2-$C11, 'SENS Tires'!$D$7:$AW$7, 'SENS Tires'!$D$24:$AW$24), 0)))))))/_xlfn.XLOOKUP($B11, 'Assumptions & Inputs'!$F$76:$L$76, 'Assumptions & Inputs'!$F$77:$L$77)*IF(OR($B11='Project List References'!$B$3, $B11='Project List References'!$B$4, $B11='Project List References'!$B$5, $B11='Project List References'!$B$6), 'Project Master Sheet'!$E11, 'Project Master Sheet'!$F11) -> #N/A | H11: =IF($B11='Project List References'!$B$3, _xlfn.IFNA(_xlfn.XLOOKUP(H$2-$C11, 'GEN-CCGT'!$D$7:$AW$7, 'GEN-CCGT'!$D$24:$AW$24), 0), IF($B11='Project List References'!$B$4, _xlfn.IFNA(_xlfn.XLOOKUP(H$2-$C11, 'GEN-SOLAR'!$D$7:$AW$7, 'GEN-SOLAR'!$D$24:$AW$24), 0), IF($B11='Project List References'!$B$5, _xlfn.IFNA(_xlfn.XLOOKUP(H$2-$C11, 'GEN-BESS'!$D$7:$AW$7, 'GEN-BESS'!$D$24:$AW$24), 0), IF($B11='Project List References'!$B$6, _xlfn.IFNA(_xlfn.XLOOKUP(H$2-$C11, 'GEN-CARBON'!$D$7:$AW$7, 'GEN-CARBON'!$D$24:$AW$24), 0), IF($B11='Project List References'!$B$7, _xlfn.IFNA(_xlfn.XLOOKUP(H$2-$C11, 'SENS Coal'!$D$7:$AW$7, 'SENS Coal'!$D$24:$AW$24), 0), IF($B11='Project List References'!$B$8, _xlfn.IFNA(_xlfn.XLOOKUP(H$2-$C11, 'SENS Tires'!$D$7:$AW$7, 'SENS Tires'!$D$24:$AW$24), 0)))))))/_xlfn.XLOOKUP($B11, 'Assumptions & Inputs'!$F$76:$L$76, 'Assumptions & Inputs'!$F$77:$L$77)*IF(OR($B11='Project List References'!$B$3, $B11='Project List References'!$B$4, $B11='Project List References'!$B$5, $B11='Project List References'!$B$6), 'Project Master Sheet'!$E11, 'Project Master Sheet'!$F11) -> #N/A | I11: =IF($B11='Project List References'!$B$3, _xlfn.IFNA(_xlfn.XLOOKUP(I$2-$C11, 'GEN-CCGT'!$D$7:$AW$7, 'GEN-CCGT'!$D$24:$AW$24), 0), IF($B11='Project List References'!$B$4, _xlfn.IFNA(_xlfn.XLOOKUP(I$2-$C11, 'GEN-SOLAR'!$D$7:$AW$7, 'GEN-SOLAR'!$D$24:$AW$24), 0), IF($B11='Project List References'!$B$5, _xlfn.IFNA(_xlfn.XLOOKUP(I$2-$C11, 'GEN-BESS'!$D$7:$AW$7, 'GEN-BESS'!$D$24:$AW$24), 0), IF($B11='Project List References'!$B$6, _xlfn.IFNA(_xlfn.XLOOKUP(I$2-$C11, 'GEN-CARBON'!$D$7:$AW$7, 'GEN-CARBON'!$D$24:$AW$24), 0), IF($B11='Project List References'!$B$7, _xlfn.IFNA(_xlfn.XLOOKUP(I$2-$C11, 'SENS Coal'!$D$7:$AW$7, 'SENS Coal'!$D$24:$AW$24), 0), IF($B11='Project List References'!$B$8, _xlfn.IFNA(_xlfn.XLOOKUP(I$2-$C11, 'SENS Tires'!$D$7:$AW$7, 'SENS Tires'!$D$24:$AW$24), 0)))))))/_xlfn.XLOOKUP($B11, 'Assumptions & Inputs'!$F$76:$L$76, 'Assumptions & Inputs'!$F$77:$L$77)*IF(OR($B11='Project List References'!$B$3, $B11='Project List References'!$B$4, $B11='Project List References'!$B$5, $B11='Project List References'!$B$6), 'Project Master Sheet'!$E11, 'Project Master Sheet'!$F11) -> #N/A | J11: =IF($B11='Project List References'!$B$3, _xlfn.IFNA(_xlfn.XLOOKUP(J$2-$C11, 'GEN-CCGT'!$D$7:$AW$7, 'GEN-CCGT'!$D$24:$AW$24), 0), IF($B11='Project List References'!$B$4, _xlfn.IFNA(_xlfn.XLOOKUP(J$2-$C11, 'GEN-SOLAR'!$D$7:$AW$7, 'GEN-SOLAR'!$D$24:$AW$24), 0), IF($B11='Project List References'!$B$5, _xlfn.IFNA(_xlfn.XLOOKUP(J$2-$C11, 'GEN-BESS'!$D$7:$AW$7, 'GEN-BESS'!$D$24:$AW$24), 0), IF($B11='Project List References'!$B$6, _xlfn.IFNA(_xlfn.XLOOKUP(J$2-$C11, 'GEN-CARBON'!$D$7:$AW$7, 'GEN-CARBON'!$D$24:$AW$24), 0), IF($B11='Project List References'!$B$7, _xlfn.IFNA(_xlfn.XLOOKUP(J$2-$C11, 'SENS Coal'!$D$7:$AW$7, 'SENS Coal'!$D$24:$AW$24), 0), IF($B11='Project List References'!$B$8, _xlfn.IFNA(_xlfn.XLOOKUP(J$2-$C11, 'SENS Tires'!$D$7:$AW$7, 'SENS Tires'!$D$24:$AW$24), 0)))))))/_xlfn.XLOOKUP($B11, 'Assumptions & Inputs'!$F$76:$L$76, 'Assumptions & Inputs'!$F$77:$L$77)*IF(OR($B11='Project List References'!$B$3, $B11='Project List References'!$B$4, $B11='Project List References'!$B$5, $B11='Project List References'!$B$6), 'Project Master Sheet'!$E11, 'Project Master Sheet'!$F11) -> #N/A | K11: =IF($B11='Project List References'!$B$3, _xlfn.IFNA(_xlfn.XLOOKUP(K$2-$C11, 'GEN-CCGT'!$D$7:$AW$7, 'GEN-CCGT'!$D$24:$AW$24), 0), IF($B11='Project List References'!$B$4, _xlfn.IFNA(_xlfn.XLOOKUP(K$2-$C11, 'GEN-SOLAR'!$D$7:$AW$7, 'GEN-SOLAR'!$D$24:$AW$24), 0), IF($B11='Project List References'!$B$5, _xlfn.IFNA(_xlfn.XLOOKUP(K$2-$C11, 'GEN-BESS'!$D$7:$AW$7, 'GEN-BESS'!$D$24:$AW$24), 0), IF($B11='Project List References'!$B$6, _xlfn.IFNA(_xlfn.XLOOKUP(K$2-$C11, 'GEN-CARBON'!$D$7:$AW$7, 'GEN-CARBON'!$D$24:$AW$24), 0), IF($B11='Project List References'!$B$7, _xlfn.IFNA(_xlfn.XLOOKUP(K$2-$C11, 'SENS Coal'!$D$7:$AW$7, 'SENS Coal'!$D$24:$AW$24), 0), IF($B11='Project List References'!$B$8, _xlfn.IFNA(_xlfn.XLOOKUP(K$2-$C11, 'SENS Tires'!$D$7:$AW$7, 'SENS Tires'!$D$24:$AW$24), 0)))))))/_xlfn.XLOOKUP($B11, 'Assumptions & Inputs'!$F$76:$L$76, 'Assumptions & Inputs'!$F$77:$L$77)*IF(OR($B11='Project List References'!$B$3, $B11='Project List References'!$B$4, $B11='Project List References'!$B$5, $B11='Project List References'!$B$6), 'Project Master Sheet'!$E11, 'Project Master Sheet'!$F11) -> #N/A | L11: =IF($B11='Project List References'!$B$3, _xlfn.IFNA(_xlfn.XLOOKUP(L$2-$C11, 'GEN-CCGT'!$D$7:$AW$7, 'GEN-CCGT'!$D$24:$AW$24), 0), IF($B11='Project List References'!$B$4, _xlfn.IFNA(_xlfn.XLOOKUP(L$2-$C11, 'GEN-SOLAR'!$D$7:$AW$7, 'GEN-SOLAR'!$D$24:$AW$24), 0), IF($B11='Project List References'!$B$5, _xlfn.IFNA(_xlfn.XLOOKUP(L$2-$C11, 'GEN-BESS'!$D$7:$AW$7, 'GEN-BESS'!$D$24:$AW$24), 0), IF($B11='Project List References'!$B$6, _xlfn.IFNA(_xlfn.XLOOKUP(L$2-$C11, 'GEN-CARBON'!$D$7:$AW$7, 'GEN-CARBON'!$D$24:$AW$24), 0), IF($B11='Project List References'!$B$7, _xlfn.IFNA(_xlfn.XLOOKUP(L$2-$C11, 'SENS Coal'!$D$7:$AW$7, 'SENS Coal'!$D$24:$AW$24), 0), IF($B11='Project List References'!$B$8, _xlfn.IFNA(_xlfn.XLOOKUP(L$2-$C11, 'SENS Tires'!$D$7:$AW$7, 'SENS Tires'!$D$24:$AW$24), 0)))))))/_xlfn.XLOOKUP($B11, 'Assumptions & Inputs'!$F$76:$L$76, 'Assumptions & Inputs'!$F$77:$L$77)*IF(OR($B11='Project List References'!$B$3, $B11='Project List References'!$B$4, $B11='Project List References'!$B$5, $B11='Project List References'!$B$6), 'Project Master Sheet'!$E11, 'Project Master Sheet'!$F11) -> #N/A | ... T11: =IF($B11='Project List References'!$B$3, _xlfn.IFNA(_xlfn.XLOOKUP(T$2-$C11, 'GEN-CCGT'!$D$7:$AW$7, 'GEN-CCGT'!$D$24:$AW$24), 0), IF($B11='Project List References'!$B$4, _xlfn.IFNA(_xlfn.XLOOKUP(T$2-$C11, 'GEN-SOLAR'!$D$7:$AW$7, 'GEN-SOLAR'!$D$24:$AW$24), 0), IF($B11='Project List References'!$B$5, _xlfn.IFNA(_xlfn.XLOOKUP(T$2-$C11, 'GEN-BESS'!$D$7:$AW$7, 'GEN-BESS'!$D$24:$AW$24), 0), IF($B11='Project List References'!$B$6, _xlfn.IFNA(_xlfn.XLOOKUP(T$2-$C11, 'GEN-CARBON'!$D$7:$AW$7, 'GEN-CARBON'!$D$24:$AW$24), 0), IF($B11='Project List References'!$B$7, _xlfn.IFNA(_xlfn.XLOOKUP(T$2-$C11, 'SENS Coal'!$D$7:$AW$7, 'SENS Coal'!$D$24:$AW$24), 0), IF($B11='Project List References'!$B$8, _xlfn.IFNA(_xlfn.XLOOKUP(T$2-$C11, 'SENS Tires'!$D$7:$AW$7, 'SENS Tires'!$D$24:$AW$24), 0)))))))/_xlfn.XLOOKUP($B11, 'Assumptions & Inputs'!$F$76:$L$76, 'Assumptions & Inputs'!$F$77:$L$77)*IF(OR($B11='Project List References'!$B$3, $B11='Project List References'!$B$4, $B11='Project List References'!$B$5, $B11='Project List References'!$B$6), 'Project Master Sheet'!$E11, 'Project Master Sheet'!$F11) -> #N/A
A12: =IF(ISBLANK('Project Master Sheet'!A12)=FALSE, 'Project Master Sheet'!A12, "") | B12: =_xlfn.IFNA(_xlfn.XLOOKUP(A12, 'Project Master Sheet'!A:A, 'Project Master Sheet'!D:D), "") | C12: =_xlfn.XLOOKUP(A12, 'Project Master Sheet'!A:A, 'Project Master Sheet'!I:I) -> #N/A | E12: =IF($B12='Project List References'!$B$3, _xlfn.IFNA(_xlfn.XLOOKUP(E$2-$C12, 'GEN-CCGT'!$D$7:$AW$7, 'GEN-CCGT'!$D$24:$AW$24), 0), IF($B12='Project List References'!$B$4, _xlfn.IFNA(_xlfn.XLOOKUP(E$2-$C12, 'GEN-SOLAR'!$D$7:$AW$7, 'GEN-SOLAR'!$D$24:$AW$24), 0), IF($B12='Project List References'!$B$5, _xlfn.IFNA(_xlfn.XLOOKUP(E$2-$C12, 'GEN-BESS'!$D$7:$AW$7, 'GEN-BESS'!$D$24:$AW$24), 0), IF($B12='Project List References'!$B$6, _xlfn.IFNA(_xlfn.XLOOKUP(E$2-$C12, 'GEN-CARBON'!$D$7:$AW$7, 'GEN-CARBON'!$D$24:$AW$24), 0), IF($B12='Project List References'!$B$7, _xlfn.IFNA(_xlfn.XLOOKUP(E$2-$C12, 'SENS Coal'!$D$7:$AW$7, 'SENS Coal'!$D$24:$AW$24), 0), IF($B12='Project List References'!$B$8, _xlfn.IFNA(_xlfn.XLOOKUP(E$2-$C12, 'SENS Tires'!$D$7:$AW$7, 'SENS Tires'!$D$24:$AW$24), 0)))))))/_xlfn.XLOOKUP($B12, 'Assumptions & Inputs'!$F$76:$L$76, 'Assumptions & Inputs'!$F$77:$L$77)*IF(OR($B12='Project List References'!$B$3, $B12='Project List References'!$B$4, $B12='Project List References'!$B$5, $B12='Project List References'!$B$6), 'Project Master Sheet'!$E12, 'Project Master Sheet'!$F12) -> #N/A | F12: =IF($B12='Project List References'!$B$3, _xlfn.IFNA(_xlfn.XLOOKUP(F$2-$C12, 'GEN-CCGT'!$D$7:$AW$7, 'GEN-CCGT'!$D$24:$AW$24), 0), IF($B12='Project List References'!$B$4, _xlfn.IFNA(_xlfn.XLOOKUP(F$2-$C12, 'GEN-SOLAR'!$D$7:$AW$7, 'GEN-SOLAR'!$D$24:$AW$24), 0), IF($B12='Project List References'!$B$5, _xlfn.IFNA(_xlfn.XLOOKUP(F$2-$C12, 'GEN-BESS'!$D$7:$AW$7, 'GEN-BESS'!$D$24:$AW$24), 0), IF($B12='Project List References'!$B$6, _xlfn.IFNA(_xlfn.XLOOKUP(F$2-$C12, 'GEN-CARBON'!$D$7:$AW$7, 'GEN-CARBON'!$D$24:$AW$24), 0), IF($B12='Project List References'!$B$7, _xlfn.IFNA(_xlfn.XLOOKUP(F$2-$C12, 'SENS Coal'!$D$7:$AW$7, 'SENS Coal'!$D$24:$AW$24), 0), IF($B12='Project List References'!$B$8, _xlfn.IFNA(_xlfn.XLOOKUP(F$2-$C12, 'SENS Tires'!$D$7:$AW$7, 'SENS Tires'!$D$24:$AW$24), 0)))))))/_xlfn.XLOOKUP($B12, 'Assumptions & Inputs'!$F$76:$L$76, 'Assumptions & Inputs'!$F$77:$L$77)*IF(OR($B12='Project List References'!$B$3, $B12='Project List References'!$B$4, $B12='Project List References'!$B$5, $B12='Project List References'!$B$6), 'Project Master Sheet'!$E12, 'Project Master Sheet'!$F12) -> #N/A | G12: =IF($B12='Project List References'!$B$3, _xlfn.IFNA(_xlfn.XLOOKUP(G$2-$C12, 'GEN-CCGT'!$D$7:$AW$7, 'GEN-CCGT'!$D$24:$AW$24), 0), IF($B12='Project List References'!$B$4, _xlfn.IFNA(_xlfn.XLOOKUP(G$2-$C12, 'GEN-SOLAR'!$D$7:$AW$7, 'GEN-SOLAR'!$D$24:$AW$24), 0), IF($B12='Project List References'!$B$5, _xlfn.IFNA(_xlfn.XLOOKUP(G$2-$C12, 'GEN-BESS'!$D$7:$AW$7, 'GEN-BESS'!$D$24:$AW$24), 0), IF($B12='Project List References'!$B$6, _xlfn.IFNA(_xlfn.XLOOKUP(G$2-$C12, 'GEN-CARBON'!$D$7:$AW$7, 'GEN-CARBON'!$D$24:$AW$24), 0), IF($B12='Project List References'!$B$7, _xlfn.IFNA(_xlfn.XLOOKUP(G$2-$C12, 'SENS Coal'!$D$7:$AW$7, 'SENS Coal'!$D$24:$AW$24), 0), IF($B12='Project List References'!$B$8, _xlfn.IFNA(_xlfn.XLOOKUP(G$2-$C12, 'SENS Tires'!$D$7:$AW$7, 'SENS Tires'!$D$24:$AW$24), 0)))))))/_xlfn.XLOOKUP($B12, 'Assumptions & Inputs'!$F$76:$L$76, 'Assumptions & Inputs'!$F$77:$L$77)*IF(OR($B12='Project List References'!$B$3, $B12='Project List References'!$B$4, $B12='Project List References'!$B$5, $B12='Project List References'!$B$6), 'Project Master Sheet'!$E12, 'Project Master Sheet'!$F12) -> #N/A | H12: =IF($B12='Project List References'!$B$3, _xlfn.IFNA(_xlfn.XLOOKUP(H$2-$C12, 'GEN-CCGT'!$D$7:$AW$7, 'GEN-CCGT'!$D$24:$AW$24), 0), IF($B12='Project List References'!$B$4, _xlfn.IFNA(_xlfn.XLOOKUP(H$2-$C12, 'GEN-SOLAR'!$D$7:$AW$7, 'GEN-SOLAR'!$D$24:$AW$24), 0), IF($B12='Project List References'!$B$5, _xlfn.IFNA(_xlfn.XLOOKUP(H$2-$C12, 'GEN-BESS'!$D$7:$AW$7, 'GEN-BESS'!$D$24:$AW$24), 0), IF($B12='Project List References'!$B$6, _xlfn.IFNA(_xlfn.XLOOKUP(H$2-$C12, 'GEN-CARBON'!$D$7:$AW$7, 'GEN-CARBON'!$D$24:$AW$24), 0), IF($B12='Project List References'!$B$7, _xlfn.IFNA(_xlfn.XLOOKUP(H$2-$C12, 'SENS Coal'!$D$7:$AW$7, 'SENS Coal'!$D$24:$AW$24), 0), IF($B12='Project List References'!$B$8, _xlfn.IFNA(_xlfn.XLOOKUP(H$2-$C12, 'SENS Tires'!$D$7:$AW$7, 'SENS Tires'!$D$24:$AW$24), 0)))))))/_xlfn.XLOOKUP($B12, 'Assumptions & Inputs'!$F$76:$L$76, 'Assumptions & Inputs'!$F$77:$L$77)*IF(OR($B12='Project List References'!$B$3, $B12='Project List References'!$B$4, $B12='Project List References'!$B$5, $B12='Project List References'!$B$6), 'Project Master Sheet'!$E12, 'Project Master Sheet'!$F12) -> #N/A | I12: =IF($B12='Project List References'!$B$3, _xlfn.IFNA(_xlfn.XLOOKUP(I$2-$C12, 'GEN-CCGT'!$D$7:$AW$7, 'GEN-CCGT'!$D$24:$AW$24), 0), IF($B12='Project List References'!$B$4, _xlfn.IFNA(_xlfn.XLOOKUP(I$2-$C12, 'GEN-SOLAR'!$D$7:$AW$7, 'GEN-SOLAR'!$D$24:$AW$24), 0), IF($B12='Project List References'!$B$5, _xlfn.IFNA(_xlfn.XLOOKUP(I$2-$C12, 'GEN-BESS'!$D$7:$AW$7, 'GEN-BESS'!$D$24:$AW$24), 0), IF($B12='Project List References'!$B$6, _xlfn.IFNA(_xlfn.XLOOKUP(I$2-$C12, 'GEN-CARBON'!$D$7:$AW$7, 'GEN-CARBON'!$D$24:$AW$24), 0), IF($B12='Project List References'!$B$7, _xlfn.IFNA(_xlfn.XLOOKUP(I$2-$C12, 'SENS Coal'!$D$7:$AW$7, 'SENS Coal'!$D$24:$AW$24), 0), IF($B12='Project List References'!$B$8, _xlfn.IFNA(_xlfn.XLOOKUP(I$2-$C12, 'SENS Tires'!$D$7:$AW$7, 'SENS Tires'!$D$24:$AW$24), 0)))))))/_xlfn.XLOOKUP($B12, 'Assumptions & Inputs'!$F$76:$L$76, 'Assumptions & Inputs'!$F$77:$L$77)*IF(OR($B12='Project List References'!$B$3, $B12='Project List References'!$B$4, $B12='Project List References'!$B$5, $B12='Project List References'!$B$6), 'Project Master Sheet'!$E12, 'Project Master Sheet'!$F12) -> #N/A | J12: =IF($B12='Project List References'!$B$3, _xlfn.IFNA(_xlfn.XLOOKUP(J$2-$C12, 'GEN-CCGT'!$D$7:$AW$7, 'GEN-CCGT'!$D$24:$AW$24), 0), IF($B12='Project List References'!$B$4, _xlfn.IFNA(_xlfn.XLOOKUP(J$2-$C12, 'GEN-SOLAR'!$D$7:$AW$7, 'GEN-SOLAR'!$D$24:$AW$24), 0), IF($B12='Project List References'!$B$5, _xlfn.IFNA(_xlfn.XLOOKUP(J$2-$C12, 'GEN-BESS'!$D$7:$AW$7, 'GEN-BESS'!$D$24:$AW$24), 0), IF($B12='Project List References'!$B$6, _xlfn.IFNA(_xlfn.XLOOKUP(J$2-$C12, 'GEN-CARBON'!$D$7:$AW$7, 'GEN-CARBON'!$D$24:$AW$24), 0), IF($B12='Project List References'!$B$7, _xlfn.IFNA(_xlfn.XLOOKUP(J$2-$C12, 'SENS Coal'!$D$7:$AW$7, 'SENS Coal'!$D$24:$AW$24), 0), IF($B12='Project List References'!$B$8, _xlfn.IFNA(_xlfn.XLOOKUP(J$2-$C12, 'SENS Tires'!$D$7:$AW$7, 'SENS Tires'!$D$24:$AW$24), 0)))))))/_xlfn.XLOOKUP($B12, 'Assumptions & Inputs'!$F$76:$L$76, 'Assumptions & Inputs'!$F$77:$L$77)*IF(OR($B12='Project List References'!$B$3, $B12='Project List References'!$B$4, $B12='Project List References'!$B$5, $B12='Project List References'!$B$6), 'Project Master Sheet'!$E12, 'Project Master Sheet'!$F12) -> #N/A | K12: =IF($B12='Project List References'!$B$3, _xlfn.IFNA(_xlfn.XLOOKUP(K$2-$C12, 'GEN-CCGT'!$D$7:$AW$7, 'GEN-CCGT'!$D$24:$AW$24), 0), IF($B12='Project List References'!$B$4, _xlfn.IFNA(_xlfn.XLOOKUP(K$2-$C12, 'GEN-SOLAR'!$D$7:$AW$7, 'GEN-SOLAR'!$D$24:$AW$24), 0), IF($B12='Project List References'!$B$5, _xlfn.IFNA(_xlfn.XLOOKUP(K$2-$C12, 'GEN-BESS'!$D$7:$AW$7, 'GEN-BESS'!$D$24:$AW$24), 0), IF($B12='Project List References'!$B$6, _xlfn.IFNA(_xlfn.XLOOKUP(K$2-$C12, 'GEN-CARBON'!$D$7:$AW$7, 'GEN-CARBON'!$D$24:$AW$24), 0), IF($B12='Project List References'!$B$7, _xlfn.IFNA(_xlfn.XLOOKUP(K$2-$C12, 'SENS Coal'!$D$7:$AW$7, 'SENS Coal'!$D$24:$AW$24), 0), IF($B12='Project List References'!$B$8, _xlfn.IFNA(_xlfn.XLOOKUP(K$2-$C12, 'SENS Tires'!$D$7:$AW$7, 'SENS Tires'!$D$24:$AW$24), 0)))))))/_xlfn.XLOOKUP($B12, 'Assumptions & Inputs'!$F$76:$L$76, 'Assumptions & Inputs'!$F$77:$L$77)*IF(OR($B12='Project List References'!$B$3, $B12='Project List References'!$B$4, $B12='Project List References'!$B$5, $B12='Project List References'!$B$6), 'Project Master Sheet'!$E12, 'Project Master Sheet'!$F12) -> #N/A | L12: =IF($B12='Project List References'!$B$3, _xlfn.IFNA(_xlfn.XLOOKUP(L$2-$C12, 'GEN-CCGT'!$D$7:$AW$7, 'GEN-CCGT'!$D$24:$AW$24), 0), IF($B12='Project List References'!$B$4, _xlfn.IFNA(_xlfn.XLOOKUP(L$2-$C12, 'GEN-SOLAR'!$D$7:$AW$7, 'GEN-SOLAR'!$D$24:$AW$24), 0), IF($B12='Project List References'!$B$5, _xlfn.IFNA(_xlfn.XLOOKUP(L$2-$C12, 'GEN-BESS'!$D$7:$AW$7, 'GEN-BESS'!$D$24:$AW$24), 0), IF($B12='Project List References'!$B$6, _xlfn.IFNA(_xlfn.XLOOKUP(L$2-$C12, 'GEN-CARBON'!$D$7:$AW$7, 'GEN-CARBON'!$D$24:$AW$24), 0), IF($B12='Project List References'!$B$7, _xlfn.IFNA(_xlfn.XLOOKUP(L$2-$C12, 'SENS Coal'!$D$7:$AW$7, 'SENS Coal'!$D$24:$AW$24), 0), IF($B12='Project List References'!$B$8, _xlfn.IFNA(_xlfn.XLOOKUP(L$2-$C12, 'SENS Tires'!$D$7:$AW$7, 'SENS Tires'!$D$24:$AW$24), 0)))))))/_xlfn.XLOOKUP($B12, 'Assumptions & Inputs'!$F$76:$L$76, 'Assumptions & Inputs'!$F$77:$L$77)*IF(OR($B12='Project List References'!$B$3, $B12='Project List References'!$B$4, $B12='Project List References'!$B$5, $B12='Project List References'!$B$6), 'Project Master Sheet'!$E12, 'Project Master Sheet'!$F12) -> #N/A | ... T12: =IF($B12='Project List References'!$B$3, _xlfn.IFNA(_xlfn.XLOOKUP(T$2-$C12, 'GEN-CCGT'!$D$7:$AW$7, 'GEN-CCGT'!$D$24:$AW$24), 0), IF($B12='Project List References'!$B$4, _xlfn.IFNA(_xlfn.XLOOKUP(T$2-$C12, 'GEN-SOLAR'!$D$7:$AW$7, 'GEN-SOLAR'!$D$24:$AW$24), 0), IF($B12='Project List References'!$B$5, _xlfn.IFNA(_xlfn.XLOOKUP(T$2-$C12, 'GEN-BESS'!$D$7:$AW$7, 'GEN-BESS'!$D$24:$AW$24), 0), IF($B12='Project List References'!$B$6, _xlfn.IFNA(_xlfn.XLOOKUP(T$2-$C12, 'GEN-CARBON'!$D$7:$AW$7, 'GEN-CARBON'!$D$24:$AW$24), 0), IF($B12='Project List References'!$B$7, _xlfn.IFNA(_xlfn.XLOOKUP(T$2-$C12, 'SENS Coal'!$D$7:$AW$7, 'SENS Coal'!$D$24:$AW$24), 0), IF($B12='Project List References'!$B$8, _xlfn.IFNA(_xlfn.XLOOKUP(T$2-$C12, 'SENS Tires'!$D$7:$AW$7, 'SENS Tires'!$D$24:$AW$24), 0)))))))/_xlfn.XLOOKUP($B12, 'Assumptions & Inputs'!$F$76:$L$76, 'Assumptions & Inputs'!$F$77:$L$77)*IF(OR($B12='Project List References'!$B$3, $B12='Project List References'!$B$4, $B12='Project List References'!$B$5, $B12='Project List References'!$B$6), 'Project Master Sheet'!$E12, 'Project Master Sheet'!$F12) -> #N/A
A13: =IF(ISBLANK('Project Master Sheet'!A13)=FALSE, 'Project Master Sheet'!A13, "") | B13: =_xlfn.IFNA(_xlfn.XLOOKUP(A13, 'Project Master Sheet'!A:A, 'Project Master Sheet'!D:D), "") | C13: =_xlfn.XLOOKUP(A13, 'Project Master Sheet'!A:A, 'Project Master Sheet'!I:I) -> #N/A | E13: =IF($B13='Project List References'!$B$3, _xlfn.IFNA(_xlfn.XLOOKUP(E$2-$C13, 'GEN-CCGT'!$D$7:$AW$7, 'GEN-CCGT'!$D$24:$AW$24), 0), IF($B13='Project List References'!$B$4, _xlfn.IFNA(_xlfn.XLOOKUP(E$2-$C13, 'GEN-SOLAR'!$D$7:$AW$7, 'GEN-SOLAR'!$D$24:$AW$24), 0), IF($B13='Project List References'!$B$5, _xlfn.IFNA(_xlfn.XLOOKUP(E$2-$C13, 'GEN-BESS'!$D$7:$AW$7, 'GEN-BESS'!$D$24:$AW$24), 0), IF($B13='Project List References'!$B$6, _xlfn.IFNA(_xlfn.XLOOKUP(E$2-$C13, 'GEN-CARBON'!$D$7:$AW$7, 'GEN-CARBON'!$D$24:$AW$24), 0), IF($B13='Project List References'!$B$7, _xlfn.IFNA(_xlfn.XLOOKUP(E$2-$C13, 'SENS Coal'!$D$7:$AW$7, 'SENS Coal'!$D$24:$AW$24), 0), IF($B13='Project List References'!$B$8, _xlfn.IFNA(_xlfn.XLOOKUP(E$2-$C13, 'SENS Tires'!$D$7:$AW$7, 'SENS Tires'!$D$24:$AW$24), 0)))))))/_xlfn.XLOOKUP($B13, 'Assumptions & Inputs'!$F$76:$L$76, 'Assumptions & Inputs'!$F$77:$L$77)*IF(OR($B13='Project List References'!$B$3, $B13='Project List References'!$B$4, $B13='Project List References'!$B$5, $B13='Project List References'!$B$6), 'Project Master Sheet'!$E13, 'Project Master Sheet'!$F13) -> #N/A | F13: =IF($B13='Project List References'!$B$3, _xlfn.IFNA(_xlfn.XLOOKUP(F$2-$C13, 'GEN-CCGT'!$D$7:$AW$7, 'GEN-CCGT'!$D$24:$AW$24), 0), IF($B13='Project List References'!$B$4, _xlfn.IFNA(_xlfn.XLOOKUP(F$2-$C13, 'GEN-SOLAR'!$D$7:$AW$7, 'GEN-SOLAR'!$D$24:$AW$24), 0), IF($B13='Project List References'!$B$5, _xlfn.IFNA(_xlfn.XLOOKUP(F$2-$C13, 'GEN-BESS'!$D$7:$AW$7, 'GEN-BESS'!$D$24:$AW$24), 0), IF($B13='Project List References'!$B$6, _xlfn.IFNA(_xlfn.XLOOKUP(F$2-$C13, 'GEN-CARBON'!$D$7:$AW$7, 'GEN-CARBON'!$D$24:$AW$24), 0), IF($B13='Project List References'!$B$7, _xlfn.IFNA(_xlfn.XLOOKUP(F$2-$C13, 'SENS Coal'!$D$7:$AW$7, 'SENS Coal'!$D$24:$AW$24), 0), IF($B13='Project List References'!$B$8, _xlfn.IFNA(_xlfn.XLOOKUP(F$2-$C13, 'SENS Tires'!$D$7:$AW$7, 'SENS Tires'!$D$24:$AW$24), 0)))))))/_xlfn.XLOOKUP($B13, 'Assumptions & Inputs'!$F$76:$L$76, 'Assumptions & Inputs'!$F$77:$L$77)*IF(OR($B13='Project List References'!$B$3, $B13='Project List References'!$B$4, $B13='Project List References'!$B$5, $B13='Project List References'!$B$6), 'Project Master Sheet'!$E13, 'Project Master Sheet'!$F13) -> #N/A | G13: =IF($B13='Project List References'!$B$3, _xlfn.IFNA(_xlfn.XLOOKUP(G$2-$C13, 'GEN-CCGT'!$D$7:$AW$7, 'GEN-CCGT'!$D$24:$AW$24), 0), IF($B13='Project List References'!$B$4, _xlfn.IFNA(_xlfn.XLOOKUP(G$2-$C13, 'GEN-SOLAR'!$D$7:$AW$7, 'GEN-SOLAR'!$D$24:$AW$24), 0), IF($B13='Project List References'!$B$5, _xlfn.IFNA(_xlfn.XLOOKUP(G$2-$C13, 'GEN-BESS'!$D$7:$AW$7, 'GEN-BESS'!$D$24:$AW$24), 0), IF($B13='Project List References'!$B$6, _xlfn.IFNA(_xlfn.XLOOKUP(G$2-$C13, 'GEN-CARBON'!$D$7:$AW$7, 'GEN-CARBON'!$D$24:$AW$24), 0), IF($B13='Project List References'!$B$7, _xlfn.IFNA(_xlfn.XLOOKUP(G$2-$C13, 'SENS Coal'!$D$7:$AW$7, 'SENS Coal'!$D$24:$AW$24), 0), IF($B13='Project List References'!$B$8, _xlfn.IFNA(_xlfn.XLOOKUP(G$2-$C13, 'SENS Tires'!$D$7:$AW$7, 'SENS Tires'!$D$24:$AW$24), 0)))))))/_xlfn.XLOOKUP($B13, 'Assumptions & Inputs'!$F$76:$L$76, 'Assumptions & Inputs'!$F$77:$L$77)*IF(OR($B13='Project List References'!$B$3, $B13='Project List References'!$B$4, $B13='Project List References'!$B$5, $B13='Project List References'!$B$6), 'Project Master Sheet'!$E13, 'Project Master Sheet'!$F13) -> #N/A | H13: =IF($B13='Project List References'!$B$3, _xlfn.IFNA(_xlfn.XLOOKUP(H$2-$C13, 'GEN-CCGT'!$D$7:$AW$7, 'GEN-CCGT'!$D$24:$AW$24), 0), IF($B13='Project List References'!$B$4, _xlfn.IFNA(_xlfn.XLOOKUP(H$2-$C13, 'GEN-SOLAR'!$D$7:$AW$7, 'GEN-SOLAR'!$D$24:$AW$24), 0), IF($B13='Project List References'!$B$5, _xlfn.IFNA(_xlfn.XLOOKUP(H$2-$C13, 'GEN-BESS'!$D$7:$AW$7, 'GEN-BESS'!$D$24:$AW$24), 0), IF($B13='Project List References'!$B$6, _xlfn.IFNA(_xlfn.XLOOKUP(H$2-$C13, 'GEN-CARBON'!$D$7:$AW$7, 'GEN-CARBON'!$D$24:$AW$24), 0), IF($B13='Project List References'!$B$7, _xlfn.IFNA(_xlfn.XLOOKUP(H$2-$C13, 'SENS Coal'!$D$7:$AW$7, 'SENS Coal'!$D$24:$AW$24), 0), IF($B13='Project List References'!$B$8, _xlfn.IFNA(_xlfn.XLOOKUP(H$2-$C13, 'SENS Tires'!$D$7:$AW$7, 'SENS Tires'!$D$24:$AW$24), 0)))))))/_xlfn.XLOOKUP($B13, 'Assumptions & Inputs'!$F$76:$L$76, 'Assumptions & Inputs'!$F$77:$L$77)*IF(OR($B13='Project List References'!$B$3, $B13='Project List References'!$B$4, $B13='Project List References'!$B$5, $B13='Project List References'!$B$6), 'Project Master Sheet'!$E13, 'Project Master Sheet'!$F13) -> #N/A | I13: =IF($B13='Project List References'!$B$3, _xlfn.IFNA(_xlfn.XLOOKUP(I$2-$C13, 'GEN-CCGT'!$D$7:$AW$7, 'GEN-CCGT'!$D$24:$AW$24), 0), IF($B13='Project List References'!$B$4, _xlfn.IFNA(_xlfn.XLOOKUP(I$2-$C13, 'GEN-SOLAR'!$D$7:$AW$7, 'GEN-SOLAR'!$D$24:$AW$24), 0), IF($B13='Project List References'!$B$5, _xlfn.IFNA(_xlfn.XLOOKUP(I$2-$C13, 'GEN-BESS'!$D$7:$AW$7, 'GEN-BESS'!$D$24:$AW$24), 0), IF($B13='Project List References'!$B$6, _xlfn.IFNA(_xlfn.XLOOKUP(I$2-$C13, 'GEN-CARBON'!$D$7:$AW$7, 'GEN-CARBON'!$D$24:$AW$24), 0), IF($B13='Project List References'!$B$7, _xlfn.IFNA(_xlfn.XLOOKUP(I$2-$C13, 'SENS Coal'!$D$7:$AW$7, 'SENS Coal'!$D$24:$AW$24), 0), IF($B13='Project List References'!$B$8, _xlfn.IFNA(_xlfn.XLOOKUP(I$2-$C13, 'SENS Tires'!$D$7:$AW$7, 'SENS Tires'!$D$24:$AW$24), 0)))))))/_xlfn.XLOOKUP($B13, 'Assumptions & Inputs'!$F$76:$L$76, 'Assumptions & Inputs'!$F$77:$L$77)*IF(OR($B13='Project List References'!$B$3, $B13='Project List References'!$B$4, $B13='Project List References'!$B$5, $B13='Project List References'!$B$6), 'Project Master Sheet'!$E13, 'Project Master Sheet'!$F13) -> #N/A | J13: =IF($B13='Project List References'!$B$3, _xlfn.IFNA(_xlfn.XLOOKUP(J$2-$C13, 'GEN-CCGT'!$D$7:$AW$7, 'GEN-CCGT'!$D$24:$AW$24), 0), IF($B13='Project List References'!$B$4, _xlfn.IFNA(_xlfn.XLOOKUP(J$2-$C13, 'GEN-SOLAR'!$D$7:$AW$7, 'GEN-SOLAR'!$D$24:$AW$24), 0), IF($B13='Project List References'!$B$5, _xlfn.IFNA(_xlfn.XLOOKUP(J$2-$C13, 'GEN-BESS'!$D$7:$AW$7, 'GEN-BESS'!$D$24:$AW$24), 0), IF($B13='Project List References'!$B$6, _xlfn.IFNA(_xlfn.XLOOKUP(J$2-$C13, 'GEN-CARBON'!$D$7:$AW$7, 'GEN-CARBON'!$D$24:$AW$24), 0), IF($B13='Project List References'!$B$7, _xlfn.IFNA(_xlfn.XLOOKUP(J$2-$C13, 'SENS Coal'!$D$7:$AW$7, 'SENS Coal'!$D$24:$AW$24), 0), IF($B13='Project List References'!$B$8, _xlfn.IFNA(_xlfn.XLOOKUP(J$2-$C13, 'SENS Tires'!$D$7:$AW$7, 'SENS Tires'!$D$24:$AW$24), 0)))))))/_xlfn.XLOOKUP($B13, 'Assumptions & Inputs'!$F$76:$L$76, 'Assumptions & Inputs'!$F$77:$L$77)*IF(OR($B13='Project List References'!$B$3, $B13='Project List References'!$B$4, $B13='Project List References'!$B$5, $B13='Project List References'!$B$6), 'Project Master Sheet'!$E13, 'Project Master Sheet'!$F13) -> #N/A | K13: =IF($B13='Project List References'!$B$3, _xlfn.IFNA(_xlfn.XLOOKUP(K$2-$C13, 'GEN-CCGT'!$D$7:$AW$7, 'GEN-CCGT'!$D$24:$AW$24), 0), IF($B13='Project List References'!$B$4, _xlfn.IFNA(_xlfn.XLOOKUP(K$2-$C13, 'GEN-SOLAR'!$D$7:$AW$7, 'GEN-SOLAR'!$D$24:$AW$24), 0), IF($B13='Project List References'!$B$5, _xlfn.IFNA(_xlfn.XLOOKUP(K$2-$C13, 'GEN-BESS'!$D$7:$AW$7, 'GEN-BESS'!$D$24:$AW$24), 0), IF($B13='Project List References'!$B$6, _xlfn.IFNA(_xlfn.XLOOKUP(K$2-$C13, 'GEN-CARBON'!$D$7:$AW$7, 'GEN-CARBON'!$D$24:$AW$24), 0), IF($B13='Project List References'!$B$7, _xlfn.IFNA(_xlfn.XLOOKUP(K$2-$C13, 'SENS Coal'!$D$7:$AW$7, 'SENS Coal'!$D$24:$AW$24), 0), IF($B13='Project List References'!$B$8, _xlfn.IFNA(_xlfn.XLOOKUP(K$2-$C13, 'SENS Tires'!$D$7:$AW$7, 'SENS Tires'!$D$24:$AW$24), 0)))))))/_xlfn.XLOOKUP($B13, 'Assumptions & Inputs'!$F$76:$L$76, 'Assumptions & Inputs'!$F$77:$L$77)*IF(OR($B13='Project List References'!$B$3, $B13='Project List References'!$B$4, $B13='Project List References'!$B$5, $B13='Project List References'!$B$6), 'Project Master Sheet'!$E13, 'Project Master Sheet'!$F13) -> #N/A | L13: =IF($B13='Project List References'!$B$3, _xlfn.IFNA(_xlfn.XLOOKUP(L$2-$C13, 'GEN-CCGT'!$D$7:$AW$7, 'GEN-CCGT'!$D$24:$AW$24), 0), IF($B13='Project List References'!$B$4, _xlfn.IFNA(_xlfn.XLOOKUP(L$2-$C13, 'GEN-SOLAR'!$D$7:$AW$7, 'GEN-SOLAR'!$D$24:$AW$24), 0), IF($B13='Project List References'!$B$5, _xlfn.IFNA(_xlfn.XLOOKUP(L$2-$C13, 'GEN-BESS'!$D$7:$AW$7, 'GEN-BESS'!$D$24:$AW$24), 0), IF($B13='Project List References'!$B$6, _xlfn.IFNA(_xlfn.XLOOKUP(L$2-$C13, 'GEN-CARBON'!$D$7:$AW$7, 'GEN-CARBON'!$D$24:$AW$24), 0), IF($B13='Project List References'!$B$7, _xlfn.IFNA(_xlfn.XLOOKUP(L$2-$C13, 'SENS Coal'!$D$7:$AW$7, 'SENS Coal'!$D$24:$AW$24), 0), IF($B13='Project List References'!$B$8, _xlfn.IFNA(_xlfn.XLOOKUP(L$2-$C13, 'SENS Tires'!$D$7:$AW$7, 'SENS Tires'!$D$24:$AW$24), 0)))))))/_xlfn.XLOOKUP($B13, 'Assumptions & Inputs'!$F$76:$L$76, 'Assumptions & Inputs'!$F$77:$L$77)*IF(OR($B13='Project List References'!$B$3, $B13='Project List References'!$B$4, $B13='Project List References'!$B$5, $B13='Project List References'!$B$6), 'Project Master Sheet'!$E13, 'Project Master Sheet'!$F13) -> #N/A | ... T13: =IF($B13='Project List References'!$B$3, _xlfn.IFNA(_xlfn.XLOOKUP(T$2-$C13, 'GEN-CCGT'!$D$7:$AW$7, 'GEN-CCGT'!$D$24:$AW$24), 0), IF($B13='Project List References'!$B$4, _xlfn.IFNA(_xlfn.XLOOKUP(T$2-$C13, 'GEN-SOLAR'!$D$7:$AW$7, 'GEN-SOLAR'!$D$24:$AW$24), 0), IF($B13='Project List References'!$B$5, _xlfn.IFNA(_xlfn.XLOOKUP(T$2-$C13, 'GEN-BESS'!$D$7:$AW$7, 'GEN-BESS'!$D$24:$AW$24), 0), IF($B13='Project List References'!$B$6, _xlfn.IFNA(_xlfn.XLOOKUP(T$2-$C13, 'GEN-CARBON'!$D$7:$AW$7, 'GEN-CARBON'!$D$24:$AW$24), 0), IF($B13='Project List References'!$B$7, _xlfn.IFNA(_xlfn.XLOOKUP(T$2-$C13, 'SENS Coal'!$D$7:$AW$7, 'SENS Coal'!$D$24:$AW$24), 0), IF($B13='Project List References'!$B$8, _xlfn.IFNA(_xlfn.XLOOKUP(T$2-$C13, 'SENS Tires'!$D$7:$AW$7, 'SENS Tires'!$D$24:$AW$24), 0)))))))/_xlfn.XLOOKUP($B13, 'Assumptions & Inputs'!$F$76:$L$76, 'Assumptions & Inputs'!$F$77:$L$77)*IF(OR($B13='Project List References'!$B$3, $B13='Project List References'!$B$4, $B13='Project List References'!$B$5, $B13='Project List References'!$B$6), 'Project Master Sheet'!$E13, 'Project Master Sheet'!$F13) -> #N/A
A14: =IF(ISBLANK('Project Master Sheet'!A14)=FALSE, 'Project Master Sheet'!A14, "") | B14: =_xlfn.IFNA(_xlfn.XLOOKUP(A14, 'Project Master Sheet'!A:A, 'Project Master Sheet'!D:D), "") | C14: =_xlfn.XLOOKUP(A14, 'Project Master Sheet'!A:A, 'Project Master Sheet'!I:I) -> #N/A | E14: =IF($B14='Project List References'!$B$3, _xlfn.IFNA(_xlfn.XLOOKUP(E$2-$C14, 'GEN-CCGT'!$D$7:$AW$7, 'GEN-CCGT'!$D$24:$AW$24), 0), IF($B14='Project List References'!$B$4, _xlfn.IFNA(_xlfn.XLOOKUP(E$2-$C14, 'GEN-SOLAR'!$D$7:$AW$7, 'GEN-SOLAR'!$D$24:$AW$24), 0), IF($B14='Project List References'!$B$5, _xlfn.IFNA(_xlfn.XLOOKUP(E$2-$C14, 'GEN-BESS'!$D$7:$AW$7, 'GEN-BESS'!$D$24:$AW$24), 0), IF($B14='Project List References'!$B$6, _xlfn.IFNA(_xlfn.XLOOKUP(E$2-$C14, 'GEN-CARBON'!$D$7:$AW$7, 'GEN-CARBON'!$D$24:$AW$24), 0), IF($B14='Project List References'!$B$7, _xlfn.IFNA(_xlfn.XLOOKUP(E$2-$C14, 'SENS Coal'!$D$7:$AW$7, 'SENS Coal'!$D$24:$AW$24), 0), IF($B14='Project List References'!$B$8, _xlfn.IFNA(_xlfn.XLOOKUP(E$2-$C14, 'SENS Tires'!$D$7:$AW$7, 'SENS Tires'!$D$24:$AW$24), 0)))))))/_xlfn.XLOOKUP($B14, 'Assumptions & Inputs'!$F$76:$L$76, 'Assumptions & Inputs'!$F$77:$L$77)*IF(OR($B14='Project List References'!$B$3, $B14='Project List References'!$B$4, $B14='Project List References'!$B$5, $B14='Project List References'!$B$6), 'Project Master Sheet'!$E14, 'Project Master Sheet'!$F14) -> #N/A | F14: =IF($B14='Project List References'!$B$3, _xlfn.IFNA(_xlfn.XLOOKUP(F$2-$C14, 'GEN-CCGT'!$D$7:$AW$7, 'GEN-CCGT'!$D$24:$AW$24), 0), IF($B14='Project List References'!$B$4, _xlfn.IFNA(_xlfn.XLOOKUP(F$2-$C14, 'GEN-SOLAR'!$D$7:$AW$7, 'GEN-SOLAR'!$D$24:$AW$24), 0), IF($B14='Project List References'!$B$5, _xlfn.IFNA(_xlfn.XLOOKUP(F$2-$C14, 'GEN-BESS'!$D$7:$AW$7, 'GEN-BESS'!$D$24:$AW$24), 0), IF($B14='Project List References'!$B$6, _xlfn.IFNA(_xlfn.XLOOKUP(F$2-$C14, 'GEN-CARBON'!$D$7:$AW$7, 'GEN-CARBON'!$D$24:$AW$24), 0), IF($B14='Project List References'!$B$7, _xlfn.IFNA(_xlfn.XLOOKUP(F$2-$C14, 'SENS Coal'!$D$7:$AW$7, 'SENS Coal'!$D$24:$AW$24), 0), IF($B14='Project List References'!$B$8, _xlfn.IFNA(_xlfn.XLOOKUP(F$2-$C14, 'SENS Tires'!$D$7:$AW$7, 'SENS Tires'!$D$24:$AW$24), 0)))))))/_xlfn.XLOOKUP($B14, 'Assumptions & Inputs'!$F$76:$L$76, 'Assumptions & Inputs'!$F$77:$L$77)*IF(OR($B14='Project List References'!$B$3, $B14='Project List References'!$B$4, $B14='Project List References'!$B$5, $B14='Project List References'!$B$6), 'Project Master Sheet'!$E14, 'Project Master Sheet'!$F14) -> #N/A | G14: =IF($B14='Project List References'!$B$3, _xlfn.IFNA(_xlfn.XLOOKUP(G$2-$C14, 'GEN-CCGT'!$D$7:$AW$7, 'GEN-CCGT'!$D$24:$AW$24), 0), IF($B14='Project List References'!$B$4, _xlfn.IFNA(_xlfn.XLOOKUP(G$2-$C14, 'GEN-SOLAR'!$D$7:$AW$7, 'GEN-SOLAR'!$D$24:$AW$24), 0), IF($B14='Project List References'!$B$5, _xlfn.IFNA(_xlfn.XLOOKUP(G$2-$C14, 'GEN-BESS'!$D$7:$AW$7, 'GEN-BESS'!$D$24:$AW$24), 0), IF($B14='Project List References'!$B$6, _xlfn.IFNA(_xlfn.XLOOKUP(G$2-$C14, 'GEN-CARBON'!$D$7:$AW$7, 'GEN-CARBON'!$D$24:$AW$24), 0), IF($B14='Project List References'!$B$7, _xlfn.IFNA(_xlfn.XLOOKUP(G$2-$C14, 'SENS Coal'!$D$7:$AW$7, 'SENS Coal'!$D$24:$AW$24), 0), IF($B14='Project List References'!$B$8, _xlfn.IFNA(_xlfn.XLOOKUP(G$2-$C14, 'SENS Tires'!$D$7:$AW$7, 'SENS Tires'!$D$24:$AW$24), 0)))))))/_xlfn.XLOOKUP($B14, 'Assumptions & Inputs'!$F$76:$L$76, 'Assumptions & Inputs'!$F$77:$L$77)*IF(OR($B14='Project List References'!$B$3, $B14='Project List References'!$B$4, $B14='Project List References'!$B$5, $B14='Project List References'!$B$6), 'Project Master Sheet'!$E14, 'Project Master Sheet'!$F14) -> #N/A | H14: =IF($B14='Project List References'!$B$3, _xlfn.IFNA(_xlfn.XLOOKUP(H$2-$C14, 'GEN-CCGT'!$D$7:$AW$7, 'GEN-CCGT'!$D$24:$AW$24), 0), IF($B14='Project List References'!$B$4, _xlfn.IFNA(_xlfn.XLOOKUP(H$2-$C14, 'GEN-SOLAR'!$D$7:$AW$7, 'GEN-SOLAR'!$D$24:$AW$24), 0), IF($B14='Project List References'!$B$5, _xlfn.IFNA(_xlfn.XLOOKUP(H$2-$C14, 'GEN-BESS'!$D$7:$AW$7, 'GEN-BESS'!$D$24:$AW$24), 0), IF($B14='Project List References'!$B$6, _xlfn.IFNA(_xlfn.XLOOKUP(H$2-$C14, 'GEN-CARBON'!$D$7:$AW$7, 'GEN-CARBON'!$D$24:$AW$24), 0), IF($B14='Project List References'!$B$7, _xlfn.IFNA(_xlfn.XLOOKUP(H$2-$C14, 'SENS Coal'!$D$7:$AW$7, 'SENS Coal'!$D$24:$AW$24), 0), IF($B14='Project List References'!$B$8, _xlfn.IFNA(_xlfn.XLOOKUP(H$2-$C14, 'SENS Tires'!$D$7:$AW$7, 'SENS Tires'!$D$24:$AW$24), 0)))))))/_xlfn.XLOOKUP($B14, 'Assumptions & Inputs'!$F$76:$L$76, 'Assumptions & Inputs'!$F$77:$L$77)*IF(OR($B14='Project List References'!$B$3, $B14='Project List References'!$B$4, $B14='Project List References'!$B$5, $B14='Project List References'!$B$6), 'Project Master Sheet'!$E14, 'Project Master Sheet'!$F14) -> #N/A | I14: =IF($B14='Project List References'!$B$3, _xlfn.IFNA(_xlfn.XLOOKUP(I$2-$C14, 'GEN-CCGT'!$D$7:$AW$7, 'GEN-CCGT'!$D$24:$AW$24), 0), IF($B14='Project List References'!$B$4, _xlfn.IFNA(_xlfn.XLOOKUP(I$2-$C14, 'GEN-SOLAR'!$D$7:$AW$7, 'GEN-SOLAR'!$D$24:$AW$24), 0), IF($B14='Project List References'!$B$5, _xlfn.IFNA(_xlfn.XLOOKUP(I$2-$C14, 'GEN-BESS'!$D$7:$AW$7, 'GEN-BESS'!$D$24:$AW$24), 0), IF($B14='Project List References'!$B$6, _xlfn.IFNA(_xlfn.XLOOKUP(I$2-$C14, 'GEN-CARBON'!$D$7:$AW$7, 'GEN-CARBON'!$D$24:$AW$24), 0), IF($B14='Project List References'!$B$7, _xlfn.IFNA(_xlfn.XLOOKUP(I$2-$C14, 'SENS Coal'!$D$7:$AW$7, 'SENS Coal'!$D$24:$AW$24), 0), IF($B14='Project List References'!$B$8, _xlfn.IFNA(_xlfn.XLOOKUP(I$2-$C14, 'SENS Tires'!$D$7:$AW$7, 'SENS Tires'!$D$24:$AW$24), 0)))))))/_xlfn.XLOOKUP($B14, 'Assumptions & Inputs'!$F$76:$L$76, 'Assumptions & Inputs'!$F$77:$L$77)*IF(OR($B14='Project List References'!$B$3, $B14='Project List References'!$B$4, $B14='Project List References'!$B$5, $B14='Project List References'!$B$6), 'Project Master Sheet'!$E14, 'Project Master Sheet'!$F14) -> #N/A | J14: =IF($B14='Project List References'!$B$3, _xlfn.IFNA(_xlfn.XLOOKUP(J$2-$C14, 'GEN-CCGT'!$D$7:$AW$7, 'GEN-CCGT'!$D$24:$AW$24), 0), IF($B14='Project List References'!$B$4, _xlfn.IFNA(_xlfn.XLOOKUP(J$2-$C14, 'GEN-SOLAR'!$D$7:$AW$7, 'GEN-SOLAR'!$D$24:$AW$24), 0), IF($B14='Project List References'!$B$5, _xlfn.IFNA(_xlfn.XLOOKUP(J$2-$C14, 'GEN-BESS'!$D$7:$AW$7, 'GEN-BESS'!$D$24:$AW$24), 0), IF($B14='Project List References'!$B$6, _xlfn.IFNA(_xlfn.XLOOKUP(J$2-$C14, 'GEN-CARBON'!$D$7:$AW$7, 'GEN-CARBON'!$D$24:$AW$24), 0), IF($B14='Project List References'!$B$7, _xlfn.IFNA(_xlfn.XLOOKUP(J$2-$C14, 'SENS Coal'!$D$7:$AW$7, 'SENS Coal'!$D$24:$AW$24), 0), IF($B14='Project List References'!$B$8, _xlfn.IFNA(_xlfn.XLOOKUP(J$2-$C14, 'SENS Tires'!$D$7:$AW$7, 'SENS Tires'!$D$24:$AW$24), 0)))))))/_xlfn.XLOOKUP($B14, 'Assumptions & Inputs'!$F$76:$L$76, 'Assumptions & Inputs'!$F$77:$L$77)*IF(OR($B14='Project List References'!$B$3, $B14='Project List References'!$B$4, $B14='Project List References'!$B$5, $B14='Project List References'!$B$6), 'Project Master Sheet'!$E14, 'Project Master Sheet'!$F14) -> #N/A | K14: =IF($B14='Project List References'!$B$3, _xlfn.IFNA(_xlfn.XLOOKUP(K$2-$C14, 'GEN-CCGT'!$D$7:$AW$7, 'GEN-CCGT'!$D$24:$AW$24), 0), IF($B14='Project List References'!$B$4, _xlfn.IFNA(_xlfn.XLOOKUP(K$2-$C14, 'GEN-SOLAR'!$D$7:$AW$7, 'GEN-SOLAR'!$D$24:$AW$24), 0), IF($B14='Project List References'!$B$5, _xlfn.IFNA(_xlfn.XLOOKUP(K$2-$C14, 'GEN-BESS'!$D$7:$AW$7, 'GEN-BESS'!$D$24:$AW$24), 0), IF($B14='Project List References'!$B$6, _xlfn.IFNA(_xlfn.XLOOKUP(K$2-$C14, 'GEN-CARBON'!$D$7:$AW$7, 'GEN-CARBON'!$D$24:$AW$24), 0), IF($B14='Project List References'!$B$7, _xlfn.IFNA(_xlfn.XLOOKUP(K$2-$C14, 'SENS Coal'!$D$7:$AW$7, 'SENS Coal'!$D$24:$AW$24), 0), IF($B14='Project List References'!$B$8, _xlfn.IFNA(_xlfn.XLOOKUP(K$2-$C14, 'SENS Tires'!$D$7:$AW$7, 'SENS Tires'!$D$24:$AW$24), 0)))))))/_xlfn.XLOOKUP($B14, 'Assumptions & Inputs'!$F$76:$L$76, 'Assumptions & Inputs'!$F$77:$L$77)*IF(OR($B14='Project List References'!$B$3, $B14='Project List References'!$B$4, $B14='Project List References'!$B$5, $B14='Project List References'!$B$6), 'Project Master Sheet'!$E14, 'Project Master Sheet'!$F14) -> #N/A | L14: =IF($B14='Project List References'!$B$3, _xlfn.IFNA(_xlfn.XLOOKUP(L$2-$C14, 'GEN-CCGT'!$D$7:$AW$7, 'GEN-CCGT'!$D$24:$AW$24), 0), IF($B14='Project List References'!$B$4, _xlfn.IFNA(_xlfn.XLOOKUP(L$2-$C14, 'GEN-SOLAR'!$D$7:$AW$7, 'GEN-SOLAR'!$D$24:$AW$24), 0), IF($B14='Project List References'!$B$5, _xlfn.IFNA(_xlfn.XLOOKUP(L$2-$C14, 'GEN-BESS'!$D$7:$AW$7, 'GEN-BESS'!$D$24:$AW$24), 0), IF($B14='Project List References'!$B$6, _xlfn.IFNA(_xlfn.XLOOKUP(L$2-$C14, 'GEN-CARBON'!$D$7:$AW$7, 'GEN-CARBON'!$D$24:$AW$24), 0), IF($B14='Project List References'!$B$7, _xlfn.IFNA(_xlfn.XLOOKUP(L$2-$C14, 'SENS Coal'!$D$7:$AW$7, 'SENS Coal'!$D$24:$AW$24), 0), IF($B14='Project List References'!$B$8, _xlfn.IFNA(_xlfn.XLOOKUP(L$2-$C14, 'SENS Tires'!$D$7:$AW$7, 'SENS Tires'!$D$24:$AW$24), 0)))))))/_xlfn.XLOOKUP($B14, 'Assumptions & Inputs'!$F$76:$L$76, 'Assumptions & Inputs'!$F$77:$L$77)*IF(OR($B14='Project List References'!$B$3, $B14='Project List References'!$B$4, $B14='Project List References'!$B$5, $B14='Project List References'!$B$6), 'Project Master Sheet'!$E14, 'Project Master Sheet'!$F14) -> #N/A | ... T14: =IF($B14='Project List References'!$B$3, _xlfn.IFNA(_xlfn.XLOOKUP(T$2-$C14, 'GEN-CCGT'!$D$7:$AW$7, 'GEN-CCGT'!$D$24:$AW$24), 0), IF($B14='Project List References'!$B$4, _xlfn.IFNA(_xlfn.XLOOKUP(T$2-$C14, 'GEN-SOLAR'!$D$7:$AW$7, 'GEN-SOLAR'!$D$24:$AW$24), 0), IF($B14='Project List References'!$B$5, _xlfn.IFNA(_xlfn.XLOOKUP(T$2-$C14, 'GEN-BESS'!$D$7:$AW$7, 'GEN-BESS'!$D$24:$AW$24), 0), IF($B14='Project List References'!$B$6, _xlfn.IFNA(_xlfn.XLOOKUP(T$2-$C14, 'GEN-CARBON'!$D$7:$AW$7, 'GEN-CARBON'!$D$24:$AW$24), 0), IF($B14='Project List References'!$B$7, _xlfn.IFNA(_xlfn.XLOOKUP(T$2-$C14, 'SENS Coal'!$D$7:$AW$7, 'SENS Coal'!$D$24:$AW$24), 0), IF($B14='Project List References'!$B$8, _xlfn.IFNA(_xlfn.XLOOKUP(T$2-$C14, 'SENS Tires'!$D$7:$AW$7, 'SENS Tires'!$D$24:$AW$24), 0)))))))/_xlfn.XLOOKUP($B14, 'Assumptions & Inputs'!$F$76:$L$76, 'Assumptions & Inputs'!$F$77:$L$77)*IF(OR($B14='Project List References'!$B$3, $B14='Project List References'!$B$4, $B14='Project List References'!$B$5, $B14='Project List References'!$B$6), 'Project Master Sheet'!$E14, 'Project Master Sheet'!$F14) -> #N/A
