Workbook

Sheet Processor Cost - Schedule
A1: Summary
C2: Category | D2: Total | F2: 1 | G2: 2 | H2: 3 | I2: 4 | J2: 5 | K2: 6 | L2: 7 | M2: 8 | N2: 9 | O2: 10 | P2: 11 | Q2: 12
C3: =A12 -> Equipment & Materials | D3: =SUM(F3:Q3) -> 5438875 | F3: =F50 -> 3228958.3 | G3: =G50 -> 1227958.3 | H3: =H50 -> 981958.33 | I3: =I50 -> 0 | J3: =J50 -> 0 | K3: =K50 -> 0 | L3: =L50 -> 0 | M3: =M50 -> 0 | ... Q3: =Q50 -> 0
C4: =A52 -> Facilities & Auxillary Support Systems | D4: =SUM(F4:Q4) -> 3674050 | F4: =F73 -> 1309683.3 | G4: =G73 -> 994683.33 | H4: =H73 -> 994683.33 | I4: =I73 -> 375000 | J4: =J73 -> 0 | K4: =K73 -> 0 | L4: =L73 -> 0 | M4: =M73 -> 0 | ... Q4: =Q73 -> 0
C5: =A75 -> Operating Costs | D5: =SUM(F5:Q5) -> 720500 | F5: =F104 -> 91450 | G5: =G104 -> 27950 | H5: =H104 -> 27950 | I5: =I104 -> 27950 | J5: =J104 -> 27950 | K5: =K104 -> 204016.67 | L5: =L104 -> 144616.67 | M5: =M104 -> 144616.67 | ... Q5: =Q104 -> 6000
C6: =A106 -> Professional Services | D6: =SUM(F6:Q6) -> 401400 | F6: =F118 -> 364550 | G6: =G118 -> 4550 | H6: =H118 -> 4550 | I6: =I118 -> 4550 | J6: =J118 -> 9550 | K6: =K118 -> 4550 | L6: =L118 -> 4550 | M6: =M118 -> 4550 | ... Q6: =Q118 -> 0
C7: =A120 -> Workforce - Role - Pay Rate | D7: =SUM(F7:Q7) -> 2775367.6 | F7: =F150 -> 338436.18 | G7: =G150 -> 338436.18 | H7: =H150 -> 338436.18 | I7: =I150 -> 338436.18 | J7: =J150 -> 355405.72 | K7: =K150 -> 355405.72 | L7: =L150 -> 355405.72 | M7: =M150 -> 355405.72 | ... Q7: =Q150 -> 0
C9: Total Cost Build 1 SENS Processor | D9: =SUM(D3:D7) -> 13010193 | F9: =SUM(F3:F7) -> 5333077.9 | G9: =SUM(G3:G7) -> 2593577.9 | H9: =SUM(H3:H7) -> 2347577.9 | I9: =SUM(I3:I7) -> 745936.18 | J9: =SUM(J3:J7) -> 392905.72 | K9: =SUM(K3:K7) -> 563972.39 | L9: =SUM(L3:L7) -> 504572.39 | M9: =SUM(M3:M7) -> 504572.39 | ... Q9: =SUM(Q3:Q7) -> 6000
A12: Equipment & Materials
B13: Category | C13: Item | D13: Per Unit (Imported) | E13: Disc Rate | F13: 1 | G13: 2 | H13: 3 | I13: 4 | J13: 5 | K13: 6 | L13: 7 | M13: 8 | N13: 9 | O13: 10 | P13: 11 | Q13: 12
B14: Equipment & Materials
C15: Pack column, demister, liquid ring | D15: ='IMPORT_OK Model'!E136/8 -> 233125 | E15: 0.2 | F15: =$D15*(1-$E15)/3 -> 62166.667 | G15: =$D15*(1-$E15)/3 -> 62166.667 | H15: =$D15*(1-$E15)/3 -> 62166.667 | I15: 0 | J15: 0 | K15: 0 | L15: 0 | M15: 0 | N15: 0 | O15: 0 | P15: 0 | Q15: 0
C16: Ovens | D16: ='IMPORT_OK Model'!E137/8 -> 609375 | E16: 0.2 | F16: =$D16*(1-$E16)/3 -> 162500 | G16: =$D16*(1-$E16)/3 -> 162500 | H16: =$D16*(1-$E16)/3 -> 162500 | I16: 0 | J16: 0 | K16: 0 | L16: 0 | M16: 0 | N16: 0 | O16: 0 | P16: 0 | Q16: 0
C17: Pipe, fittings, auger tube shafts | D17: ='IMPORT_OK Model'!E138/8 -> 516250 | E17: 0.2 | F17: =$D17*(1-$E17)/3 -> 137666.67 | G17: =$D17*(1-$E17)/3 -> 137666.67 | H17: =$D17*(1-$E17)/3 -> 137666.67 | I17: 0 | J17: 0 | K17: 0 | L17: 0 | M17: 0 | N17: 0 | O17: 0 | P17: 0 | Q17: 0
C18: Weight hopper feed system | D18: ='IMPORT_OK Model'!E139/8 -> 582500 | E18: 0.2 | F18: =$D18*(1-$E18)/3 -> 155333.33 | G18: =$D18*(1-$E18)/3 -> 155333.33 | H18: =$D18*(1-$E18)/3 -> 155333.33 | I18: 0 | J18: 0 | K18: 0 | L18: 0 | M18: 0 | N18: 0 | O18: 0 | P18: 0 | Q18: 0
B19: National Tube sales
C20: Auger tubes | D20: ='IMPORT_OK Model'!E141/8 -> 330000 | E20: 0.2 | F20: =$D20*(1-$E20)/2 -> 132000 | G20: =$D20*(1-$E20)/2 -> 132000 | H20: 0 | I20: 0 | J20: 0 | K20: 0 | L20: 0 | M20: 0 | N20: 0 | O20: 0 | P20: 0 | Q20: 0
B21: Thomas Conveyor
C22: Auger flights | D22: ='IMPORT_OK Model'!E143/8 -> 160000 | E22: 0.2 | F22: =$D22*(1-$E22)/2 -> 64000 | G22: =$D22*(1-$E22)/2 -> 64000 | H22: 0 | I22: 0 | J22: 0 | K22: 0 | L22: 0 | M22: 0 | N22: 0 | O22: 0 | P22: 0 | Q22: 0
C23: Tapered Screw for weigh hopper | D23: ='IMPORT_OK Model'!E144/8 -> 125000 | E23: 0.2 | F23: =$D23*(1-$E23)/2 -> 50000 | G23: =$D23*(1-$E23)/2 -> 50000 | H23: 0 | I23: 0 | J23: 0 | K23: 0 | L23: 0 | M23: 0 | N23: 0 | O23: 0 | P23: 0 | Q23: 0
B24: Controls, motors and pumps
C25: Control Automation Component | D25: ='IMPORT_OK Model'!E146/8 -> 478125 | E25: 0.2 | F25: =$D25*(1-$E25) -> 382500 | G25: 0 | H25: 0 | I25: 0 | J25: 0 | K25: 0 | L25: 0 | M25: 0 | N25: 0 | O25: 0 | P25: 0 | Q25: 0
C26: Motors, gearboxes, drives, bucket elevators | D26: ='IMPORT_OK Model'!E147/8 -> 356250 | E26: 0.2 | F26: =$D26*(1-$E26) -> 285000 | G26: 0 | H26: 0 | I26: 0 | J26: 0 | K26: 0 | L26: 0 | M26: 0 | N26: 0 | O26: 0 | P26: 0 | Q26: 0
C27: Chiller Contols & Electrical | D27: ='IMPORT_OK Model'!E148/8 -> 197500 | E27: 0.2 | F27: =$D27*(1-$E27) -> 158000 | G27: 0 | H27: 0 | I27: 0 | J27: 0 | K27: 0 | L27: 0 | M27: 0 | N27: 0 | O27: 0 | P27: 0 | Q27: 0
C28: Myers (Flapper valves) | D28: ='IMPORT_OK Model'!E149/8 -> 112500 | E28: 0.2 | F28: =$D28*(1-$E28) -> 90000 | G28: 0 | H28: 0 | I28: 0 | J28: 0 | K28: 0 | L28: 0 | M28: 0 | N28: 0 | O28: 0 | P28: 0 | Q28: 0
C29: Myers Aubrey (Steam, and Gas Processing control valves) | D29: ='IMPORT_OK Model'!E150/8 -> 335625 | E29: 0.2 | F29: =$D29*(1-$E29) -> 268500 | G29: 0 | H29: 0 | I29: 0 | J29: 0 | K29: 0 | L29: 0 | M29: 0 | N29: 0 | O29: 0 | P29: 0 | Q29: 0
C30: Myers Aubrey (Flow meters) | D30: ='IMPORT_OK Model'!E151/8 -> 170000 | E30: 0.2 | F30: =$D30*(1-$E30) -> 136000 | G30: 0 | H30: 0 | I30: 0 | J30: 0 | K30: 0 | L30: 0 | M30: 0 | N30: 0 | O30: 0 | P30: 0 | Q30: 0
C31: Automatic Pump (Vacuum and Oil Water Separator) | D31: ='IMPORT_OK Model'!E152/8 -> 172500 | E31: 0.2 | F31: =$D31*(1-$E31) -> 138000 | G31: 0 | H31: 0 | I31: 0 | J31: 0 | K31: 0 | L31: 0 | M31: 0 | N31: 0 | O31: 0 | P31: 0 | Q31: 0
C32: Roberts & Spencer (Pressure transmitters, Vac Control Valves, level indicators) | D32: ='IMPORT_OK Model'!E153/8 -> 168125 | E32: 0.2 | F32: =$D32*(1-$E32) -> 134500 | G32: 0 | H32: 0 | I32: 0 | J32: 0 | K32: 0 | L32: 0 | M32: 0 | N32: 0 | O32: 0 | P32: 0 | Q32: 0
C33: Switch Gear and Generator | D33: ='IMPORT_OK Model'!E154/8 -> 203125 | E33: 0.2 | F33: =$D33*(1-$E33) -> 162500 | G33: 0 | H33: 0 | I33: 0 | J33: 0 | K33: 0 | L33: 0 | M33: 0 | N33: 0 | O33: 0 | P33: 0 | Q33: 0
C34: Control Valves, Modules, automation component | D34: ='IMPORT_OK Model'!E155/8 -> 397500 | E34: 0.2 | F34: =$D34*(1-$E34) -> 318000 | G34: 0 | H34: 0 | I34: 0 | J34: 0 | K34: 0 | L34: 0 | M34: 0 | N34: 0 | O34: 0 | P34: 0 | Q34: 0
B35: Oven
C36: Harbison-Walker (Refractory) | D36: ='IMPORT_OK Model'!E157/8 -> 180000 | E36: 0.2 | G36: =$D36*(1-$E36)/2 -> 72000 | H36: =$D36*(1-$E36)/2 -> 72000 | I36: 0 | J36: 0 | K36: 0 | L36: 0 | M36: 0 | N36: 0 | O36: 0 | P36: 0 | Q36: 0
C37: GTI-Engineering (Eclipse Burner and controls) | D37: ='IMPORT_OK Model'!E158/8 -> 357500 | E37: 0.2 | F37: =$D37*(1-$E37)/3 -> 95333.333 | G37: =$D37*(1-$E37)/3 -> 95333.333 | H37: =$D37*(1-$E37)/3 -> 95333.333 | I37: 0 | J37: 0 | K37: 0 | L37: 0 | M37: 0 | N37: 0 | O37: 0 | P37: 0 | Q37: 0
C38: Exothermics (Air to Air heat exchanger) | D38: ='IMPORT_OK Model'!E159/8 -> 265000 | E38: 0.2 | F38: =$D38*(1-$E38)/3 -> 70666.667 | G38: =$D38*(1-$E38)/3 -> 70666.667 | H38: =$D38*(1-$E38)/3 -> 70666.667 | I38: 0 | J38: 0 | K38: 0 | L38: 0 | M38: 0 | N38: 0 | O38: 0 | P38: 0 | Q38: 0
C39: Hubbel Water heater | D39: ='IMPORT_OK Model'!E160/8 -> 262500 | E39: 0.25 | F39: =$D39*(1-$E39)/3 -> 65625 | G39: =$D39*(1-$E39)/3 -> 65625 | H39: =$D39*(1-$E39)/3 -> 65625 | I39: 0 | J39: 0 | K39: 0 | L39: 0 | M39: 0 | N39: 0 | O39: 0 | P39: 0 | Q39: 0
C40: Emerson Thermal Couplers | D40: ='IMPORT_OK Model'!E161/8 -> 120000 | E40: 0.2 | F40: =$D40*(1-$E40)/3 -> 32000 | G40: =$D40*(1-$E40)/3 -> 32000 | H40: =$D40*(1-$E40)/3 -> 32000 | I40: 0 | J40: 0 | K40: 0 | L40: 0 | M40: 0 | N40: 0 | O40: 0 | P40: 0 | Q40: 0
B41: Reactor
C42: Cappco Fabricators (rolling and endplates) | D42: ='IMPORT_OK Model'!E163/8 -> 120000 | E42: 0.2 | F42: =$D42*(1-$E42)/3 -> 32000 | G42: =$D42*(1-$E42)/3 -> 32000 | H42: =$D42*(1-$E42)/3 -> 32000 | I42: 0 | J42: 0 | K42: 0 | L42: 0 | M42: 0 | N42: 0 | O42: 0 | P42: 0 | Q42: 0
C43: O&D Manufacturing (Brass seals and Bearings) | D43: ='IMPORT_OK Model'!E164/8 -> 120000 | E43: 0.2 | F43: =$D43*(1-$E43)/3 -> 32000 | G43: =$D43*(1-$E43)/3 -> 32000 | H43: =$D43*(1-$E43)/3 -> 32000 | I43: 0 | J43: 0 | K43: 0 | L43: 0 | M43: 0 | N43: 0 | O43: 0 | P43: 0 | Q43: 0
C44: Machining-Shafts,drum bearings, exp joint etc | D44: ='IMPORT_OK Model'!E165/8 -> 72500 | E44: 0.2 | F44: =$D44*(1-$E44)/3 -> 19333.333 | G44: =$D44*(1-$E44)/3 -> 19333.333 | H44: =$D44*(1-$E44)/3 -> 19333.333 | I44: 0 | J44: 0 | K44: 0 | L44: 0 | M44: 0 | N44: 0 | O44: 0 | P44: 0 | Q44: 0
B46: Engineering and EPC Fees | D46: ='IMPORT_OK Model'!E167/8 -> 475597.55 | E46: 1 | F46: =$D46*(1-$E46)/3 -> 0 | G46: =$D46*(1-$E46)/3 -> 0 | H46: =$D46*(1-$E46)/3 -> 0 | I46: 0 | J46: 0 | K46: 0 | L46: 0 | M46: 0 | N46: 0 | O46: 0 | P46: 0 | Q46: 0
B47: Commissioning | D47: ='IMPORT_OK Model'!E168/8 -> 100000 | E47: 0.2 | F47: =$D47*(1-$E47)/3 -> 26666.667 | G47: =$D47*(1-$E47)/3 -> 26666.667 | H47: =$D47*(1-$E47)/3 -> 26666.667 | I47: 0 | J47: 0 | K47: 0 | L47: 0 | M47: 0 | N47: 0 | O47: 0 | P47: 0 | Q47: 0
B48: Certification and Testing | D48: ='IMPORT_OK Model'!E169/8 -> 70000 | E48: 0.2 | F48: =$D48*(1-$E48)/3 -> 18666.667 | G48: =$D48*(1-$E48)/3 -> 18666.667 | H48: =$D48*(1-$E48)/3 -> 18666.667 | I48: 0 | J48: 0 | K48: 0 | L48: 0 | M48: 0 | N48: 0 | O48: 0 | P48: 0 | Q48: 0
C50: Total Equipment & Materials | D50: =SUM(D14:D48) -> 7290597.5 | E50: =SUM(F50:M50)/D50 -> 0.74601224 | F50: =SUM(F15:F48) -> 3228958.3 | G50: =SUM(G15:G48) -> 1227958.3 | H50: =SUM(H15:H48) -> 981958.33
A52: Facilities & Auxillary Support Systems
B53: Facilities
A54: Texas Vessel | C54: Shop
C55: Sq Ft Required | D55: 10000
C56: Rate | D56: 150
C57: Total Facilities | D57: =D55*D56 -> 1500000 | F57: =$D57*(1-$E57)/4 -> 375000 | G57: =$D57*(1-$E57)/4 -> 375000 | H57: =$D57*(1-$E57)/4 -> 375000 | I57: =$D57*(1-$E57)/4 -> 375000 | J57: 0 | K57: 0 | L57: 0 | M57: 0 | N57: 0 | O57: 0 | P57: 0 | Q57: 0
B59: Aux Support Systems
A60: Texas Vessel | C60: Process Mechanical | D60: ='IMPORT_OK Model'!E115/8-D116 -> 313500 | E60: 0.2 | F60: =$D60*(1-$E60)/3 -> 83600 | G60: =$D60*(1-$E60)/3 -> 83600 | H60: =$D60*(1-$E60)/3 -> 83600 | I60: 0 | J60: 0 | K60: 0 | L60: 0 | M60: 0 | N60: 0 | O60: 0 | P60: 0 | Q60: 0
A61: Texas Vessel | C61: Process Civl | D61: ='IMPORT_OK Model'!E116/8 -> 121875 | E61: 0.2 | F61: =$D61*(1-$E61)/3 -> 32500 | G61: =$D61*(1-$E61)/3 -> 32500 | H61: =$D61*(1-$E61)/3 -> 32500 | I61: 0 | J61: 0 | K61: 0 | L61: 0 | M61: 0 | N61: 0 | O61: 0 | P61: 0 | Q61: 0
C62: Chilled Water Plant | D62: ='IMPORT_OK Model'!E117/8 -> 393750 | E62: 0.2 | F62: =$D62*(1-$E62) -> 315000 | I62: c | J62: 0 | K62: 0 | L62: 0 | M62: 0 | N62: 0 | O62: 0 | P62: 0 | Q62: 0
C63: Gas & Oil Processing / Storage | D63: ='IMPORT_OK Model'!E118/8 -> 737500 | E63: 0.5 | F63: =$D63*(1-$E63)/3 -> 122916.67 | G63: =$D63*(1-$E63)/3 -> 122916.67 | H63: =$D63*(1-$E63)/3 -> 122916.67 | I63: 0 | J63: 0 | K63: 0 | L63: 0 | M63: 0 | N63: 0 | O63: 0 | P63: 0 | Q63: 0
C64: Flare Stack | D64: ='IMPORT_OK Model'!E119 -> 300000 | E64: 0.2 | F64: =$D64*(1-$E64)/3 -> 80000 | G64: =$D64*(1-$E64)/3 -> 80000 | H64: =$D64*(1-$E64)/3 -> 80000 | I64: 0 | J64: 0 | K64: 0 | L64: 0 | M64: 0 | N64: 0 | O64: 0 | P64: 0 | Q64: 0
C65: Carbon Black Processing / Storage | D65: ='IMPORT_OK Model'!E120/8 -> 812500 | E65: 0.4 | F65: =$D65*(1-$E65)/3 -> 162500 | G65: =$D65*(1-$E65)/3 -> 162500 | H65: =$D65*(1-$E65)/3 -> 162500 | I65: 0 | J65: 0 | K65: 0 | L65: 0 | M65: 0 | N65: 0 | O65: 0 | P65: 0 | Q65: 0
C66: Steam Boiler | D66: ='IMPORT_OK Model'!E121/8 -> 293125 | E66: 0.2 | F66: =$D66*(1-$E66)/3 -> 78166.667 | G66: =$D66*(1-$E66)/3 -> 78166.667 | H66: =$D66*(1-$E66)/3 -> 78166.667 | I66: 0 | J66: 0 | K66: 0 | L66: 0 | M66: 0 | N66: 0 | O66: 0 | P66: 0 | Q66: 0
C67: Dirty Water Treatment | D67: ='IMPORT_OK Model'!E122/8 -> 93750 | E67: 0.2 | F67: =$D67*(1-$E67)/3 -> 25000 | G67: =$D67*(1-$E67)/3 -> 25000 | H67: =$D67*(1-$E67)/3 -> 25000 | I67: 0 | J67: 0 | K67: 0 | L67: 0 | M67: 0 | N67: 0 | O67: 0 | P67: 0 | Q67: 0
C68: Compressed Air Plant | D68: ='IMPORT_OK Model'!E125/8 -> 100000 | E68: 0.2 | F68: =$D68*(1-$E68)/3 -> 26666.667 | G68: =$D68*(1-$E68)/3 -> 26666.667 | H68: =$D68*(1-$E68)/3 -> 26666.667 | I68: 0 | J68: 0 | K68: 0 | L68: 0 | M68: 0 | N68: 0 | O68: 0 | P68: 0 | Q68: 0
C69: Pressure wash system | D69: ='IMPORT_OK Model'!E126/8 -> 31250 | E69: 0.2 | F69: =$D69*(1-$E69)/3 -> 8333.3333 | G69: =$D69*(1-$E69)/3 -> 8333.3333 | H69: =$D69*(1-$E69)/3 -> 8333.3333 | I69: 0 | J69: 0 | K69: 0 | L69: 0 | M69: 0 | N69: 0 | O69: 0 | P69: 0 | Q69: 0
C71: Total Aux Supporty Systems | D71: =SUM(D60:D69) -> 3197250 | F71: =SUM(F60:F69) -> 934683.33 | G71: =SUM(G60:G69) -> 619683.33 | H71: =SUM(H60:H69) -> 619683.33 | I71: =SUM(I60:I69) -> 0 | J71: =SUM(J60:J69) -> 0 | K71: =SUM(K60:K69) -> 0 | L71: =SUM(L60:L69) -> 0 | M71: =SUM(M60:M69) -> 0 | ... Q71: =SUM(Q60:Q69) -> 0
C73: Total Facilities & Aux | D73: =SUM(F73:Q73) -> 3674050 | F73: =SUM(F71+F57) -> 1309683.3 | G73: =SUM(G71+G57) -> 994683.33 | H73: =SUM(H71+H57) -> 994683.33 | I73: =SUM(I71+I57) -> 375000 | J73: =SUM(J71+J57) -> 0 | K73: =SUM(K71+K57) -> 0 | L73: =SUM(L71+L57) -> 0 | M73: =SUM(M71+M57) -> 0 | ... Q73: =SUM(Q71+Q57) -> 0
A75: Operating Costs
B76: Category | C76: Item | D76: Per Unit (Imported) | E76: Disc Rate | F76: 1 | G76: 2 | H76: 3 | I76: 4 | J76: 5 | K76: 6 | L76: 7 | M76: 8 | N76: 9 | O76: 10 | P76: 11 | Q76: 12
B77: Corporate Infrastructure
C78: Business Licenses & Memberships | D78: 2000 | F78: =$D78 -> 2000 | G78: =$D78 -> 2000 | H78: =$D78 -> 2000 | I78: =$D78 -> 2000 | J78: =$D78 -> 2000 | K78: =$D78 -> 2000 | L78: =$D78 -> 2000 | M78: =$D78 -> 2000 | N78: 0 | O78: 0 | P78: 0 | Q78: 0
C79: Software & Licenses | D79: 2500 | F79: =$D79 -> 2500 | G79: =$D79 -> 2500 | H79: =$D79 -> 2500 | I79: =$D79 -> 2500 | J79: =$D79 -> 2500 | K79: =$D79 -> 2500 | L79: =$D79 -> 2500 | M79: =$D79 -> 2500 | N79: 0 | O79: 0 | P79: 0 | Q79: 0
C80: Insurance - General | D80: 2000 | F80: =$D80 -> 2000 | G80: =$D80 -> 2000 | H80: =$D80 -> 2000 | I80: =$D80 -> 2000 | J80: =$D80 -> 2000 | K80: =$D80 -> 2000 | L80: =$D80 -> 2000 | M80: =$D80 -> 2000 | N80: 0 | O80: 0 | P80: 0 | Q80: 0
C81: Interest & Bank Charges | D81: 250 | F81: =$D81 -> 250 | G81: =$D81 -> 250 | H81: =$D81 -> 250 | I81: =$D81 -> 250 | J81: =$D81 -> 250 | K81: =$D81 -> 250 | L81: =$D81 -> 250 | M81: =$D81 -> 250 | N81: 0 | O81: 0 | P81: 0 | Q81: 0
C82: Web Hosting/Domains/Azure | D82: 1200 | F82: =$D82 -> 1200 | G82: =$D82 -> 1200 | H82: =$D82 -> 1200 | I82: =$D82 -> 1200 | J82: =$D82 -> 1200 | K82: =$D82 -> 1200 | L82: =$D82 -> 1200 | M82: =$D82 -> 1200 | N82: 0 | O82: 0 | P82: 0 | Q82: 0
C83: L1 Visas - 7500 / person (5 people) | D83: 37500 | F83: =D83 -> 37500 | G83: 0 | H83: 0 | I83: 0 | J83: 0 | K83: 0 | L83: 0 | M83: 0 | N83: 0 | O83: 0 | P83: 0 | Q83: 0
C85: Total Corporate Infrastructure | F85: =SUM(F78:F83) -> 45450 | G85: =SUM(G78:G83) -> 7950 | H85: =SUM(H78:H83) -> 7950 | I85: =SUM(I78:I83) -> 7950 | J85: =SUM(J78:J83) -> 7950 | K85: =SUM(K78:K83) -> 7950 | L85: =SUM(L78:L83) -> 7950 | M85: =SUM(M78:M83) -> 7950 | ... Q85: =SUM(Q78:Q83) -> 0
B87: Travel & Accommodations
C88: Travel | D88: 5000 | F88: =$D88 -> 5000 | G88: =$D88 -> 5000 | H88: =$D88 -> 5000 | I88: =$D88 -> 5000 | J88: =$D88 -> 5000 | K88: =$D88 -> 5000 | L88: =$D88 -> 5000 | M88: =$D88 -> 5000 | N88: 0 | O88: 0 | P88: 0 | Q88: 0
C89: Home Lease + Utilities | D89: 6000 | F89: =$D89*2 -> 12000 | G89: =$D89 -> 6000 | H89: =$D89 -> 6000 | I89: =$D89 -> 6000 | J89: =$D89 -> 6000 | K89: =$D89 -> 6000 | L89: =$D89 -> 6000 | M89: =$D89 -> 6000 | N89: =$D89 -> 6000 | ... Q89: =$D89 -> 6000
C90: Home Lease + Furnishing | D90: 20000 | F90: 20000 | G90: 0 | H90: 0 | I90: 0 | J90: 0 | K90: 0 | L90: 0 | M90: 0 | N90: 0 | O90: 0 | P90: 0 | Q90: 0
C91: Lodging | D91: 1000 | F91: =$D91 -> 1000 | G91: =$D91 -> 1000 | H91: =$D91 -> 1000 | I91: =$D91 -> 1000 | J91: =$D91 -> 1000 | K91: =$D91 -> 1000 | L91: =$D91 -> 1000 | M91: =$D91 -> 1000 | N91: 0 | O91: 0 | P91: 0 | Q91: 0
C92: Meals | D92: 5000 | F92: =$D92 -> 5000 | G92: =$D92 -> 5000 | H92: =$D92 -> 5000 | I92: =$D92 -> 5000 | J92: =$D92 -> 5000 | K92: =$D92 -> 5000 | L92: =$D92 -> 5000 | M92: =$D92 -> 5000 | N92: 0 | O92: 0 | P92: 0 | Q92: 0
C93: Vehicle Rent | D93: 3000 | F93: =$D93 -> 3000 | G93: =$D93 -> 3000 | H93: =$D93 -> 3000 | I93: =$D93 -> 3000 | J93: =$D93 -> 3000 | K93: =$D93 -> 3000 | L93: =$D93 -> 3000 | M93: =$D93 -> 3000 | N93: 0 | O93: 0 | P93: 0 | Q93: 0
C95: Total Travel & Accommodations | F95: =SUM(F88:F93) -> 46000 | G95: =SUM(G88:G93) -> 20000 | H95: =SUM(H88:H93) -> 20000 | I95: =SUM(I88:I93) -> 20000 | J95: =SUM(J88:J93) -> 20000 | K95: =SUM(K88:K93) -> 20000 | L95: =SUM(L88:L93) -> 20000 | M95: =SUM(M88:M93) -> 20000 | ... Q95: =SUM(Q88:Q93) -> 6000
B97: Lab Testing & Sampling
C98: Lab Fees | D98: 350000 | F98: 0 | G98: 0 | H98: 0 | I98: 0 | J98: 0 | K98: =$D98/3 -> 116666.67 | L98: =$D98/3 -> 116666.67 | M98: =$D98/3 -> 116666.67 | N98: 0 | O98: 0 | P98: 0 | Q98: 0
C99: Feedstock - Coal (220 Tons $50 / ton) | D99: 11000 | F99: 0 | G99: 0 | H99: 0 | I99: 0 | J99: 0 | K99: =D99 -> 11000 | L99: 0 | M99: 0 | N99: 0 | O99: 0 | P99: 0 | Q99: 0
C100: Feedstock - Tires (220 Tons .10/lb) | D100: 48400 | F100: 0 | G100: 0 | H100: 0 | I100: 0 | J100: 0 | K100: =D100 -> 48400 | L100: 0 | M100: 0 | N100: 0 | O100: 0 | P100: 0 | Q100: 0
C102: Total Lab Testing & Sampling | F102: =SUM(F98:F100) -> 0 | G102: =SUM(G98:G100) -> 0 | H102: =SUM(H98:H100) -> 0 | I102: =SUM(I98:I100) -> 0 | J102: =SUM(J98:J100) -> 0 | K102: =SUM(K98:K100) -> 176066.67 | L102: =SUM(L98:L100) -> 116666.67 | M102: =SUM(M98:M100) -> 116666.67 | ... Q102: =SUM(Q98:Q100) -> 0
C104: Total Operating Costs | F104: =SUM(F102+F95+F85) -> 91450 | G104: =SUM(G102+G95+G85) -> 27950 | H104: =SUM(H102+H95+H85) -> 27950 | I104: =SUM(I102+I95+I85) -> 27950 | J104: =SUM(J102+J95+J85) -> 27950 | K104: =SUM(K102+K95+K85) -> 204016.67 | L104: =SUM(L102+L95+L85) -> 144616.67 | M104: =SUM(M102+M95+M85) -> 144616.67 | ... Q104: =SUM(Q102+Q95+Q85) -> 6000
A106: Professional Services
B107: Category | C107: Item | D107: Per Unit (Imported) | E107: Disc Rate | F107: 1 | G107: 2 | H107: 3 | I107: 4 | J107: 5 | K107: 6 | L107: 7 | M107: 8
B108: Accounting
C109: HGA Accounting Services | D109: 1000 | F109: =$D109 -> 1000 | G109: =$D109 -> 1000 | H109: =$D109 -> 1000 | I109: =$D109 -> 1000 | J109: =$D109 -> 1000 | K109: =$D109 -> 1000 | L109: =$D109 -> 1000 | M109: =$D109 -> 1000 | N109: 0 | O109: 0 | P109: 0 | Q109: 0
B110: Legal
C111: HGA - Vendor / Employee Contracts | D111: 1000 | F111: =$D111 -> 1000 | G111: =$D111 -> 1000 | H111: =$D111 -> 1000 | I111: =$D111 -> 1000 | J111: =$D111 -> 1000 | K111: =$D111 -> 1000 | L111: =$D111 -> 1000 | M111: =$D111 -> 1000 | N111: 0 | O111: 0 | P111: 0 | Q111: 0
B112: IT & Security
C113: Hardware/Equipment Supply (Per Employee) | D113: 5000 | F113: =COUNT(F$123:F$139)*$D113 -> 85000 | G113: 0 | H113: 0 | I113: 0 | J113: 5000 | K113: 0 | L113: 0 | M113: 0 | N113: 0 | O113: 0 | P113: 0 | Q113: 0
C114: IT Support (Per Employee) | D114: 150 | F114: =COUNT(F$123:F$139)*$D114 -> 2550 | G114: =COUNT(G$123:G$139)*$D114 -> 2550 | H114: =COUNT(H$123:H$139)*$D114 -> 2550 | I114: =COUNT(I$123:I$139)*$D114 -> 2550 | J114: =COUNT(J$123:J$139)*$D114 -> 2550 | K114: =COUNT(K$123:K$139)*$D114 -> 2550 | L114: =COUNT(L$123:L$139)*$D114 -> 2550 | M114: =COUNT(M$123:M$139)*$D114 -> 2550 | N114: 0 | O114: 0 | P114: 0 | Q114: 0
B115: Manufacturing Consultant
C116: Contractor Harold (Lexon Group) | D116: 275000 | F116: =D116 -> 275000 | G116: 0 | H116: 0 | I116: 0 | J116: 0 | K116: 0 | L116: 0 | M116: 0 | N116: 0 | O116: 0 | P116: 0 | Q116: 0
C118: Total Professional Services | F118: =SUM(F109:F116) -> 364550 | G118: =SUM(G109:G116) -> 4550 | H118: =SUM(H109:H116) -> 4550 | I118: =SUM(I109:I116) -> 4550 | J118: =SUM(J109:J116) -> 9550 | K118: =SUM(K109:K116) -> 4550 | L118: =SUM(L109:L116) -> 4550 | M118: =SUM(M109:M116) -> 4550 | ... Q118: =SUM(Q109:Q116) -> 0
...

Sheet Sheet1
A1: Summary
C2: Category | D2: Total | F2: 1 | G2: 2 | H2: 3 | I2: 4 | J2: 5 | K2: 6 | L2: 7 | M2: 8 | N2: 9 | O2: 10 | P2: 11 | Q2: 12
C3: Equipment & Materials | D3: 5438875 | F3: 3228958.3 | G3: 1227958.3 | H3: 981958.33 | I3: 0 | J3: 0 | K3: 0 | L3: 0 | M3: 0 | N3: 0 | O3: 0 | P3: 0 | Q3: 0
C4: Facilities & Auxillary Support Systems | D4: 3674050 | F4: 1309683.3 | G4: 994683.33 | H4: 994683.33 | I4: 375000 | J4: 0 | K4: 0 | L4: 0 | M4: 0 | N4: 0 | O4: 0 | P4: 0 | Q4: 0
C5: Operating Costs | D5: 720500 | F5: 91450 | G5: 27950 | H5: 27950 | I5: 27950 | J5: 27950 | K5: 204016.67 | L5: 144616.67 | M5: 144616.67 | N5: 6000 | O5: 6000 | P5: 6000 | Q5: 6000
C6: Professional Services | D6: 401400 | F6: 364550 | G6: 4550 | H6: 4550 | I6: 4550 | J6: 9550 | K6: 4550 | L6: 4550 | M6: 4550 | N6: 0 | O6: 0 | P6: 0 | Q6: 0
C7: Workforce - Role - Pay Rate | D7: 2775367.6 | F7: 338436.18 | G7: 338436.18 | H7: 338436.18 | I7: 338436.18 | J7: 355405.72 | K7: 355405.72 | L7: 355405.72 | M7: 355405.72 | N7: 0 | O7: 0 | P7: 0 | Q7: 0
C9: Total Cost Build 1 SENS Processor | D9: 13010193 | F9: 5333077.9 | G9: 2593577.9 | H9: 2347577.9 | I9: 745936.18 | J9: 392905.72 | K9: 563972.39 | L9: 504572.39 | M9: 504572.39 | N9: 6000 | O9: 6000 | P9: 6000 | Q9: 6000
A12: Equipment & Materials
B13: Category | C13: Item | D13: Per Unit (Imported) | E13: Disc Rate | F13: 1 | G13: 2 | H13: 3 | I13: 4 | J13: 5 | K13: 6 | L13: 7 | M13: 8 | N13: 9 | O13: 10 | P13: 11 | Q13: 12
B14: Equipment & Materials
C15: Pack column, demister, liquid ring | D15: 233125 | E15: 0.2 | F15: 62166.667 | G15: 62166.667 | H15: 62166.667 | I15: 0 | J15: 0 | K15: 0 | L15: 0 | M15: 0 | N15: 0 | O15: 0 | P15: 0 | Q15: 0
C16: Ovens | D16: 609375 | E16: 0.2 | F16: 162500 | G16: 162500 | H16: 162500 | I16: 0 | J16: 0 | K16: 0 | L16: 0 | M16: 0 | N16: 0 | O16: 0 | P16: 0 | Q16: 0
C17: Pipe, fittings, auger tube shafts | D17: 516250 | E17: 0.2 | F17: 137666.67 | G17: 137666.67 | H17: 137666.67 | I17: 0 | J17: 0 | K17: 0 | L17: 0 | M17: 0 | N17: 0 | O17: 0 | P17: 0 | Q17: 0
C18: Weight hopper feed system | D18: 582500 | E18: 0.2 | F18: 155333.33 | G18: 155333.33 | H18: 155333.33 | I18: 0 | J18: 0 | K18: 0 | L18: 0 | M18: 0 | N18: 0 | O18: 0 | P18: 0 | Q18: 0
B19: National Tube sales
C20: Auger tubes | D20: 330000 | E20: 0.2 | F20: 132000 | G20: 132000 | H20: 0 | I20: 0 | J20: 0 | K20: 0 | L20: 0 | M20: 0 | N20: 0 | O20: 0 | P20: 0 | Q20: 0
B21: Thomas Conveyor
C22: Auger flights | D22: 160000 | E22: 0.2 | F22: 64000 | G22: 64000 | H22: 0 | I22: 0 | J22: 0 | K22: 0 | L22: 0 | M22: 0 | N22: 0 | O22: 0 | P22: 0 | Q22: 0
C23: Tapered Screw for weigh hopper | D23: 125000 | E23: 0.2 | F23: 50000 | G23: 50000 | H23: 0 | I23: 0 | J23: 0 | K23: 0 | L23: 0 | M23: 0 | N23: 0 | O23: 0 | P23: 0 | Q23: 0
B24: Controls, motors and pumps
C25: Control Automation Component | D25: 478125 | E25: 0.2 | F25: 382500 | G25: 0 | H25: 0 | I25: 0 | J25: 0 | K25: 0 | L25: 0 | M25: 0 | N25: 0 | O25: 0 | P25: 0 | Q25: 0
C26: Motors, gearboxes, drives, bucket elevators | D26: 356250 | E26: 0.2 | F26: 285000 | G26: 0 | H26: 0 | I26: 0 | J26: 0 | K26: 0 | L26: 0 | M26: 0 | N26: 0 | O26: 0 | P26: 0 | Q26: 0
C27: Chiller Contols & Electrical | D27: 197500 | E27: 0.2 | F27: 158000 | G27: 0 | H27: 0 | I27: 0 | J27: 0 | K27: 0 | L27: 0 | M27: 0 | N27: 0 | O27: 0 | P27: 0 | Q27: 0
C28: Myers (Flapper valves) | D28: 112500 | E28: 0.2 | F28: 90000 | G28: 0 | H28: 0 | I28: 0 | J28: 0 | K28: 0 | L28: 0 | M28: 0 | N28: 0 | O28: 0 | P28: 0 | Q28: 0
C29: Myers Aubrey (Steam, and Gas Processing control valves) | D29: 335625 | E29: 0.2 | F29: 268500 | G29: 0 | H29: 0 | I29: 0 | J29: 0 | K29: 0 | L29: 0 | M29: 0 | N29: 0 | O29: 0 | P29: 0 | Q29: 0
C30: Myers Aubrey (Flow meters) | D30: 170000 | E30: 0.2 | F30: 136000 | G30: 0 | H30: 0 | I30: 0 | J30: 0 | K30: 0 | L30: 0 | M30: 0 | N30: 0 | O30: 0 | P30: 0 | Q30: 0
C31: Automatic Pump (Vacuum and Oil Water Separator) | D31: 172500 | E31: 0.2 | F31: 138000 | G31: 0 | H31: 0 | I31: 0 | J31: 0 | K31: 0 | L31: 0 | M31: 0 | N31: 0 | O31: 0 | P31: 0 | Q31: 0
C32: Roberts & Spencer (Pressure transmitters, Vac Control Valves, level indicators) | D32: 168125 | E32: 0.2 | F32: 134500 | G32: 0 | H32: 0 | I32: 0 | J32: 0 | K32: 0 | L32: 0 | M32: 0 | N32: 0 | O32: 0 | P32: 0 | Q32: 0
C33: Switch Gear and Generator | D33: 203125 | E33: 0.2 | F33: 162500 | G33: 0 | H33: 0 | I33: 0 | J33: 0 | K33: 0 | L33: 0 | M33: 0 | N33: 0 | O33: 0 | P33: 0 | Q33: 0
C34: Control Valves, Modules, automation component | D34: 397500 | E34: 0.2 | F34: 318000 | G34: 0 | H34: 0 | I34: 0 | J34: 0 | K34: 0 | L34: 0 | M34: 0 | N34: 0 | O34: 0 | P34: 0 | Q34: 0
B35: Oven
C36: Harbison-Walker (Refractory) | D36: 180000 | E36: 0.2 | G36: 72000 | H36: 72000 | I36: 0 | J36: 0 | K36: 0 | L36: 0 | M36: 0 | N36: 0 | O36: 0 | P36: 0 | Q36: 0
C37: GTI-Engineering (Eclipse Burner and controls) | D37: 357500 | E37: 0.2 | F37: 95333.333 | G37: 95333.333 | H37: 95333.333 | I37: 0 | J37: 0 | K37: 0 | L37: 0 | M37: 0 | N37: 0 | O37: 0 | P37: 0 | Q37: 0
C38: Exothermics (Air to Air heat exchanger) | D38: 265000 | E38: 0.2 | F38: 70666.667 | G38: 70666.667 | H38: 70666.667 | I38: 0 | J38: 0 | K38: 0 | L38: 0 | M38: 0 | N38: 0 | O38: 0 | P38: 0 | Q38: 0
C39: Hubbel Water heater | D39: 262500 | E39: 0.25 | F39: 65625 | G39: 65625 | H39: 65625 | I39: 0 | J39: 0 | K39: 0 | L39: 0 | M39: 0 | N39: 0 | O39: 0 | P39: 0 | Q39: 0
C40: Emerson Thermal Couplers | D40: 120000 | E40: 0.2 | F40: 32000 | G40: 32000 | H40: 32000 | I40: 0 | J40: 0 | K40: 0 | L40: 0 | M40: 0 | N40: 0 | O40: 0 | P40: 0 | Q40: 0
B41: Reactor
C42: Cappco Fabricators (rolling and endplates) | D42: 120000 | E42: 0.2 | F42: 32000 | G42: 32000 | H42: 32000 | I42: 0 | J42: 0 | K42: 0 | L42: 0 | M42: 0 | N42: 0 | O42: 0 | P42: 0 | Q42: 0
C43: O&D Manufacturing (Brass seals and Bearings) | D43: 120000 | E43: 0.2 | F43: 32000 | G43: 32000 | H43: 32000 | I43: 0 | J43: 0 | K43: 0 | L43: 0 | M43: 0 | N43: 0 | O43: 0 | P43: 0 | Q43: 0
C44: Machining-Shafts,drum bearings, exp joint etc | D44: 72500 | E44: 0.2 | F44: 19333.333 | G44: 19333.333 | H44: 19333.333 | I44: 0 | J44: 0 | K44: 0 | L44: 0 | M44: 0 | N44: 0 | O44: 0 | P44: 0 | Q44: 0
B46: Engineering and EPC Fees | D46: 475597.55 | E46: 1 | F46: 0 | G46: 0 | H46: 0 | I46: 0 | J46: 0 | K46: 0 | L46: 0 | M46: 0 | N46: 0 | O46: 0 | P46: 0 | Q46: 0
B47: Commissioning | D47: 100000 | E47: 0.2 | F47: 26666.667 | G47: 26666.667 | H47: 26666.667 | I47: 0 | J47: 0 | K47: 0 | L47: 0 | M47: 0 | N47: 0 | O47: 0 | P47: 0 | Q47: 0
B48: Certification and Testing | D48: 70000 | E48: 0.2 | F48: 18666.667 | G48: 18666.667 | H48: 18666.667 | I48: 0 | J48: 0 | K48: 0 | L48: 0 | M48: 0 | N48: 0 | O48: 0 | P48: 0 | Q48: 0
C50: Total Equipment & Materials | D50: 7290597.5 | E50: 0.74601224 | F50: 3228958.3 | G50: 1227958.3 | H50: 981958.33
A52: Facilities & Auxillary Support Systems
B53: Facilities
A54: Texas Vessel | C54: Shop
C55: Sq Ft Required | D55: 10000
C56: Rate | D56: 150
C57: Total Facilities | D57: 1500000 | F57: 375000 | G57: 375000 | H57: 375000 | I57: 375000 | J57: 0 | K57: 0 | L57: 0 | M57: 0 | N57: 0 | O57: 0 | P57: 0 | Q57: 0
B59: Aux Support Systems
A60: Texas Vessel | C60: Process Mechanical | D60: 313500 | E60: 0.2 | F60: 83600 | G60: 83600 | H60: 83600 | I60: 0 | J60: 0 | K60: 0 | L60: 0 | M60: 0 | N60: 0 | O60: 0 | P60: 0 | Q60: 0
A61: Texas Vessel | C61: Process Civl | D61: 121875 | E61: 0.2 | F61: 32500 | G61: 32500 | H61: 32500 | I61: 0 | J61: 0 | K61: 0 | L61: 0 | M61: 0 | N61: 0 | O61: 0 | P61: 0 | Q61: 0
C62: Chilled Water Plant | D62: 393750 | E62: 0.2 | F62: 315000 | I62: c | J62: 0 | K62: 0 | L62: 0 | M62: 0 | N62: 0 | O62: 0 | P62: 0 | Q62: 0
C63: Gas & Oil Processing / Storage | D63: 737500 | E63: 0.5 | F63: 122916.67 | G63: 122916.67 | H63: 122916.67 | I63: 0 | J63: 0 | K63: 0 | L63: 0 | M63: 0 | N63: 0 | O63: 0 | P63: 0 | Q63: 0
C64: Flare Stack | D64: 300000 | E64: 0.2 | F64: 80000 | G64: 80000 | H64: 80000 | I64: 0 | J64: 0 | K64: 0 | L64: 0 | M64: 0 | N64: 0 | O64: 0 | P64: 0 | Q64: 0
C65: Carbon Black Processing / Storage | D65: 812500 | E65: 0.4 | F65: 162500 | G65: 162500 | H65: 162500 | I65: 0 | J65: 0 | K65: 0 | L65: 0 | M65: 0 | N65: 0 | O65: 0 | P65: 0 | Q65: 0
C66: Steam Boiler | D66: 293125 | E66: 0.2 | F66: 78166.667 | G66: 78166.667 | H66: 78166.667 | I66: 0 | J66: 0 | K66: 0 | L66: 0 | M66: 0 | N66: 0 | O66: 0 | P66: 0 | Q66: 0
C67: Dirty Water Treatment | D67: 93750 | E67: 0.2 | F67: 25000 | G67: 25000 | H67: 25000 | I67: 0 | J67: 0 | K67: 0 | L67: 0 | M67: 0 | N67: 0 | O67: 0 | P67: 0 | Q67: 0
C68: Compressed Air Plant | D68: 100000 | E68: 0.2 | F68: 26666.667 | G68: 26666.667 | H68: 26666.667 | I68: 0 | J68: 0 | K68: 0 | L68: 0 | M68: 0 | N68: 0 | O68: 0 | P68: 0 | Q68: 0
C69: Pressure wash system | D69: 31250 | E69: 0.2 | F69: 8333.3333 | G69: 8333.3333 | H69: 8333.3333 | I69: 0 | J69: 0 | K69: 0 | L69: 0 | M69: 0 | N69: 0 | O69: 0 | P69: 0 | Q69: 0
C71: Total Aux Supporty Systems | D71: 3197250 | F71: 934683.33 | G71: 619683.33 | H71: 619683.33 | I71: 0 | J71: 0 | K71: 0 | L71: 0 | M71: 0 | N71: 0 | O71: 0 | P71: 0 | Q71: 0
C73: Total Facilities & Aux | D73: 3674050 | F73: 1309683.3 | G73: 994683.33 | H73: 994683.33 | I73: 375000 | J73: 0 | K73: 0 | L73: 0 | M73: 0 | N73: 0 | O73: 0 | P73: 0 | Q73: 0
A75: Operating Costs
B76: Category | C76: Item | D76: Per Unit (Imported) | E76: Disc Rate | F76: 1 | G76: 2 | H76: 3 | I76: 4 | J76: 5 | K76: 6 | L76: 7 | M76: 8 | N76: 9 | O76: 10 | P76: 11 | Q76: 12
B77: Corporate Infrastructure
C78: Business Licenses & Memberships | D78: 2000 | F78: 2000 | G78: 2000 | H78: 2000 | I78: 2000 | J78: 2000 | K78: 2000 | L78: 2000 | M78: 2000 | N78: 0 | O78: 0 | P78: 0 | Q78: 0
C79: Software & Licenses | D79: 2500 | F79: 2500 | G79: 2500 | H79: 2500 | I79: 2500 | J79: 2500 | K79: 2500 | L79: 2500 | M79: 2500 | N79: 0 | O79: 0 | P79: 0 | Q79: 0
C80: Insurance - General | D80: 2000 | F80: 2000 | G80: 2000 | H80: 2000 | I80: 2000 | J80: 2000 | K80: 2000 | L80: 2000 | M80: 2000 | N80: 0 | O80: 0 | P80: 0 | Q80: 0
C81: Interest & Bank Charges | D81: 250 | F81: 250 | G81: 250 | H81: 250 | I81: 250 | J81: 250 | K81: 250 | L81: 250 | M81: 250 | N81: 0 | O81: 0 | P81: 0 | Q81: 0
C82: Web Hosting/Domains/Azure | D82: 1200 | F82: 1200 | G82: 1200 | H82: 1200 | I82: 1200 | J82: 1200 | K82: 1200 | L82: 1200 | M82: 1200 | N82: 0 | O82: 0 | P82: 0 | Q82: 0
C83: L1 Visas - 7500 / person (5 people) | D83: 37500 | F83: 37500 | G83: 0 | H83: 0 | I83: 0 | J83: 0 | K83: 0 | L83: 0 | M83: 0 | N83: 0 | O83: 0 | P83: 0 | Q83: 0
C85: Total Corporate Infrastructure | F85: 45450 | G85: 7950 | H85: 7950 | I85: 7950 | J85: 7950 | K85: 7950 | L85: 7950 | M85: 7950 | N85: 0 | O85: 0 | P85: 0 | Q85: 0
B87: Travel & Accommodations
C88: Travel | D88: 5000 | F88: 5000 | G88: 5000 | H88: 5000 | I88: 5000 | J88: 5000 | K88: 5000 | L88: 5000 | M88: 5000 | N88: 0 | O88: 0 | P88: 0 | Q88: 0
C89: Home Lease + Utilities | D89: 6000 | F89: 12000 | G89: 6000 | H89: 6000 | I89: 6000 | J89: 6000 | K89: 6000 | L89: 6000 | M89: 6000 | N89: 6000 | O89: 6000 | P89: 6000 | Q89: 6000
C90: Home Lease + Furnishing | D90: 20000 | F90: 20000 | G90: 0 | H90: 0 | I90: 0 | J90: 0 | K90: 0 | L90: 0 | M90: 0 | N90: 0 | O90: 0 | P90: 0 | Q90: 0
C91: Lodging | D91: 1000 | F91: 1000 | G91: 1000 | H91: 1000 | I91: 1000 | J91: 1000 | K91: 1000 | L91: 1000 | M91: 1000 | N91: 0 | O91: 0 | P91: 0 | Q91: 0
C92: Meals | D92: 5000 | F92: 5000 | G92: 5000 | H92: 5000 | I92: 5000 | J92: 5000 | K92: 5000 | L92: 5000 | M92: 5000 | N92: 0 | O92: 0 | P92: 0 | Q92: 0
C93: Vehicle Rent | D93: 3000 | F93: 3000 | G93: 3000 | H93: 3000 | I93: 3000 | J93: 3000 | K93: 3000 | L93: 3000 | M93: 3000 | N93: 0 | O93: 0 | P93: 0 | Q93: 0
C95: Total Travel & Accommodations | F95: 46000 | G95: 20000 | H95: 20000 | I95: 20000 | J95: 20000 | K95: 20000 | L95: 20000 | M95: 20000 | N95: 6000 | O95: 6000 | P95: 6000 | Q95: 6000
B97: Lab Testing & Sampling
C98: Lab Fees | D98: 350000 | F98: 0 | G98: 0 | H98: 0 | I98: 0 | J98: 0 | K98: 116666.67 | L98: 116666.67 | M98: 116666.67 | N98: 0 | O98: 0 | P98: 0 | Q98: 0
C99: Feedstock - Coal (220 Tons $50 / ton) | D99: 11000 | F99: 0 | G99: 0 | H99: 0 | I99: 0 | J99: 0 | K99: 11000 | L99: 0 | M99: 0 | N99: 0 | O99: 0 | P99: 0 | Q99: 0
C100: Feedstock - Tires (220 Tons .10/lb) | D100: 48400 | F100: 0 | G100: 0 | H100: 0 | I100: 0 | J100: 0 | K100: 48400 | L100: 0 | M100: 0 | N100: 0 | O100: 0 | P100: 0 | Q100: 0
C102: Total Lab Testing & Sampling | F102: 0 | G102: 0 | H102: 0 | I102: 0 | J102: 0 | K102: 176066.67 | L102: 116666.67 | M102: 116666.67 | N102: 0 | O102: 0 | P102: 0 | Q102: 0
C104: Total Operating Costs | F104: 91450 | G104: 27950 | H104: 27950 | I104: 27950 | J104: 27950 | K104: 204016.67 | L104: 144616.67 | M104: 144616.67 | N104: 6000 | O104: 6000 | P104: 6000 | Q104: 6000
A106: Professional Services
B107: Category | C107: Item | D107: Per Unit (Imported) | E107: Disc Rate | F107: 1 | G107: 2 | H107: 3 | I107: 4 | J107: 5 | K107: 6 | L107: 7 | M107: 8
B108: Accounting
C109: HGA Accounting Services | D109: 1000 | F109: 1000 | G109: 1000 | H109: 1000 | I109: 1000 | J109: 1000 | K109: 1000 | L109: 1000 | M109: 1000 | N109: 0 | O109: 0 | P109: 0 | Q109: 0
B110: Legal
C111: HGA - Vendor / Employee Contracts | D111: 1000 | F111: 1000 | G111: 1000 | H111: 1000 | I111: 1000 | J111: 1000 | K111: 1000 | L111: 1000 | M111: 1000 | N111: 0 | O111: 0 | P111: 0 | Q111: 0
B112: IT & Security
C113: Hardware/Equipment Supply (Per Employee) | D113: 5000 | F113: 85000 | G113: 0 | H113: 0 | I113: 0 | J113: 5000 | K113: 0 | L113: 0 | M113: 0 | N113: 0 | O113: 0 | P113: 0 | Q113: 0
C114: IT Support (Per Employee) | D114: 150 | F114: 2550 | G114: 2550 | H114: 2550 | I114: 2550 | J114: 2550 | K114: 2550 | L114: 2550 | M114: 2550 | N114: 0 | O114: 0 | P114: 0 | Q114: 0
B115: Manufacturing Consultant
C116: Contractor Harold (Lexon Group) | D116: 275000 | F116: 275000 | G116: 0 | H116: 0 | I116: 0 | J116: 0 | K116: 0 | L116: 0 | M116: 0 | N116: 0 | O116: 0 | P116: 0 | Q116: 0
C118: Total Professional Services | F118: 364550 | G118: 4550 | H118: 4550 | I118: 4550 | J118: 9550 | K118: 4550 | L118: 4550 | M118: 4550 | N118: 0 | O118: 0 | P118: 0 | Q118: 0
...

Sheet IMPORT_OK Model
A4: =[1]ModelDescription!A4 -> Economic Forecasting Model
A5: =[1]ModelDescription!C6 -> Oklahoma TDF Processing Site Economic Evaluation All Phase V4
B6: Period | F6: =[1]Assumptions!B56 -> 1 | G6: =[1]Assumptions!C56 -> 2 | H6: =[1]Assumptions!D56 -> 3 | I6: =[1]Assumptions!E56 -> 4 | J6: =[1]Assumptions!F56 -> 5 | K6: =[1]Assumptions!G56 -> 6 | L6: =[1]Assumptions!H56 -> 7 | M6: =[1]Assumptions!I56 -> 8 | ... BM6: =[1]Assumptions!BI56 -> 60
B7: Year | F7: =[1]Assumptions!B57 -> 2023 | G7: =[1]Assumptions!C57 -> 2023 | H7: =[1]Assumptions!D57 -> 2023 | I7: =[1]Assumptions!E57 -> 2024 | J7: =[1]Assumptions!F57 -> 2024 | K7: =[1]Assumptions!G57 -> 2024 | L7: =[1]Assumptions!H57 -> 2024 | M7: =[1]Assumptions!I57 -> 2024 | ... BM7: =[1]Assumptions!BI57 -> 2028
B8: Month | F8: =[1]Assumptions!B58 -> October | G8: =[1]Assumptions!C58 -> November | H8: =[1]Assumptions!D58 -> Dec | I8: =[1]Assumptions!E58 -> Jan | J8: =[1]Assumptions!F58 -> Feb | K8: =[1]Assumptions!G58 -> Mar | L8: =[1]Assumptions!H58 -> April | M8: =[1]Assumptions!I58 -> May | ... BM8: =[1]Assumptions!BI58 -> Sept
B9: Days | F9: =[1]Assumptions!B60 -> 31 | G9: =[1]Assumptions!C60 -> 30 | H9: =[1]Assumptions!D60 -> 31 | I9: =[1]Assumptions!E60 -> 31 | J9: =[1]Assumptions!F60 -> 29 | K9: =[1]Assumptions!G60 -> 31 | L9: =[1]Assumptions!H60 -> 30 | M9: =[1]Assumptions!I60 -> 31 | ... BM9: =[1]Assumptions!BI60 -> 30
B10: Revenue | C10: R | E10: =SUM(F10:BM10) -> 6.3688762e+08 | F10: =SUMPRODUCT((F$20:F$343)*($C$20:$C$343=$C10)) -> 0 | G10: =SUMPRODUCT((G$20:G$343)*($C$20:$C$343=$C10)) -> 0 | H10: =SUMPRODUCT((H$20:H$343)*($C$20:$C$343=$C10)) -> 0 | I10: =SUMPRODUCT((I$20:I$343)*($C$20:$C$343=$C10)) -> 0 | J10: =SUMPRODUCT((J$20:J$343)*($C$20:$C$343=$C10)) -> 0 | K10: =SUMPRODUCT((K$20:K$343)*($C$20:$C$343=$C10)) -> 0 | L10: =SUMPRODUCT((L$20:L$343)*($C$20:$C$343=$C10)) -> 25920 | M10: =SUMPRODUCT((M$20:M$343)*($C$20:$C$343=$C10)) -> 147312 | ... BM10: =SUMPRODUCT((BM$20:BM$343)*($C$20:$C$343=$C10)) -> 17355822
B11: Capital Investment ( Loan) | C11: L | E11: =SUM(F11:BM11) -> 86000000 | F11: 43000000 | G11: 0 | H11: 0 | I11: 18000000 | J11: 0 | K11: 0 | L11: 20000000 | M11: 0 | N11: =SUMPRODUCT((N$20:N$343)*($C$20:$C$343=$C11)) -> 0 | O11: =SUMPRODUCT((O$20:O$343)*($C$20:$C$343=$C11)) -> 5000000 | P11: 0 | Q11: =SUMPRODUCT((Q$20:Q$343)*($C$20:$C$343=$C11)) -> 0 | R11: =SUMPRODUCT((R$20:R$343)*($C$20:$C$343=$C11)) -> 0 | S11: =SUMPRODUCT((S$20:S$343)*($C$20:$C$343=$C11)) -> 0 | T11: =SUMPRODUCT((T$20:T$343)*($C$20:$C$343=$C11)) -> 0 | U11: =SUMPRODUCT((U$20:U$343)*($C$20:$C$343=$C11)) -> 0 | V11: =SUMPRODUCT((V$20:V$343)*($C$20:$C$343=$C11)) -> 0 | W11: =SUMPRODUCT((W$20:W$343)*($C$20:$C$343=$C11)) -> 0 | X11: =SUMPRODUCT((X$20:X$343)*($C$20:$C$343=$C11)) -> 0 | ... BM11: =SUMPRODUCT((BM$20:BM$343)*($C$20:$C$343=$C11)) -> 0
B12: Costs | C12: C | E12: =SUM(F12:BM12) -> 1.648922e+08 | F12: =SUMPRODUCT((F$20:F$343)*($C$20:$C$343=$C12)) -> 4450000 | G12: =SUMPRODUCT((G$20:G$343)*($C$20:$C$343=$C12)) -> 0 | H12: =SUMPRODUCT((H$20:H$343)*($C$20:$C$343=$C12)) -> 0 | I12: =SUMPRODUCT((I$20:I$343)*($C$20:$C$343=$C12)) -> 0 | J12: =SUMPRODUCT((J$20:J$343)*($C$20:$C$343=$C12)) -> 0 | K12: =SUMPRODUCT((K$20:K$343)*($C$20:$C$343=$C12)) -> 0 | L12: =SUMPRODUCT((L$20:L$343)*($C$20:$C$343=$C12)) -> 0 | M12: =SUMPRODUCT((M$20:M$343)*($C$20:$C$343=$C12)) -> 0 | ... BM12: =SUMPRODUCT((BM$20:BM$343)*($C$20:$C$343=$C12)) -> 2333862.2
B13: Business Overhead | C13: O | E13: =SUM(F13:BM13) -> 19325434 | F13: =SUMPRODUCT((F$20:F$343)*($C$20:$C$343=$C13)) -> 0 | G13: =SUMPRODUCT((G$20:G$343)*($C$20:$C$343=$C13)) -> 0 | H13: =SUMPRODUCT((H$20:H$343)*($C$20:$C$343=$C13)) -> 0 | I13: =SUMPRODUCT((I$20:I$343)*($C$20:$C$343=$C13)) -> 0 | J13: =SUMPRODUCT((J$20:J$343)*($C$20:$C$343=$C13)) -> 0 | K13: =SUMPRODUCT((K$20:K$343)*($C$20:$C$343=$C13)) -> 0 | L13: =SUMPRODUCT((L$20:L$343)*($C$20:$C$343=$C13)) -> 48000 | M13: =SUMPRODUCT((M$20:M$343)*($C$20:$C$343=$C13)) -> 48000 | ... BM13: =SUMPRODUCT((BM$20:BM$343)*($C$20:$C$343=$C13)) -> 406637.2
B14: Capital Costs | C14: CAP | E14: =SUM(F14:BM14) -> 1.2193606e+08 | F14: =SUMPRODUCT((F$20:F$343)*($C$20:$C$343=$C14)) -> 14011030 | G14: =SUMPRODUCT((G$20:G$343)*($C$20:$C$343=$C14)) -> 11299454 | H14: =SUMPRODUCT((H$20:H$343)*($C$20:$C$343=$C14)) -> 10141630 | I14: =SUMPRODUCT((I$20:I$343)*($C$20:$C$343=$C14)) -> 4586380 | J14: =SUMPRODUCT((J$20:J$343)*($C$20:$C$343=$C14)) -> 8715230.4 | K14: =SUMPRODUCT((K$20:K$343)*($C$20:$C$343=$C14)) -> 3189780 | L14: =SUMPRODUCT((L$20:L$343)*($C$20:$C$343=$C14)) -> 8483088 | M14: =SUMPRODUCT((M$20:M$343)*($C$20:$C$343=$C14)) -> 3523960.8 | ... BM14: =SUMPRODUCT((BM$20:BM$343)*($C$20:$C$343=$C14)) -> 173830
B15: Loan Payment | C15: LP | E15: =SUM(F15:BM15) -> 86000000 | F15: =SUMPRODUCT((F$20:F$343)*($C$20:$C$343=$C15)) -> 0 | G15: =SUMPRODUCT((G$20:G$343)*($C$20:$C$343=$C15)) -> 0 | H15: =SUMPRODUCT((H$20:H$343)*($C$20:$C$343=$C15)) -> 0 | I15: =SUMPRODUCT((I$20:I$343)*($C$20:$C$343=$C15)) -> 0 | J15: =SUMPRODUCT((J$20:J$343)*($C$20:$C$343=$C15)) -> 0 | K15: =SUMPRODUCT((K$20:K$343)*($C$20:$C$343=$C15)) -> 0 | L15: =SUMPRODUCT((L$20:L$343)*($C$20:$C$343=$C15)) -> 0 | M15: =SUMPRODUCT((M$20:M$343)*($C$20:$C$343=$C15)) -> 0 | ... X15: =SUMPRODUCT((X$20:X$343)*($C$20:$C$343=$C15)) -> 0 | Y15: 0 | Z15: 5000000 | AA15: 5000000 | AB15: 5000000 | AC15: 5000000 | AD15: 5000000 | AE15: 5000000 | AF15: 5000000 | AG15: 5000000 | AH15: 5000000 | AI15: 5000000 | AJ15: 5000000 | AK15: 5000000 | AL15: 5000000 | AM15: 5000000 | AN15: 5000000 | AO15: 5000000 | AP15: 6000000 | AQ15: 0 | AR15: 0 | AS15: =SUMPRODUCT((AS$20:AS$343)*($C$20:$C$343=$C15)) -> 0 | AT15: 0 | AU15: =SUMPRODUCT((AU$20:AU$343)*($C$20:$C$343=$C15)) -> 0 | AV15: =SUMPRODUCT((AV$20:AV$343)*($C$20:$C$343=$C15)) -> 0 | AW15: 0 | AX15: =SUMPRODUCT((AX$20:AX$343)*($C$20:$C$343=$C15)) -> 0 | AY15: =SUMPRODUCT((AY$20:AY$343)*($C$20:$C$343=$C15)) -> 0 | AZ15: 0 | BA15: =SUMPRODUCT((BA$20:BA$343)*($C$20:$C$343=$C15)) -> 0 | BB15: =SUMPRODUCT((BB$20:BB$343)*($C$20:$C$343=$C15)) -> 0 | BC15: 0 | BD15: =SUMPRODUCT((BD$20:BD$343)*($C$20:$C$343=$C15)) -> 0 | BE15: =SUMPRODUCT((BE$20:BE$343)*($C$20:$C$343=$C15)) -> 0 | BF15: 0 | BG15: =SUMPRODUCT((BG$20:BG$343)*($C$20:$C$343=$C15)) -> 0 | BH15: =SUMPRODUCT((BH$20:BH$343)*($C$20:$C$343=$C15)) -> 0 | BI15: 0 | BJ15: =SUMPRODUCT((BJ$20:BJ$343)*($C$20:$C$343=$C15)) -> 0 | BK15: =SUMPRODUCT((BK$20:BK$343)*($C$20:$C$343=$C15)) -> 0 | BL15: =SUMPRODUCT((BL$20:BL$343)*($C$20:$C$343=$C15)) -> 0 | BM15: =SUMPRODUCT((BM$20:BM$343)*($C$20:$C$343=$C15)) -> 0
B16: Depreciation | C16: DEP | E16: =SUM(F16:BM16) -> 85444192 | F16: =SUMPRODUCT((F$20:F$343)*($C$20:$C$343=$C16)) -> 0 | G16: =SUMPRODUCT((G$20:G$343)*($C$20:$C$343=$C16)) -> 0 | H16: =SUMPRODUCT((H$20:H$343)*($C$20:$C$343=$C16)) -> 0 | I16: =SUMPRODUCT((I$20:I$343)*($C$20:$C$343=$C16)) -> 0 | J16: =SUMPRODUCT((J$20:J$343)*($C$20:$C$343=$C16)) -> 0 | K16: =SUMPRODUCT((K$20:K$343)*($C$20:$C$343=$C16)) -> 0 | L16: =SUMPRODUCT((L$20:L$343)*($C$20:$C$343=$C16)) -> 0 | M16: =SUMPRODUCT((M$20:M$343)*($C$20:$C$343=$C16)) -> 0 | N16: =SUMPRODUCT((N$20:N$343)*($C$20:$C$343=$C16)) -> 0 | O16: {=SUMPRODUCT((O$20:O$343)*($C$20:$C$343=$C16))} -> 1369307.7 | P16: =SUMPRODUCT((P$20:P$343)*($C$20:$C$343=$C16)) -> 1369307.7 | Q16: =SUMPRODUCT((Q$20:Q$343)*($C$20:$C$343=$C16)) -> 1369307.7 | R16: =SUMPRODUCT((R$20:R$343)*($C$20:$C$343=$C16)) -> 1369307.7 | S16: =SUMPRODUCT((S$20:S$343)*($C$20:$C$343=$C16)) -> 1369307.7 | T16: =SUMPRODUCT((T$20:T$343)*($C$20:$C$343=$C16)) -> 1369307.7 | U16: =SUMPRODUCT((U$20:U$343)*($C$20:$C$343=$C16)) -> 1369307.7 | V16: =SUMPRODUCT((V$20:V$343)*($C$20:$C$343=$C16)) -> 1369307.7 | W16: =SUMPRODUCT((W$20:W$343)*($C$20:$C$343=$C16)) -> 1369307.7 | ... BH16: =SUMPRODUCT((BH$20:BH$343)*($C$20:$C$343=$C16)) -> 1889624.4 | BI16: {=SUMPRODUCT((BI$20:BI$343)*($C$20:$C$343=$C16))} -> 1889624.4 | BJ16: =SUMPRODUCT((BJ$20:BJ$343)*($C$20:$C$343=$C16)) -> 1889624.4 | BK16: =SUMPRODUCT((BK$20:BK$343)*($C$20:$C$343=$C16)) -> 1889624.4 | BL16: =SUMPRODUCT((BL$20:BL$343)*($C$20:$C$343=$C16)) -> 1889624.4 | BM16: =SUMPRODUCT((BM$20:BM$343)*($C$20:$C$343=$C16)) -> 1889624.4
B17: Monthly Profit/Loss (EBITDA) | F17: =SUM(F10:F11)-SUM(F12:F15) -> 24538970 | G17: =SUM(G10:G11)-SUM(G12:G15) -> -11299454 | H17: =SUM(H10:H11)-SUM(H12:H15) -> -10141630 | I17: =SUM(I10:I11)-SUM(I12:I15) -> 13413620 | J17: =SUM(J10:J11)-SUM(J12:J15) -> -8715230.4 | K17: =SUM(K10:K11)-SUM(K12:K15) -> -3189780 | L17: =SUM(L10:L11)-SUM(L12:L15) -> 11494832 | M17: =SUM(M10:M11)-SUM(M12:M15) -> -3424648.8 | ... BM17: =SUM(BM10:BM11)-SUM(BM12:BM15) -> 14441493
B18: Project Cumulative Cash Flow | F18: =E18+F17 -> 24538970 | G18: =F18+G17 -> 13239516 | H18: =G18+H17 -> 3097886 | I18: =H18+I17 -> 16511506 | J18: =I18+J17 -> 7796275.6 | K18: =J18+K17 -> 4606495.6 | L18: =K18+L17 -> 16101328 | M18: =L18+M17 -> 12676679 | ... BM18: =BL18+BM17 -> 3.3073393e+08
A22: Project Capital
B23: Capital Investment USD | C23: L | E23: =SUM(F23:BM23) -> 86000000 | F23: 43000000 | G23: 0 | H23: 0 | I23: 18000000 | J23: 0 | K23: 0 | L23: 20000000 | M23: 0 | O23: 5000000 | P23: 0
B24: Cash Draw | E24: =SUM(F24:BM24) -> 86000000 | F24: 43000000 | G24: 0 | H24: 0 | I24: 18000000 | J24: 0 | K24: 0 | L24: 20000000 | M24: 0 | O24: 5000000 | P24: 0
E25: =SUM(F25:BM25) -> 0
B26: Loan Payments | C26: LP | E26: =SUM(F26:BM26) -> 0 | AC26: 0 | AE26: 0 | AH26: 0 | AK26: 0 | AN26: 0 | AQ26: 0 | AT26: 0 | AW26: 0 | AZ26: 0 | BC26: 0
A29: Investment Costs
B30: Prepaid Expences | E30: =SUM(F30:BM30) -> 0 | F30: 0
B31: Past accumulatded Cost Pay Out | E31: =SUM(F31:BM31) -> 4200000 | F31: 4200000
B32: Consultant Introduction Fee | E32: =SUM(F32:BM32) -> 250000 | F32: 250000 | G32: 0 | H32: 0 | I32: 0 | J32: 0 | L32: 0 | O32: 0
B33: Interest (0.0% annual Interest) | D33: 0 | E33: =SUM(F33:BM33) -> 0 | O33: =-IPMT($D33/12,O6-$N6,$BM6-$N6,$F23,) -> 0 | P33: =-IPMT($D33/12,P6-$N6,$BM6-$N6,$F23,) -> 0 | Q33: =-IPMT($D33/12,Q6-$N6,$BM6-$N6,$F23,) -> 0 | R33: =-IPMT($D33/12,R6-$N6,$BM6-$N6,$F23,) -> 0 | S33: =-IPMT($D33/12,S6-$N6,$BM6-$N6,$F23,) -> 0 | T33: =-IPMT($D33/12,T6-$N6,$BM6-$N6,$F23,) -> 0 | U33: =-IPMT($D33/12,U6-$N6,$BM6-$N6,$F23,) -> 0 | V33: =-IPMT($D33/12,V6-$N6,$BM6-$N6,$F23,) -> 0 | ... BM33: =-IPMT($D33/12,BM6-$N6,$BM6-$N6,$F23,) -> 0
E34: =SUM(F34:BM34) -> 0 | AO34: =F25 -> 0
B35: Total Pre Development Costs | C35: C | D35: =E35/E23 -> 0.051744186 | E35: =SUM(F35:BM35) -> 4450000 | F35: =SUM(F30:F34) -> 4450000 | G35: =SUM(G30:G34) -> 0 | H35: =SUM(H30:H34) -> 0 | I35: =SUM(I30:I34) -> 0 | J35: =SUM(J30:J34) -> 0 | K35: =SUM(K30:K34) -> 0 | L35: =SUM(L30:L34) -> 0 | M35: =SUM(M30:M34) -> 0 | ... BM35: =SUM(BM30:BM34) -> 0
A37: Fulcrum Corporate Office ( Proportionate share to project)
B39: Executive Office (Edmonton)
B40: Fulcrum/FES - Office Equipment Security Expense (Furniture, Electronics, Software, Computers etc) * (PMT Plan) | E40: =SUM(F40:BM40) -> 0 | F40: 0 | G40: =F40 -> 0 | H40: =G40 -> 0 | I40: =H40 -> 0 | J40: =I40 -> 0 | K40: =J40 -> 0 | L40: =K40 -> 0 | M40: =L40 -> 0 | N40: =M40 -> 0 | ... Q40: =P40 -> 0
B41: Fulcrum - Auto Exp. | E41: =SUM(F41:BM41) -> 150000 | F41: 2500 | G41: =F41 -> 2500 | H41: =G41 -> 2500 | I41: =H41 -> 2500 | J41: =I41 -> 2500 | K41: =J41 -> 2500 | L41: =K41 -> 2500 | M41: =L41 -> 2500 | N41: =M41 -> 2500 | ... BM41: =BL41 -> 2500
B42: Fulcrum - Office Supplies | E42: =SUM(F42:BM42) -> 9000 | F42: 150 | G42: =F42 -> 150 | H42: =G42 -> 150 | I42: =H42 -> 150 | J42: =I42 -> 150 | K42: =J42 -> 150 | L42: =K42 -> 150 | M42: =L42 -> 150 | N42: =M42 -> 150 | ... BM42: =BL42 -> 150
B43: Fulcrum - Office Expenses | E43: =SUM(F43:BM43) -> 0 | F43: 0 | G43: =F43 -> 0 | H43: =G43 -> 0 | I43: =H43 -> 0 | J43: =I43 -> 0 | K43: =J43 -> 0 | L43: =K43 -> 0 | M43: =L43 -> 0 | N43: =M43 -> 0 | ... BM43: =BL43 -> 0
B44: Fulcrum - Salaries & Wages - Executive/ Administrative | E44: =SUM(F44:BM44) -> 3408000 | F44: 56800 | G44: =F44 -> 56800 | H44: =G44 -> 56800 | I44: =H44 -> 56800 | J44: =I44 -> 56800 | K44: =J44 -> 56800 | L44: =K44 -> 56800 | M44: =L44 -> 56800 | N44: =M44 -> 56800 | ... BM44: =BL44 -> 56800
B45: Fulcrum - Benefts | E45: =SUM(F45:BM45) -> 132000 | F45: 2200 | G45: =F45 -> 2200 | H45: =G45 -> 2200 | I45: =H45 -> 2200 | J45: =I45 -> 2200 | K45: =J45 -> 2200 | L45: =K45 -> 2200 | M45: =L45 -> 2200 | N45: =M45 -> 2200 | ... BM45: =BL45 -> 2200
B46: Fulcrum - Payroll Burden | E46: =SUM(F46:BM46) -> 708000 | F46: =SUM(F44:F45)*0.2 -> 11800 | G46: =F46 -> 11800 | H46: =G46 -> 11800 | I46: =H46 -> 11800 | J46: =I46 -> 11800 | K46: =J46 -> 11800 | L46: =K46 -> 11800 | M46: =L46 -> 11800 | N46: =M46 -> 11800 | ... BM46: =BL46 -> 11800
B47: Fulcrum - Office Rent Inc. CAC Costs | E47: =SUM(F47:BM47) -> 450000 | F47: 7500 | G47: =F47 -> 7500 | H47: =G47 -> 7500 | I47: =H47 -> 7500 | J47: =I47 -> 7500 | K47: =J47 -> 7500 | L47: =K47 -> 7500 | M47: =L47 -> 7500 | N47: =M47 -> 7500 | ... BM47: =BL47 -> 7500
B48: Fulcrum - Security Expense | E48: =SUM(F48:BM48) -> 0 | F48: 0 | G48: =F48 -> 0 | H48: =G48 -> 0 | I48: =H48 -> 0 | J48: =I48 -> 0 | K48: =J48 -> 0 | L48: =K48 -> 0 | M48: =L48 -> 0 | N48: =M48 -> 0 | ... BM48: =BL48 -> 0
B49: Fulcrum - Utilities: Telephone & Internet | E49: =SUM(F49:BM49) -> 36000 | F49: 600 | G49: =F49 -> 600 | H49: =G49 -> 600 | I49: =H49 -> 600 | J49: =I49 -> 600 | K49: =J49 -> 600 | L49: =K49 -> 600 | M49: =L49 -> 600 | N49: =M49 -> 600 | ... BM49: =BL49 -> 600
B50: Fulcrum - Utilities: Gas | E50: =SUM(F50:BM50) -> 21000 | F50: 350 | G50: =F50 -> 350 | H50: =G50 -> 350 | I50: =H50 -> 350 | J50: =I50 -> 350 | K50: =J50 -> 350 | L50: =K50 -> 350 | M50: =L50 -> 350 | N50: =M50 -> 350 | ... BM50: =BL50 -> 350
B51: Fulcrum - Utilities:Electricity | E51: =SUM(F51:BM51) -> 45000 | F51: 750 | G51: =F51 -> 750 | H51: =G51 -> 750 | I51: =H51 -> 750 | J51: =I51 -> 750 | K51: =J51 -> 750 | L51: =K51 -> 750 | M51: =L51 -> 750 | N51: =M51 -> 750 | ... BM51: =BL51 -> 750
B52: Fulcrum - Utilities:Cell Phones | E52: =SUM(F52:BM52) -> 36000 | F52: 600 | G52: =F52 -> 600 | H52: =G52 -> 600 | I52: =H52 -> 600 | J52: =I52 -> 600 | K52: =J52 -> 600 | L52: =K52 -> 600 | M52: =L52 -> 600 | N52: =M52 -> 600 | ... BM52: =BL52 -> 600
B53: Fulcrum - Travel - Airfare | E53: =SUM(F53:BM53) -> 168000 | F53: 2800 | G53: =F53 -> 2800 | H53: =G53 -> 2800 | I53: =H53 -> 2800 | J53: =I53 -> 2800 | K53: =J53 -> 2800 | L53: =K53 -> 2800 | M53: =L53 -> 2800 | N53: =M53 -> 2800 | ... BM53: =BL53 -> 2800
B54: Fulcrum - Travel - Meals & Entertainment - 100 % | E54: =SUM(F54:BM54) -> 72000 | F54: 1200 | G54: =F54 -> 1200 | H54: =G54 -> 1200 | I54: =H54 -> 1200 | J54: =I54 -> 1200 | K54: =J54 -> 1200 | L54: =K54 -> 1200 | M54: =L54 -> 1200 | N54: =M54 -> 1200 | ... BM54: =BL54 -> 1200
B55: Fulcrum - Travel - Lodging | E55: =SUM(F55:BM55) -> 108000 | F55: 1800 | G55: =F55 -> 1800 | H55: =G55 -> 1800 | I55: =H55 -> 1800 | J55: =I55 -> 1800 | K55: =J55 -> 1800 | L55: =K55 -> 1800 | M55: =L55 -> 1800 | N55: =M55 -> 1800 | ... BM55: =BL55 -> 1800
B56: Fulcrum - Travel - Car Expense | E56: =SUM(F56:BM56) -> 48000 | F56: 800 | G56: =F56 -> 800 | H56: =G56 -> 800 | I56: =H56 -> 800 | J56: =I56 -> 800 | K56: =J56 -> 800 | L56: =K56 -> 800 | M56: =L56 -> 800 | N56: =M56 -> 800 | ... BM56: =BL56 -> 800
B57: Fulcrum - Meals & Entertainment - 50% | E57: =SUM(F57:BM57) -> 12000 | F57: 200 | G57: =F57 -> 200 | H57: =G57 -> 200 | I57: =H57 -> 200 | J57: =I57 -> 200 | K57: =J57 -> 200 | L57: =K57 -> 200 | M57: =L57 -> 200 | N57: =M57 -> 200 | ... BM57: =BL57 -> 200
B58: Fulcrum - Meals & Entertainment - 50% (Non Travel) | E58: =SUM(F58:BM58) -> 12000 | F58: 200 | G58: =F58 -> 200 | H58: =G58 -> 200 | I58: =H58 -> 200 | J58: =I58 -> 200 | K58: =J58 -> 200 | L58: =K58 -> 200 | M58: =L58 -> 200 | N58: =M58 -> 200 | ... BM58: =BL58 -> 200
... B62: Fulcrum - Commercial & Liability | E62: =SUM(F62:BM62) -> 24000 | F62: 400 | G62: =F62 -> 400 | H62: =G62 -> 400 | I62: =H62 -> 400 | J62: =I62 -> 400 | K62: =J62 -> 400 | L62: =K62 -> 400 | M62: =L62 -> 400 | N62: =M62 -> 400 | ... BM62: =BL62 -> 400
B63: Total Executive Office | C63: CAP | E63: =SUM(F63:BM63) -> 5475000 | F63: =SUM(F40:F62) -> 91250 | G63: =SUM(G40:G62) -> 91250 | H63: =SUM(H40:H62) -> 91250 | I63: =SUM(I40:I62) -> 91250 | J63: =SUM(J40:J62) -> 91250 | K63: =SUM(K40:K62) -> 91250 | L63: =SUM(L40:L62) -> 91250 | M63: =SUM(M40:M62) -> 91250 | ... BM63: =SUM(BM40:BM62) -> 91250
A65: FES , Texas
B66: Manufacturing Facility (Proportionate Share to Project)
B67: FES - Facilities Lease | E67: =SUM(F67:BM67) -> 450000 | F67: 7500 | G67: =F67 -> 7500 | H67: =G67 -> 7500 | I67: =H67 -> 7500 | J67: =I67 -> 7500 | K67: =J67 -> 7500 | L67: =K67 -> 7500 | M67: =L67 -> 7500 | N67: =M67 -> 7500 | ... BM67: =BL67 -> 7500
B68: FES - Auto (Site Truck) | E68: =SUM(F68:BM68) -> 69000 | F68: 1150 | G68: 1150 | H68: 1150 | I68: 1150 | J68: 1150 | K68: 1150 | L68: 1150 | M68: 1150 | N68: 1150 | O68: 1150 | P68: 1150 | Q68: 1150 | R68: 1150 | S68: 1150 | T68: 1150 | U68: 1150 | V68: 1150 | W68: 1150 | X68: 1150 | Y68: 1150 | Z68: 1150 | AA68: 1150 | AB68: 1150 | AC68: 1150 | AD68: 1150 | AE68: 1150 | AF68: 1150 | AG68: 1150 | AH68: 1150 | AI68: 1150 | AJ68: 1150 | AK68: 1150 | AL68: 1150 | AM68: 1150 | AN68: 1150 | AO68: 1150 | AP68: 1150 | AQ68: 1150 | AR68: 1150 | AS68: 1150 | AT68: 1150 | AU68: 1150 | AV68: 1150 | AW68: 1150 | AX68: 1150 | AY68: 1150 | AZ68: 1150 | BA68: 1150 | BB68: 1150 | BC68: 1150 | BD68: 1150 | BE68: 1150 | BF68: 1150 | BG68: 1150 | BH68: 1150 | BI68: 1150 | BJ68: 1150 | BK68: 1150 | BL68: 1150 | BM68: 1150
B69: FES - Vehicle Insurance | E69: =SUM(F69:BM69) -> 15600 | F69: 260 | G69: =F69 -> 260 | H69: =G69 -> 260 | I69: =H69 -> 260 | J69: =I69 -> 260 | K69: =J69 -> 260 | L69: =K69 -> 260 | M69: =L69 -> 260 | N69: =M69 -> 260 | ... BM69: =BL69 -> 260
B70: FES - Auto Mileage Expense | E70: =SUM(F70:BM70) -> 0 | F70: 0 | G70: =F70 -> 0 | H70: =G70 -> 0 | I70: =H70 -> 0 | J70: =I70 -> 0 | K70: =J70 -> 0 | L70: =K70 -> 0 | M70: =L70 -> 0 | N70: =M70 -> 0 | ... BM70: =BL70 -> 0
B71: FES - Auto Fuel Expense | E71: =SUM(F71:BM71) -> 0 | F71: 0 | G71: =F71 -> 0 | H71: =G71 -> 0 | I71: =H71 -> 0 | J71: =I71 -> 0 | K71: =J71 -> 0 | L71: =K71 -> 0 | M71: =L71 -> 0 | N71: =M71 -> 0 | ... BM71: =BL71 -> 0
B72: FES - Auto Insurance | E72: =SUM(F72:BM72) -> 0 | F72: 0 | G72: =F72 -> 0 | H72: =G72 -> 0 | I72: =H72 -> 0 | J72: =I72 -> 0 | K72: =J72 -> 0 | L72: =K72 -> 0 | M72: =L72 -> 0 | N72: =M72 -> 0 | ... BM72: =BL72 -> 0
B73: FES - Office Expense (Pens, paper, ink) | E73: =SUM(F73:BM73) -> 0 | F73: 0 | G73: =F73 -> 0 | H73: =G73 -> 0 | I73: =H73 -> 0 | J73: =I73 -> 0 | K73: =J73 -> 0 | L73: =K73 -> 0 | M73: =L73 -> 0 | N73: =M73 -> 0 | ... BM73: =BL73 -> 0
B74: FES - Equipment Service Agreement | E74: =SUM(F74:BM74) -> 0 | F74: 0 | G74: =F74 -> 0 | H74: =G74 -> 0 | I74: =H74 -> 0 | J74: =I74 -> 0 | K74: =J74 -> 0 | L74: =K74 -> 0 | M74: =L74 -> 0 | N74: =M74 -> 0 | ... BM74: =BL74 -> 0
B75: FES - Office Expense (Cleaning Supplies, Water, Coffee Etc) | E75: =SUM(F75:BM75) -> 4500 | F75: 75 | G75: =F75 -> 75 | H75: =G75 -> 75 | I75: =H75 -> 75 | J75: =I75 -> 75 | K75: =J75 -> 75 | L75: =K75 -> 75 | M75: =L75 -> 75 | N75: =M75 -> 75 | ... BM75: =BL75 -> 75
B76: FES - Fabrication Equipment Purchases | E76: =SUM(F76:BM76) -> 270000 | F76: 0 | G76: 100000 | H76: 0 | I76: =H76 -> 0 | J76: =I76 -> 0 | K76: 100000 | L76: 0 | M76: =L76 -> 0 | N76: 70000 | O76: 0 | P76: =O76 -> 0 | Q76: =P76 -> 0 | R76: =Q76 -> 0 | S76: =R76 -> 0 | T76: =S76 -> 0 | U76: =T76 -> 0 | V76: =U76 -> 0 | W76: =V76 -> 0 | ... BM76: =BL76 -> 0
B77: FES - Other / Misc Sundry | E77: =SUM(F77:BM77) -> 0 | F77: 0 | G77: =F77 -> 0 | H77: =G77 -> 0 | I77: =H77 -> 0 | J77: =I77 -> 0 | K77: =J77 -> 0 | L77: =K77 -> 0 | M77: =L77 -> 0 | N77: =M77 -> 0 | ... BM77: =BL77 -> 0
B78: FES - CTO | E78: =SUM(F78:BM78) -> 884000 | F78: 13000 | G78: =F78 -> 13000 | H78: =G78 -> 13000 | I78: =H78 -> 13000 | J78: =I78 -> 13000 | K78: =J78 -> 13000 | L78: =K78 -> 13000 | M78: 13000 | N78: 15000 | O78: =N78 -> 15000 | P78: =O78 -> 15000 | Q78: =P78 -> 15000 | R78: =Q78 -> 15000 | S78: =R78 -> 15000 | T78: =S78 -> 15000 | U78: =T78 -> 15000 | V78: =U78 -> 15000 | ... BM78: =BL78 -> 15000
B79: FES - Salaries and Wages (Admin/Reception) | E79: =SUM(F79:BM79) -> 240000 | F79: 4000 | G79: =F79 -> 4000 | H79: =G79 -> 4000 | I79: =H79 -> 4000 | J79: =I79 -> 4000 | K79: =J79 -> 4000 | L79: =K79 -> 4000 | M79: =L79 -> 4000 | N79: =M79 -> 4000 | ... BM79: =BL79 -> 4000
B80: FES - Salaries and Wages (Scope Writer) | E80: =SUM(F80:BM80) -> 472000 | G80: 8000 | H80: =G80 -> 8000 | I80: =H80 -> 8000 | J80: =I80 -> 8000 | K80: =J80 -> 8000 | L80: =K80 -> 8000 | M80: =L80 -> 8000 | N80: =M80 -> 8000 | O80: =N80 -> 8000 | ... BM80: =BL80 -> 8000
B81: FES - Salaries and Wages Burden (20%) | E81: =SUM(F81:BM81) -> 288800 | F81: =SUM(F78:F80)*0.2 -> 3400 | G81: =F81 -> 3400 | H81: =G81 -> 3400 | I81: =H81 -> 3400 | J81: =I81 -> 3400 | K81: =J81 -> 3400 | L81: =K81 -> 3400 | M81: =SUM(M78:M80)*0.2 -> 5000 | N81: =M81 -> 5000 | O81: =N81 -> 5000 | P81: =O81 -> 5000 | Q81: =P81 -> 5000 | R81: =Q81 -> 5000 | S81: =R81 -> 5000 | T81: =S81 -> 5000 | U81: =T81 -> 5000 | ... BM81: =BL81 -> 5000
B82: FES - Property Taxes | E82: =SUM(F82:BM82) -> 30000 | F82: 500 | G82: 500 | H82: 500 | I82: 500 | J82: =I82 -> 500 | K82: =J82 -> 500 | L82: =K82 -> 500 | M82: =L82 -> 500 | N82: =M82 -> 500 | O82: =N82 -> 500 | P82: =O82 -> 500 | Q82: =P82 -> 500 | ... BM82: =BL82 -> 500
B83: FES - Utilities: Security Expense | E83: =SUM(F83:BM83) -> 0 | F83: 0 | G83: =F83 -> 0 | H83: =G83 -> 0 | I83: =H83 -> 0 | J83: =I83 -> 0 | K83: =J83 -> 0 | L83: =K83 -> 0 | M83: =L83 -> 0 | N83: =M83 -> 0 | ... BM83: =BL83 -> 0
B84: FES - Utilities: Telephone & Internet | E84: =SUM(F84:BM84) -> 27000 | F84: 450 | G84: =F84 -> 450 | H84: =G84 -> 450 | I84: =H84 -> 450 | J84: =I84 -> 450 | K84: =J84 -> 450 | L84: =K84 -> 450 | M84: =L84 -> 450 | N84: =M84 -> 450 | ... BM84: =BL84 -> 450
B85: FES - Utilities: Gas | E85: =SUM(F85:BM85) -> 15000 | F85: 250 | G85: =F85 -> 250 | H85: =G85 -> 250 | I85: =H85 -> 250 | J85: =I85 -> 250 | K85: =J85 -> 250 | L85: =K85 -> 250 | M85: =L85 -> 250 | N85: =M85 -> 250 | ... BM85: =BL85 -> 250
B86: FES - Utilities: Electricity | E86: =SUM(F86:BM86) -> 96000 | F86: 1600 | G86: =F86 -> 1600 | H86: =G86 -> 1600 | I86: =H86 -> 1600 | J86: =I86 -> 1600 | K86: =J86 -> 1600 | L86: =K86 -> 1600 | M86: =L86 -> 1600 | N86: =M86 -> 1600 | ... BM86: =BL86 -> 1600
B87: FES - Utilities: Water | E87: =SUM(F87:BM87) -> 9000 | F87: 150 | G87: =F87 -> 150 | H87: =G87 -> 150 | I87: =H87 -> 150 | J87: =I87 -> 150 | K87: =J87 -> 150 | L87: =K87 -> 150 | M87: =L87 -> 150 | N87: =M87 -> 150 | ... BM87: =BL87 -> 150
B88: FES - Utilities Trash/Dumpster | E88: =SUM(F88:BM88) -> 12000 | F88: 200 | G88: =F88 -> 200 | H88: =G88 -> 200 | I88: =H88 -> 200 | J88: =I88 -> 200 | K88: =J88 -> 200 | L88: =K88 -> 200 | M88: =L88 -> 200 | N88: =M88 -> 200 | ... BM88: =BL88 -> 200
B89: FES - Courier & Shipping | E89: =SUM(F89:BM89) -> 24000 | F89: 400 | G89: =F89 -> 400 | H89: =G89 -> 400 | I89: =H89 -> 400 | J89: =I89 -> 400 | K89: =J89 -> 400 | L89: =K89 -> 400 | M89: =L89 -> 400 | N89: =M89 -> 400 | ... BM89: =BL89 -> 400
B90: FES - WCB & Insurance Costs | E90: =SUM(F90:BM90) -> 68700 | F90: 1145 | G90: =F90 -> 1145 | H90: =G90 -> 1145 | I90: =H90 -> 1145 | J90: =I90 -> 1145 | K90: =J90 -> 1145 | L90: =K90 -> 1145 | M90: =L90 -> 1145 | N90: =M90 -> 1145 | ... BM90: =BL90 -> 1145
B91: FES - Commercial & Liability | E91: =SUM(F91:BM91) -> 108000 | F91: 1800 | G91: =F91 -> 1800 | H91: =G91 -> 1800 | I91: =H91 -> 1800 | J91: =I91 -> 1800 | K91: =J91 -> 1800 | L91: =K91 -> 1800 | M91: =L91 -> 1800 | N91: =M91 -> 1800 | ... BM91: =BL91 -> 1800
B92: Total FES Shop & Operations | C92: CAP | E92: =SUM(F92:BM92) -> 3083600 | F92: =SUM(F67:F91) -> 35880 | G92: =SUM(G67:G91) -> 143880 | H92: =SUM(H67:H91) -> 43880 | I92: =SUM(I67:I91) -> 43880 | J92: =SUM(J67:J91) -> 43880 | K92: =SUM(K67:K91) -> 143880 | L92: =SUM(L67:L91) -> 43880 | M92: =SUM(M67:M91) -> 45480 | ... BM92: =SUM(BM67:BM91) -> 47480
A94: Project Management External)
B95: Project Controller / Auditor | E95: =SUM(F95:BM95) -> 309000 | F95: 13000 | G95: =F95 -> 13000 | H95: =G95 -> 13000 | I95: =H95 -> 13000 | J95: =I95 -> 13000 | K95: =J95 -> 13000 | L95: =K95 -> 13000 | M95: =L95 -> 13000 | N95: =M95 -> 13000 | O95: 6000 | P95: 6000 | Q95: 6000 | R95: 6000 | S95: 6000 | T95: 6000 | U95: 6000 | V95: 6000 | W95: 6000 | X95: 6000 | Y95: 6000 | Z95: 6000 | AA95: 6000 | AB95: 6000 | AC95: 6000 | AD95: 6000 | AE95: 6000 | AF95: 6000 | AG95: 6000 | AH95: 6000 | AI95: 6000 | AJ95: 6000 | AK95: 6000 | AL95: 6000 | AM95: 6000 | AN95: 6000 | AO95: 6000 | AP95: 6000 | AQ95: 6000 | AR95: 6000 | AS95: 6000 | AT95: 6000
B96: Construction Coodinator- Lexon | E96: =SUM(F96:BM96) -> 492000 | F96: 12000 | G96: =F96 -> 12000 | H96: =G96 -> 12000 | I96: =H96 -> 12000 | J96: =I96 -> 12000 | K96: =J96 -> 12000 | L96: =K96 -> 12000 | M96: =L96 -> 12000 | N96: =M96 -> 12000 | O96: 12000 | P96: 12000 | Q96: 12000 | R96: 12000 | S96: 12000 | T96: 12000 | U96: 12000 | V96: 12000 | W96: 12000 | X96: 12000 | Y96: 12000 | Z96: 12000 | AA96: 12000 | AB96: 12000 | AC96: 12000 | AD96: 12000 | AE96: 12000 | AF96: 12000 | AG96: 12000 | AH96: 12000 | AI96: 12000 | AJ96: 12000 | AK96: 12000 | AL96: 12000 | AM96: 12000 | AN96: 12000 | AO96: 12000 | AP96: 12000 | AQ96: 12000 | AR96: 12000 | AS96: 12000 | AT96: 12000
B97: Project Travel & Accomodation | E97: =SUM(F97:BM97) -> 82000 | F97: 2000 | G97: 2000 | H97: 2000 | I97: 2000 | J97: 2000 | K97: 2000 | L97: 2000 | M97: 2000 | N97: 2000 | O97: 2000 | P97: 2000 | Q97: 2000 | R97: 2000 | S97: 2000 | T97: 2000 | U97: 2000 | V97: 2000 | W97: 2000 | X97: 2000 | Y97: 2000 | Z97: 2000 | AA97: 2000 | AB97: 2000 | AC97: 2000 | AD97: 2000 | AE97: 2000 | AF97: 2000 | AG97: 2000 | AH97: 2000 | AI97: 2000 | AJ97: 2000 | AK97: 2000 | AL97: 2000 | AM97: 2000 | AN97: 2000 | AO97: 2000 | AP97: 2000 | AQ97: 2000 | AR97: 2000 | AS97: 2000 | AT97: 2000 | AU97: 0 | AV97: 0 | AW97: 0 | AX97: 0 | AY97: 0 | AZ97: 0 | BA97: 0 | BB97: 0 | BC97: 0 | BD97: 0 | BE97: 0 | BF97: 0 | BG97: 0 | BH97: 0 | BI97: 0 | BJ97: 0 | BK97: 0 | BL97: 0 | BM97: 0
B98: Total Project Management | C98: CAP | E98: =SUM(F98:BM98) -> 883000 | F98: =SUM(F95:F97) -> 27000 | G98: =SUM(G95:G97) -> 27000 | H98: =SUM(H95:H97) -> 27000 | I98: =SUM(I95:I97) -> 27000 | J98: =SUM(J95:J97) -> 27000 | K98: =SUM(K95:K97) -> 27000 | L98: =SUM(L95:L97) -> 27000 | M98: =SUM(M95:M97) -> 27000 | ... BM98: =SUM(BM95:BM97) -> 0
A100: Noble, Oklahoma Tire Processing Project
B101: Land and Permitting
B102: Property (20 acres @ $0.77/sq.ft) | E102: =SUM(F102:BM102) -> 670824 | G102: =20*43560*0.77 -> 670824 | H102: 0
B103: Closing costs & Road Crossing | E103: =SUM(F103:BM103) -> 110000 | F103: 0 | G103: 35000 | H103: 75000 | I103: 0
B104: Site Power U/G | E104: =SUM(F104:BM104) -> 96000 | F104: 0 | G104: 0 | H104: 96000 | I104: 0
B105: Fire Pond & Equipment | E105: =SUM(F105:BM105) -> 475000 | F105: 0 | H105: 250000 | I105: 225000 | J105: 0 | N105: 0
B106: Land Prep and Roads | E106: =SUM(F106:BM106) -> 800000 | F106: 0 | G106: 0 | H106: 175000 | I106: 250000 | J106: 150000 | K106: 225000 | L106: 0 | AD106: 0
B107: Developmemnt Permit/ Consultants Fees | E107: =SUM(F107:BM107) -> 150000 | F107: 0 | G107: 0 | H107: 65000 | I107: 35000 | J107: 50000 | AD107: 0
B108: Total Land & Permitting | C108: CAP | E108: =SUM(F108:BM108) -> 2301824 | F108: =SUM(F102:F107) -> 0 | G108: =SUM(G102:G107) -> 705824 | H108: =SUM(H102:H107) -> 661000 | I108: =SUM(I102:I107) -> 510000 | J108: =SUM(J102:J107) -> 200000 | K108: =SUM(K102:K107) -> 225000 | L108: =SUM(L102:L107) -> 0 | M108: =SUM(M102:M107) -> 0 | N108: =SUM(N102:N107) -> 0 | AD108: =SUM(AD102:AD107) -> 0 | AE108: =SUM(AE102:AE107) -> 0 | AF108: =SUM(AF102:AF107) -> 0 | AG108: =SUM(AG102:AG107) -> 0 | AH108: =SUM(AH102:AH107) -> 0 | AI108: =SUM(AI102:AI107) -> 0 | AJ108: =SUM(AJ102:AJ107) -> 0 | AK108: =SUM(AK102:AK107) -> 0 | AL108: =SUM(AL102:AL107) -> 0
B110: Project EPC - Lexon
B111: Site Works / Engineering Final | E111: =SUM(F111:BM111) -> 1975000 | F111: 250000 | G111: 250000 | H111: 300000 | I111: 350000 | J111: 250000 | K111: 275000 | L111: 150000 | M111: 150000 | AD111: 0 | AE111: 0 | AF111: 0 | AG111: 0 | AH111: 0 | AI111: 0
B112: UnderGround and Site Utilities | E112: =SUM(F112:BM112) -> 608510 | F112: 0 | G112: 0 | H112: 100000 | I112: 100000 | J112: 83510 | K112: 175000 | L112: 150000 | AD112: 0 | AE112: 0 | AF112: 0 | AG112: 0 | AH112: 0 | AI112: 0
B113: Warehouse 2 @10,000 Sq Ft | E113: =SUM(F113:BM113) -> 4775000 | F113: 0 | G113: 0 | H113: 850000 | I113: 200000 | J113: 225000 | K113: 250000 | L113: 300000 | M113: 200000 | N113: 250000 | O113: 150000 | P113: 150000 | Q113: 175000 | R113: 450000 | S113: 175000 | T113: 150000 | U113: 250000 | V113: 150000 | W113: 275000 | X113: 150000 | Y113: 175000 | Z113: 250000 | AD113: 0 | AE113: 0 | AF113: 0 | AG113: 0 | AH113: 0 | AI113: 0
B114: OfficeBuilding | E114: =SUM(F114:BM114) -> 1908000 | F114: 0 | G114: 0 | H114: 0 | I114: 100000 | J114: 100000 | K114: 150000 | L114: 250000 | M114: 300000 | N114: 250000 | O114: 250000 | P114: 208000 | Q114: 200000 | R114: 100000 | AD114: 0 | AE114: 0 | AF114: 0 | AG114: 0 | AH114: 0 | AI114: 0 | AJ114: 0 | AK114: 0 | AL114: 0
B115: Process Mechanical | E115: =SUM(F115:BM115) -> 4708000 | F115: 0 | G115: 450000 | H115: 350000 | I115: 300000 | J115: 250000 | K115: 250000 | L115: 208000 | M115: 200000 | N115: 350000 | O115: 250000 | P115: 175000 | Q115: 200000 | R115: 300000 | S115: 300000 | T115: 200000 | U115: 200000 | V115: 150000 | W115: 100000 | X115: 100000 | Y115: 125000 | Z115: 100000 | AA115: 150000 | AD115: 0 | AE115: 0 | AF115: 0 | AG115: 0 | AH115: 0 | AI115: 0 | AJ115: 0
B116: Process Civil | E116: =SUM(F116:BM116) -> 975000 | F116: 0 | G116: 250000 | H116: 250000 | I116: 150000 | J116: 100000 | K116: 75000 | L116: 50000 | M116: 50000 | N116: 50000 | AF116: 0 | AG116: 0 | AH116: 0 | AI116: 0 | AJ116: 0 | AK116: 0 | AL116: 0
B117: Chilled Water Plant | E117: =SUM(F117:BM117) -> 3150000 | G117: 450000 | H117: 0 | I117: 0 | J117: 450000 | K117: 0 | L117: 0 | M117: 450000 | N117: 0 | P117: 450000 | S117: 450000 | V117: 450000 | X117: 450000 | AD117: 0 | AE117: 0 | AF117: 0 | AG117: 0 | AH117: 0 | AI117: 0
...
