Workbook
Name FV: #REF!
Name FV: #REF!
Name FVV: #REF!
Name FVVV: #REF!

Sheet ModelDescription
A2: Economic Forecasting Model
A4: PLAN: | C4: Noble, OK 6 Processor Facility - Series A + Series B
B6: Main Assumptions / Planning Contingencies
B7: 1 | C7: Economics run for a period of 15 years
B8: =1+B7 -> 2 | C8: ="Crumb rubber purchase price assumed to be $"&Assumptions!$D$13&"/lb - market price is $.10-.15/lb" -> Crumb rubber purchase price assumed to be $0.1/lb - market price is $.10-.15/lb
B9: =1+B8 -> 3 | C9: Crumb rubber product assumed to have composition that allows for processing splits of 45% solvent/45% carbon black/10% process gas by weight
B10: =1+B9 -> 4 | C10: ="Solvent based on $"&Assumptions!$D$16&"/gal - competitive market price is approx. $10-18/gal" -> Solvent based on $8/gal - competitive market price is approx. $10-18/gal
B11: =1+B10 -> 5 | C11: ="Carbon Black based on $"&Assumptions!D17&"/lb - competitive market price is approx. $.55/lb+" -> Carbon Black based on $0.5/lb - competitive market price is approx. $.55/lb+
B12: =1+B11 -> 6 | C12: ="RNG is priced at $"&Assumptions!D18&"/MCF - wholesale market price fluctuates between $2-5/MCF" -> RNG is priced at $1.5/MCF - wholesale market price fluctuates between $2-5/MCF
B13: =1+B12 -> 7 | C13: Series A $15 unlocks 1 machine - for Series A specific finances, turn dial below to "1 Machine"; Series B $110M unlocks additional 5 machines and site buildout - for complete project finances, turn dial below to "6 Machine"
B14: =1+B13 -> 8 | C14: $125 Million in total used to purchase and develop land, carbon handling, gas handling, construct facilities and 6 TiPs processors and related storage with 10% project capex buffer; construction budget has 20% contingency built in; machine capex has 30% buffer
B15: =1+B14 -> 9 | C15: External Utility Expense Utilized on Operating Costs - Will be reduced by 95% utilizing own power generation and Gas from Process at full operation
B16: =1+B17 -> 11 | C16: 48 tons per day production for each TiPs unit; Total of 6 Processors at full operation
B17: =1+B15 -> 10 | C17: ="Plant availability is set at "&TEXT(Assumptions!D36,"0.0%")&", where operation capacity is expected to be 90%+" -> Plant availability is set at 0.0%, where operation capacity is expected to be 90%+
B18: =1+B16 -> 12 | C18: Capital assets are depreciated over 15 years; depreciation begins for machine 1 when it is operational; depreciation begins on machines 2-6 when machine 6 is operational
B19: =1+B18 -> 13 | C19: No shredding requirement as crumb feed is purchased from local supplier
B20: =1+B19 -> 14 | C20: Machine build time assumed to be 8 months; actual expected to be 5 months
B21: =1+B20 -> 15 | C21: Sensitivity Analysis performed on pricing for crumb rubber, carbon black, solvent, as well as personnel costs and product cut
C23: 1 Machine / 6 Machine Switch | D23: 1 Machine
C25: Economic Highlights (at the end of 15 years)
C26: Revenue | D26: =Economics!T7 -> 3.105788e+08
C27: EBITDA | D27: =Economics!T11 -> 1.8174581e+08
C28: Sales Margin | D28: =Economics!U9 -> 0.64389453
C29: Fixed Asset Value | D29: =Economics!R27 -> 1037487
C30: Investment | D30: =Economics!D20 -> 15000000
C31: Net Present Value (NPV) | D31: =Economics!R29 -> 14574636
C33: Internal Rate of Return (IRR) Year 5 - Series A Investment | D33: =Economics!H34 -> 0.19504061
C34: Internal Rate of Return (IRR) Year 15 - Series A Investment | D34: =Economics!R34 -> 0.38133255

Sheet Sheet5

Sheet Sheet6

Sheet Economics
A2: =ModelDescription!A2 -> Economic Forecasting Model
A3: =ModelDescription!C4 -> Noble, OK 6 Processor Facility - Series A + Series B
B5: Year | D5: =MthCashSum!F6 -> 2026 | E5: =D5+1 -> 2027 | F5: =E5+1 -> 2028 | G5: =F5+1 -> 2029 | H5: =G5+1 -> 2030 | I5: =H5+1 -> 2031 | J5: =I5+1 -> 2032 | K5: =J5+1 -> 2033 | L5: =K5+1 -> 2034 | ... R5: =Q5+1 -> 2040 | T5: Total
B6: Annual Period | D6: 1 | E6: =D6+1 -> 2 | F6: =E6+1 -> 3 | G6: =F6+1 -> 4 | H6: =G6+1 -> 5 | I6: =H6+1 -> 6 | J6: =I6+1 -> 7 | K6: =J6+1 -> 8 | L6: =K6+1 -> 9 | ... R6: =Q6+1 -> 15
B7: Revenue Forward | C7: R | D7: {=SUMPRODUCT((D$39:D$82)*($C$39:$C$82=$C7))} -> 8947438.7 | E7: {=SUMPRODUCT((E$39:E$82)*($C$39:$C$82=$C7))} -> 21545097 | F7: =SUMPRODUCT((F$39:F$82)*($C$39:$C$82=$C7)) -> 21545097 | G7: =SUMPRODUCT((G$39:G$82)*($C$39:$C$82=$C7)) -> 21545097 | H7: =SUMPRODUCT((H$39:H$82)*($C$39:$C$82=$C7)) -> 21545097 | I7: =SUMPRODUCT((I$39:I$82)*($C$39:$C$82=$C7)) -> 21545097 | J7: =SUMPRODUCT((J$39:J$82)*($C$39:$C$82=$C7)) -> 21545097 | K7: =SUMPRODUCT((K$39:K$82)*($C$39:$C$82=$C7)) -> 21545097 | L7: =SUMPRODUCT((L$39:L$82)*($C$39:$C$82=$C7)) -> 21545097 | M7: =SUMPRODUCT((M$39:M$82)*($C$39:$C$82=$C7)) -> 21545097 | ... R7: =SUMPRODUCT((R$39:R$82)*($C$39:$C$82=$C7)) -> 21545097 | T7: =SUM(D7:R7) -> 3.105788e+08
B8: Costs | C8: C | D8: {=-SUMPRODUCT((D$39:D$82)*($C$39:$C$82=$C8))} -> -3215165.3 | E8: =-SUMPRODUCT((E$39:E$82)*($C$39:$C$82=$C8)) -> -7670260.4 | F8: =-SUMPRODUCT((F$39:F$82)*($C$39:$C$82=$C8)) -> -7670260.4 | G8: =-SUMPRODUCT((G$39:G$82)*($C$39:$C$82=$C8)) -> -7670260.4 | H8: =-SUMPRODUCT((H$39:H$82)*($C$39:$C$82=$C8)) -> -7670260.4 | I8: =-SUMPRODUCT((I$39:I$82)*($C$39:$C$82=$C8)) -> -7670260.4 | J8: =-SUMPRODUCT((J$39:J$82)*($C$39:$C$82=$C8)) -> -7670260.4 | K8: =-SUMPRODUCT((K$39:K$82)*($C$39:$C$82=$C8)) -> -7670260.4 | L8: =-SUMPRODUCT((L$39:L$82)*($C$39:$C$82=$C8)) -> -7670260.4 | ... R8: =-SUMPRODUCT((R$39:R$82)*($C$39:$C$82=$C8)) -> -7670260.4 | T8: =SUM(D8:R8) -> -1.1059881e+08
B9: Job Profit | D9: =D7+D8 -> 5732273.4 | E9: =E7+E8 -> 13874837 | F9: =F7+F8 -> 13874837 | G9: =G7+G8 -> 13874837 | H9: =H7+H8 -> 13874837 | I9: =I7+I8 -> 13874837 | J9: =J7+J8 -> 13874837 | K9: =K7+K8 -> 13874837 | ... R9: =R7+R8 -> 13874837 | T9: =SUM(D9:R9) -> 1.9997999e+08 | U9: =T9/T7 -> 0.64389453
B10: Business Overhead | C10: O | D10: {=-SUMPRODUCT((D$39:D$82)*($C$39:$C$82=$C10))} -> -528333.66 | E10: =-SUMPRODUCT((E$39:E$82)*($C$39:$C$82=$C10)) -> -1264703.2 | F10: =-SUMPRODUCT((F$39:F$82)*($C$39:$C$82=$C10)) -> -1264703.2 | G10: =-SUMPRODUCT((G$39:G$82)*($C$39:$C$82=$C10)) -> -1264703.2 | H10: =-SUMPRODUCT((H$39:H$82)*($C$39:$C$82=$C10)) -> -1264703.2 | I10: =-SUMPRODUCT((I$39:I$82)*($C$39:$C$82=$C10)) -> -1264703.2 | J10: =-SUMPRODUCT((J$39:J$82)*($C$39:$C$82=$C10)) -> -1264703.2 | K10: =-SUMPRODUCT((K$39:K$82)*($C$39:$C$82=$C10)) -> -1264703.2 | L10: =-SUMPRODUCT((L$39:L$82)*($C$39:$C$82=$C10)) -> -1264703.2 | ... R10: =-SUMPRODUCT((R$39:R$82)*($C$39:$C$82=$C10)) -> -1264703.2 | T10: =SUM(D10:R10) -> -18234178 | U10: Margin
B11: Profit/Loss Earnings (EBITDA) | D11: =D9+D10 -> 5203939.8 | E11: =E9+E10 -> 12610134 | F11: =F9+F10 -> 12610134 | G11: =G9+G10 -> 12610134 | H11: =H9+H10 -> 12610134 | I11: =I9+I10 -> 12610134 | J11: =J9+J10 -> 12610134 | K11: =K9+K10 -> 12610134 | ... R11: =R9+R10 -> 12610134 | T11: =SUM(D11:R11) -> 1.8174581e+08
B13: Working Capital % per Rev | C13: =Assumptions!D6 -> 0.15 | D13: =D7*$C13 -> 1342115.8 | E13: =E7*$C13 -> 3231764.6 | F13: =F7*$C13 -> 3231764.6 | G13: =G7*$C13 -> 3231764.6 | H13: =H7*$C13 -> 3231764.6 | I13: =I7*$C13 -> 3231764.6 | J13: =J7*$C13 -> 3231764.6 | K13: =K7*$C13 -> 3231764.6 | ... R13: =R7*$C13 -> 3231764.6
B14: Tax Rate (tbd for region) | D14: =WACC!C18 -> 0.21 | E14: =D14 -> 0.21 | F14: =E14 -> 0.21 | G14: =F14 -> 0.21 | H14: =G14 -> 0.21 | I14: =H14 -> 0.21 | J14: =I14 -> 0.21 | K14: =J14 -> 0.21 | L14: =K14 -> 0.21 | ... R14: =Q14 -> 0.21
B15: After Tax Profit/Loss | D15: =IF(D11<0,D11,D11*(1-D14)) -> 4111112.4 | E15: =IF(E11<0,E11,E11*(1-E14)) -> 9962005.6 | F15: =IF(F11<0,F11,F11*(1-F14)) -> 9962005.6 | G15: =IF(G11<0,G11,G11*(1-G14)) -> 9962005.6 | H15: =IF(H11<0,H11,H11*(1-H14)) -> 9962005.6 | I15: =IF(I11<0,I11,I11*(1-I14)) -> 9962005.6 | J15: =IF(J11<0,J11,J11*(1-J14)) -> 9962005.6 | K15: =IF(K11<0,K11,K11*(1-K14)) -> 9962005.6 | ... R15: =IF(R11<0,R11,R11*(1-R14)) -> 9962005.6 | T15: =SUM(D15:R15) -> 1.4357919e+08
B17: Capital Costs | C17: CAP | D17: {=-SUMPRODUCT((D$39:D$82)*($C$39:$C$82=$C17))} -> -15843457 | E17: =-SUMPRODUCT((E$39:E$82)*($C$39:$C$82=$C17)) -> 0 | F17: =-SUMPRODUCT((F$39:F$82)*($C$39:$C$82=$C17)) -> 0 | G17: =-SUMPRODUCT((G$39:G$82)*($C$39:$C$82=$C17)) -> 0 | H17: =-SUMPRODUCT((H$39:H$82)*($C$39:$C$82=$C17)) -> 0 | I17: =-SUMPRODUCT((I$39:I$82)*($C$39:$C$82=$C17)) -> 0 | J17: =-SUMPRODUCT((J$39:J$82)*($C$39:$C$82=$C17)) -> 0 | K17: =-SUMPRODUCT((K$39:K$82)*($C$39:$C$82=$C17)) -> 0 | L17: =-SUMPRODUCT((L$39:L$82)*($C$39:$C$82=$C17)) -> 0 | ... R17: =-SUMPRODUCT((R$39:R$82)*($C$39:$C$82=$C17)) -> 0 | T17: =SUM(D17:R17) -> -15843457
B18: Depreciation | C18: DEP | D18: {=SUMPRODUCT((D$39:D$59)*($C$39:$C$59=$C18))} -> 18743.479 | E18: {=SUMPRODUCT((E$39:E$59)*($C$39:$C$59=$C18))} -> 1056230.4 | F18: {=SUMPRODUCT((F$39:F$59)*($C$39:$C$59=$C18))} -> 1056230.4 | G18: {=SUMPRODUCT((G$39:G$59)*($C$39:$C$59=$C18))} -> 1056230.4 | H18: {=SUMPRODUCT((H$39:H$59)*($C$39:$C$59=$C18))} -> 1056230.4 | I18: {=SUMPRODUCT((I$39:I$59)*($C$39:$C$59=$C18))} -> 1056230.4 | J18: {=SUMPRODUCT((J$39:J$59)*($C$39:$C$59=$C18))} -> 1056230.4 | K18: {=SUMPRODUCT((K$39:K$59)*($C$39:$C$59=$C18))} -> 1056230.4 | ... R18: {=SUMPRODUCT((R$39:R$59)*($C$39:$C$59=$C18))} -> 1056230.4 | T18: =SUM(D18:R18) -> 14805970
B19: Change in Working Capital | D19: =-D13 -> -1342115.8 | E19: =D13-E13 -> -1889648.8 | F19: =E13-F13 -> 0 | G19: =F13-G13 -> 0 | H19: =G13-H13 -> 0 | I19: =H13-I13 -> 0 | J19: =I13-J13 -> 0 | K19: =J13-K13 -> 0 | L19: =K13-L13 -> 0 | ... R19: =Q13-R13 -> 0
B20: Investment | D20: =Proforma!E10 -> 15000000
B21: Free Cash Flow | D21: =SUM(D15:D19) -> -13055716 | E21: =SUM(E15:E19) -> 9128587.3 | F21: =SUM(F15:F19) -> 11018236 | G21: =SUM(G15:G19) -> 11018236 | H21: =SUM(H15:H19) -> 11018236 | I21: =SUM(I15:I19) -> 11018236 | J21: =SUM(J15:J19) -> 11018236 | K21: =SUM(K15:K19) -> 11018236 | ... R21: =SUM(R15:R19) -> 11018236 | T21: =SUM(D21:R21) -> 1.3930994e+08
B23: Discount Rate (WACC) | D23: =WACC!C23 -> 0.2 | E23: =D23 -> 0.2 | F23: =E23 -> 0.2 | G23: =F23 -> 0.2 | H23: =G23 -> 0.2 | I23: =H23 -> 0.2 | J23: =I23 -> 0.2 | K23: =J23 -> 0.2 | L23: =K23 -> 0.2 | ... R23: =Q23 -> 0.2
B24: Discounted Cash Flow | D24: =D21/(1+D23)^D6 -> -10879764 | E24: =E21/(1+E23)^E6 -> 6339296.7 | F24: =F21/(1+F23)^F6 -> 6376294 | G24: =G21/(1+G23)^G6 -> 5313578.3 | H24: =H21/(1+H23)^H6 -> 4427982 | I24: =I21/(1+I23)^I6 -> 3689985 | J24: =J21/(1+J23)^J6 -> 3074987.5 | K24: =K21/(1+K23)^K6 -> 2562489.6 | ... R24: =R21/(1+R23)^R6 -> 715143.81
B25: Multiple on earnings (3yr avg) | C25: 5 | F25: =AVERAGE(D11:F11)*$C25 -> 50707012 | G25: =AVERAGE(E11:G11)*$C25 -> 63050668 | H25: =AVERAGE(F11:H11)*$C25 -> 63050668 | I25: =AVERAGE(G11:I11)*$C25 -> 63050668 | J25: =AVERAGE(H11:J11)*$C25 -> 63050668 | K25: =AVERAGE(I11:K11)*$C25 -> 63050668 | L25: =AVERAGE(J11:L11)*$C25 -> 63050668 | M25: =AVERAGE(K11:M11)*$C25 -> 63050668 | ... R25: =AVERAGE(P11:R11)*$C25 -> 63050668
B27: Fixed Assets | D27: =SUM($D44:D44)-SUM($D46:D46) -> 15824713 | E27: =SUM($D44:E44)-SUM($D46:E46) -> 14768483 | F27: =SUM($D44:F44)-SUM($D46:F46) -> 13712252 | G27: =SUM($D44:G44)-SUM($D46:G46) -> 12656022 | H27: =SUM($D44:H44)-SUM($D46:H46) -> 11599791 | I27: =SUM($D44:I44)-SUM($D46:I46) -> 10543561 | J27: =SUM($D44:J44)-SUM($D46:J46) -> 9487330.5 | K27: =SUM($D44:K44)-SUM($D46:K46) -> 8431100 | ... R27: =SUM($D44:R44)-SUM($D46:R46) -> 1037487
B28: Investment | D28: =D20 -> 15000000 | E28: =E20 -> 0 | F28: =F20 -> 0 | G28: =G20 -> 0 | H28: =H20 -> 0 | I28: =I20 -> 0 | J28: =J20 -> 0 | K28: =K20 -> 0 | ... R28: =R20 -> 0
B29: Project NPV | H29: =NPV(0.1,D24:H24) -> 6517671.9 | R29: =NPV(0.1,D24:R24) -> 14574636
B30: Project IRR | G30: Project IRR | H30: =IRR(D21:H21,0.1) -> 0.67926385 | Q30: Project IRR | R30: =IRR(D21:R21,0.1) -> 0.78024157
B32: Series A Investor Equity | D32: =IF(ModelDescription!$D$23="On", IF(ROUNDUP((AVERAGE(Assumptions!$B$82:$B$88)+Assumptions!$D$33)/12, 0)>Economics!D$6, Assumptions!$D$25, Assumptions!$D$30), Assumptions!$D$25) -> 0.5 | E32: =IF(ModelDescription!$D$23=Assumptions!$E$28, IF(ROUNDUP((AVERAGE(Assumptions!$B$82:$B$88)+Assumptions!$D$33)/12, 0)>Economics!E$6, Assumptions!$D$25, Assumptions!$D$30), Assumptions!$D$25) -> 0.5 | F32: =IF(ModelDescription!$D$23=Assumptions!$E$28, IF(ROUNDUP((AVERAGE(Assumptions!$B$82:$B$88)+Assumptions!$D$33)/12, 0)>Economics!F$6, Assumptions!$D$25, Assumptions!$D$30), Assumptions!$D$25) -> 0.5 | G32: =IF(ModelDescription!$D$23=Assumptions!$E$28, IF(ROUNDUP((AVERAGE(Assumptions!$B$82:$B$88)+Assumptions!$D$33)/12, 0)>Economics!G$6, Assumptions!$D$25, Assumptions!$D$30), Assumptions!$D$25) -> 0.5 | H32: =IF(ModelDescription!$D$23=Assumptions!$E$28, IF(ROUNDUP((AVERAGE(Assumptions!$B$82:$B$88)+Assumptions!$D$33)/12, 0)>Economics!H$6, Assumptions!$D$25, Assumptions!$D$30), Assumptions!$D$25) -> 0.5 | I32: =IF(ModelDescription!$D$23=Assumptions!$E$28, IF(ROUNDUP((AVERAGE(Assumptions!$B$82:$B$88)+Assumptions!$D$33)/12, 0)>Economics!I$6, Assumptions!$D$25, Assumptions!$D$30), Assumptions!$D$25) -> 0.5 | J32: =IF(ModelDescription!$D$23=Assumptions!$E$28, IF(ROUNDUP((AVERAGE(Assumptions!$B$82:$B$88)+Assumptions!$D$33)/12, 0)>Economics!J$6, Assumptions!$D$25, Assumptions!$D$30), Assumptions!$D$25) -> 0.5 | K32: =IF(ModelDescription!$D$23=Assumptions!$E$28, IF(ROUNDUP((AVERAGE(Assumptions!$B$82:$B$88)+Assumptions!$D$33)/12, 0)>Economics!K$6, Assumptions!$D$25, Assumptions!$D$30), Assumptions!$D$25) -> 0.5 | L32: =IF(ModelDescription!$D$23=Assumptions!$E$28, IF(ROUNDUP((AVERAGE(Assumptions!$B$82:$B$88)+Assumptions!$D$33)/12, 0)>Economics!L$6, Assumptions!$D$25, Assumptions!$D$30), Assumptions!$D$25) -> 0.5 | ... R32: =IF(ModelDescription!$D$23=Assumptions!$E$28, IF(ROUNDUP((AVERAGE(Assumptions!$B$82:$B$88)+Assumptions!$D$33)/12, 0)>Economics!R$6, Assumptions!$D$25, Assumptions!$D$30), Assumptions!$D$25) -> 0.5
B33: Series A Investor Cash Flow | D33: =D$32*(D15+D18+D19)-Proforma!$F$26 -> -13606130 | E33: =E$32*(E15+E18+E19) -> 4564293.6 | F33: =F$32*(F15+F18+F19) -> 5509118 | G33: =G$32*(G15+G18+G19) -> 5509118 | H33: =H$32*(H15+H18+H19) -> 5509118 | I33: =I$32*(I15+I18+I19) -> 5509118 | J33: =J$32*(J15+J18+J19) -> 5509118 | K33: =K$32*(K15+K18+K19) -> 5509118 | L33: =L$32*(L15+L18+L19) -> 5509118 | ... R33: =R$32*(R15+R18+R19) -> 5509118
B34: Series A Investor IRR | G34: IRR | H34: =IRR(D33:H33) -> 0.19504061 | Q34: IRR | R34: =IRR(D33:R33) -> 0.38133255
B36: NOPAT | D36: =(D40-D42-D43-D46)*(1-D14) -> 4096305.1 | E36: =(E40-E42-E43-E46)*(1-E14) -> 9127583.6 | F36: =(F40-F42-F43-F46)*(1-F14) -> 9127583.6 | G36: =(G40-G42-G43-G46)*(1-G14) -> 9127583.6 | H36: =(H40-H42-H43-H46)*(1-H14) -> 9127583.6 | I36: =(I40-I42-I43-I46)*(1-I14) -> 9127583.6 | J36: =(J40-J42-J43-J46)*(1-J14) -> 9127583.6 | K36: =(K40-K42-K43-K46)*(1-K14) -> 9127583.6 | ... R36: =(R40-R42-R43-R46)*(1-R14) -> 9127583.6
B37: ROIC | D37: =SUM($D36:D36)/SUM($D41:D41) -> 0.273087 | E37: =SUM($D36:E36)/SUM($D41:E41) -> 0.88159258 | F37: =SUM($D36:F36)/SUM($D41:F41) -> 1.4900981 | G37: =SUM($D36:G36)/SUM($D41:G41) -> 2.0986037 | H37: =SUM($D36:H36)/SUM($D41:H41) -> 2.7071093 | I37: =SUM($D36:I36)/SUM($D41:I41) -> 3.3156149 | J37: =SUM($D36:J36)/SUM($D41:J41) -> 3.9241204 | K37: =SUM($D36:K36)/SUM($D41:K41) -> 4.532626 | ... R37: =SUM($D36:R36)/SUM($D41:R41) -> 8.792165
A39: Summary Info
B40: Revenue | C40: R | D40: =SUM(MthCashSum!F9:Q9) -> 8947438.7 | E40: =SUM(MthCashSum!R9:AC9) -> 21545097 | F40: =SUM(MthCashSum!AD9:AO9) -> 21545097 | G40: =SUM(MthCashSum!AP9:BA9) -> 21545097 | H40: =SUM(MthCashSum!BB9:BM9) -> 21545097 | I40: =SUM(MthCashSum!BN9:BY9) -> 21545097 | J40: =SUM(MthCashSum!BZ9:CK9) -> 21545097 | K40: =SUM(MthCashSum!CL9:CW9) -> 21545097 | L40: =SUM(MthCashSum!CX9:DI9) -> 21545097 | M40: =SUM(MthCashSum!DJ9:DU9) -> 21545097 | N40: =SUM(MthCashSum!DV9:EG9) -> 21545097 | O40: =SUM(MthCashSum!EH9:ES9) -> 21545097 | P40: =SUM(MthCashSum!ET9:FE9) -> 21545097 | Q40: =SUM(MthCashSum!FF9:FQ9) -> 21545097 | R40: =SUM(MthCashSum!FR9:GC9) -> 21545097 | T40: =SUM(D40:R40) -> 3.105788e+08
B41: Investment | C41: L | D41: =SUM(MthCashSum!F10:Q10) -> 15000000 | E41: =SUM(MthCashSum!R10:AC10) -> 0 | F41: =SUM(MthCashSum!AD10:AO10) -> 0 | G41: =SUM(MthCashSum!AP10:BA10) -> 0 | H41: =SUM(MthCashSum!BB10:BM10) -> 0 | I41: =SUM(MthCashSum!BN10:BY10) -> 0 | J41: =SUM(MthCashSum!BZ10:CK10) -> 0 | K41: =SUM(MthCashSum!CL10:CW10) -> 0 | L41: =SUM(MthCashSum!CX10:DI10) -> 0 | M41: =SUM(MthCashSum!DJ10:DU10) -> 0 | N41: =SUM(MthCashSum!DV10:EG10) -> 0 | O41: =SUM(MthCashSum!EH10:ES10) -> 0 | P41: =SUM(MthCashSum!ET10:FE10) -> 0 | Q41: =SUM(MthCashSum!FF10:FQ10) -> 0 | R41: =SUM(MthCashSum!FR10:GC10) -> 0 | T41: =SUM(D41:R41) -> 15000000
B42: Costs | C42: C | D42: =SUM(MthCashSum!F11:Q11) -> 3215165.3 | E42: =SUM(MthCashSum!R11:AC11) -> 7670260.4 | F42: =SUM(MthCashSum!AD11:AO11) -> 7670260.4 | G42: =SUM(MthCashSum!AP11:BA11) -> 7670260.4 | H42: =SUM(MthCashSum!BB11:BM11) -> 7670260.4 | I42: =SUM(MthCashSum!BN11:BY11) -> 7670260.4 | J42: =SUM(MthCashSum!BZ11:CK11) -> 7670260.4 | K42: =SUM(MthCashSum!CL11:CW11) -> 7670260.4 | L42: =SUM(MthCashSum!CX11:DI11) -> 7670260.4 | M42: =SUM(MthCashSum!DJ11:DU11) -> 7670260.4 | N42: =SUM(MthCashSum!DV11:EG11) -> 7670260.4 | O42: =SUM(MthCashSum!EH11:ES11) -> 7670260.4 | P42: =SUM(MthCashSum!ET11:FE11) -> 7670260.4 | Q42: =SUM(MthCashSum!FF11:FQ11) -> 7670260.4 | R42: =SUM(MthCashSum!FR11:GC11) -> 7670260.4 | T42: =SUM(D42:R42) -> 1.1059881e+08
B43: Business Overhead | C43: O | D43: =SUM(MthCashSum!F12:Q12) -> 528333.66 | E43: =SUM(MthCashSum!R12:AC12) -> 1264703.2 | F43: =SUM(MthCashSum!AD12:AO12) -> 1264703.2 | G43: =SUM(MthCashSum!AP12:BA12) -> 1264703.2 | H43: =SUM(MthCashSum!BB12:BM12) -> 1264703.2 | I43: =SUM(MthCashSum!BN12:BY12) -> 1264703.2 | J43: =SUM(MthCashSum!BZ12:CK12) -> 1264703.2 | K43: =SUM(MthCashSum!CL12:CW12) -> 1264703.2 | L43: =SUM(MthCashSum!CX12:DI12) -> 1264703.2 | M43: =SUM(MthCashSum!DJ12:DU12) -> 1264703.2 | N43: =SUM(MthCashSum!DV12:EG12) -> 1264703.2 | O43: =SUM(MthCashSum!EH12:ES12) -> 1264703.2 | P43: =SUM(MthCashSum!ET12:FE12) -> 1264703.2 | Q43: =SUM(MthCashSum!FF12:FQ12) -> 1264703.2 | R43: =SUM(MthCashSum!FR12:GC12) -> 1264703.2 | T43: =SUM(D43:R43) -> 18234178
B44: Capital Costs | C44: CAP | D44: =SUM(MthCashSum!F13:Q13) -> 15843457 | E44: =SUM(MthCashSum!R13:AC13) -> 0 | F44: =SUM(MthCashSum!AD13:AO13) -> 0 | G44: =SUM(MthCashSum!AP13:BA13) -> 0 | H44: =SUM(MthCashSum!BB13:BM13) -> 0 | I44: =SUM(MthCashSum!BN13:BY13) -> 0 | J44: =SUM(MthCashSum!BZ13:CK13) -> 0 | K44: =SUM(MthCashSum!CL13:CW13) -> 0 | L44: =SUM(MthCashSum!CX13:DI13) -> 0 | M44: =SUM(MthCashSum!DJ13:DU13) -> 0 | N44: =SUM(MthCashSum!DV13:EG13) -> 0 | O44: =SUM(MthCashSum!EH13:ES13) -> 0 | P44: =SUM(MthCashSum!ET13:FE13) -> 0 | Q44: =SUM(MthCashSum!FF13:FQ13) -> 0 | R44: =SUM(MthCashSum!FR13:GC13) -> 0 | T44: =SUM(D44:R44) -> 15843457
B45: Loan Payment | C45: C | D45: =SUM(MthCashSum!F14:Q14) -> 0 | E45: =SUM(MthCashSum!R14:AC14) -> 0 | F45: =SUM(MthCashSum!AD14:AO14) -> 0 | G45: =SUM(MthCashSum!AP14:BA14) -> 0 | H45: =SUM(MthCashSum!BB14:BM14) -> 0 | I45: =SUM(MthCashSum!BN14:BY14) -> 0 | J45: =SUM(MthCashSum!BZ14:CK14) -> 0 | K45: =SUM(MthCashSum!CL14:CW14) -> 0 | L45: =SUM(MthCashSum!CX14:DI14) -> 0 | M45: =SUM(MthCashSum!DJ14:DU14) -> 0 | N45: =SUM(MthCashSum!DV14:EG14) -> 0 | O45: =SUM(MthCashSum!EH14:ES14) -> 0 | P45: =SUM(MthCashSum!ET14:FE14) -> 0 | Q45: =SUM(MthCashSum!FF14:FQ14) -> 0 | R45: =SUM(MthCashSum!FR14:GC14) -> 0 | T45: =SUM(D45:R45) -> 0
B46: Depreciation | C46: DEP | D46: =SUM(MthCashSum!F15:Q15) -> 18743.479 | E46: =SUM(MthCashSum!R15:AC15) -> 1056230.4 | F46: =SUM(MthCashSum!AD15:AO15) -> 1056230.4 | G46: =SUM(MthCashSum!AP15:BA15) -> 1056230.4 | H46: =SUM(MthCashSum!BB15:BM15) -> 1056230.4 | I46: =SUM(MthCashSum!BN15:BY15) -> 1056230.4 | J46: =SUM(MthCashSum!BZ15:CK15) -> 1056230.4 | K46: =SUM(MthCashSum!CL15:CW15) -> 1056230.4 | L46: =SUM(MthCashSum!CX15:DI15) -> 1056230.4 | M46: =SUM(MthCashSum!DJ15:DU15) -> 1056230.4 | N46: =SUM(MthCashSum!DV15:EG15) -> 1056230.4 | O46: =SUM(MthCashSum!EH15:ES15) -> 1056230.4 | P46: =SUM(MthCashSum!ET15:FE15) -> 1056230.4 | Q46: =SUM(MthCashSum!FF15:FQ15) -> 1056230.4 | R46: =SUM(MthCashSum!FR15:GC15) -> 1056230.4 | T46: =SUM(D46:R46) -> 14805970
A48: Production Info
B49: Equivalent tires processed | D49: =SUM(Proforma!F133:Q133) -> 685440 | E49: =SUM(Proforma!R133:AC133) -> 1635200 | F49: =SUM(Proforma!AD133:AO133) -> 1635200 | G49: =SUM(Proforma!AP133:BA133) -> 1635200 | H49: =SUM(Proforma!BB133:BM133) -> 1635200 | I49: =SUM(Proforma!BN133:BY133) -> 1635200 | J49: =SUM(Proforma!BZ133:CK133) -> 1635200 | K49: =SUM(Proforma!CL133:CW133) -> 1635200 | L49: =SUM(Proforma!CX133:DI133) -> 1635200 | M49: =SUM(Proforma!DJ133:DU133) -> 1635200 | N49: =SUM(Proforma!DV133:EG133) -> 1635200 | O49: =SUM(Proforma!EH133:ES133) -> 1635200 | P49: =SUM(Proforma!ET133:FE133) -> 1635200 | Q49: =SUM(Proforma!FF133:FQ133) -> 1635200 | R49: =SUM(Proforma!FR133:GC133) -> 1635200 | T49: =SUM(D49:R49) -> 23578240
B50: Solvent (gallons) | D50: =SUM(Proforma!F144:Q144) -> 740275.2 | E50: =SUM(Proforma!R144:AC144) -> 1766016 | F50: =SUM(Proforma!AD144:AO144) -> 1766016 | G50: =SUM(Proforma!AP144:BA144) -> 1766016 | H50: =SUM(Proforma!BB144:BM144) -> 1766016 | I50: =SUM(Proforma!BN144:BY144) -> 1766016 | J50: =SUM(Proforma!BZ144:CK144) -> 1766016 | K50: =SUM(Proforma!CL144:CW144) -> 1766016 | L50: =SUM(Proforma!CX144:DI144) -> 1766016 | M50: =SUM(Proforma!DJ144:DU144) -> 1766016 | N50: =SUM(Proforma!DV144:EG144) -> 1766016 | O50: =SUM(Proforma!EH144:ES144) -> 1766016 | P50: =SUM(Proforma!ET144:FE144) -> 1766016 | Q50: =SUM(Proforma!FF144:FQ144) -> 1766016 | R50: =SUM(Proforma!FR144:GC144) -> 1766016 | T50: =SUM(D50:R50) -> 25464499
B51: Carbon Black (lbs) | D51: =SUM(Proforma!F145:Q145) -> 5552064 | E51: =SUM(Proforma!R145:AC145) -> 13245120 | F51: =SUM(Proforma!AD145:AO145) -> 13245120 | G51: =SUM(Proforma!AP145:BA145) -> 13245120 | H51: =SUM(Proforma!BB145:BM145) -> 13245120 | I51: =SUM(Proforma!BN145:BY145) -> 13245120 | J51: =SUM(Proforma!BZ145:CK145) -> 13245120 | K51: =SUM(Proforma!CL145:CW145) -> 13245120 | L51: =SUM(Proforma!CX145:DI145) -> 13245120 | M51: =SUM(Proforma!DJ145:DU145) -> 13245120 | N51: =SUM(Proforma!DV145:EG145) -> 13245120 | O51: =SUM(Proforma!EH145:ES145) -> 13245120 | P51: =SUM(Proforma!ET145:FE145) -> 13245120 | Q51: =SUM(Proforma!FF145:FQ145) -> 13245120 | R51: =SUM(Proforma!FR145:GC145) -> 13245120 | T51: =SUM(D51:R51) -> 190983744
B52: Gas Production (MCF) | D52: =SUM(Proforma!F146:Q146) -> 166136.74 | E52: =SUM(Proforma!R146:AC146) -> 529606.2 | F52: =SUM(Proforma!AD146:AO146) -> 529606.2 | G52: =SUM(Proforma!AP146:BA146) -> 529606.2 | H52: =SUM(Proforma!BB146:BM146) -> 529606.2 | I52: =SUM(Proforma!BN146:BY146) -> 529606.2 | J52: =SUM(Proforma!BZ146:CK146) -> 529606.2 | K52: =SUM(Proforma!CL146:CW146) -> 529606.2 | L52: =SUM(Proforma!CX146:DI146) -> 529606.2 | M52: =SUM(Proforma!DJ146:DU146) -> 529606.2 | N52: =SUM(Proforma!DV146:EG146) -> 529606.2 | O52: =SUM(Proforma!EH146:ES146) -> 529606.2 | P52: =SUM(Proforma!ET146:FE146) -> 529606.2 | Q52: =SUM(Proforma!FF146:FQ146) -> 529606.2 | R52: =SUM(Proforma!FR146:GC146) -> 529606.2 | T52: =SUM(D52:R52) -> 7580623.5
A54: Commodity Sales
B55: Solvent (gallons) | D55: =D50*Assumptions!$D$16 -> 5922201.6 | E55: =E50*Assumptions!$D$16 -> 14128128 | F55: =F50*Assumptions!$D$16 -> 14128128 | G55: =G50*Assumptions!$D$16 -> 14128128 | H55: =H50*Assumptions!$D$16 -> 14128128 | I55: =I50*Assumptions!$D$16 -> 14128128 | J55: =J50*Assumptions!$D$16 -> 14128128 | K55: =K50*Assumptions!$D$16 -> 14128128 | ... R55: =R50*Assumptions!$D$16 -> 14128128 | T55: =SUM(D55:R55) -> 2.0371599e+08
B56: Carbon Black (lbs) | D56: =D51*Assumptions!$D$17 -> 2776032 | E56: =E51*Assumptions!$D$17 -> 6622560 | F56: =F51*Assumptions!$D$17 -> 6622560 | G56: =G51*Assumptions!$D$17 -> 6622560 | H56: =H51*Assumptions!$D$17 -> 6622560 | I56: =I51*Assumptions!$D$17 -> 6622560 | J56: =J51*Assumptions!$D$17 -> 6622560 | K56: =K51*Assumptions!$D$17 -> 6622560 | ... R56: =R51*Assumptions!$D$17 -> 6622560 | T56: =SUM(D56:R56) -> 95491872
B57: Gas Production (MCF) | D57: =D52*Assumptions!$D$18 -> 249205.11 | E57: =E52*Assumptions!$D$18 -> 794409.3 | F57: =F52*Assumptions!$D$18 -> 794409.3 | G57: =G52*Assumptions!$D$18 -> 794409.3 | H57: =H52*Assumptions!$D$18 -> 794409.3 | I57: =I52*Assumptions!$D$18 -> 794409.3 | J57: =J52*Assumptions!$D$18 -> 794409.3 | K57: =K52*Assumptions!$D$18 -> 794409.3 | ... R57: =R52*Assumptions!$D$18 -> 794409.3 | T57: =SUM(D57:R57) -> 11370935

Sheet Proforma
A2: =ModelDescription!A2 -> Economic Forecasting Model
A3: =ModelDescription!C4 -> Noble, OK 6 Processor Facility - Series A + Series B
B5: Period | F5: =Assumptions!D76 -> 1 | G5: =Assumptions!E76 -> 2 | H5: =Assumptions!F76 -> 3 | I5: =Assumptions!G76 -> 4 | J5: =Assumptions!H76 -> 5 | K5: =Assumptions!I76 -> 6 | L5: =Assumptions!J76 -> 7 | M5: =Assumptions!K76 -> 8 | ... GC5: =Assumptions!GA76 -> 180
B6: Year | F6: =Assumptions!D77 -> 2026 | G6: =Assumptions!E77 -> 2026 | H6: =Assumptions!F77 -> 2026 | I6: =Assumptions!G77 -> 2026 | J6: =Assumptions!H77 -> 2026 | K6: =Assumptions!I77 -> 2026 | L6: =Assumptions!J77 -> 2026 | M6: =Assumptions!K77 -> 2026 | ... GC6: =Assumptions!GA77 -> 2040
B7: Month | F7: =Assumptions!D78 -> Jan | G7: =Assumptions!E78 -> Feb | H7: =Assumptions!F78 -> Mar | I7: =Assumptions!G78 -> Apr | J7: =Assumptions!H78 -> May | K7: =Assumptions!I78 -> Jun | L7: =Assumptions!J78 -> Jul | M7: =Assumptions!K78 -> Aug | ... GC7: =Assumptions!GA78 -> Dec
B8: Days | F8: =Assumptions!D80 -> 31 | G8: =Assumptions!E80 -> 28 | H8: =Assumptions!F80 -> 31 | I8: =Assumptions!G80 -> 30 | J8: =Assumptions!H80 -> 31 | K8: =Assumptions!I80 -> 30 | L8: =Assumptions!J80 -> 31 | M8: =Assumptions!K80 -> 31 | ... GC8: =Assumptions!GA80 -> 31
B9: Revenue | C9: R | E9: =SUM(F9:GC9) -> 3.105788e+08 | F9: {=SUMPRODUCT((F$25:F$162)*($C$25:$C$162=$C9))} -> 0 | G9: {=SUMPRODUCT((G$25:G$162)*($C$25:$C$162=$C9))} -> 0 | H9: {=SUMPRODUCT((H$25:H$162)*($C$25:$C$162=$C9))} -> 0 | I9: {=SUMPRODUCT((I$25:I$162)*($C$25:$C$162=$C9))} -> 0 | J9: {=SUMPRODUCT((J$25:J$162)*($C$25:$C$162=$C9))} -> 0 | K9: {=SUMPRODUCT((K$25:K$162)*($C$25:$C$162=$C9))} -> 0 | L9: {=SUMPRODUCT((L$25:L$162)*($C$25:$C$162=$C9))} -> 0 | M9: {=SUMPRODUCT((M$25:M$162)*($C$25:$C$162=$C9))} -> 1762387.2 | ... GC9: {=SUMPRODUCT((GC$25:GC$162)*($C$25:$C$162=$C9))} -> 1829857.6
B10: Capital Investment ( Loan) | C10: L | E10: =SUM(F10:GC10) -> 15000000 | F10: {=SUMPRODUCT((F$25:F$162)*($C$25:$C$162=$C10))} -> 15000000 | G10: {=SUMPRODUCT((G$25:G$162)*($C$25:$C$162=$C10))} -> 0 | H10: {=SUMPRODUCT((H$25:H$162)*($C$25:$C$162=$C10))} -> 0 | I10: {=SUMPRODUCT((I$25:I$162)*($C$25:$C$162=$C10))} -> 0 | J10: {=SUMPRODUCT((J$25:J$162)*($C$25:$C$162=$C10))} -> 0 | K10: {=SUMPRODUCT((K$25:K$162)*($C$25:$C$162=$C10))} -> 0 | L10: {=SUMPRODUCT((L$25:L$162)*($C$25:$C$162=$C10))} -> 0 | M10: {=SUMPRODUCT((M$25:M$162)*($C$25:$C$162=$C10))} -> 0 | ... GC10: {=SUMPRODUCT((GC$25:GC$162)*($C$25:$C$162=$C10))} -> 0
B11: Costs | C11: C | E11: =SUM(F11:GC11) -> 1.1059881e+08 | F11: {=SUMPRODUCT((F$25:F$162)*($C$25:$C$162=$C11))} -> 0 | G11: {=SUMPRODUCT((G$25:G$162)*($C$25:$C$162=$C11))} -> 0 | H11: {=SUMPRODUCT((H$25:H$162)*($C$25:$C$162=$C11))} -> 0 | I11: {=SUMPRODUCT((I$25:I$162)*($C$25:$C$162=$C11))} -> 0 | J11: {=SUMPRODUCT((J$25:J$162)*($C$25:$C$162=$C11))} -> 0 | K11: {=SUMPRODUCT((K$25:K$162)*($C$25:$C$162=$C11))} -> 0 | L11: {=SUMPRODUCT((L$25:L$162)*($C$25:$C$162=$C11))} -> 0 | M11: {=SUMPRODUCT((M$25:M$162)*($C$25:$C$162=$C11))} -> 651421.46 | ... GC11: {=SUMPRODUCT((GC$25:GC$162)*($C$25:$C$162=$C11))} -> 651421.46
B12: Business Overhead | C12: O | E12: =SUM(F12:GC12) -> 18234178 | F12: {=SUMPRODUCT((F$25:F$162)*($C$25:$C$162=$C12))} -> 0 | G12: {=SUMPRODUCT((G$25:G$162)*($C$25:$C$162=$C12))} -> 0 | H12: {=SUMPRODUCT((H$25:H$162)*($C$25:$C$162=$C12))} -> 0 | I12: {=SUMPRODUCT((I$25:I$162)*($C$25:$C$162=$C12))} -> 0 | J12: {=SUMPRODUCT((J$25:J$162)*($C$25:$C$162=$C12))} -> 0 | K12: {=SUMPRODUCT((K$25:K$162)*($C$25:$C$162=$C12))} -> 0 | L12: {=SUMPRODUCT((L$25:L$162)*($C$25:$C$162=$C12))} -> 0 | M12: {=SUMPRODUCT((M$25:M$162)*($C$25:$C$162=$C12))} -> 106266.3 | ... GC12: {=SUMPRODUCT((GC$25:GC$162)*($C$25:$C$162=$C12))} -> 106266.3
B13: Capital Costs | C13: CAP | E13: =SUM(F13:GC13) -> 15843457 | F13: {=SUMPRODUCT((F$25:F$162)*($C$25:$C$162=$C13))} -> 6697158.3 | G13: {=SUMPRODUCT((G$25:G$162)*($C$25:$C$162=$C13))} -> 3337788.9 | H13: {=SUMPRODUCT((H$25:H$162)*($C$25:$C$162=$C13))} -> 3077158.3 | I13: {=SUMPRODUCT((I$25:I$162)*($C$25:$C$162=$C13))} -> 735585.86 | J13: {=SUMPRODUCT((J$25:J$162)*($C$25:$C$162=$C13))} -> 398442.91 | K13: {=SUMPRODUCT((K$25:K$162)*($C$25:$C$162=$C13))} -> 553103.08 | L13: {=SUMPRODUCT((L$25:L$162)*($C$25:$C$162=$C13))} -> 510109.58 | M13: {=SUMPRODUCT((M$25:M$162)*($C$25:$C$162=$C13))} -> 510109.58 | ... GC13: {=SUMPRODUCT((GC$25:GC$162)*($C$25:$C$162=$C13))} -> 0
B14: Loan Payment | C14: LP | E14: =SUM(F14:GC14) -> 0 | F14: {=SUMPRODUCT((F$25:F$162)*($C$25:$C$162=$C14))} -> 0 | G14: {=SUMPRODUCT((G$25:G$162)*($C$25:$C$162=$C14))} -> 0 | H14: {=SUMPRODUCT((H$25:H$162)*($C$25:$C$162=$C14))} -> 0 | I14: {=SUMPRODUCT((I$25:I$162)*($C$25:$C$162=$C14))} -> 0 | J14: {=SUMPRODUCT((J$25:J$162)*($C$25:$C$162=$C14))} -> 0 | K14: {=SUMPRODUCT((K$25:K$162)*($C$25:$C$162=$C14))} -> 0 | L14: {=SUMPRODUCT((L$25:L$162)*($C$25:$C$162=$C14))} -> 0 | M14: {=SUMPRODUCT((M$25:M$162)*($C$25:$C$162=$C14))} -> 0 | ... GC14: {=SUMPRODUCT((GC$25:GC$162)*($C$25:$C$162=$C14))} -> 0
B15: Depreciation | C15: DEP | E15: =SUM(F15:GC15) -> 14805970 | F15: {=SUMPRODUCT((F$25:F$162)*($C$25:$C$162=$C15))} -> 0 | G15: {=SUMPRODUCT((G$25:G$162)*($C$25:$C$162=$C15))} -> 0 | H15: {=SUMPRODUCT((H$25:H$162)*($C$25:$C$162=$C15))} -> 0 | I15: {=SUMPRODUCT((I$25:I$162)*($C$25:$C$162=$C15))} -> 0 | J15: {=SUMPRODUCT((J$25:J$162)*($C$25:$C$162=$C15))} -> 0 | K15: {=SUMPRODUCT((K$25:K$162)*($C$25:$C$162=$C15))} -> 0 | L15: {=SUMPRODUCT((L$25:L$162)*($C$25:$C$162=$C15))} -> 0 | M15: {=SUMPRODUCT((M$25:M$162)*($C$25:$C$162=$C15))} -> 0 | ... GC15: {=SUMPRODUCT((GC$25:GC$162)*($C$25:$C$162=$C15))} -> 88019.203
B16: Monthly Profit/Loss (EBITDA) | F16: =SUM(F9:F10)-SUM(F11:F14) -> 8302841.7 | G16: =SUM(G9:G10)-SUM(G11:G14) -> -3337788.9 | H16: =SUM(H9:H10)-SUM(H11:H14) -> -3077158.3 | I16: =SUM(I9:I10)-SUM(I11:I14) -> -735585.86 | J16: =SUM(J9:J10)-SUM(J11:J14) -> -398442.91 | K16: =SUM(K9:K10)-SUM(K11:K14) -> -553103.08 | L16: =SUM(L9:L10)-SUM(L11:L14) -> -510109.58 | M16: =SUM(M9:M10)-SUM(M11:M14) -> 494589.86 | ... GC16: =SUM(GC9:GC10)-SUM(GC11:GC14) -> 1072169.8
B17: Project Cumulative Cash Flow | F17: =E17+F16 -> 8302841.7 | G17: =F17+G16 -> 4965052.8 | H17: =G17+H16 -> 1887894.4 | I17: =H17+I16 -> 1152308.6 | J17: =I17+J16 -> 753865.66 | K17: =J17+K16 -> 200762.58 | L17: =K17+L16 -> -309347 | M17: =L17+M16 -> 185242.87 | ... GC17: =GB17+GC16 -> 1.8090235e+08
B21: Investment Rounds | F21: =IF(Assumptions!$D$24=Proforma!F5, Assumptions!$B$24, IF(AND(ModelDescription!$D$23=Assumptions!$E$28, Assumptions!$D$29=Proforma!F5), Assumptions!$B$29, "")) -> Series A | G21: =IF(Assumptions!$D$24=Proforma!G5, Assumptions!$B$24, IF(AND(ModelDescription!$D$23=Assumptions!$E$28, Assumptions!$D$29=Proforma!G5), Assumptions!$B$29, "")) | H21: =IF(Assumptions!$D$24=Proforma!H5, Assumptions!$B$24, IF(AND(ModelDescription!$D$23=Assumptions!$E$28, Assumptions!$D$29=Proforma!H5), Assumptions!$B$29, "")) | I21: =IF(Assumptions!$D$24=Proforma!I5, Assumptions!$B$24, IF(AND(ModelDescription!$D$23=Assumptions!$E$28, Assumptions!$D$29=Proforma!I5), Assumptions!$B$29, "")) | J21: =IF(Assumptions!$D$24=Proforma!J5, Assumptions!$B$24, IF(AND(ModelDescription!$D$23=Assumptions!$E$28, Assumptions!$D$29=Proforma!J5), Assumptions!$B$29, "")) | K21: =IF(Assumptions!$D$24=Proforma!K5, Assumptions!$B$24, IF(AND(ModelDescription!$D$23=Assumptions!$E$28, Assumptions!$D$29=Proforma!K5), Assumptions!$B$29, "")) | L21: =IF(Assumptions!$D$24=Proforma!L5, Assumptions!$B$24, IF(AND(ModelDescription!$D$23=Assumptions!$E$28, Assumptions!$D$29=Proforma!L5), Assumptions!$B$29, "")) | M21: =IF(Assumptions!$D$24=Proforma!M5, Assumptions!$B$24, IF(AND(ModelDescription!$D$23=Assumptions!$E$28, Assumptions!$D$29=Proforma!M5), Assumptions!$B$29, "")) | ... GC21: =IF(Assumptions!$D$24=Proforma!GC5, Assumptions!$B$24, IF(AND(ModelDescription!$D$23=Assumptions!$E$28, Assumptions!$D$29=Proforma!GC5), Assumptions!$B$29, ""))
B22: Plants Beginning Construction | F22: =COUNTIF(Assumptions!D81:D88, 1) -> 1 | G22: =COUNTIF(Assumptions!E81:E88, 1) -> 0 | H22: =COUNTIF(Assumptions!F81:F88, 1) -> 0 | I22: =COUNTIF(Assumptions!G81:G88, 1) -> 0 | J22: =COUNTIF(Assumptions!H81:H88, 1) -> 0 | K22: =COUNTIF(Assumptions!I81:I88, 1) -> 0 | L22: =COUNTIF(Assumptions!J81:J88, 1) -> 0 | M22: =COUNTIF(Assumptions!K81:K88, 1) -> 0 | ... GC22: =COUNTIF(Assumptions!GA81:GA88, 1) -> 0
B23: Number of Plants in Operation | F23: =E23+COUNTIF(Assumptions!D81:D88, Assumptions!$D$33) -> 0 | G23: =F23+COUNTIF(Assumptions!E81:E88, Assumptions!$D$33) -> 0 | H23: =G23+COUNTIF(Assumptions!F81:F88, Assumptions!$D$33) -> 0 | I23: =H23+COUNTIF(Assumptions!G81:G88, Assumptions!$D$33) -> 0 | J23: =I23+COUNTIF(Assumptions!H81:H88, Assumptions!$D$33) -> 0 | K23: =J23+COUNTIF(Assumptions!I81:I88, Assumptions!$D$33) -> 0 | L23: =K23+COUNTIF(Assumptions!J81:J88, Assumptions!$D$33) -> 0 | M23: =L23+COUNTIF(Assumptions!K81:K88, Assumptions!$D$33) -> 1 | ... GC23: =GB23+COUNTIF(Assumptions!GA81:GA88, Assumptions!$D$33) -> 1
A25: Project Capital
B26: Capital Investment USD | C26: L | E26: =SUM(F26:GC26) -> 15000000 | F26: =IF(F21="Series A", Assumptions!$D$23, IF(F21="Series B", Assumptions!$D$28, 0)) -> 15000000 | G26: =IF(G21="Series A", Assumptions!$D$23, IF(G21="Series B", Assumptions!$D$28, 0)) -> 0 | H26: =IF(H21="Series A", Assumptions!$D$23, IF(H21="Series B", Assumptions!$D$28, 0)) -> 0 | I26: =IF(I21="Series A", Assumptions!$D$23, IF(I21="Series B", Assumptions!$D$28, 0)) -> 0 | J26: =IF(J21="Series A", Assumptions!$D$23, IF(J21="Series B", Assumptions!$D$28, 0)) -> 0 | K26: =IF(K21="Series A", Assumptions!$D$23, IF(K21="Series B", Assumptions!$D$28, 0)) -> 0 | L26: =IF(L21="Series A", Assumptions!$D$23, IF(L21="Series B", Assumptions!$D$28, 0)) -> 0 | M26: =IF(M21="Series A", Assumptions!$D$23, IF(M21="Series B", Assumptions!$D$28, 0)) -> 0 | ... GC26: =IF(GC21="Series A", Assumptions!$D$23, IF(GC21="Series B", Assumptions!$D$28, 0)) -> 0
A28: Total Capital Costs
B30: Equipment & Materials | E30: =SUM(F30:GC30) -> 7290598 | F30: =SUM(_xlfn.IFNA(_xlfn.XLOOKUP(Assumptions!D$81, '1 Machine Build'!$F$11:$Q$11, '1 Machine Build'!$F12:$Q12), 0), _xlfn.IFNA(_xlfn.XLOOKUP(Assumptions!D$82, '1 Machine Build'!$F$11:$Q$11, '1 Machine Build'!$F12:$Q12), 0), _xlfn.IFNA(_xlfn.XLOOKUP(Assumptions!D$83, '1 Machine Build'!$F$11:$Q$11, '1 Machine Build'!$F12:$Q12), 0), _xlfn.IFNA(_xlfn.XLOOKUP(Assumptions!D$84, '1 Machine Build'!$F$11:$Q$11, '1 Machine Build'!$F12:$Q12), 0), _xlfn.IFNA(_xlfn.XLOOKUP(Assumptions!D$85, '1 Machine Build'!$F$11:$Q$11, '1 Machine Build'!$F12:$Q12), 0), _xlfn.IFNA(_xlfn.XLOOKUP(Assumptions!D$86, '1 Machine Build'!$F$11:$Q$11, '1 Machine Build'!$F12:$Q12), 0), _xlfn.IFNA(_xlfn.XLOOKUP(Assumptions!D$87, '1 Machine Build'!$F$11:$Q$11, '1 Machine Build'!$F12:$Q12), 0), _xlfn.IFNA(_xlfn.XLOOKUP(Assumptions!D$88, '1 Machine Build'!$F$11:$Q$11, '1 Machine Build'!$F12:$Q12), 0)) -> 4200199.3 | G30: =SUM(_xlfn.IFNA(_xlfn.XLOOKUP(Assumptions!E$81, '1 Machine Build'!$F$11:$Q$11, '1 Machine Build'!$F12:$Q12), 0), _xlfn.IFNA(_xlfn.XLOOKUP(Assumptions!E$82, '1 Machine Build'!$F$11:$Q$11, '1 Machine Build'!$F12:$Q12), 0), _xlfn.IFNA(_xlfn.XLOOKUP(Assumptions!E$83, '1 Machine Build'!$F$11:$Q$11, '1 Machine Build'!$F12:$Q12), 0), _xlfn.IFNA(_xlfn.XLOOKUP(Assumptions!E$84, '1 Machine Build'!$F$11:$Q$11, '1 Machine Build'!$F12:$Q12), 0), _xlfn.IFNA(_xlfn.XLOOKUP(Assumptions!E$85, '1 Machine Build'!$F$11:$Q$11, '1 Machine Build'!$F12:$Q12), 0), _xlfn.IFNA(_xlfn.XLOOKUP(Assumptions!E$86, '1 Machine Build'!$F$11:$Q$11, '1 Machine Build'!$F12:$Q12), 0), _xlfn.IFNA(_xlfn.XLOOKUP(Assumptions!E$87, '1 Machine Build'!$F$11:$Q$11, '1 Machine Build'!$F12:$Q12), 0), _xlfn.IFNA(_xlfn.XLOOKUP(Assumptions!E$88, '1 Machine Build'!$F$11:$Q$11, '1 Machine Build'!$F12:$Q12), 0)) -> 1698949.3 | H30: =SUM(_xlfn.IFNA(_xlfn.XLOOKUP(Assumptions!F$81, '1 Machine Build'!$F$11:$Q$11, '1 Machine Build'!$F12:$Q12), 0), _xlfn.IFNA(_xlfn.XLOOKUP(Assumptions!F$82, '1 Machine Build'!$F$11:$Q$11, '1 Machine Build'!$F12:$Q12), 0), _xlfn.IFNA(_xlfn.XLOOKUP(Assumptions!F$83, '1 Machine Build'!$F$11:$Q$11, '1 Machine Build'!$F12:$Q12), 0), _xlfn.IFNA(_xlfn.XLOOKUP(Assumptions!F$84, '1 Machine Build'!$F$11:$Q$11, '1 Machine Build'!$F12:$Q12), 0), _xlfn.IFNA(_xlfn.XLOOKUP(Assumptions!F$85, '1 Machine Build'!$F$11:$Q$11, '1 Machine Build'!$F12:$Q12), 0), _xlfn.IFNA(_xlfn.XLOOKUP(Assumptions!F$86, '1 Machine Build'!$F$11:$Q$11, '1 Machine Build'!$F12:$Q12), 0), _xlfn.IFNA(_xlfn.XLOOKUP(Assumptions!F$87, '1 Machine Build'!$F$11:$Q$11, '1 Machine Build'!$F12:$Q12), 0), _xlfn.IFNA(_xlfn.XLOOKUP(Assumptions!F$88, '1 Machine Build'!$F$11:$Q$11, '1 Machine Build'!$F12:$Q12), 0)) -> 1391449.3 | I30: =SUM(_xlfn.IFNA(_xlfn.XLOOKUP(Assumptions!G$81, '1 Machine Build'!$F$11:$Q$11, '1 Machine Build'!$F12:$Q12), 0), _xlfn.IFNA(_xlfn.XLOOKUP(Assumptions!G$82, '1 Machine Build'!$F$11:$Q$11, '1 Machine Build'!$F12:$Q12), 0), _xlfn.IFNA(_xlfn.XLOOKUP(Assumptions!G$83, '1 Machine Build'!$F$11:$Q$11, '1 Machine Build'!$F12:$Q12), 0), _xlfn.IFNA(_xlfn.XLOOKUP(Assumptions!G$84, '1 Machine Build'!$F$11:$Q$11, '1 Machine Build'!$F12:$Q12), 0), _xlfn.IFNA(_xlfn.XLOOKUP(Assumptions!G$85, '1 Machine Build'!$F$11:$Q$11, '1 Machine Build'!$F12:$Q12), 0), _xlfn.IFNA(_xlfn.XLOOKUP(Assumptions!G$86, '1 Machine Build'!$F$11:$Q$11, '1 Machine Build'!$F12:$Q12), 0), _xlfn.IFNA(_xlfn.XLOOKUP(Assumptions!G$87, '1 Machine Build'!$F$11:$Q$11, '1 Machine Build'!$F12:$Q12), 0), _xlfn.IFNA(_xlfn.XLOOKUP(Assumptions!G$88, '1 Machine Build'!$F$11:$Q$11, '1 Machine Build'!$F12:$Q12), 0)) -> 0 | J30: =SUM(_xlfn.IFNA(_xlfn.XLOOKUP(Assumptions!H$81, '1 Machine Build'!$F$11:$Q$11, '1 Machine Build'!$F12:$Q12), 0), _xlfn.IFNA(_xlfn.XLOOKUP(Assumptions!H$82, '1 Machine Build'!$F$11:$Q$11, '1 Machine Build'!$F12:$Q12), 0), _xlfn.IFNA(_xlfn.XLOOKUP(Assumptions!H$83, '1 Machine Build'!$F$11:$Q$11, '1 Machine Build'!$F12:$Q12), 0), _xlfn.IFNA(_xlfn.XLOOKUP(Assumptions!H$84, '1 Machine Build'!$F$11:$Q$11, '1 Machine Build'!$F12:$Q12), 0), _xlfn.IFNA(_xlfn.XLOOKUP(Assumptions!H$85, '1 Machine Build'!$F$11:$Q$11, '1 Machine Build'!$F12:$Q12), 0), _xlfn.IFNA(_xlfn.XLOOKUP(Assumptions!H$86, '1 Machine Build'!$F$11:$Q$11, '1 Machine Build'!$F12:$Q12), 0), _xlfn.IFNA(_xlfn.XLOOKUP(Assumptions!H$87, '1 Machine Build'!$F$11:$Q$11, '1 Machine Build'!$F12:$Q12), 0), _xlfn.IFNA(_xlfn.XLOOKUP(Assumptions!H$88, '1 Machine Build'!$F$11:$Q$11, '1 Machine Build'!$F12:$Q12), 0)) -> 0 | K30: =SUM(_xlfn.IFNA(_xlfn.XLOOKUP(Assumptions!I$81, '1 Machine Build'!$F$11:$Q$11, '1 Machine Build'!$F12:$Q12), 0), _xlfn.IFNA(_xlfn.XLOOKUP(Assumptions!I$82, '1 Machine Build'!$F$11:$Q$11, '1 Machine Build'!$F12:$Q12), 0), _xlfn.IFNA(_xlfn.XLOOKUP(Assumptions!I$83, '1 Machine Build'!$F$11:$Q$11, '1 Machine Build'!$F12:$Q12), 0), _xlfn.IFNA(_xlfn.XLOOKUP(Assumptions!I$84, '1 Machine Build'!$F$11:$Q$11, '1 Machine Build'!$F12:$Q12), 0), _xlfn.IFNA(_xlfn.XLOOKUP(Assumptions!I$85, '1 Machine Build'!$F$11:$Q$11, '1 Machine Build'!$F12:$Q12), 0), _xlfn.IFNA(_xlfn.XLOOKUP(Assumptions!I$86, '1 Machine Build'!$F$11:$Q$11, '1 Machine Build'!$F12:$Q12), 0), _xlfn.IFNA(_xlfn.XLOOKUP(Assumptions!I$87, '1 Machine Build'!$F$11:$Q$11, '1 Machine Build'!$F12:$Q12), 0), _xlfn.IFNA(_xlfn.XLOOKUP(Assumptions!I$88, '1 Machine Build'!$F$11:$Q$11, '1 Machine Build'!$F12:$Q12), 0)) -> 0 | L30: =SUM(_xlfn.IFNA(_xlfn.XLOOKUP(Assumptions!J$81, '1 Machine Build'!$F$11:$Q$11, '1 Machine Build'!$F12:$Q12), 0), _xlfn.IFNA(_xlfn.XLOOKUP(Assumptions!J$82, '1 Machine Build'!$F$11:$Q$11, '1 Machine Build'!$F12:$Q12), 0), _xlfn.IFNA(_xlfn.XLOOKUP(Assumptions!J$83, '1 Machine Build'!$F$11:$Q$11, '1 Machine Build'!$F12:$Q12), 0), _xlfn.IFNA(_xlfn.XLOOKUP(Assumptions!J$84, '1 Machine Build'!$F$11:$Q$11, '1 Machine Build'!$F12:$Q12), 0), _xlfn.IFNA(_xlfn.XLOOKUP(Assumptions!J$85, '1 Machine Build'!$F$11:$Q$11, '1 Machine Build'!$F12:$Q12), 0), _xlfn.IFNA(_xlfn.XLOOKUP(Assumptions!J$86, '1 Machine Build'!$F$11:$Q$11, '1 Machine Build'!$F12:$Q12), 0), _xlfn.IFNA(_xlfn.XLOOKUP(Assumptions!J$87, '1 Machine Build'!$F$11:$Q$11, '1 Machine Build'!$F12:$Q12), 0), _xlfn.IFNA(_xlfn.XLOOKUP(Assumptions!J$88, '1 Machine Build'!$F$11:$Q$11, '1 Machine Build'!$F12:$Q12), 0)) -> 0 | M30: =SUM(_xlfn.IFNA(_xlfn.XLOOKUP(Assumptions!K$81, '1 Machine Build'!$F$11:$Q$11, '1 Machine Build'!$F12:$Q12), 0), _xlfn.IFNA(_xlfn.XLOOKUP(Assumptions!K$82, '1 Machine Build'!$F$11:$Q$11, '1 Machine Build'!$F12:$Q12), 0), _xlfn.IFNA(_xlfn.XLOOKUP(Assumptions!K$83, '1 Machine Build'!$F$11:$Q$11, '1 Machine Build'!$F12:$Q12), 0), _xlfn.IFNA(_xlfn.XLOOKUP(Assumptions!K$84, '1 Machine Build'!$F$11:$Q$11, '1 Machine Build'!$F12:$Q12), 0), _xlfn.IFNA(_xlfn.XLOOKUP(Assumptions!K$85, '1 Machine Build'!$F$11:$Q$11, '1 Machine Build'!$F12:$Q12), 0), _xlfn.IFNA(_xlfn.XLOOKUP(Assumptions!K$86, '1 Machine Build'!$F$11:$Q$11, '1 Machine Build'!$F12:$Q12), 0), _xlfn.IFNA(_xlfn.XLOOKUP(Assumptions!K$87, '1 Machine Build'!$F$11:$Q$11, '1 Machine Build'!$F12:$Q12), 0), _xlfn.IFNA(_xlfn.XLOOKUP(Assumptions!K$88, '1 Machine Build'!$F$11:$Q$11, '1 Machine Build'!$F12:$Q12), 0)) -> 0 | ... GC30: =SUM(_xlfn.IFNA(_xlfn.XLOOKUP(Assumptions!GA$81, '1 Machine Build'!$F$11:$Q$11, '1 Machine Build'!$F12:$Q12), 0), _xlfn.IFNA(_xlfn.XLOOKUP(Assumptions!GA$82, '1 Machine Build'!$F$11:$Q$11, '1 Machine Build'!$F12:$Q12), 0), _xlfn.IFNA(_xlfn.XLOOKUP(Assumptions!GA$83, '1 Machine Build'!$F$11:$Q$11, '1 Machine Build'!$F12:$Q12), 0), _xlfn.IFNA(_xlfn.XLOOKUP(Assumptions!GA$84, '1 Machine Build'!$F$11:$Q$11, '1 Machine Build'!$F12:$Q12), 0), _xlfn.IFNA(_xlfn.XLOOKUP(Assumptions!GA$85, '1 Machine Build'!$F$11:$Q$11, '1 Machine Build'!$F12:$Q12), 0), _xlfn.IFNA(_xlfn.XLOOKUP(Assumptions!GA$86, '1 Machine Build'!$F$11:$Q$11, '1 Machine Build'!$F12:$Q12), 0), _xlfn.IFNA(_xlfn.XLOOKUP(Assumptions!GA$87, '1 Machine Build'!$F$11:$Q$11, '1 Machine Build'!$F12:$Q12), 0), _xlfn.IFNA(_xlfn.XLOOKUP(Assumptions!GA$88, '1 Machine Build'!$F$11:$Q$11, '1 Machine Build'!$F12:$Q12), 0)) -> 0
B31: Facilities & Auxillary Support Systems | E31: =SUM(F31:GC31) -> 4697250 | F31: =SUM(_xlfn.IFNA(_xlfn.XLOOKUP(Assumptions!D$81, '1 Machine Build'!$F$11:$Q$11, '1 Machine Build'!$F13:$Q13), 0), _xlfn.IFNA(_xlfn.XLOOKUP(F$5, 'Site Construction Budget'!$E$13:$Z$13, 'Site Construction Budget'!$E$40:$Z$40), 0)) -> 1703250 | G31: =SUM(_xlfn.IFNA(_xlfn.XLOOKUP(Assumptions!E$81, '1 Machine Build'!$F$11:$Q$11, '1 Machine Build'!$F13:$Q13), 0), _xlfn.IFNA(_xlfn.XLOOKUP(G$5, 'Site Construction Budget'!$E$13:$Z$13, 'Site Construction Budget'!$E$40:$Z$40), 0)) -> 1309500 | H31: =SUM(_xlfn.IFNA(_xlfn.XLOOKUP(Assumptions!F$81, '1 Machine Build'!$F$11:$Q$11, '1 Machine Build'!$F13:$Q13), 0), _xlfn.IFNA(_xlfn.XLOOKUP(H$5, 'Site Construction Budget'!$E$13:$Z$13, 'Site Construction Budget'!$E$40:$Z$40), 0)) -> 1309500 | I31: =SUM(_xlfn.IFNA(_xlfn.XLOOKUP(Assumptions!G$81, '1 Machine Build'!$F$11:$Q$11, '1 Machine Build'!$F13:$Q13), 0), _xlfn.IFNA(_xlfn.XLOOKUP(I$5, 'Site Construction Budget'!$E$13:$Z$13, 'Site Construction Budget'!$E$40:$Z$40), 0)) -> 375000 | J31: =SUM(_xlfn.IFNA(_xlfn.XLOOKUP(Assumptions!H$81, '1 Machine Build'!$F$11:$Q$11, '1 Machine Build'!$F13:$Q13), 0), _xlfn.IFNA(_xlfn.XLOOKUP(J$5, 'Site Construction Budget'!$E$13:$Z$13, 'Site Construction Budget'!$E$40:$Z$40), 0)) -> 0 | K31: =SUM(_xlfn.IFNA(_xlfn.XLOOKUP(Assumptions!I$81, '1 Machine Build'!$F$11:$Q$11, '1 Machine Build'!$F13:$Q13), 0), _xlfn.IFNA(_xlfn.XLOOKUP(K$5, 'Site Construction Budget'!$E$13:$Z$13, 'Site Construction Budget'!$E$40:$Z$40), 0)) -> 0 | L31: =SUM(_xlfn.IFNA(_xlfn.XLOOKUP(Assumptions!J$81, '1 Machine Build'!$F$11:$Q$11, '1 Machine Build'!$F13:$Q13), 0), _xlfn.IFNA(_xlfn.XLOOKUP(L$5, 'Site Construction Budget'!$E$13:$Z$13, 'Site Construction Budget'!$E$40:$Z$40), 0)) -> 0 | M31: =SUM(_xlfn.IFNA(_xlfn.XLOOKUP(Assumptions!K$81, '1 Machine Build'!$F$11:$Q$11, '1 Machine Build'!$F13:$Q13), 0), _xlfn.IFNA(_xlfn.XLOOKUP(M$5, 'Site Construction Budget'!$E$13:$Z$13, 'Site Construction Budget'!$E$40:$Z$40), 0)) -> 0 | ... GC31: =SUM(_xlfn.IFNA(_xlfn.XLOOKUP(Assumptions!GA$81, '1 Machine Build'!$F$11:$Q$11, '1 Machine Build'!$F13:$Q13), 0), _xlfn.IFNA(_xlfn.XLOOKUP(GC$5, 'Site Construction Budget'!$E$13:$Z$13, 'Site Construction Budget'!$E$40:$Z$40), 0)) -> 0
B32: Operating Costs | E32: =SUM(F32:GC32) -> 714500 | F32: =SUM(_xlfn.IFNA(_xlfn.XLOOKUP(Assumptions!D$81, '1 Machine Build'!$F$11:$Q$11, '1 Machine Build'!$F14:$Q14), 0), _xlfn.IFNA(_xlfn.XLOOKUP(Assumptions!D$82, '1 Machine Build'!$F$11:$Q$11, '1 Machine Build'!$F14:$Q14), 0), _xlfn.IFNA(_xlfn.XLOOKUP(Assumptions!D$83, '1 Machine Build'!$F$11:$Q$11, '1 Machine Build'!$F14:$Q14), 0), _xlfn.IFNA(_xlfn.XLOOKUP(Assumptions!D$84, '1 Machine Build'!$F$11:$Q$11, '1 Machine Build'!$F14:$Q14), 0), _xlfn.IFNA(_xlfn.XLOOKUP(Assumptions!D$85, '1 Machine Build'!$F$11:$Q$11, '1 Machine Build'!$F14:$Q14), 0), _xlfn.IFNA(_xlfn.XLOOKUP(Assumptions!D$86, '1 Machine Build'!$F$11:$Q$11, '1 Machine Build'!$F14:$Q14), 0), _xlfn.IFNA(_xlfn.XLOOKUP(Assumptions!D$87, '1 Machine Build'!$F$11:$Q$11, '1 Machine Build'!$F14:$Q14), 0), _xlfn.IFNA(_xlfn.XLOOKUP(Assumptions!D$88, '1 Machine Build'!$F$11:$Q$11, '1 Machine Build'!$F14:$Q14), 0)) -> 85450 | G32: =SUM(_xlfn.IFNA(_xlfn.XLOOKUP(Assumptions!E$81, '1 Machine Build'!$F$11:$Q$11, '1 Machine Build'!$F14:$Q14), 0), _xlfn.IFNA(_xlfn.XLOOKUP(Assumptions!E$82, '1 Machine Build'!$F$11:$Q$11, '1 Machine Build'!$F14:$Q14), 0), _xlfn.IFNA(_xlfn.XLOOKUP(Assumptions!E$83, '1 Machine Build'!$F$11:$Q$11, '1 Machine Build'!$F14:$Q14), 0), _xlfn.IFNA(_xlfn.XLOOKUP(Assumptions!E$84, '1 Machine Build'!$F$11:$Q$11, '1 Machine Build'!$F14:$Q14), 0), _xlfn.IFNA(_xlfn.XLOOKUP(Assumptions!E$85, '1 Machine Build'!$F$11:$Q$11, '1 Machine Build'!$F14:$Q14), 0), _xlfn.IFNA(_xlfn.XLOOKUP(Assumptions!E$86, '1 Machine Build'!$F$11:$Q$11, '1 Machine Build'!$F14:$Q14), 0), _xlfn.IFNA(_xlfn.XLOOKUP(Assumptions!E$87, '1 Machine Build'!$F$11:$Q$11, '1 Machine Build'!$F14:$Q14), 0), _xlfn.IFNA(_xlfn.XLOOKUP(Assumptions!E$88, '1 Machine Build'!$F$11:$Q$11, '1 Machine Build'!$F14:$Q14), 0)) -> 27950 | H32: =SUM(_xlfn.IFNA(_xlfn.XLOOKUP(Assumptions!F$81, '1 Machine Build'!$F$11:$Q$11, '1 Machine Build'!$F14:$Q14), 0), _xlfn.IFNA(_xlfn.XLOOKUP(Assumptions!F$82, '1 Machine Build'!$F$11:$Q$11, '1 Machine Build'!$F14:$Q14), 0), _xlfn.IFNA(_xlfn.XLOOKUP(Assumptions!F$83, '1 Machine Build'!$F$11:$Q$11, '1 Machine Build'!$F14:$Q14), 0), _xlfn.IFNA(_xlfn.XLOOKUP(Assumptions!F$84, '1 Machine Build'!$F$11:$Q$11, '1 Machine Build'!$F14:$Q14), 0), _xlfn.IFNA(_xlfn.XLOOKUP(Assumptions!F$85, '1 Machine Build'!$F$11:$Q$11, '1 Machine Build'!$F14:$Q14), 0), _xlfn.IFNA(_xlfn.XLOOKUP(Assumptions!F$86, '1 Machine Build'!$F$11:$Q$11, '1 Machine Build'!$F14:$Q14), 0), _xlfn.IFNA(_xlfn.XLOOKUP(Assumptions!F$87, '1 Machine Build'!$F$11:$Q$11, '1 Machine Build'!$F14:$Q14), 0), _xlfn.IFNA(_xlfn.XLOOKUP(Assumptions!F$88, '1 Machine Build'!$F$11:$Q$11, '1 Machine Build'!$F14:$Q14), 0)) -> 27950 | I32: =SUM(_xlfn.IFNA(_xlfn.XLOOKUP(Assumptions!G$81, '1 Machine Build'!$F$11:$Q$11, '1 Machine Build'!$F14:$Q14), 0), _xlfn.IFNA(_xlfn.XLOOKUP(Assumptions!G$82, '1 Machine Build'!$F$11:$Q$11, '1 Machine Build'!$F14:$Q14), 0), _xlfn.IFNA(_xlfn.XLOOKUP(Assumptions!G$83, '1 Machine Build'!$F$11:$Q$11, '1 Machine Build'!$F14:$Q14), 0), _xlfn.IFNA(_xlfn.XLOOKUP(Assumptions!G$84, '1 Machine Build'!$F$11:$Q$11, '1 Machine Build'!$F14:$Q14), 0), _xlfn.IFNA(_xlfn.XLOOKUP(Assumptions!G$85, '1 Machine Build'!$F$11:$Q$11, '1 Machine Build'!$F14:$Q14), 0), _xlfn.IFNA(_xlfn.XLOOKUP(Assumptions!G$86, '1 Machine Build'!$F$11:$Q$11, '1 Machine Build'!$F14:$Q14), 0), _xlfn.IFNA(_xlfn.XLOOKUP(Assumptions!G$87, '1 Machine Build'!$F$11:$Q$11, '1 Machine Build'!$F14:$Q14), 0), _xlfn.IFNA(_xlfn.XLOOKUP(Assumptions!G$88, '1 Machine Build'!$F$11:$Q$11, '1 Machine Build'!$F14:$Q14), 0)) -> 27950 | J32: =SUM(_xlfn.IFNA(_xlfn.XLOOKUP(Assumptions!H$81, '1 Machine Build'!$F$11:$Q$11, '1 Machine Build'!$F14:$Q14), 0), _xlfn.IFNA(_xlfn.XLOOKUP(Assumptions!H$82, '1 Machine Build'!$F$11:$Q$11, '1 Machine Build'!$F14:$Q14), 0), _xlfn.IFNA(_xlfn.XLOOKUP(Assumptions!H$83, '1 Machine Build'!$F$11:$Q$11, '1 Machine Build'!$F14:$Q14), 0), _xlfn.IFNA(_xlfn.XLOOKUP(Assumptions!H$84, '1 Machine Build'!$F$11:$Q$11, '1 Machine Build'!$F14:$Q14), 0), _xlfn.IFNA(_xlfn.XLOOKUP(Assumptions!H$85, '1 Machine Build'!$F$11:$Q$11, '1 Machine Build'!$F14:$Q14), 0), _xlfn.IFNA(_xlfn.XLOOKUP(Assumptions!H$86, '1 Machine Build'!$F$11:$Q$11, '1 Machine Build'!$F14:$Q14), 0), _xlfn.IFNA(_xlfn.XLOOKUP(Assumptions!H$87, '1 Machine Build'!$F$11:$Q$11, '1 Machine Build'!$F14:$Q14), 0), _xlfn.IFNA(_xlfn.XLOOKUP(Assumptions!H$88, '1 Machine Build'!$F$11:$Q$11, '1 Machine Build'!$F14:$Q14), 0)) -> 27950 | K32: =SUM(_xlfn.IFNA(_xlfn.XLOOKUP(Assumptions!I$81, '1 Machine Build'!$F$11:$Q$11, '1 Machine Build'!$F14:$Q14), 0), _xlfn.IFNA(_xlfn.XLOOKUP(Assumptions!I$82, '1 Machine Build'!$F$11:$Q$11, '1 Machine Build'!$F14:$Q14), 0), _xlfn.IFNA(_xlfn.XLOOKUP(Assumptions!I$83, '1 Machine Build'!$F$11:$Q$11, '1 Machine Build'!$F14:$Q14), 0), _xlfn.IFNA(_xlfn.XLOOKUP(Assumptions!I$84, '1 Machine Build'!$F$11:$Q$11, '1 Machine Build'!$F14:$Q14), 0), _xlfn.IFNA(_xlfn.XLOOKUP(Assumptions!I$85, '1 Machine Build'!$F$11:$Q$11, '1 Machine Build'!$F14:$Q14), 0), _xlfn.IFNA(_xlfn.XLOOKUP(Assumptions!I$86, '1 Machine Build'!$F$11:$Q$11, '1 Machine Build'!$F14:$Q14), 0), _xlfn.IFNA(_xlfn.XLOOKUP(Assumptions!I$87, '1 Machine Build'!$F$11:$Q$11, '1 Machine Build'!$F14:$Q14), 0), _xlfn.IFNA(_xlfn.XLOOKUP(Assumptions!I$88, '1 Machine Build'!$F$11:$Q$11, '1 Machine Build'!$F14:$Q14), 0)) -> 204016.67 | L32: =SUM(_xlfn.IFNA(_xlfn.XLOOKUP(Assumptions!J$81, '1 Machine Build'!$F$11:$Q$11, '1 Machine Build'!$F14:$Q14), 0), _xlfn.IFNA(_xlfn.XLOOKUP(Assumptions!J$82, '1 Machine Build'!$F$11:$Q$11, '1 Machine Build'!$F14:$Q14), 0), _xlfn.IFNA(_xlfn.XLOOKUP(Assumptions!J$83, '1 Machine Build'!$F$11:$Q$11, '1 Machine Build'!$F14:$Q14), 0), _xlfn.IFNA(_xlfn.XLOOKUP(Assumptions!J$84, '1 Machine Build'!$F$11:$Q$11, '1 Machine Build'!$F14:$Q14), 0), _xlfn.IFNA(_xlfn.XLOOKUP(Assumptions!J$85, '1 Machine Build'!$F$11:$Q$11, '1 Machine Build'!$F14:$Q14), 0), _xlfn.IFNA(_xlfn.XLOOKUP(Assumptions!J$86, '1 Machine Build'!$F$11:$Q$11, '1 Machine Build'!$F14:$Q14), 0), _xlfn.IFNA(_xlfn.XLOOKUP(Assumptions!J$87, '1 Machine Build'!$F$11:$Q$11, '1 Machine Build'!$F14:$Q14), 0), _xlfn.IFNA(_xlfn.XLOOKUP(Assumptions!J$88, '1 Machine Build'!$F$11:$Q$11, '1 Machine Build'!$F14:$Q14), 0)) -> 144616.67 | M32: =SUM(_xlfn.IFNA(_xlfn.XLOOKUP(Assumptions!K$81, '1 Machine Build'!$F$11:$Q$11, '1 Machine Build'!$F14:$Q14), 0), _xlfn.IFNA(_xlfn.XLOOKUP(Assumptions!K$82, '1 Machine Build'!$F$11:$Q$11, '1 Machine Build'!$F14:$Q14), 0), _xlfn.IFNA(_xlfn.XLOOKUP(Assumptions!K$83, '1 Machine Build'!$F$11:$Q$11, '1 Machine Build'!$F14:$Q14), 0), _xlfn.IFNA(_xlfn.XLOOKUP(Assumptions!K$84, '1 Machine Build'!$F$11:$Q$11, '1 Machine Build'!$F14:$Q14), 0), _xlfn.IFNA(_xlfn.XLOOKUP(Assumptions!K$85, '1 Machine Build'!$F$11:$Q$11, '1 Machine Build'!$F14:$Q14), 0), _xlfn.IFNA(_xlfn.XLOOKUP(Assumptions!K$86, '1 Machine Build'!$F$11:$Q$11, '1 Machine Build'!$F14:$Q14), 0), _xlfn.IFNA(_xlfn.XLOOKUP(Assumptions!K$87, '1 Machine Build'!$F$11:$Q$11, '1 Machine Build'!$F14:$Q14), 0), _xlfn.IFNA(_xlfn.XLOOKUP(Assumptions!K$88, '1 Machine Build'!$F$11:$Q$11, '1 Machine Build'!$F14:$Q14), 0)) -> 144616.67 | ... GC32: =SUM(_xlfn.IFNA(_xlfn.XLOOKUP(Assumptions!GA$81, '1 Machine Build'!$F$11:$Q$11, '1 Machine Build'!$F14:$Q14), 0), _xlfn.IFNA(_xlfn.XLOOKUP(Assumptions!GA$82, '1 Machine Build'!$F$11:$Q$11, '1 Machine Build'!$F14:$Q14), 0), _xlfn.IFNA(_xlfn.XLOOKUP(Assumptions!GA$83, '1 Machine Build'!$F$11:$Q$11, '1 Machine Build'!$F14:$Q14), 0), _xlfn.IFNA(_xlfn.XLOOKUP(Assumptions!GA$84, '1 Machine Build'!$F$11:$Q$11, '1 Machine Build'!$F14:$Q14), 0), _xlfn.IFNA(_xlfn.XLOOKUP(Assumptions!GA$85, '1 Machine Build'!$F$11:$Q$11, '1 Machine Build'!$F14:$Q14), 0), _xlfn.IFNA(_xlfn.XLOOKUP(Assumptions!GA$86, '1 Machine Build'!$F$11:$Q$11, '1 Machine Build'!$F14:$Q14), 0), _xlfn.IFNA(_xlfn.XLOOKUP(Assumptions!GA$87, '1 Machine Build'!$F$11:$Q$11, '1 Machine Build'!$F14:$Q14), 0), _xlfn.IFNA(_xlfn.XLOOKUP(Assumptions!GA$88, '1 Machine Build'!$F$11:$Q$11, '1 Machine Build'!$F14:$Q14), 0)) -> 0
B33: Professional Services | E33: =SUM(F33:GC33) -> 401400 | F33: =SUM(_xlfn.IFNA(_xlfn.XLOOKUP(Assumptions!D$81, '1 Machine Build'!$F$11:$Q$11, '1 Machine Build'!$F15:$Q15), 0), _xlfn.IFNA(_xlfn.XLOOKUP(Assumptions!D$82, '1 Machine Build'!$F$11:$Q$11, '1 Machine Build'!$F15:$Q15), 0), _xlfn.IFNA(_xlfn.XLOOKUP(Assumptions!D$83, '1 Machine Build'!$F$11:$Q$11, '1 Machine Build'!$F15:$Q15), 0), _xlfn.IFNA(_xlfn.XLOOKUP(Assumptions!D$84, '1 Machine Build'!$F$11:$Q$11, '1 Machine Build'!$F15:$Q15), 0), _xlfn.IFNA(_xlfn.XLOOKUP(Assumptions!D$85, '1 Machine Build'!$F$11:$Q$11, '1 Machine Build'!$F15:$Q15), 0), _xlfn.IFNA(_xlfn.XLOOKUP(Assumptions!D$86, '1 Machine Build'!$F$11:$Q$11, '1 Machine Build'!$F15:$Q15), 0), _xlfn.IFNA(_xlfn.XLOOKUP(Assumptions!D$87, '1 Machine Build'!$F$11:$Q$11, '1 Machine Build'!$F15:$Q15), 0), _xlfn.IFNA(_xlfn.XLOOKUP(Assumptions!D$88, '1 Machine Build'!$F$11:$Q$11, '1 Machine Build'!$F15:$Q15), 0)) -> 364550 | G33: =SUM(_xlfn.IFNA(_xlfn.XLOOKUP(Assumptions!E$81, '1 Machine Build'!$F$11:$Q$11, '1 Machine Build'!$F15:$Q15), 0), _xlfn.IFNA(_xlfn.XLOOKUP(Assumptions!E$82, '1 Machine Build'!$F$11:$Q$11, '1 Machine Build'!$F15:$Q15), 0), _xlfn.IFNA(_xlfn.XLOOKUP(Assumptions!E$83, '1 Machine Build'!$F$11:$Q$11, '1 Machine Build'!$F15:$Q15), 0), _xlfn.IFNA(_xlfn.XLOOKUP(Assumptions!E$84, '1 Machine Build'!$F$11:$Q$11, '1 Machine Build'!$F15:$Q15), 0), _xlfn.IFNA(_xlfn.XLOOKUP(Assumptions!E$85, '1 Machine Build'!$F$11:$Q$11, '1 Machine Build'!$F15:$Q15), 0), _xlfn.IFNA(_xlfn.XLOOKUP(Assumptions!E$86, '1 Machine Build'!$F$11:$Q$11, '1 Machine Build'!$F15:$Q15), 0), _xlfn.IFNA(_xlfn.XLOOKUP(Assumptions!E$87, '1 Machine Build'!$F$11:$Q$11, '1 Machine Build'!$F15:$Q15), 0), _xlfn.IFNA(_xlfn.XLOOKUP(Assumptions!E$88, '1 Machine Build'!$F$11:$Q$11, '1 Machine Build'!$F15:$Q15), 0)) -> 4550 | H33: =SUM(_xlfn.IFNA(_xlfn.XLOOKUP(Assumptions!F$81, '1 Machine Build'!$F$11:$Q$11, '1 Machine Build'!$F15:$Q15), 0), _xlfn.IFNA(_xlfn.XLOOKUP(Assumptions!F$82, '1 Machine Build'!$F$11:$Q$11, '1 Machine Build'!$F15:$Q15), 0), _xlfn.IFNA(_xlfn.XLOOKUP(Assumptions!F$83, '1 Machine Build'!$F$11:$Q$11, '1 Machine Build'!$F15:$Q15), 0), _xlfn.IFNA(_xlfn.XLOOKUP(Assumptions!F$84, '1 Machine Build'!$F$11:$Q$11, '1 Machine Build'!$F15:$Q15), 0), _xlfn.IFNA(_xlfn.XLOOKUP(Assumptions!F$85, '1 Machine Build'!$F$11:$Q$11, '1 Machine Build'!$F15:$Q15), 0), _xlfn.IFNA(_xlfn.XLOOKUP(Assumptions!F$86, '1 Machine Build'!$F$11:$Q$11, '1 Machine Build'!$F15:$Q15), 0), _xlfn.IFNA(_xlfn.XLOOKUP(Assumptions!F$87, '1 Machine Build'!$F$11:$Q$11, '1 Machine Build'!$F15:$Q15), 0), _xlfn.IFNA(_xlfn.XLOOKUP(Assumptions!F$88, '1 Machine Build'!$F$11:$Q$11, '1 Machine Build'!$F15:$Q15), 0)) -> 4550 | I33: =SUM(_xlfn.IFNA(_xlfn.XLOOKUP(Assumptions!G$81, '1 Machine Build'!$F$11:$Q$11, '1 Machine Build'!$F15:$Q15), 0), _xlfn.IFNA(_xlfn.XLOOKUP(Assumptions!G$82, '1 Machine Build'!$F$11:$Q$11, '1 Machine Build'!$F15:$Q15), 0), _xlfn.IFNA(_xlfn.XLOOKUP(Assumptions!G$83, '1 Machine Build'!$F$11:$Q$11, '1 Machine Build'!$F15:$Q15), 0), _xlfn.IFNA(_xlfn.XLOOKUP(Assumptions!G$84, '1 Machine Build'!$F$11:$Q$11, '1 Machine Build'!$F15:$Q15), 0), _xlfn.IFNA(_xlfn.XLOOKUP(Assumptions!G$85, '1 Machine Build'!$F$11:$Q$11, '1 Machine Build'!$F15:$Q15), 0), _xlfn.IFNA(_xlfn.XLOOKUP(Assumptions!G$86, '1 Machine Build'!$F$11:$Q$11, '1 Machine Build'!$F15:$Q15), 0), _xlfn.IFNA(_xlfn.XLOOKUP(Assumptions!G$87, '1 Machine Build'!$F$11:$Q$11, '1 Machine Build'!$F15:$Q15), 0), _xlfn.IFNA(_xlfn.XLOOKUP(Assumptions!G$88, '1 Machine Build'!$F$11:$Q$11, '1 Machine Build'!$F15:$Q15), 0)) -> 4550 | J33: =SUM(_xlfn.IFNA(_xlfn.XLOOKUP(Assumptions!H$81, '1 Machine Build'!$F$11:$Q$11, '1 Machine Build'!$F15:$Q15), 0), _xlfn.IFNA(_xlfn.XLOOKUP(Assumptions!H$82, '1 Machine Build'!$F$11:$Q$11, '1 Machine Build'!$F15:$Q15), 0), _xlfn.IFNA(_xlfn.XLOOKUP(Assumptions!H$83, '1 Machine Build'!$F$11:$Q$11, '1 Machine Build'!$F15:$Q15), 0), _xlfn.IFNA(_xlfn.XLOOKUP(Assumptions!H$84, '1 Machine Build'!$F$11:$Q$11, '1 Machine Build'!$F15:$Q15), 0), _xlfn.IFNA(_xlfn.XLOOKUP(Assumptions!H$85, '1 Machine Build'!$F$11:$Q$11, '1 Machine Build'!$F15:$Q15), 0), _xlfn.IFNA(_xlfn.XLOOKUP(Assumptions!H$86, '1 Machine Build'!$F$11:$Q$11, '1 Machine Build'!$F15:$Q15), 0), _xlfn.IFNA(_xlfn.XLOOKUP(Assumptions!H$87, '1 Machine Build'!$F$11:$Q$11, '1 Machine Build'!$F15:$Q15), 0), _xlfn.IFNA(_xlfn.XLOOKUP(Assumptions!H$88, '1 Machine Build'!$F$11:$Q$11, '1 Machine Build'!$F15:$Q15), 0)) -> 9550 | K33: =SUM(_xlfn.IFNA(_xlfn.XLOOKUP(Assumptions!I$81, '1 Machine Build'!$F$11:$Q$11, '1 Machine Build'!$F15:$Q15), 0), _xlfn.IFNA(_xlfn.XLOOKUP(Assumptions!I$82, '1 Machine Build'!$F$11:$Q$11, '1 Machine Build'!$F15:$Q15), 0), _xlfn.IFNA(_xlfn.XLOOKUP(Assumptions!I$83, '1 Machine Build'!$F$11:$Q$11, '1 Machine Build'!$F15:$Q15), 0), _xlfn.IFNA(_xlfn.XLOOKUP(Assumptions!I$84, '1 Machine Build'!$F$11:$Q$11, '1 Machine Build'!$F15:$Q15), 0), _xlfn.IFNA(_xlfn.XLOOKUP(Assumptions!I$85, '1 Machine Build'!$F$11:$Q$11, '1 Machine Build'!$F15:$Q15), 0), _xlfn.IFNA(_xlfn.XLOOKUP(Assumptions!I$86, '1 Machine Build'!$F$11:$Q$11, '1 Machine Build'!$F15:$Q15), 0), _xlfn.IFNA(_xlfn.XLOOKUP(Assumptions!I$87, '1 Machine Build'!$F$11:$Q$11, '1 Machine Build'!$F15:$Q15), 0), _xlfn.IFNA(_xlfn.XLOOKUP(Assumptions!I$88, '1 Machine Build'!$F$11:$Q$11, '1 Machine Build'!$F15:$Q15), 0)) -> 4550 | L33: =SUM(_xlfn.IFNA(_xlfn.XLOOKUP(Assumptions!J$81, '1 Machine Build'!$F$11:$Q$11, '1 Machine Build'!$F15:$Q15), 0), _xlfn.IFNA(_xlfn.XLOOKUP(Assumptions!J$82, '1 Machine Build'!$F$11:$Q$11, '1 Machine Build'!$F15:$Q15), 0), _xlfn.IFNA(_xlfn.XLOOKUP(Assumptions!J$83, '1 Machine Build'!$F$11:$Q$11, '1 Machine Build'!$F15:$Q15), 0), _xlfn.IFNA(_xlfn.XLOOKUP(Assumptions!J$84, '1 Machine Build'!$F$11:$Q$11, '1 Machine Build'!$F15:$Q15), 0), _xlfn.IFNA(_xlfn.XLOOKUP(Assumptions!J$85, '1 Machine Build'!$F$11:$Q$11, '1 Machine Build'!$F15:$Q15), 0), _xlfn.IFNA(_xlfn.XLOOKUP(Assumptions!J$86, '1 Machine Build'!$F$11:$Q$11, '1 Machine Build'!$F15:$Q15), 0), _xlfn.IFNA(_xlfn.XLOOKUP(Assumptions!J$87, '1 Machine Build'!$F$11:$Q$11, '1 Machine Build'!$F15:$Q15), 0), _xlfn.IFNA(_xlfn.XLOOKUP(Assumptions!J$88, '1 Machine Build'!$F$11:$Q$11, '1 Machine Build'!$F15:$Q15), 0)) -> 4550 | M33: =SUM(_xlfn.IFNA(_xlfn.XLOOKUP(Assumptions!K$81, '1 Machine Build'!$F$11:$Q$11, '1 Machine Build'!$F15:$Q15), 0), _xlfn.IFNA(_xlfn.XLOOKUP(Assumptions!K$82, '1 Machine Build'!$F$11:$Q$11, '1 Machine Build'!$F15:$Q15), 0), _xlfn.IFNA(_xlfn.XLOOKUP(Assumptions!K$83, '1 Machine Build'!$F$11:$Q$11, '1 Machine Build'!$F15:$Q15), 0), _xlfn.IFNA(_xlfn.XLOOKUP(Assumptions!K$84, '1 Machine Build'!$F$11:$Q$11, '1 Machine Build'!$F15:$Q15), 0), _xlfn.IFNA(_xlfn.XLOOKUP(Assumptions!K$85, '1 Machine Build'!$F$11:$Q$11, '1 Machine Build'!$F15:$Q15), 0), _xlfn.IFNA(_xlfn.XLOOKUP(Assumptions!K$86, '1 Machine Build'!$F$11:$Q$11, '1 Machine Build'!$F15:$Q15), 0), _xlfn.IFNA(_xlfn.XLOOKUP(Assumptions!K$87, '1 Machine Build'!$F$11:$Q$11, '1 Machine Build'!$F15:$Q15), 0), _xlfn.IFNA(_xlfn.XLOOKUP(Assumptions!K$88, '1 Machine Build'!$F$11:$Q$11, '1 Machine Build'!$F15:$Q15), 0)) -> 4550 | ... GC33: =SUM(_xlfn.IFNA(_xlfn.XLOOKUP(Assumptions!GA$81, '1 Machine Build'!$F$11:$Q$11, '1 Machine Build'!$F15:$Q15), 0), _xlfn.IFNA(_xlfn.XLOOKUP(Assumptions!GA$82, '1 Machine Build'!$F$11:$Q$11, '1 Machine Build'!$F15:$Q15), 0), _xlfn.IFNA(_xlfn.XLOOKUP(Assumptions!GA$83, '1 Machine Build'!$F$11:$Q$11, '1 Machine Build'!$F15:$Q15), 0), _xlfn.IFNA(_xlfn.XLOOKUP(Assumptions!GA$84, '1 Machine Build'!$F$11:$Q$11, '1 Machine Build'!$F15:$Q15), 0), _xlfn.IFNA(_xlfn.XLOOKUP(Assumptions!GA$85, '1 Machine Build'!$F$11:$Q$11, '1 Machine Build'!$F15:$Q15), 0), _xlfn.IFNA(_xlfn.XLOOKUP(Assumptions!GA$86, '1 Machine Build'!$F$11:$Q$11, '1 Machine Build'!$F15:$Q15), 0), _xlfn.IFNA(_xlfn.XLOOKUP(Assumptions!GA$87, '1 Machine Build'!$F$11:$Q$11, '1 Machine Build'!$F15:$Q15), 0), _xlfn.IFNA(_xlfn.XLOOKUP(Assumptions!GA$88, '1 Machine Build'!$F$11:$Q$11, '1 Machine Build'!$F15:$Q15), 0)) -> 0
B34: Workforce - Role - Pay Rate | E34: =SUM(F34:GC34) -> 2739708.6 | F34: =SUM(_xlfn.IFNA(_xlfn.XLOOKUP(Assumptions!D$81, '1 Machine Build'!$F$11:$Q$11, '1 Machine Build'!$F16:$Q16), 0), _xlfn.IFNA(_xlfn.XLOOKUP(Assumptions!D$82, '1 Machine Build'!$F$11:$Q$11, '1 Machine Build'!$F16:$Q16), 0), _xlfn.IFNA(_xlfn.XLOOKUP(Assumptions!D$83, '1 Machine Build'!$F$11:$Q$11, '1 Machine Build'!$F16:$Q16), 0), _xlfn.IFNA(_xlfn.XLOOKUP(Assumptions!D$84, '1 Machine Build'!$F$11:$Q$11, '1 Machine Build'!$F16:$Q16), 0), _xlfn.IFNA(_xlfn.XLOOKUP(Assumptions!D$85, '1 Machine Build'!$F$11:$Q$11, '1 Machine Build'!$F16:$Q16), 0), _xlfn.IFNA(_xlfn.XLOOKUP(Assumptions!D$86, '1 Machine Build'!$F$11:$Q$11, '1 Machine Build'!$F16:$Q16), 0), _xlfn.IFNA(_xlfn.XLOOKUP(Assumptions!D$87, '1 Machine Build'!$F$11:$Q$11, '1 Machine Build'!$F16:$Q16), 0), _xlfn.IFNA(_xlfn.XLOOKUP(Assumptions!D$88, '1 Machine Build'!$F$11:$Q$11, '1 Machine Build'!$F16:$Q16), 0)) -> 343708.99 | G34: =SUM(_xlfn.IFNA(_xlfn.XLOOKUP(Assumptions!E$81, '1 Machine Build'!$F$11:$Q$11, '1 Machine Build'!$F16:$Q16), 0), _xlfn.IFNA(_xlfn.XLOOKUP(Assumptions!E$82, '1 Machine Build'!$F$11:$Q$11, '1 Machine Build'!$F16:$Q16), 0), _xlfn.IFNA(_xlfn.XLOOKUP(Assumptions!E$83, '1 Machine Build'!$F$11:$Q$11, '1 Machine Build'!$F16:$Q16), 0), _xlfn.IFNA(_xlfn.XLOOKUP(Assumptions!E$84, '1 Machine Build'!$F$11:$Q$11, '1 Machine Build'!$F16:$Q16), 0), _xlfn.IFNA(_xlfn.XLOOKUP(Assumptions!E$85, '1 Machine Build'!$F$11:$Q$11, '1 Machine Build'!$F16:$Q16), 0), _xlfn.IFNA(_xlfn.XLOOKUP(Assumptions!E$86, '1 Machine Build'!$F$11:$Q$11, '1 Machine Build'!$F16:$Q16), 0), _xlfn.IFNA(_xlfn.XLOOKUP(Assumptions!E$87, '1 Machine Build'!$F$11:$Q$11, '1 Machine Build'!$F16:$Q16), 0), _xlfn.IFNA(_xlfn.XLOOKUP(Assumptions!E$88, '1 Machine Build'!$F$11:$Q$11, '1 Machine Build'!$F16:$Q16), 0)) -> 296839.58 | H34: =SUM(_xlfn.IFNA(_xlfn.XLOOKUP(Assumptions!F$81, '1 Machine Build'!$F$11:$Q$11, '1 Machine Build'!$F16:$Q16), 0), _xlfn.IFNA(_xlfn.XLOOKUP(Assumptions!F$82, '1 Machine Build'!$F$11:$Q$11, '1 Machine Build'!$F16:$Q16), 0), _xlfn.IFNA(_xlfn.XLOOKUP(Assumptions!F$83, '1 Machine Build'!$F$11:$Q$11, '1 Machine Build'!$F16:$Q16), 0), _xlfn.IFNA(_xlfn.XLOOKUP(Assumptions!F$84, '1 Machine Build'!$F$11:$Q$11, '1 Machine Build'!$F16:$Q16), 0), _xlfn.IFNA(_xlfn.XLOOKUP(Assumptions!F$85, '1 Machine Build'!$F$11:$Q$11, '1 Machine Build'!$F16:$Q16), 0), _xlfn.IFNA(_xlfn.XLOOKUP(Assumptions!F$86, '1 Machine Build'!$F$11:$Q$11, '1 Machine Build'!$F16:$Q16), 0), _xlfn.IFNA(_xlfn.XLOOKUP(Assumptions!F$87, '1 Machine Build'!$F$11:$Q$11, '1 Machine Build'!$F16:$Q16), 0), _xlfn.IFNA(_xlfn.XLOOKUP(Assumptions!F$88, '1 Machine Build'!$F$11:$Q$11, '1 Machine Build'!$F16:$Q16), 0)) -> 343708.99 | I34: =SUM(_xlfn.IFNA(_xlfn.XLOOKUP(Assumptions!G$81, '1 Machine Build'!$F$11:$Q$11, '1 Machine Build'!$F16:$Q16), 0), _xlfn.IFNA(_xlfn.XLOOKUP(Assumptions!G$82, '1 Machine Build'!$F$11:$Q$11, '1 Machine Build'!$F16:$Q16), 0), _xlfn.IFNA(_xlfn.XLOOKUP(Assumptions!G$83, '1 Machine Build'!$F$11:$Q$11, '1 Machine Build'!$F16:$Q16), 0), _xlfn.IFNA(_xlfn.XLOOKUP(Assumptions!G$84, '1 Machine Build'!$F$11:$Q$11, '1 Machine Build'!$F16:$Q16), 0), _xlfn.IFNA(_xlfn.XLOOKUP(Assumptions!G$85, '1 Machine Build'!$F$11:$Q$11, '1 Machine Build'!$F16:$Q16), 0), _xlfn.IFNA(_xlfn.XLOOKUP(Assumptions!G$86, '1 Machine Build'!$F$11:$Q$11, '1 Machine Build'!$F16:$Q16), 0), _xlfn.IFNA(_xlfn.XLOOKUP(Assumptions!G$87, '1 Machine Build'!$F$11:$Q$11, '1 Machine Build'!$F16:$Q16), 0), _xlfn.IFNA(_xlfn.XLOOKUP(Assumptions!G$88, '1 Machine Build'!$F$11:$Q$11, '1 Machine Build'!$F16:$Q16), 0)) -> 328085.86 | J34: =SUM(_xlfn.IFNA(_xlfn.XLOOKUP(Assumptions!H$81, '1 Machine Build'!$F$11:$Q$11, '1 Machine Build'!$F16:$Q16), 0), _xlfn.IFNA(_xlfn.XLOOKUP(Assumptions!H$82, '1 Machine Build'!$F$11:$Q$11, '1 Machine Build'!$F16:$Q16), 0), _xlfn.IFNA(_xlfn.XLOOKUP(Assumptions!H$83, '1 Machine Build'!$F$11:$Q$11, '1 Machine Build'!$F16:$Q16), 0), _xlfn.IFNA(_xlfn.XLOOKUP(Assumptions!H$84, '1 Machine Build'!$F$11:$Q$11, '1 Machine Build'!$F16:$Q16), 0), _xlfn.IFNA(_xlfn.XLOOKUP(Assumptions!H$85, '1 Machine Build'!$F$11:$Q$11, '1 Machine Build'!$F16:$Q16), 0), _xlfn.IFNA(_xlfn.XLOOKUP(Assumptions!H$86, '1 Machine Build'!$F$11:$Q$11, '1 Machine Build'!$F16:$Q16), 0), _xlfn.IFNA(_xlfn.XLOOKUP(Assumptions!H$87, '1 Machine Build'!$F$11:$Q$11, '1 Machine Build'!$F16:$Q16), 0), _xlfn.IFNA(_xlfn.XLOOKUP(Assumptions!H$88, '1 Machine Build'!$F$11:$Q$11, '1 Machine Build'!$F16:$Q16), 0)) -> 360942.91 | K34: =SUM(_xlfn.IFNA(_xlfn.XLOOKUP(Assumptions!I$81, '1 Machine Build'!$F$11:$Q$11, '1 Machine Build'!$F16:$Q16), 0), _xlfn.IFNA(_xlfn.XLOOKUP(Assumptions!I$82, '1 Machine Build'!$F$11:$Q$11, '1 Machine Build'!$F16:$Q16), 0), _xlfn.IFNA(_xlfn.XLOOKUP(Assumptions!I$83, '1 Machine Build'!$F$11:$Q$11, '1 Machine Build'!$F16:$Q16), 0), _xlfn.IFNA(_xlfn.XLOOKUP(Assumptions!I$84, '1 Machine Build'!$F$11:$Q$11, '1 Machine Build'!$F16:$Q16), 0), _xlfn.IFNA(_xlfn.XLOOKUP(Assumptions!I$85, '1 Machine Build'!$F$11:$Q$11, '1 Machine Build'!$F16:$Q16), 0), _xlfn.IFNA(_xlfn.XLOOKUP(Assumptions!I$86, '1 Machine Build'!$F$11:$Q$11, '1 Machine Build'!$F16:$Q16), 0), _xlfn.IFNA(_xlfn.XLOOKUP(Assumptions!I$87, '1 Machine Build'!$F$11:$Q$11, '1 Machine Build'!$F16:$Q16), 0), _xlfn.IFNA(_xlfn.XLOOKUP(Assumptions!I$88, '1 Machine Build'!$F$11:$Q$11, '1 Machine Build'!$F16:$Q16), 0)) -> 344536.42 | L34: =SUM(_xlfn.IFNA(_xlfn.XLOOKUP(Assumptions!J$81, '1 Machine Build'!$F$11:$Q$11, '1 Machine Build'!$F16:$Q16), 0), _xlfn.IFNA(_xlfn.XLOOKUP(Assumptions!J$82, '1 Machine Build'!$F$11:$Q$11, '1 Machine Build'!$F16:$Q16), 0), _xlfn.IFNA(_xlfn.XLOOKUP(Assumptions!J$83, '1 Machine Build'!$F$11:$Q$11, '1 Machine Build'!$F16:$Q16), 0), _xlfn.IFNA(_xlfn.XLOOKUP(Assumptions!J$84, '1 Machine Build'!$F$11:$Q$11, '1 Machine Build'!$F16:$Q16), 0), _xlfn.IFNA(_xlfn.XLOOKUP(Assumptions!J$85, '1 Machine Build'!$F$11:$Q$11, '1 Machine Build'!$F16:$Q16), 0), _xlfn.IFNA(_xlfn.XLOOKUP(Assumptions!J$86, '1 Machine Build'!$F$11:$Q$11, '1 Machine Build'!$F16:$Q16), 0), _xlfn.IFNA(_xlfn.XLOOKUP(Assumptions!J$87, '1 Machine Build'!$F$11:$Q$11, '1 Machine Build'!$F16:$Q16), 0), _xlfn.IFNA(_xlfn.XLOOKUP(Assumptions!J$88, '1 Machine Build'!$F$11:$Q$11, '1 Machine Build'!$F16:$Q16), 0)) -> 360942.91 | M34: =SUM(_xlfn.IFNA(_xlfn.XLOOKUP(Assumptions!K$81, '1 Machine Build'!$F$11:$Q$11, '1 Machine Build'!$F16:$Q16), 0), _xlfn.IFNA(_xlfn.XLOOKUP(Assumptions!K$82, '1 Machine Build'!$F$11:$Q$11, '1 Machine Build'!$F16:$Q16), 0), _xlfn.IFNA(_xlfn.XLOOKUP(Assumptions!K$83, '1 Machine Build'!$F$11:$Q$11, '1 Machine Build'!$F16:$Q16), 0), _xlfn.IFNA(_xlfn.XLOOKUP(Assumptions!K$84, '1 Machine Build'!$F$11:$Q$11, '1 Machine Build'!$F16:$Q16), 0), _xlfn.IFNA(_xlfn.XLOOKUP(Assumptions!K$85, '1 Machine Build'!$F$11:$Q$11, '1 Machine Build'!$F16:$Q16), 0), _xlfn.IFNA(_xlfn.XLOOKUP(Assumptions!K$86, '1 Machine Build'!$F$11:$Q$11, '1 Machine Build'!$F16:$Q16), 0), _xlfn.IFNA(_xlfn.XLOOKUP(Assumptions!K$87, '1 Machine Build'!$F$11:$Q$11, '1 Machine Build'!$F16:$Q16), 0), _xlfn.IFNA(_xlfn.XLOOKUP(Assumptions!K$88, '1 Machine Build'!$F$11:$Q$11, '1 Machine Build'!$F16:$Q16), 0)) -> 360942.91 | ... GC34: =SUM(_xlfn.IFNA(_xlfn.XLOOKUP(Assumptions!GA$81, '1 Machine Build'!$F$11:$Q$11, '1 Machine Build'!$F16:$Q16), 0), _xlfn.IFNA(_xlfn.XLOOKUP(Assumptions!GA$82, '1 Machine Build'!$F$11:$Q$11, '1 Machine Build'!$F16:$Q16), 0), _xlfn.IFNA(_xlfn.XLOOKUP(Assumptions!GA$83, '1 Machine Build'!$F$11:$Q$11, '1 Machine Build'!$F16:$Q16), 0), _xlfn.IFNA(_xlfn.XLOOKUP(Assumptions!GA$84, '1 Machine Build'!$F$11:$Q$11, '1 Machine Build'!$F16:$Q16), 0), _xlfn.IFNA(_xlfn.XLOOKUP(Assumptions!GA$85, '1 Machine Build'!$F$11:$Q$11, '1 Machine Build'!$F16:$Q16), 0), _xlfn.IFNA(_xlfn.XLOOKUP(Assumptions!GA$86, '1 Machine Build'!$F$11:$Q$11, '1 Machine Build'!$F16:$Q16), 0), _xlfn.IFNA(_xlfn.XLOOKUP(Assumptions!GA$87, '1 Machine Build'!$F$11:$Q$11, '1 Machine Build'!$F16:$Q16), 0), _xlfn.IFNA(_xlfn.XLOOKUP(Assumptions!GA$88, '1 Machine Build'!$F$11:$Q$11, '1 Machine Build'!$F16:$Q16), 0)) -> 0
B36: Total Capital Costs | C36: CAP | E36: =SUM(F36:GC36) -> 15843457 | F36: =SUM(F30:F34) -> 6697158.3 | G36: =SUM(G30:G34) -> 3337788.9 | H36: =SUM(H30:H34) -> 3077158.3 | I36: =SUM(I30:I34) -> 735585.86 | J36: =SUM(J30:J34) -> 398442.91 | K36: =SUM(K30:K34) -> 553103.08 | L36: =SUM(L30:L34) -> 510109.58 | M36: =SUM(M30:M34) -> 510109.58 | ... GC36: =SUM(GC30:GC34) -> 0
B38: Depreciation on Assets (5 Year)
B39: Series A Depreciation | F39: =IF(AND(_xlfn.XLOOKUP(12, Assumptions!$D$81:$GA$81, $F$5:$GC$5)<F$5, _xlfn.XLOOKUP(12, Assumptions!$D$81:$GA$81, $F$5:$GC$5)+Assumptions!$D$9*12>=F$5), _xlfn.XLOOKUP("Series A", Proforma!$F$21:$GC$21, Proforma!$F$26:$GC$26)/(Assumptions!$D$9*12), 0) -> 0 | G39: =IF(AND(_xlfn.XLOOKUP(12, Assumptions!$D$81:$GA$81, $F$5:$GC$5)<G$5, _xlfn.XLOOKUP(12, Assumptions!$D$81:$GA$81, $F$5:$GC$5)+Assumptions!$D$9*12>=G$5), _xlfn.XLOOKUP("Series A", Proforma!$F$21:$GC$21, Proforma!$F$26:$GC$26)/(Assumptions!$D$9*12), 0) -> 0 | H39: =IF(AND(_xlfn.XLOOKUP(12, Assumptions!$D$81:$GA$81, $F$5:$GC$5)<H$5, _xlfn.XLOOKUP(12, Assumptions!$D$81:$GA$81, $F$5:$GC$5)+Assumptions!$D$9*12>=H$5), _xlfn.XLOOKUP("Series A", Proforma!$F$21:$GC$21, Proforma!$F$26:$GC$26)/(Assumptions!$D$9*12), 0) -> 0 | I39: =IF(AND(_xlfn.XLOOKUP(12, Assumptions!$D$81:$GA$81, $F$5:$GC$5)<I$5, _xlfn.XLOOKUP(12, Assumptions!$D$81:$GA$81, $F$5:$GC$5)+Assumptions!$D$9*12>=I$5), _xlfn.XLOOKUP("Series A", Proforma!$F$21:$GC$21, Proforma!$F$26:$GC$26)/(Assumptions!$D$9*12), 0) -> 0 | J39: =IF(AND(_xlfn.XLOOKUP(12, Assumptions!$D$81:$GA$81, $F$5:$GC$5)<J$5, _xlfn.XLOOKUP(12, Assumptions!$D$81:$GA$81, $F$5:$GC$5)+Assumptions!$D$9*12>=J$5), _xlfn.XLOOKUP("Series A", Proforma!$F$21:$GC$21, Proforma!$F$26:$GC$26)/(Assumptions!$D$9*12), 0) -> 0 | K39: =IF(AND(_xlfn.XLOOKUP(12, Assumptions!$D$81:$GA$81, $F$5:$GC$5)<K$5, _xlfn.XLOOKUP(12, Assumptions!$D$81:$GA$81, $F$5:$GC$5)+Assumptions!$D$9*12>=K$5), _xlfn.XLOOKUP("Series A", Proforma!$F$21:$GC$21, Proforma!$F$26:$GC$26)/(Assumptions!$D$9*12), 0) -> 0 | L39: =IF(AND(_xlfn.XLOOKUP(12, Assumptions!$D$81:$GA$81, $F$5:$GC$5)<L$5, _xlfn.XLOOKUP(12, Assumptions!$D$81:$GA$81, $F$5:$GC$5)+Assumptions!$D$9*12>=L$5), _xlfn.XLOOKUP("Series A", Proforma!$F$21:$GC$21, Proforma!$F$26:$GC$26)/(Assumptions!$D$9*12), 0) -> 0 | M39: =IF(AND(_xlfn.XLOOKUP(12, Assumptions!$D$81:$GA$81, $F$5:$GC$5)<M$5, _xlfn.XLOOKUP(12, Assumptions!$D$81:$GA$81, $F$5:$GC$5)+Assumptions!$D$9*12>=M$5), _xlfn.XLOOKUP("Series A", Proforma!$F$21:$GC$21, Proforma!$F$26:$GC$26)/(Assumptions!$D$9*12), 0) -> 0 | ... GC39: =IF(AND(_xlfn.XLOOKUP(12, Assumptions!$D$81:$GA$81, $F$5:$GC$5)<GC$5, _xlfn.XLOOKUP(12, Assumptions!$D$81:$GA$81, $F$5:$GC$5)+Assumptions!$D$9*12>=GC$5), _xlfn.XLOOKUP("Series A", Proforma!$F$21:$GC$21, Proforma!$F$26:$GC$26)/(Assumptions!$D$9*12), 0) -> 83333.333
B40: Series B Depreciation | F40: =_xlfn.IFNA(IF(AND(_xlfn.XLOOKUP(MAX($F$23:$GC$23), Assumptions!$A$81:$A$88, Assumptions!$B$81:$B$88)+(Assumptions!$D$33-1)<F$5, _xlfn.XLOOKUP(MAX($F$23:$GC$23), Assumptions!$A$81:$A$88, Assumptions!$B$81:$B$88)+(Assumptions!$D$33-1)+Assumptions!$D$9*12>=F$5), ($E$36-Assumptions!$D$23)/(Assumptions!$D$9*12), 0), 0) -> 0 | G40: =_xlfn.IFNA(IF(AND(_xlfn.XLOOKUP(MAX($F$23:$GC$23), Assumptions!$A$81:$A$88, Assumptions!$B$81:$B$88)+(Assumptions!$D$33-1)<G$5, _xlfn.XLOOKUP(MAX($F$23:$GC$23), Assumptions!$A$81:$A$88, Assumptions!$B$81:$B$88)+(Assumptions!$D$33-1)+Assumptions!$D$9*12>=G$5), ($E$36-Assumptions!$D$23)/(Assumptions!$D$9*12), 0), 0) -> 0 | H40: =_xlfn.IFNA(IF(AND(_xlfn.XLOOKUP(MAX($F$23:$GC$23), Assumptions!$A$81:$A$88, Assumptions!$B$81:$B$88)+(Assumptions!$D$33-1)<H$5, _xlfn.XLOOKUP(MAX($F$23:$GC$23), Assumptions!$A$81:$A$88, Assumptions!$B$81:$B$88)+(Assumptions!$D$33-1)+Assumptions!$D$9*12>=H$5), ($E$36-Assumptions!$D$23)/(Assumptions!$D$9*12), 0), 0) -> 0 | I40: =_xlfn.IFNA(IF(AND(_xlfn.XLOOKUP(MAX($F$23:$GC$23), Assumptions!$A$81:$A$88, Assumptions!$B$81:$B$88)+(Assumptions!$D$33-1)<I$5, _xlfn.XLOOKUP(MAX($F$23:$GC$23), Assumptions!$A$81:$A$88, Assumptions!$B$81:$B$88)+(Assumptions!$D$33-1)+Assumptions!$D$9*12>=I$5), ($E$36-Assumptions!$D$23)/(Assumptions!$D$9*12), 0), 0) -> 0 | J40: =_xlfn.IFNA(IF(AND(_xlfn.XLOOKUP(MAX($F$23:$GC$23), Assumptions!$A$81:$A$88, Assumptions!$B$81:$B$88)+(Assumptions!$D$33-1)<J$5, _xlfn.XLOOKUP(MAX($F$23:$GC$23), Assumptions!$A$81:$A$88, Assumptions!$B$81:$B$88)+(Assumptions!$D$33-1)+Assumptions!$D$9*12>=J$5), ($E$36-Assumptions!$D$23)/(Assumptions!$D$9*12), 0), 0) -> 0 | K40: =_xlfn.IFNA(IF(AND(_xlfn.XLOOKUP(MAX($F$23:$GC$23), Assumptions!$A$81:$A$88, Assumptions!$B$81:$B$88)+(Assumptions!$D$33-1)<K$5, _xlfn.XLOOKUP(MAX($F$23:$GC$23), Assumptions!$A$81:$A$88, Assumptions!$B$81:$B$88)+(Assumptions!$D$33-1)+Assumptions!$D$9*12>=K$5), ($E$36-Assumptions!$D$23)/(Assumptions!$D$9*12), 0), 0) -> 0 | L40: =_xlfn.IFNA(IF(AND(_xlfn.XLOOKUP(MAX($F$23:$GC$23), Assumptions!$A$81:$A$88, Assumptions!$B$81:$B$88)+(Assumptions!$D$33-1)<L$5, _xlfn.XLOOKUP(MAX($F$23:$GC$23), Assumptions!$A$81:$A$88, Assumptions!$B$81:$B$88)+(Assumptions!$D$33-1)+Assumptions!$D$9*12>=L$5), ($E$36-Assumptions!$D$23)/(Assumptions!$D$9*12), 0), 0) -> 0 | M40: =_xlfn.IFNA(IF(AND(_xlfn.XLOOKUP(MAX($F$23:$GC$23), Assumptions!$A$81:$A$88, Assumptions!$B$81:$B$88)+(Assumptions!$D$33-1)<M$5, _xlfn.XLOOKUP(MAX($F$23:$GC$23), Assumptions!$A$81:$A$88, Assumptions!$B$81:$B$88)+(Assumptions!$D$33-1)+Assumptions!$D$9*12>=M$5), ($E$36-Assumptions!$D$23)/(Assumptions!$D$9*12), 0), 0) -> 0 | ... GC40: =_xlfn.IFNA(IF(AND(_xlfn.XLOOKUP(MAX($F$23:$GC$23), Assumptions!$A$81:$A$88, Assumptions!$B$81:$B$88)+(Assumptions!$D$33-1)<GC$5, _xlfn.XLOOKUP(MAX($F$23:$GC$23), Assumptions!$A$81:$A$88, Assumptions!$B$81:$B$88)+(Assumptions!$D$33-1)+Assumptions!$D$9*12>=GC$5), ($E$36-Assumptions!$D$23)/(Assumptions!$D$9*12), 0), 0) -> 4685.8699
B41: Total Depreciation | C41: DEP | F41: =F40+F39 -> 0 | G41: =G40+G39 -> 0 | H41: =H40+H39 -> 0 | I41: =I40+I39 -> 0 | J41: =J40+J39 -> 0 | K41: =K40+K39 -> 0 | L41: =L40+L39 -> 0 | M41: =M40+M39 -> 0 | ... GC41: =GC40+GC39 -> 88019.203
A43: Site Management and Office
B44: Plant Mgr | E44: =SUM(F44:GC44) -> 1799200 | F44: =IF(F$23>0, Assumptions!$G59, 0) -> 0 | G44: =IF(G$23>0, Assumptions!$G59, 0) -> 0 | H44: =IF(H$23>0, Assumptions!$G59, 0) -> 0 | I44: =IF(I$23>0, Assumptions!$G59, 0) -> 0 | J44: =IF(J$23>0, Assumptions!$G59, 0) -> 0 | K44: =IF(K$23>0, Assumptions!$G59, 0) -> 0 | L44: =IF(L$23>0, Assumptions!$G59, 0) -> 0 | M44: =IF(M$23>0, Assumptions!$G59, 0) -> 10400 | ... GC44: =IF(GC$23>0, Assumptions!$G59, 0) -> 10400
B45: Maintenance Mgr | E45: =SUM(F45:GC45) -> 1574300 | F45: =IF(F$23>0, Assumptions!$G60, 0) -> 0 | G45: =IF(G$23>0, Assumptions!$G60, 0) -> 0 | H45: =IF(H$23>0, Assumptions!$G60, 0) -> 0 | I45: =IF(I$23>0, Assumptions!$G60, 0) -> 0 | J45: =IF(J$23>0, Assumptions!$G60, 0) -> 0 | K45: =IF(K$23>0, Assumptions!$G60, 0) -> 0 | L45: =IF(L$23>0, Assumptions!$G60, 0) -> 0 | M45: =IF(M$23>0, Assumptions!$G60, 0) -> 9100 | ... GC45: =IF(GC$23>0, Assumptions!$G60, 0) -> 9100
B46: QC Mgr | E46: =SUM(F46:GC46) -> 1574300 | F46: =IF(F$23>0, Assumptions!$G61, 0) -> 0 | G46: =IF(G$23>0, Assumptions!$G61, 0) -> 0 | H46: =IF(H$23>0, Assumptions!$G61, 0) -> 0 | I46: =IF(I$23>0, Assumptions!$G61, 0) -> 0 | J46: =IF(J$23>0, Assumptions!$G61, 0) -> 0 | K46: =IF(K$23>0, Assumptions!$G61, 0) -> 0 | L46: =IF(L$23>0, Assumptions!$G61, 0) -> 0 | M46: =IF(M$23>0, Assumptions!$G61, 0) -> 9100 | ... GC46: =IF(GC$23>0, Assumptions!$G61, 0) -> 9100
B47: Shipping and receiving clerk | E47: =SUM(F47:GC47) -> 1574300 | F47: =IF(F$23>0, Assumptions!$G62, 0) -> 0 | G47: =IF(G$23>0, Assumptions!$G62, 0) -> 0 | H47: =IF(H$23>0, Assumptions!$G62, 0) -> 0 | I47: =IF(I$23>0, Assumptions!$G62, 0) -> 0 | J47: =IF(J$23>0, Assumptions!$G62, 0) -> 0 | K47: =IF(K$23>0, Assumptions!$G62, 0) -> 0 | L47: =IF(L$23>0, Assumptions!$G62, 0) -> 0 | M47: =IF(M$23>0, Assumptions!$G62, 0) -> 9100 | ... GC47: =IF(GC$23>0, Assumptions!$G62, 0) -> 9100
B48: office mgr / Safety Coordinator | E48: =SUM(F48:GC48) -> 1124500 | F48: =IF(F$23>0, Assumptions!$G63, 0) -> 0 | G48: =IF(G$23>0, Assumptions!$G63, 0) -> 0 | H48: =IF(H$23>0, Assumptions!$G63, 0) -> 0 | I48: =IF(I$23>0, Assumptions!$G63, 0) -> 0 | J48: =IF(J$23>0, Assumptions!$G63, 0) -> 0 | K48: =IF(K$23>0, Assumptions!$G63, 0) -> 0 | L48: =IF(L$23>0, Assumptions!$G63, 0) -> 0 | M48: =IF(M$23>0, Assumptions!$G63, 0) -> 6500 | ... GC48: =IF(GC$23>0, Assumptions!$G63, 0) -> 6500
B49: administrator | E49: =SUM(F49:GC49) -> 1124500 | F49: =IF(F$23>0, Assumptions!$G64, 0) -> 0 | G49: =IF(G$23>0, Assumptions!$G64, 0) -> 0 | H49: =IF(H$23>0, Assumptions!$G64, 0) -> 0 | I49: =IF(I$23>0, Assumptions!$G64, 0) -> 0 | J49: =IF(J$23>0, Assumptions!$G64, 0) -> 0 | K49: =IF(K$23>0, Assumptions!$G64, 0) -> 0 | L49: =IF(L$23>0, Assumptions!$G64, 0) -> 0 | M49: =IF(M$23>0, Assumptions!$G64, 0) -> 6500 | ... GC49: =IF(GC$23>0, Assumptions!$G64, 0) -> 6500
B50: Materials Coordinator | E50: =SUM(F50:GC50) -> 1574300 | F50: =IF(F$23>0, Assumptions!$G65, 0) -> 0 | G50: =IF(G$23>0, Assumptions!$G65, 0) -> 0 | H50: =IF(H$23>0, Assumptions!$G65, 0) -> 0 | I50: =IF(I$23>0, Assumptions!$G65, 0) -> 0 | J50: =IF(J$23>0, Assumptions!$G65, 0) -> 0 | K50: =IF(K$23>0, Assumptions!$G65, 0) -> 0 | L50: =IF(L$23>0, Assumptions!$G65, 0) -> 0 | M50: =IF(M$23>0, Assumptions!$G65, 0) -> 9100 | ... GC50: =IF(GC$23>0, Assumptions!$G65, 0) -> 9100
B51: Total Management & Office | C51: O | E51: =SUM(F51:GC51) -> 10345400 | F51: =SUM(F43:F49) -> 0 | G51: =SUM(G43:G49) -> 0 | H51: =SUM(H43:H49) -> 0 | I51: =SUM(I43:I49) -> 0 | J51: =SUM(J43:J49) -> 0 | K51: =SUM(K44:K50) -> 0 | L51: =SUM(L44:L50) -> 0 | M51: =SUM(M44:M50) -> 59800 | N51: =SUM(N44:N50) -> 59800 | O51: =SUM(O44:O50) -> 59800 | P51: =SUM(P44:P50) -> 59800 | Q51: =SUM(Q44:Q50) -> 59800 | R51: =SUM(R44:R50) -> 59800 | ... GC51: =SUM(GC44:GC50) -> 59800
B52: Percent of Revenue | E52: =SUM(E51:E51)/SUM(E155:E158) -> 0.033310065
A54: Operating Labour
B55: Hours - Day Shift | F55: =IF(F$23>0, 12, 0) -> 0 | G55: =IF(G$23>0, 12, 0) -> 0 | H55: =IF(H$23>0, 12, 0) -> 0 | I55: =IF(I$23>0, 12, 0) -> 0 | J55: =IF(J$23>0, 12, 0) -> 0 | K55: =IF(K$23>0, 12, 0) -> 0 | L55: =IF(L$23>0, 12, 0) -> 0 | M55: =IF(M$23>0, 12, 0) -> 12 | ... GC55: =IF(GC$23>0, 12, 0) -> 12
B56: Hours - Night Shift | F56: =IF(F$23>0, 12, 0) -> 0 | G56: =IF(G$23>0, 12, 0) -> 0 | H56: =IF(H$23>0, 12, 0) -> 0 | I56: =IF(I$23>0, 12, 0) -> 0 | J56: =IF(J$23>0, 12, 0) -> 0 | K56: =IF(K$23>0, 12, 0) -> 0 | L56: =IF(L$23>0, 12, 0) -> 0 | M56: =IF(M$23>0, 12, 0) -> 12 | ... GC56: =IF(GC$23>0, 12, 0) -> 12
A57: Dayshift
B58: Supervision $/hr | F58: =Assumptions!$D$37*(1+Assumptions!$D$66) -> 65 | G58: =Assumptions!$D$37*(1+Assumptions!$D$66) -> 65 | H58: =Assumptions!$D$37*(1+Assumptions!$D$66) -> 65 | I58: =Assumptions!$D$37*(1+Assumptions!$D$66) -> 65 | J58: =Assumptions!$D$37*(1+Assumptions!$D$66) -> 65 | K58: =Assumptions!$D$37*(1+Assumptions!$D$66) -> 65 | L58: =Assumptions!$D$37*(1+Assumptions!$D$66) -> 65 | M58: =Assumptions!$D$37*(1+Assumptions!$D$66) -> 65 | ... GC58: =Assumptions!$D$37*(1+Assumptions!$D$66) -> 65
B59: number | F59: =ROUNDUP(F23*Assumptions!$D$69,0) -> 0 | G59: =ROUNDUP(G23*Assumptions!$D$69,0) -> 0 | H59: =ROUNDUP(H23*Assumptions!$D$69,0) -> 0 | I59: =ROUNDUP(I23*Assumptions!$D$69,0) -> 0 | J59: =ROUNDUP(J23*Assumptions!$D$69,0) -> 0 | K59: =ROUNDUP(K23*Assumptions!$D$69,0) -> 0 | L59: =ROUNDUP(L23*Assumptions!$D$69,0) -> 0 | M59: =ROUNDUP(M23*Assumptions!$D$69,0) -> 1 | ... GC59: =ROUNDUP(GC23*Assumptions!$D$69,0) -> 1
B60: Plant Operators ($/hr) | F60: =Assumptions!$D$38*(1+Assumptions!$D$66) -> 50 | G60: =Assumptions!$D$38*(1+Assumptions!$D$66) -> 50 | H60: =Assumptions!$D$38*(1+Assumptions!$D$66) -> 50 | I60: =Assumptions!$D$38*(1+Assumptions!$D$66) -> 50 | J60: =Assumptions!$D$38*(1+Assumptions!$D$66) -> 50 | K60: =Assumptions!$D$38*(1+Assumptions!$D$66) -> 50 | L60: =Assumptions!$D$38*(1+Assumptions!$D$66) -> 50 | M60: =Assumptions!$D$38*(1+Assumptions!$D$66) -> 50 | ... GC60: =Assumptions!$D$38*(1+Assumptions!$D$66) -> 50
B61: number | F61: =ROUNDUP(F23*Assumptions!$D$70,0) -> 0 | G61: =ROUNDUP(G23*Assumptions!$D$70,0) -> 0 | H61: =ROUNDUP(H23*Assumptions!$D$70,0) -> 0 | I61: =ROUNDUP(I23*Assumptions!$D$70,0) -> 0 | J61: =ROUNDUP(J23*Assumptions!$D$70,0) -> 0 | K61: =ROUNDUP(K23*Assumptions!$D$70,0) -> 0 | L61: =ROUNDUP(L23*Assumptions!$D$70,0) -> 0 | M61: =ROUNDUP(M23*Assumptions!$D$70,0) -> 3 | ... GC61: =ROUNDUP(GC23*Assumptions!$D$70,0) -> 3
B62: Material Handling ($/hr) | F62: =Assumptions!$D$39*(1+Assumptions!$D$66) -> 30 | G62: =Assumptions!$D$39*(1+Assumptions!$D$66) -> 30 | H62: =Assumptions!$D$39*(1+Assumptions!$D$66) -> 30 | I62: =Assumptions!$D$39*(1+Assumptions!$D$66) -> 30 | J62: =Assumptions!$D$39*(1+Assumptions!$D$66) -> 30 | K62: =Assumptions!$D$39*(1+Assumptions!$D$66) -> 30 | L62: =Assumptions!$D$39*(1+Assumptions!$D$66) -> 30 | M62: =Assumptions!$D$39*(1+Assumptions!$D$66) -> 30 | ... GC62: =Assumptions!$D$39*(1+Assumptions!$D$66) -> 30
B63: number | F63: =ROUNDUP(F23*Assumptions!$D$71,0) -> 0 | G63: =ROUNDUP(G23*Assumptions!$D$71,0) -> 0 | H63: =ROUNDUP(H23*Assumptions!$D$71,0) -> 0 | I63: =ROUNDUP(I23*Assumptions!$D$71,0) -> 0 | J63: =ROUNDUP(J23*Assumptions!$D$71,0) -> 0 | K63: =ROUNDUP(K23*Assumptions!$D$71,0) -> 0 | L63: =ROUNDUP(L23*Assumptions!$D$71,0) -> 0 | M63: =ROUNDUP(M23*Assumptions!$D$71,0) -> 3 | ... GC63: =ROUNDUP(GC23*Assumptions!$D$71,0) -> 3
B64: Packaging ($/hr) | F64: =Assumptions!$D$40*(1+Assumptions!$D$66) -> 25 | G64: =Assumptions!$D$40*(1+Assumptions!$D$66) -> 25 | H64: =Assumptions!$D$40*(1+Assumptions!$D$66) -> 25 | I64: =Assumptions!$D$40*(1+Assumptions!$D$66) -> 25 | J64: =Assumptions!$D$40*(1+Assumptions!$D$66) -> 25 | K64: =Assumptions!$D$40*(1+Assumptions!$D$66) -> 25 | L64: =Assumptions!$D$40*(1+Assumptions!$D$66) -> 25 | M64: =Assumptions!$D$40*(1+Assumptions!$D$66) -> 25 | ... GC64: =Assumptions!$D$40*(1+Assumptions!$D$66) -> 25
B65: number | F65: =ROUNDUP(F23*Assumptions!$D$72,0) -> 0 | G65: =ROUNDUP(G23*Assumptions!$D$72,0) -> 0 | H65: =ROUNDUP(H23*Assumptions!$D$72,0) -> 0 | I65: =ROUNDUP(I23*Assumptions!$D$72,0) -> 0 | J65: =ROUNDUP(J23*Assumptions!$D$72,0) -> 0 | K65: =ROUNDUP(K23*Assumptions!$D$72,0) -> 0 | L65: =ROUNDUP(L23*Assumptions!$D$72,0) -> 0 | M65: =ROUNDUP(M23*Assumptions!$D$72,0) -> 3 | ... GC65: =ROUNDUP(GC23*Assumptions!$D$72,0) -> 3
A66: Nightshift
B67: Supervision $/hr | F67: =F58 -> 65 | G67: =G58 -> 65 | H67: =H58 -> 65 | I67: =I58 -> 65 | J67: =J58 -> 65 | K67: =K58 -> 65 | L67: =L58 -> 65 | M67: =M58 -> 65 | ... GC67: =GC58 -> 65
B68: number | F68: =F59 -> 0 | G68: =G59 -> 0 | H68: =H59 -> 0 | I68: =I59 -> 0 | J68: =J59 -> 0 | K68: =K59 -> 0 | L68: =L59 -> 0 | M68: =M59 -> 1 | ... GC68: =GC59 -> 1
B69: Plant Operators ($/hr) | F69: =F60 -> 50 | G69: =G60 -> 50 | H69: =H60 -> 50 | I69: =I60 -> 50 | J69: =J60 -> 50 | K69: =K60 -> 50 | L69: =L60 -> 50 | M69: =M60 -> 50 | ... GC69: =GC60 -> 50
B70: number | F70: =F61 -> 0 | G70: =G61 -> 0 | H70: =H61 -> 0 | I70: =I61 -> 0 | J70: =J61 -> 0 | K70: =K61 -> 0 | L70: =L61 -> 0 | M70: =M61 -> 3 | ... GC70: =GC61 -> 3
B71: Material Handling ($/hr) | F71: =F62 -> 30 | G71: =G62 -> 30 | H71: =H62 -> 30 | I71: =I62 -> 30 | J71: =J62 -> 30 | K71: =K62 -> 30 | L71: =L62 -> 30 | M71: =M62 -> 30 | ... GC71: =GC62 -> 30
B72: number | F72: =F63 -> 0 | G72: =G63 -> 0 | H72: =H63 -> 0 | I72: =I63 -> 0 | J72: =J63 -> 0 | K72: =K63 -> 0 | L72: =L63 -> 0 | M72: =M63 -> 3 | ... GC72: =GC63 -> 3
B73: Packaging ($/hr) | F73: =F64 -> 25 | G73: =G64 -> 25 | H73: =H64 -> 25 | I73: =I64 -> 25 | J73: =J64 -> 25 | K73: =K64 -> 25 | L73: =L64 -> 25 | M73: =M64 -> 25 | ... GC73: =GC64 -> 25
B74: number | F74: =F65 -> 0 | G74: =G65 -> 0 | H74: =H65 -> 0 | I74: =I65 -> 0 | J74: =J65 -> 0 | K74: =K65 -> 0 | L74: =L65 -> 0 | M74: =M65 -> 3 | ... GC74: =GC65 -> 3
B76: SubTotal Salary per day | F76: =(F58*F59+F60*F61+F62*F63+F64*F65)*F55+(F67*F68+F69*F70+F71*F72+F73*F74)*F56 -> 0 | G76: =(G58*G59+G60*G61+G62*G63+G64*G65)*G55+(G67*G68+G69*G70+G71*G72+G73*G74)*G56 -> 0 | H76: =(H58*H59+H60*H61+H62*H63+H64*H65)*H55+(H67*H68+H69*H70+H71*H72+H73*H74)*H56 -> 0 | I76: =(I58*I59+I60*I61+I62*I63+I64*I65)*I55+(I67*I68+I69*I70+I71*I72+I73*I74)*I56 -> 0 | J76: =(J58*J59+J60*J61+J62*J63+J64*J65)*J55+(J67*J68+J69*J70+J71*J72+J73*J74)*J56 -> 0 | K76: =(K58*K59+K60*K61+K62*K63+K64*K65)*K55+(K67*K68+K69*K70+K71*K72+K73*K74)*K56 -> 0 | L76: =(L58*L59+L60*L61+L62*L63+L64*L65)*L55+(L67*L68+L69*L70+L71*L72+L73*L74)*L56 -> 0 | M76: =(M58*M59+M60*M61+M62*M63+M64*M65)*M55+(M67*M68+M69*M70+M71*M72+M73*M74)*M56 -> 9120 | ... GC76: =(GC58*GC59+GC60*GC61+GC62*GC63+GC64*GC65)*GC55+(GC67*GC68+GC69*GC70+GC71*GC72+GC73*GC74)*GC56 -> 9120
B77: Burden | D77: =Assumptions!E58 -> 0.3 | F77: =F76*$D77 -> 0 | G77: =G76*$D77 -> 0 | H77: =H76*$D77 -> 0 | I77: =I76*$D77 -> 0 | J77: =J76*$D77 -> 0 | K77: =K76*$D77 -> 0 | L77: =L76*$D77 -> 0 | M77: =M76*$D77 -> 2736 | ... GC77: =GC76*$D77 -> 2736
B78: Direct Labor costs per day | F78: =F76+F77 -> 0 | G78: =G76+G77 -> 0 | H78: =H76+H77 -> 0 | I78: =I76+I77 -> 0 | J78: =J76+J77 -> 0 | K78: =K76+K77 -> 0 | L78: =L76+L77 -> 0 | M78: =M76+M77 -> 11856 | ... GC78: =GC76+GC77 -> 11856
B80: Days per month operating | E80: =SUM(F80:GC80) -> 5475 | F80: =F8 -> 31 | G80: =G8 -> 28 | H80: =H8 -> 31 | I80: =I8 -> 30 | J80: =J8 -> 31 | K80: =K8 -> 30 | L80: =L8 -> 31 | M80: =M8 -> 31 | ... GC80: =GC8 -> 31
B81: Direct Labour Costs per month | C81: C | E81: =SUM(F81:GC81) -> 62398128 | F81: =F80*F78 -> 0 | G81: =G80*G78 -> 0 | H81: =H80*H78 -> 0 | I81: =I80*I78 -> 0 | J81: =J80*J78 -> 0 | K81: =K80*K78 -> 0 | L81: =L80*L78 -> 0 | M81: =M80*M78 -> 367536 | ... GC81: =GC80*GC78 -> 367536
B82: Percent of Revenue | E82: =SUM(E81:E81)/SUM(E155:E158) -> 0.20090917
A84: Operating Expense
A85: Direct Operating Costs
B86: Fuel | E86: =SUM(F86:GC86) -> 567351.4 | F86: =OpCost!$E$12*F$130 -> 0 | G86: =OpCost!$E$12*G$130 -> 0 | H86: =OpCost!$E$12*H$130 -> 0 | I86: =OpCost!$E$12*I$130 -> 0 | J86: =OpCost!$E$12*J$130 -> 0 | K86: =OpCost!$E$12*K$130 -> 0 | L86: =OpCost!$E$12*L$130 -> 0 | M86: =OpCost!$E$12*M$130 -> 3341.8 | ... GC86: =OpCost!$E$12*GC$130 -> 3341.8
B87: Process Equip Maintenance | E87: =SUM(F87:GC87) -> 1296803.2 | F87: =OpCost!$E$13*F$130 -> 0 | G87: =OpCost!$E$13*G$130 -> 0 | H87: =OpCost!$E$13*H$130 -> 0 | I87: =OpCost!$E$13*I$130 -> 0 | J87: =OpCost!$E$13*J$130 -> 0 | K87: =OpCost!$E$13*K$130 -> 0 | L87: =OpCost!$E$13*L$130 -> 0 | M87: =OpCost!$E$13*M$130 -> 7638.4 | ... GC87: =OpCost!$E$13*GC$130 -> 7638.4
B88: Equipment Lease | E88: =SUM(F88:GC88) -> 0 | F88: =OpCost!$E$14*F$130 -> 0 | G88: =OpCost!$E$14*G$130 -> 0 | H88: =OpCost!$E$14*H$130 -> 0 | I88: =OpCost!$E$14*I$130 -> 0 | J88: =OpCost!$E$14*J$130 -> 0 | K88: =OpCost!$E$14*K$130 -> 0 | L88: =OpCost!$E$14*L$130 -> 0 | M88: =OpCost!$E$14*M$130 -> 0 | ... GC88: =OpCost!$E$14*GC$130 -> 0
B89: Tools | E89: =SUM(F89:GC89) -> 32420.08 | F89: =OpCost!$E$15*F$130 -> 0 | G89: =OpCost!$E$15*G$130 -> 0 | H89: =OpCost!$E$15*H$130 -> 0 | I89: =OpCost!$E$15*I$130 -> 0 | J89: =OpCost!$E$15*J$130 -> 0 | K89: =OpCost!$E$15*K$130 -> 0 | L89: =OpCost!$E$15*L$130 -> 0 | M89: =OpCost!$E$15*M$130 -> 190.96 | ... GC89: =OpCost!$E$15*GC$130 -> 190.96
B90: Ground Transport | E90: =SUM(F90:GC90) -> 64840.16 | F90: =OpCost!$E$17*F$130 -> 0 | G90: =OpCost!$E$17*G$130 -> 0 | H90: =OpCost!$E$17*H$130 -> 0 | I90: =OpCost!$E$17*I$130 -> 0 | J90: =OpCost!$E$17*J$130 -> 0 | K90: =OpCost!$E$17*K$130 -> 0 | L90: =OpCost!$E$17*L$130 -> 0 | M90: =OpCost!$E$17*M$130 -> 381.92 | ... GC90: =OpCost!$E$17*GC$130 -> 381.92
B91: Product Packaging Carbon | E91: =SUM(F91:GC91) -> 1701869.4 | F91: =OpCost!$E$21*F$130 -> 0 | G91: =OpCost!$E$21*G$130 -> 0 | H91: =OpCost!$E$21*H$130 -> 0 | I91: =OpCost!$E$21*I$130 -> 0 | J91: =OpCost!$E$21*J$130 -> 0 | K91: =OpCost!$E$21*K$130 -> 0 | L91: =OpCost!$E$21*L$130 -> 0 | M91: =OpCost!$E$21*M$130 -> 10024.312 | ... GC91: =OpCost!$E$21*GC$130 -> 10024.312
B92: Plant Supplies | E92: =SUM(F92:GC92) -> 567351.4 | F92: =OpCost!$E$22*F$130 -> 0 | G92: =OpCost!$E$22*G$130 -> 0 | H92: =OpCost!$E$22*H$130 -> 0 | I92: =OpCost!$E$22*I$130 -> 0 | J92: =OpCost!$E$22*J$130 -> 0 | K92: =OpCost!$E$22*K$130 -> 0 | L92: =OpCost!$E$22*L$130 -> 0 | M92: =OpCost!$E$22*M$130 -> 3341.8 | ... GC92: =OpCost!$E$22*GC$130 -> 3341.8
B93: Plant Shipping | E93: =SUM(F93:GC93) -> 72945.18 | F93: =OpCost!$E$24*F$130 -> 0 | G93: =OpCost!$E$24*G$130 -> 0 | H93: =OpCost!$E$24*H$130 -> 0 | I93: =OpCost!$E$24*I$130 -> 0 | J93: =OpCost!$E$24*J$130 -> 0 | K93: =OpCost!$E$24*K$130 -> 0 | L93: =OpCost!$E$24*L$130 -> 0 | M93: =OpCost!$E$24*M$130 -> 429.66 | ... GC93: =OpCost!$E$24*GC$130 -> 429.66
B94: Plant Maintenance and Consumables | E94: =SUM(F94:GC94) -> 790239.45 | F94: =OpCost!$E$26*F$130 -> 0 | G94: =OpCost!$E$26*G$130 -> 0 | H94: =OpCost!$E$26*H$130 -> 0 | I94: =OpCost!$E$26*I$130 -> 0 | J94: =OpCost!$E$26*J$130 -> 0 | K94: =OpCost!$E$26*K$130 -> 0 | L94: =OpCost!$E$26*L$130 -> 0 | M94: =OpCost!$E$26*M$130 -> 4654.65 | ... GC94: =OpCost!$E$26*GC$130 -> 4654.65
B95: Gas | E95: =SUM(F95:GC95) -> 113470.28 | F95: =OpCost!$E$42*F$130 -> 0 | G95: =OpCost!$E$42*G$130 -> 0 | H95: =OpCost!$E$42*H$130 -> 0 | I95: =OpCost!$E$42*I$130 -> 0 | J95: =OpCost!$E$42*J$130 -> 0 | K95: =OpCost!$E$42*K$130 -> 0 | L95: =OpCost!$E$42*L$130 -> 0 | M95: =OpCost!$E$42*M$130 -> 668.36 | ... GC95: =OpCost!$E$42*GC$130 -> 668.36
B96: Electricity | E96: =SUM(F96:GC96) -> 226940.56 | F96: =OpCost!$E$43*F$130 -> 0 | G96: =OpCost!$E$43*G$130 -> 0 | H96: =OpCost!$E$43*H$130 -> 0 | I96: =OpCost!$E$43*I$130 -> 0 | J96: =OpCost!$E$43*J$130 -> 0 | K96: =OpCost!$E$43*K$130 -> 0 | L96: =OpCost!$E$43*L$130 -> 0 | M96: =OpCost!$E$43*M$130 -> 1336.72 | ... GC96: =OpCost!$E$43*GC$130 -> 1336.72
B97: Water | E97: =SUM(F97:GC97) -> 97260.24 | F97: =OpCost!$E$44*F$130 -> 0 | G97: =OpCost!$E$44*G$130 -> 0 | H97: =OpCost!$E$44*H$130 -> 0 | I97: =OpCost!$E$44*I$130 -> 0 | J97: =OpCost!$E$44*J$130 -> 0 | K97: =OpCost!$E$44*K$130 -> 0 | L97: =OpCost!$E$44*L$130 -> 0 | M97: =OpCost!$E$44*M$130 -> 572.88 | ... GC97: =OpCost!$E$44*GC$130 -> 572.88
B98: Vehicles | E98: =SUM(F98:GC98) -> 228360 | F98: =IF(F23>0, OpCost!$D$16, 0) -> 0 | G98: =IF(G23>0, OpCost!$D$16, 0) -> 0 | H98: =IF(H23>0, OpCost!$D$16, 0) -> 0 | I98: =IF(I23>0, OpCost!$D$16, 0) -> 0 | J98: =IF(J23>0, OpCost!$D$16, 0) -> 0 | K98: =IF(K23>0, OpCost!$D$16, 0) -> 0 | L98: =IF(L23>0, OpCost!$D$16, 0) -> 0 | M98: =IF(M23>0, OpCost!$D$16, 0) -> 1320 | ... GC98: =IF(GC23>0, OpCost!$D$16, 0) -> 1320
B99: Total Direct Costs | C99: C | E99: =SUM(F99:GC99) -> 5759851.4 | F99: =SUM(F86:F98) -> 0 | G99: =SUM(G86:G98) -> 0 | H99: =SUM(H86:H98) -> 0 | I99: =SUM(I86:I98) -> 0 | J99: =SUM(J86:J98) -> 0 | K99: =SUM(K86:K98) -> 0 | L99: =SUM(L86:L98) -> 0 | M99: =SUM(M86:M98) -> 33901.462 | ... GC99: =SUM(GC86:GC98) -> 33901.462
B100: Percent of Revenue | E100: =SUM(E99:E99)/SUM(E155:E158) -> 0.018545539
A102: Indirect Operating Costs (Overhead)
B103: Plant Office Supplies | E103: =SUM(F103:GC103) -> 145890.36 | F103: =OpCost!$E$23*F$130 -> 0 | G103: =OpCost!$E$23*G$130 -> 0 | H103: =OpCost!$E$23*H$130 -> 0 | I103: =OpCost!$E$23*I$130 -> 0 | J103: =OpCost!$E$23*J$130 -> 0 | K103: =OpCost!$E$23*K$130 -> 0 | L103: =OpCost!$E$23*L$130 -> 0 | M103: =OpCost!$E$23*M$130 -> 859.32 | ... GC103: =OpCost!$E$23*GC$130 -> 859.32
B104: State Compliance | E104: =SUM(F104:GC104) -> 486301.2 | F104: =OpCost!$E$25*F$130 -> 0 | G104: =OpCost!$E$25*G$130 -> 0 | H104: =OpCost!$E$25*H$130 -> 0 | I104: =OpCost!$E$25*I$130 -> 0 | J104: =OpCost!$E$25*J$130 -> 0 | K104: =OpCost!$E$25*K$130 -> 0 | L104: =OpCost!$E$25*L$130 -> 0 | M104: =OpCost!$E$25*M$130 -> 2864.4 | ... GC104: =OpCost!$E$25*GC$130 -> 2864.4
B105: General Liability Insurance | E105: =SUM(F105:GC105) -> 810502 | F105: =OpCost!$E$27*F$130 -> 0 | G105: =OpCost!$E$27*G$130 -> 0 | H105: =OpCost!$E$27*H$130 -> 0 | I105: =OpCost!$E$27*I$130 -> 0 | J105: =OpCost!$E$27*J$130 -> 0 | K105: =OpCost!$E$27*K$130 -> 0 | L105: =OpCost!$E$27*L$130 -> 0 | M105: =OpCost!$E$27*M$130 -> 4774 | ... GC105: =OpCost!$E$27*GC$130 -> 4774
B106: Plant & Equipment Insurance | E106: =SUM(F106:GC106) -> 486301.2 | F106: =OpCost!$E$28*F$130 -> 0 | G106: =OpCost!$E$28*G$130 -> 0 | H106: =OpCost!$E$28*H$130 -> 0 | I106: =OpCost!$E$28*I$130 -> 0 | J106: =OpCost!$E$28*J$130 -> 0 | K106: =OpCost!$E$28*K$130 -> 0 | L106: =OpCost!$E$28*L$130 -> 0 | M106: =OpCost!$E$28*M$130 -> 2864.4 | ... GC106: =OpCost!$E$28*GC$130 -> 2864.4
B107: Workers Comp | E107: =SUM(F107:GC107) -> 2693460.2 | F107: =OpCost!$E$29*F$130 -> 0 | G107: =OpCost!$E$29*G$130 -> 0 | H107: =OpCost!$E$29*H$130 -> 0 | I107: =OpCost!$E$29*I$130 -> 0 | J107: =OpCost!$E$29*J$130 -> 0 | K107: =OpCost!$E$29*K$130 -> 0 | L107: =OpCost!$E$29*L$130 -> 0 | M107: =OpCost!$E$29*M$130 -> 15864.957 | ... GC107: =OpCost!$E$29*GC$130 -> 15864.957
B108: Pollution Insurnace | E108: =SUM(F108:GC108) -> 324200.8 | F108: =OpCost!$E$30*F$130 -> 0 | G108: =OpCost!$E$30*G$130 -> 0 | H108: =OpCost!$E$30*H$130 -> 0 | I108: =OpCost!$E$30*I$130 -> 0 | J108: =OpCost!$E$30*J$130 -> 0 | K108: =OpCost!$E$30*K$130 -> 0 | L108: =OpCost!$E$30*L$130 -> 0 | M108: =OpCost!$E$30*M$130 -> 1909.6 | ... GC108: =OpCost!$E$30*GC$130 -> 1909.6
B109: Insurance - Vehicles | E109: =SUM(F109:GC109) -> 121575.3 | F109: =OpCost!$E$31*F$130 -> 0 | G109: =OpCost!$E$31*G$130 -> 0 | H109: =OpCost!$E$31*H$130 -> 0 | I109: =OpCost!$E$31*I$130 -> 0 | J109: =OpCost!$E$31*J$130 -> 0 | K109: =OpCost!$E$31*K$130 -> 0 | L109: =OpCost!$E$31*L$130 -> 0 | M109: =OpCost!$E$31*M$130 -> 716.1 | ... GC109: =OpCost!$E$31*GC$130 -> 716.1
B110: 3rd Party Consulting | E110: =SUM(F110:GC110) -> 486301.2 | F110: =OpCost!$E$32*F$130 -> 0 | G110: =OpCost!$E$32*G$130 -> 0 | H110: =OpCost!$E$32*H$130 -> 0 | I110: =OpCost!$E$32*I$130 -> 0 | J110: =OpCost!$E$32*J$130 -> 0 | K110: =OpCost!$E$32*K$130 -> 0 | L110: =OpCost!$E$32*L$130 -> 0 | M110: =OpCost!$E$32*M$130 -> 2864.4 | ... GC110: =OpCost!$E$32*GC$130 -> 2864.4
B111: Accounting | E111: =SUM(F111:GC111) -> 648401.6 | F111: =OpCost!$E$33*F$130 -> 0 | G111: =OpCost!$E$33*G$130 -> 0 | H111: =OpCost!$E$33*H$130 -> 0 | I111: =OpCost!$E$33*I$130 -> 0 | J111: =OpCost!$E$33*J$130 -> 0 | K111: =OpCost!$E$33*K$130 -> 0 | L111: =OpCost!$E$33*L$130 -> 0 | M111: =OpCost!$E$33*M$130 -> 3819.2 | ... GC111: =OpCost!$E$33*GC$130 -> 3819.2
B112: Professional Fees/Dues | E112: =SUM(F112:GC112) -> 40525.1 | F112: =OpCost!$E$34*F$130 -> 0 | G112: =OpCost!$E$34*G$130 -> 0 | H112: =OpCost!$E$34*H$130 -> 0 | I112: =OpCost!$E$34*I$130 -> 0 | J112: =OpCost!$E$34*J$130 -> 0 | K112: =OpCost!$E$34*K$130 -> 0 | L112: =OpCost!$E$34*L$130 -> 0 | M112: =OpCost!$E$34*M$130 -> 238.7 | ... GC112: =OpCost!$E$34*GC$130 -> 238.7
B113: Legal Expense | E113: =SUM(F113:GC113) -> 243150.6 | F113: =OpCost!$E$35*F$130 -> 0 | G113: =OpCost!$E$35*G$130 -> 0 | H113: =OpCost!$E$35*H$130 -> 0 | I113: =OpCost!$E$35*I$130 -> 0 | J113: =OpCost!$E$35*J$130 -> 0 | K113: =OpCost!$E$35*K$130 -> 0 | L113: =OpCost!$E$35*L$130 -> 0 | M113: =OpCost!$E$35*M$130 -> 1432.2 | ... GC113: =OpCost!$E$35*GC$130 -> 1432.2
B114: IT Computer Support | E114: =SUM(F114:GC114) -> 486301.2 | F114: =OpCost!$E$36*F$130 -> 0 | G114: =OpCost!$E$36*G$130 -> 0 | H114: =OpCost!$E$36*H$130 -> 0 | I114: =OpCost!$E$36*I$130 -> 0 | J114: =OpCost!$E$36*J$130 -> 0 | K114: =OpCost!$E$36*K$130 -> 0 | L114: =OpCost!$E$36*L$130 -> 0 | M114: =OpCost!$E$36*M$130 -> 2864.4 | ... GC114: =OpCost!$E$36*GC$130 -> 2864.4
B115: Office Supplies | E115: =SUM(F115:GC115) -> 97260.24 | F115: =OpCost!$E$37*F$130 -> 0 | G115: =OpCost!$E$37*G$130 -> 0 | H115: =OpCost!$E$37*H$130 -> 0 | I115: =OpCost!$E$37*I$130 -> 0 | J115: =OpCost!$E$37*J$130 -> 0 | K115: =OpCost!$E$37*K$130 -> 0 | L115: =OpCost!$E$37*L$130 -> 0 | M115: =OpCost!$E$37*M$130 -> 572.88 | ... GC115: =OpCost!$E$37*GC$130 -> 572.88
B116: Contract Services | E116: =SUM(F116:GC116) -> 32420.08 | F116: =OpCost!$E$38*F$130 -> 0 | G116: =OpCost!$E$38*G$130 -> 0 | H116: =OpCost!$E$38*H$130 -> 0 | I116: =OpCost!$E$38*I$130 -> 0 | J116: =OpCost!$E$38*J$130 -> 0 | K116: =OpCost!$E$38*K$130 -> 0 | L116: =OpCost!$E$38*L$130 -> 0 | M116: =OpCost!$E$38*M$130 -> 190.96 | ... GC116: =OpCost!$E$38*GC$130 -> 190.96
...

Sheet Market Pricing of Products
A2: =ModelDescription!A2 -> Economic Forecasting Model
A3: =ModelDescription!C4 -> Noble, OK 6 Processor Facility - Series A + Series B
A5: N330 Carbon Black Historical Pricing (2020-2025)
A6: Sources: PriceWatch, IMARC Group, Intratec, industry reports. Prices approximate based on market data.
A8: Period | B8: China FOB ($/MT) | C8: India Ex-Jamnagar ($/MT) | D8: US Ex-Works ($/MT) | E8: China ($/lb) | F8: India ($/lb) | G8: US ($/lb) | H8: SENS Carbon Black
A9: Q1 2020 | B9: 680 | C9: 850 | D9: 1400 | E9: 0.308 | F9: 0.386 | G9: 0.635 | H9: 0.55
A10: Q2 2020 | B10: 620 | C10: 780 | D10: 1300 | E10: 0.281 | F10: 0.354 | G10: 0.59 | H10: 0.55
A11: Q3 2020 | B11: 700 | C11: 860 | D11: 1450 | E11: 0.318 | F11: 0.39 | G11: 0.658 | H11: 0.55
A12: Q4 2020 | B12: 780 | C12: 950 | D12: 1600 | E12: 0.354 | F12: 0.431 | G12: 0.726 | H12: 0.55
A13: Q1 2021 | B13: 850 | C13: 1020 | D13: 1700 | E13: 0.386 | F13: 0.463 | G13: 0.771 | H13: 0.55
A14: Q2 2021 | B14: 950 | C14: 1120 | D14: 1850 | E14: 0.431 | F14: 0.508 | G14: 0.839 | H14: 0.55
A15: Q3 2021 | B15: 1050 | C15: 1200 | D15: 2000 | E15: 0.476 | F15: 0.544 | G15: 0.907 | H15: 0.55
A16: Q4 2021 | B16: 1150 | C16: 1280 | D16: 2150 | E16: 0.522 | F16: 0.581 | G16: 0.975 | H16: 0.55
A17: Q1 2022 | B17: 1250 | C17: 1350 | D17: 2300 | E17: 0.567 | F17: 0.612 | G17: 1.043 | H17: 0.55
A18: Q2 2022 | B18: 1400 | C18: 1480 | D18: 2450 | E18: 0.635 | F18: 0.671 | G18: 1.111 | H18: 0.55
A19: Q3 2022 | B19: 1550 | C19: 1580 | D19: 2500 | E19: 0.703 | F19: 0.717 | G19: 1.134 | H19: 0.55
A20: Q4 2022 | B20: 1700 | C20: 1650 | D20: 2220 | E20: 0.771 | F20: 0.748 | G20: 1.007 | H20: 0.55
... A31: Q3 2025 | B31: 925 | C31: 1135 | D31: 1790 | E31: 0.42 | F31: 0.515 | G31: 0.812 | H31: 0.55
A34: Summary Statistics
A35: Current (Q3 2025): | E35: 0.42 | F35: 0.515 | G35: 0.812
A36: 5-Year High: | E36: 0.771 | F36: 0.748 | G36: 1.134
A37: 5-Year Low: | E37: 0.281 | F37: 0.354 | G37: 0.59
A38: 5-Year Average: | E38: 0.504 | F38: 0.545 | G38: 0.857
A43: Year | B43: Mixed Xylene | C43: Aromatic 150 | D43: Aromatic 200 | E43: SENS Diluent | F43: Terpene Low | G43: Terpene Range | H43: Terpene High
A44: Q1 2020 | B44: 2.1 | C44: 2.8 | D44: 3.1 | E44: 8 | F44: 5.5 | G44: =H44-F44 -> 3 | H44: 8.5
A45: Q2 2020 | B45: 2.325 | C45: 3 | D45: 3.325 | E45: 8 | F45: 5.75 | G45: =H45-F45 -> 3.125 | H45: 8.875
A46: Q3 2020 | B46: 2.55 | C46: 3.2 | D46: 3.55 | E46: 8 | F46: 6 | G46: =H46-F46 -> 3.25 | H46: 9.25
A47: Q4 2020 | B47: 2.775 | C47: 3.4 | D47: 3.775 | E47: 8 | F47: 6.25 | G47: =H47-F47 -> 3.375 | H47: 9.625
A48: Q1 2021 | B48: 3 | C48: 3.6 | D48: 4 | E48: 8 | F48: 6.5 | G48: =H48-F48 -> 3.5 | H48: 10
A49: Q2 2021 | B49: 3.225 | C49: 3.9 | D49: 4.3 | E49: 8 | F49: 6.875 | G49: =H49-F49 -> 3.75 | H49: 10.625
A50: Q3 2021 | B50: 3.45 | C50: 4.2 | D50: 4.6 | E50: 8 | F50: 7.25 | G50: =H50-F50 -> 4 | H50: 11.25
A51: Q4 2021 | B51: 3.675 | C51: 4.5 | D51: 4.9 | E51: 8 | F51: 7.625 | G51: =H51-F51 -> 4.25 | H51: 11.875
A52: Q1 2022 | B52: 3.9 | C52: 4.8 | D52: 5.2 | E52: 8 | F52: 8 | G52: =H52-F52 -> 4.5 | H52: 12.5
A53: Q2 2022 | B53: 3.8 | C53: 4.675 | D53: 5.075 | E53: 8 | F53: 7.8 | G53: =H53-F53 -> 4.325 | H53: 12.125
A54: Q3 2022 | B54: 3.7 | C54: 4.55 | D54: 4.95 | E54: 8 | F54: 7.6 | G54: =H54-F54 -> 4.15 | H54: 11.75
A55: Q4 2022 | B55: 3.6 | C55: 4.425 | D55: 4.825 | E55: 8 | F55: 7.4 | G55: =H55-F55 -> 3.975 | H55: 11.375
... A63: Q4 2024 | B63: 3.2 | C63: 4.1 | D63: 4.5 | E63: 8 | F63: 6.8 | G63: =H63-F63 -> 3.2 | H63: 10

Sheet Assumptions
A2: =ModelDescription!A2 -> Economic Forecasting Model
A3: =ModelDescription!C4 -> Noble, OK 6 Processor Facility - Series A + Series B
A5: Economic Assumptions | C5: Unit
B6: Working Capital % per Rev | C6: % | D6: 0.15 | Q6: Crumb Rubber ($/lb) | R6: =Economics!$H$30 -> 0.67926385 | S6: =Economics!$R$30 -> 0.78024157 | T6: =Economics!$R$29 -> 14574636 | U6: =Economics!$U$9 -> 0.64389453 | AF6: Solvent ($/gallon) | AG6: =Economics!$H$30 -> 0.67926385 | AH6: =Economics!$R$30 -> 0.78024157 | AI6: =Economics!$R$29 -> 14574636 | AJ6: =Economics!$U$9 -> 0.64389453
B7: Tax Rate | C7: % | D7: =WACC!C18 -> 0.21 | Q7: 0.01 | R7: 0.92341599 | S7: 0.99896011 | T7: 20091965 | U7: 0.76688022 | AF7: =AF8-1 -> 3 | AG7: -0.0093614193 | AH7: 0.23456284 | AI7: -2954326.6 | AJ7: 0.39648018
B8: Discount Rate (WACC) | C8: % | D8: =WACC!C23 -> 0.2 | Q8: =Q7+0.01 -> 0.02 | R8: 0.89502831 | S8: 0.97308507 | T8: 19478928 | U8: 0.75321514 | AF8: =AF9-1 -> 4 | AG8: 0.13294763 | AH8: 0.33596432 | AI8: 551466.01 | AJ8: 0.47011122
B9: Depreciation Period on Capital Equipment | C9: Years | D9: 15 | Q9: =Q8+0.01 -> 0.03 | R9: 0.86698311 | S9: 0.94762558 | T9: 18865892 | U9: 0.73955006 | AF9: =AF10-1 -> 5 | AG9: 0.26912965 | AH9: 0.43898891 | AI9: 4057258.6 | AJ9: 0.5277295
B10: Debt/Loan Interest Rate | C10: % | D10: 0 | Q10: =Q9+0.01 -> 0.04 | R10: 0.83926833 | S10: 0.92257171 | T10: 18252855 | U10: 0.72588499 | AF10: =AF11-1 -> 6 | AG10: 0.40376261 | AH10: 0.54634436 | AI10: 7563051.2 | AJ10: 0.57404623
Q11: =Q10+0.01 -> 0.05 | R11: 0.81187209 | S11: 0.89791379 | T11: 17639819 | U11: 0.71221991 | AF11: =AF12-1 -> 7 | AG11: 0.53975326 | AH11: 0.65968135 | AI11: 11068844 | AJ11: 0.61208957
A12: Cost of Goods Sold | D12: Start-up | E12: 12 | F12: 24 | G12: 36 | H12: 48 | Q12: =Q11+0.01 -> 0.06 | R12: 0.78478269 | S12: 0.87364242 | T12: 17026782 | U12: 0.69855483 | AF12: =AF13-1 -> 8 | AG12: 0.67926385 | AH12: 0.78024157 | AI12: 14574636 | AJ12: 0.64389453
B13: TDF - crumb rubber - metal free ($/lb) | C13: $/lb | D13: 0.1 | E13: =D13 -> 0.1 | F13: =E13 -> 0.1 | G13: =F13 -> 0.1 | H13: =G13 -> 0.1 | Q13: =Q12+0.01 -> 0.07 | R13: 0.75798856 | S13: 0.84974839 | T13: 16413746 | U13: 0.68488976 | AF13: =AF14-1 -> 9 | AG13: 0.82411424 | AH13: 0.90914482 | AI13: 18080429 | AJ13: 0.67087928
A14: Product Sales Price | Q14: =Q13+0.01 -> 0.08 | R14: 0.73147825 | S14: 0.82622274 | T14: 15800709 | U14: 0.67122468 | AF14: 10 | AG14: 0.9759907 | AH14: 1.0475363 | AI14: 21586222 | AJ14: 0.69406245
D15: Start-up | E15: 12 | F15: 24 | G15: 36 | Q15: =Q14+0.01 -> 0.09 | R15: 0.70524043 | S15: 0.80305667 | T15: 15187673 | U15: 0.6575596 | AF15: =AF16-1 -> 11 | AG15: 1.136574 | AH15: 1.1966742 | AI15: 25092014 | AJ15: 0.7141945
B16: Solvent | C16: $/gal | D16: 8 | E16: =D16 -> 8 | F16: =E16 -> 8 | G16: =F16 -> 8 | Q16: 0.1 | R16: 0.67926385 | S16: 0.78024157 | T16: 14574636 | U16: 0.64389453 | AF16: 12 | AG16: 1.3076324 | AH16: 1.3579933 | AI16: 28597807 | AJ16: 0.73184058
B17: Carbon Black | C17: $/lb | D17: 0.5 | Q17: =Q16+0.01 -> 0.11 | R17: 0.65353732 | S17: 0.75776898 | T17: 13961600 | U17: 0.63022945 | AF17: =AF16+1 -> 13 | AG17: 1.491102 | AH17: 1.5331631 | AI17: 32103600 | AJ17: 0.74743438
B18: Gas | C18: $/MCF | D18: 1.5 | Q18: =Q17+0.01 -> 0.12 | R18: 0.62804969 | S18: 0.73563058 | T18: 13348563 | U18: 0.61656437 | AF18: =AF17+1 -> 14 | AG18: 1.6891668 | AH18: 1.7241521 | AI18: 35609392 | AJ18: 0.76131425
B19: Steel | C19: $/lb | D19: 0 | Q19: =Q18+0.01 -> 0.13 | R19: 0.60278981 | S19: 0.71381816 | T19: 12735527 | U19: 0.60289929 | AF19: =AF18+1 -> 15 | AG19: 1.9043477 | AH19: 1.9333043 | AI19: 39115185 | AJ19: 0.77374804
B20: Tire Tipping Fee | C20: $/tire | D20: 0 | Q20: =Q19+0.01 -> 0.14 | R20: 0.57774653 | S20: 0.69232359 | T20: 12122491 | U20: 0.58923422 | AF20: =AF19+1 -> 16 | AG20: 2.1396103 | AH20: 2.1634385 | AI20: 42620977 | AJ20: 0.78495055
Q21: =Q20+0.01 -> 0.15 | R21: 0.55290866 | S21: 0.67113883 | T21: 11509454 | U21: 0.57556914 | AF21: =AF20+1 -> 17 | AG21: 2.3985003 | AH21: 2.4179769 | AI21: 46126770 | AJ21: 0.79509605
A22: TiPs1000 - Capital Assumptions | Q22: =Q21+0.01 -> 0.16 | R22: 0.52826494 | S22: 0.65025587 | T22: 10896418 | U22: 0.56190406 | AF22: =AF21+1 -> 18 | AG22: 2.6853213 | AH22: 2.7011181 | AI22: 49632563 | AJ22: 0.8043274
B23: CapEx - Series A | C23: $ | D23: 15000000 | E23: 1 Machine | Q23: =Q22+0.01 -> 0.17 | R23: 0.50380399 | S23: 0.62966672 | T23: 10283381 | U23: 0.54823899 | AF23: =AF22+1 -> 19 | AG23: 3.0053733 | AH23: 3.0180719 | AI23: 53138355 | AJ23: 0.81276282
B24: Series A | C24: Month | D24: 1 | Q24: =Q23+0.01 -> 0.18 | R24: 0.47951432 | S24: 0.60936338 | T24: 9670344.6 | U24: 0.53457391 | AF24: =AF23+1 -> 20 | AG24: 3.3652809 | AH24: 3.3753852 | AI24: 56644148 | AJ24: 0.820501
B25: Series A Equity | C25: % | D25: 0.5 | Q25: =Q24+0.01 -> 0.19 | R25: 0.45538425 | S25: 0.5893378 | T25: 9057308.1 | U25: 0.52090883 | AF25: =AF24+1 -> 21 | AG25: 3.7734553 | AH25: 3.7814013 | AI25: 60149940 | AJ25: 0.82762495
Q26: =Q25+0.01 -> 0.2 | R26: 0.4314019 | S26: 0.56958186 | T26: 8444271.6 | U26: 0.50724376 | AF26: =AF25+1 -> 22 | AG26: 4.2407583 | AH26: 4.2469226 | AI26: 63655733 | AJ26: 0.83420502
Q27: =Q26+0.01 -> 0.21 | R27: 0.40755512 | S27: 0.55008734 | T27: 7831235.1 | U27: 0.49357868 | AF27: =AF26+1 -> 23 | AG27: 4.7814838 | AH27: 4.7861907 | AI27: 67161526 | AJ27: 0.8403012
B28: CapEx - Series B | C28: $ | D28: 110000000 | E28: 6 Machine
B29: Series B | C29: Month | D29: 7 | Q29: Workforce Cost Sensitvity | R29: =Economics!$H$30 -> 0.67926385 | S29: =Economics!$R$30 -> 0.78024157 | T29: =Economics!$R$29 -> 14574636 | U29: =Economics!$U$9 -> 0.64389453 | AF29: Carbon Black ($/lb) | AG29: =Economics!$H$30 -> 0.67926385 | AH29: =Economics!$R$30 -> 0.78024157 | AI29: =Economics!$R$29 -> 14574636 | AJ29: =Economics!$U$9 -> 0.64389453
B30: Series B Equity | C30: % | D30: =1/(COUNTIFS(B81:B88, ">0")) -> 0.16666667 | Q30: =Q31-0.05 -> -0.45 | R30: 0.88689688 | S30: 0.96569246 | T30: 19302615 | U30: 0.73430365 | AF30: =AF31-0.05 -> 0.05 | AG30: 0.21843732 | AH30: 0.39995916 | AI30: 2742586.4 | AJ30: 0.50765347
Q31: =Q32-0.05 -> -0.4 | R31: 0.86293067 | S31: 0.94395545 | T31: 18777284 | U31: 0.72425819 | AF31: =AF32-0.05 -> 0.1 | AG31: 0.26912965 | AH31: 0.43898891 | AI31: 4057258.6 | AJ31: 0.5277295
A32: TiPs1000 - Operating Assumptions | Q32: =Q33-0.05 -> -0.35 | R32: 0.83920555 | S32: 0.92251499 | T32: 18251953 | U32: 0.71421273 | AF32: =AF33-0.05 -> 0.15 | AG32: 0.31961928 | AH32: 0.4786372 | AI32: 5371930.9 | AJ32: 0.54623241
B33: Machine Operations Start | C33: Month | D33: 8 | Q33: =Q34-0.05 -> -0.3 | R33: 0.81571405 | S33: 0.90136501 | T33: 17726622 | U33: 0.70416728 | AF33: =AF34-0.05 -> 0.2 | AG33: 0.37007351 | AH33: 0.51899909 | AI33: 6686603.1 | AJ33: 0.56334016
B34: Operating Schedule | C34: Hours/day | D34: 24 | Q34: =Q35-0.05 -> -0.25 | R34: 0.79244883 | S34: 0.88049959 | T34: 17201291 | U34: 0.69412182 | AF34: =AF35-0.05 -> 0.25 | AG34: 0.42063791 | AH34: 0.56015656 | AI34: 8001275.3 | AJ34: 0.57920479
B35: Operating Availability | C35: % | D35: 0.84 | Q35: =Q36-0.05 -> -0.2 | R35: 0.76940257 | S35: 0.85991291 | T35: 16675960 | U35: 0.68407636 | AF35: =AF36-0.05 -> 0.3 | AG35: 0.47144172 | AH35: 0.60218231 | AI35: 9315947.5 | AJ35: 0.59395705
A36: Labour | Q36: =Q37-0.05 -> -0.15 | R36: 0.74656808 | S36: 0.83959931 | T36: 16150629 | U36: 0.6740309 | AF36: =AF37-0.05 -> 0.35 | AG36: 0.52260186 | AH36: 0.6451427 | AI36: 10630620 | AJ36: 0.60770998
B37: Supervision | C37: $/hr | D37: 65 | Q37: =Q38-0.05 -> -0.1 | R37: 0.72393819 | S37: 0.81955318 | T37: 15625298 | U37: 0.66398544 | AF37: =AF38-0.05 -> 0.4 | AG37: 0.57422599 | AH37: 0.68909985 | AI37: 11945292 | AJ37: 0.62056179
B38: Plant Operators | C38: $/hr | D38: 50 | Q38: =Q39-0.05 -> -0.05 | R38: 0.7015058 | S38: 0.79976907 | T38: 15099967 | U38: 0.65393998 | AF38: =AF39-0.05 -> 0.45 | AG38: 0.6264148 | AH38: 0.73411335 | AI38: 13259964 | AJ38: 0.63259824
B39: Material Handling | C39: $/hr | D39: 30 | Q39: 0 | R39: 0.67926385 | S39: 0.78024157 | T39: 14574636 | U39: 0.64389453 | AF39: 0.5 | AG39: 0.67926385 | AH39: 0.78024157 | AI39: 14574636 | AJ39: 0.64389453
B40: Packaging | C40: $/hr | D40: 25 | Q40: =Q39+0.05 -> 0.05 | R40: 0.65720531 | S40: 0.76096538 | T40: 14049306 | U40: 0.63384907 | AF40: =AF39+0.05 -> 0.55 | AG40: 0.73286506 | AH40: 0.82754271 | AI40: 15889309 | AJ40: 0.65451689
Q41: =Q40+0.05 -> 0.1 | R41: 0.63532315 | S41: 0.74193527 | T41: 13523975 | U41: 0.62380361 | AF41: =AF40+0.05 -> 0.6 | AG41: 0.78730791 | AH41: 0.8760756 | AI41: 17203981 | AJ41: 0.66452391
A42: Operating Expense per ton processed - see "Opcost" tab for details | Q42: =Q41+0.05 -> 0.15 | R42: 0.61361038 | S42: 0.72314605 | T42: 12998644 | U42: 0.61375815 | AF42: =AF41+0.05 -> 0.65 | AG42: 0.84268046 | AH42: 0.92590044 | AI42: 18518653 | AJ42: 0.67396752
B43: Contigency | C43: % | D43: 0.1 | Q43: =Q42+0.05 -> 0.2 | R43: 0.59206 | S43: 0.70459261 | T43: 12473313 | U43: 0.60371269 | AF43: =AF42+0.05 -> 0.7 | AG43: 0.89907023 | AH43: 0.97707936 | AI43: 19833325 | AJ43: 0.68289402
Q44: =Q43+0.05 -> 0.25 | R44: 0.57066497 | S44: 0.68626988 | T44: 11947982 | U44: 0.59366723 | AF44: =AF43+0.05 -> 0.75 | AG44: 0.95656496 | AH44: 1.0296769 | AI44: 21147998 | AJ44: 0.69134475
A45: Production per TIPs Unit | Q45: =Q44+0.05 -> 0.3 | R45: 0.54941824 | S45: 0.6681728 | T45: 11422651 | U45: 0.58362178 | AF45: =AF44+0.05 -> 0.8 | AG45: 1.0152533 | AH45: 1.0837607 | AI45: 22462670 | AJ45: 0.69935675
B46: Tire crumb feed per hour production | C46: Ton/hour | D46: =D47/D34 -> 2 | Q46: =Q45+0.05 -> 0.35 | R46: 0.52831273 | S46: 0.65029634 | T46: 10897320 | U46: 0.57357632 | AF46: =AF45+0.05 -> 0.85 | AG46: 1.0752255 | AH46: 1.1394016 | AI46: 23777342 | AJ46: 0.70696333
B47: Tire crumb feed per day production | C47: Ton/day | D47: =2*24 -> 48 | Q47: =Q46+0.05 -> 0.4 | R47: 0.50734128 | S47: 0.63263549 | T47: 10371989 | U47: 0.56353086 | AF47: =AF46+0.05 -> 0.9 | AG47: 1.136574 | AH47: 1.1966742 | AI47: 25092014 | AJ47: 0.7141945
B48: Average weight of scrap tire before shred (lbs) | C48: Lbs/tire | D48: 18 | Q48: =Q47+0.05 -> 0.45 | R48: 0.48649666 | S48: 0.61518522 | T48: 9846658 | U48: 0.5534854 | AF48: =AF47+0.05 -> 0.95 | AG48: 1.1993938 | AH48: 1.2556574 | AI48: 26406687 | AJ48: 0.72107738
B49: Avg amount of steel per tire | C49: Lbs/tire | D49: 0 | Q49: =Q48+0.05 -> 0.5 | R49: 0.46577157 | S49: 0.59794048 | T49: 9321327.1 | U49: 0.54343994 | AF49: =AF48+0.05 -> 1 | AG49: 1.2637835 | AH49: 1.3164348 | AI49: 27721359 | AJ49: 0.72763655
A51: Product Cut from tire crumb | Q51: Tire Composistion (Solvent %) | R51: =Economics!$H$30 -> 0.67926385 | S51: =Economics!$R$30 -> 0.78024157 | T51: =Economics!$R$29 -> 14574636 | U51: =Economics!$U$9 -> 0.64389453
B52: See "TiPsCalulator" tab for detail on product weight percent | Q52: =Q53-0.025 -> 0.2 | R52: 0.35511883 | S52: 0.50696055 | T52: 6297070.6 | U52: 0.5584072
B53: Ratio of Solvent by weight | D53: 0.45 | Q53: =Q54-0.025 -> 0.225 | R53: 0.3869094 | S53: 0.5326261 | T53: 7124827.2 | U53: 0.56875963
B54: Ratio of Carbon Black by weight | D54: =1-D53-D55 -> 0.45 | Q54: =Q55-0.025 -> 0.25 | R54: 0.41876164 | S54: 0.55861715 | T54: 7952583.8 | U54: 0.57863779
B55: Ratio of Gas output by weight | D55: 0.1 | Q55: =Q56-0.025 -> 0.275 | R55: 0.45070724 | S55: 0.58495153 | T55: 8780340.3 | U55: 0.58807354
Q56: =Q57-0.025 -> 0.3 | R56: 0.48277593 | S56: 0.61164606 | T56: 9608096.9 | U56: 0.59709595
A57: Management & Overhead | D57: Base | E57: Burden | F57: Annual | G57: Monthly | Q57: =Q58-0.025 -> 0.325 | R57: 0.51499582 | S57: 0.63871677 | T57: 10435854 | U57: 0.60573159
E58: 0.3 | Q58: =Q59-0.025 -> 0.35 | R58: 0.54739366 | S58: 0.66617911 | T58: 11263610 | U58: 0.61400482
B59: Plant Mgr | C59: $/head | D59: 96000 | E59: =D59*E$58 -> 28800 | F59: =(D59+E59)*(1+$D$66) -> 124800 | G59: =F59/12 -> 10400 | Q59: =Q60-0.025 -> 0.375 | R59: 0.57999508 | S59: 0.69404811 | T59: 12091367 | U59: 0.62193798
B60: Maintenance Mgr | C60: $/head | D60: 84000 | E60: =D60*E$58 -> 25200 | F60: =(D60+E60)*(1+$D$66) -> 109200 | G60: =F60/12 -> 9100 | Q60: =Q61-0.025 -> 0.4 | R60: 0.61282475 | S60: 0.72233848 | T60: 12919123 | U60: 0.62955161
B61: QC Mgr | C61: $/head | D61: 84000 | E61: =D61*E$58 -> 25200 | F61: =(D61+E61)*(1+$D$66) -> 109200 | G61: =F61/12 -> 9100 | Q61: =Q62-0.025 -> 0.425 | R61: 0.64590658 | S61: 0.75106481 | T61: 13746880 | U61: 0.63686464
B62: Shipping and receiving clerk | C62: $/head | D62: 84000 | E62: =D62*E$58 -> 25200 | F62: =(D62+E62)*(1+$D$66) -> 109200 | G62: =F62/12 -> 9100 | Q62: 0.45 | R62: 0.67926385 | S62: 0.78024157 | T62: 14574636 | U62: 0.64389453
B63: office mgr / Safety Coordinator | C63: $/head | D63: 60000 | E63: =D63*E$58 -> 18000 | F63: =(D63+E63)*(1+$D$66) -> 78000 | G63: =F63/12 -> 6500 | Q63: =Q62+0.025 -> 0.475 | R63: 0.71291935 | S63: 0.80988331 | T63: 15402393 | U63: 0.6506574
B64: Administrator | C64: $/year | D64: 60000 | E64: =D64*E$58 -> 18000 | F64: =(D64+E64)*(1+$D$66) -> 78000 | G64: =F64/12 -> 6500 | Q64: =Q63+0.025 -> 0.5 | R64: 0.74689549 | S64: 0.84000464 | T64: 16230150 | U64: 0.65716819
B65: Materials Coordinator | C65: $/head | D65: 84000 | E65: =D65*E$58 -> 25200 | F65: =(D65+E65)*(1+$D$66) -> 109200 | G65: =F65/12 -> 9100 | Q65: =Q64+0.025 -> 0.525 | R65: 0.7812144 | S65: 0.87062037 | T65: 17057906 | U65: 0.66344074
B66: Management + Labor Contigency | C66: % | D66: 0 | Q66: =Q65+0.025 -> 0.55 | R66: 0.81589802 | S66: 0.90174556 | T66: 17885663 | U66: 0.66948788
A67: Operating Labor | Q67: =Q66+0.025 -> 0.575 | R67: 0.8509682 | S67: 0.93339553 | T67: 18713419 | U67: 0.67532155
D68: Base Need | Q68: =Q67+0.025 -> 0.6 | R68: 0.88644678 | S68: 0.96558598 | T68: 19541176 | U68: 0.68095286
B69: Supervision | C69: Heads/machine | D69: 0.33 | Q69: =Q68+0.025 -> 0.625 | R69: 0.92235563 | S69: 0.998333 | T69: 20368933 | U69: 0.68639216
B70: Plant Operators ($/hr) | C70: Heads/machine | D70: 2.5 | Q70: =Q69+0.025 -> 0.65 | R70: 0.95871676 | S70: 1.0316531 | T70: 21196689 | U70: 0.6916491
B71: Material Handling ($/hr) | C71: Heads/machine | D71: 2.5 | Q71: =Q70+0.025 -> 0.675 | R71: 0.99555237 | S71: 1.0655634 | T71: 22024446 | U71: 0.6967327
B72: Packaging | C72: Heads/machine | D72: 2.5
A75: Schedule
C76: Period | D76: 1 | E76: 2 | F76: 3 | G76: 4 | H76: 5 | I76: 6 | J76: 7 | K76: 8 | L76: 9 | M76: 10 | N76: 11 | O76: 12 | P76: 13 | Q76: 14 | R76: 15 | S76: 16 | T76: 17 | U76: 18 | V76: 19 | W76: 20 | X76: 21 | Y76: 22 | Z76: 23 | AA76: 24 | AB76: 25 | AC76: 26 | AD76: 27 | AE76: 28 | AF76: 29 | AG76: 30 | AH76: 31 | AI76: 32 | AJ76: 33 | AK76: 34 | AL76: 35 | AM76: 36 | AN76: 37 | AO76: 38 | AP76: 39 | AQ76: 40 | AR76: 41 | AS76: 42 | AT76: 43 | AU76: 44 | AV76: 45 | AW76: 46 | AX76: 47 | AY76: 48 | AZ76: 49 | BA76: 50 | BB76: 51 | BC76: 52 | BD76: 53 | BE76: 54 | BF76: 55 | BG76: 56 | BH76: 57 | BI76: 58 | BJ76: 59 | BK76: 60 | BL76: 61 | BM76: 62 | BN76: 63 | BO76: 64 | BP76: 65 | BQ76: 66 | BR76: 67 | BS76: 68 | BT76: 69 | BU76: 70 | BV76: 71 | BW76: 72 | BX76: 73 | BY76: 74 | BZ76: 75 | CA76: 76 | CB76: 77 | CC76: 78 | CD76: 79 | CE76: 80 | CF76: 81 | CG76: 82 | CH76: 83 | CI76: 84 | CJ76: 85 | CK76: 86 | CL76: 87 | CM76: 88 | CN76: 89 | CO76: 90 | CP76: 91 | CQ76: 92 | CR76: 93 | CS76: 94 | CT76: 95 | CU76: 96 | CV76: 97 | CW76: 98 | CX76: 99 | CY76: 100 | CZ76: 101 | DA76: 102 | DB76: 103 | DC76: 104 | DD76: 105 | DE76: 106 | DF76: 107 | DG76: 108 | DH76: 109 | DI76: 110 | DJ76: 111 | DK76: 112 | DL76: 113 | DM76: 114 | DN76: 115 | DO76: 116 | DP76: 117 | DQ76: 118 | DR76: 119 | DS76: 120 | DT76: 121 | DU76: 122 | DV76: 123 | DW76: 124 | DX76: 125 | DY76: 126 | DZ76: 127 | EA76: 128 | EB76: 129 | EC76: 130 | ED76: 131 | EE76: 132 | EF76: 133 | EG76: 134 | EH76: 135 | EI76: 136 | EJ76: 137 | EK76: 138 | EL76: 139 | EM76: 140 | EN76: 141 | EO76: 142 | EP76: 143 | EQ76: 144 | ER76: 145 | ES76: 146 | ET76: 147 | EU76: 148 | EV76: 149 | EW76: 150 | EX76: 151 | EY76: 152 | EZ76: 153 | FA76: 154 | FB76: 155 | FC76: 156 | FD76: 157 | FE76: 158 | FF76: 159 | FG76: 160 | FH76: 161 | FI76: 162 | FJ76: 163 | FK76: 164 | FL76: 165 | FM76: 166 | FN76: 167 | FO76: 168 | FP76: 169 | FQ76: 170 | FR76: 171 | FS76: 172 | FT76: 173 | FU76: 174 | FV76: 175 | FW76: 176 | FX76: 177 | FY76: 178 | FZ76: 179 | GA76: 180
C77: Year | D77: 2026 | E77: 2026 | F77: 2026 | G77: 2026 | H77: 2026 | I77: 2026 | J77: 2026 | K77: 2026 | L77: 2026 | M77: 2026 | N77: 2026 | O77: 2026 | P77: 2027 | Q77: 2027 | R77: 2027 | S77: 2027 | T77: 2027 | U77: 2027 | V77: 2027 | W77: 2027 | X77: 2027 | Y77: 2027 | Z77: 2027 | AA77: 2027 | AB77: 2028 | AC77: 2028 | AD77: 2028 | AE77: 2028 | AF77: 2028 | AG77: 2028 | AH77: 2028 | AI77: 2028 | AJ77: 2028 | AK77: 2028 | AL77: 2028 | AM77: 2028 | AN77: 2029 | AO77: 2029 | AP77: 2029 | AQ77: 2029 | AR77: 2029 | AS77: 2029 | AT77: 2029 | AU77: 2029 | AV77: 2029 | AW77: 2029 | AX77: 2029 | AY77: 2029 | AZ77: 2030 | BA77: 2030 | BB77: 2030 | BC77: 2030 | BD77: 2030 | BE77: 2030 | BF77: 2030 | BG77: 2030 | BH77: 2030 | BI77: 2030 | BJ77: 2030 | BK77: 2030 | BL77: 2031 | BM77: 2031 | BN77: 2031 | BO77: 2031 | BP77: 2031 | BQ77: 2031 | BR77: 2031 | BS77: 2031 | BT77: 2031 | BU77: 2031 | BV77: 2031 | BW77: 2031 | BX77: 2032 | BY77: 2032 | BZ77: 2032 | CA77: 2032 | CB77: 2032 | CC77: 2032 | CD77: 2032 | CE77: 2032 | CF77: 2032 | CG77: 2032 | CH77: 2032 | CI77: 2032 | CJ77: 2033 | CK77: 2033 | CL77: 2033 | CM77: 2033 | CN77: 2033 | CO77: 2033 | CP77: 2033 | CQ77: 2033 | CR77: 2033 | CS77: 2033 | CT77: 2033 | CU77: 2033 | CV77: 2034 | CW77: 2034 | CX77: 2034 | CY77: 2034 | CZ77: 2034 | DA77: 2034 | DB77: 2034 | DC77: 2034 | DD77: 2034 | DE77: 2034 | DF77: 2034 | DG77: 2034 | DH77: 2035 | DI77: 2035 | DJ77: 2035 | DK77: 2035 | DL77: 2035 | DM77: 2035 | DN77: 2035 | DO77: 2035 | DP77: 2035 | DQ77: 2035 | DR77: 2035 | DS77: 2035 | DT77: 2036 | DU77: 2036 | DV77: 2036 | DW77: 2036 | DX77: 2036 | DY77: 2036 | DZ77: 2036 | EA77: 2036 | EB77: 2036 | EC77: 2036 | ED77: 2036 | EE77: 2036 | EF77: 2037 | EG77: 2037 | EH77: 2037 | EI77: 2037 | EJ77: 2037 | EK77: 2037 | EL77: 2037 | EM77: 2037 | EN77: 2037 | EO77: 2037 | EP77: 2037 | EQ77: 2037 | ER77: 2038 | ES77: 2038 | ET77: 2038 | EU77: 2038 | EV77: 2038 | EW77: 2038 | EX77: 2038 | EY77: 2038 | EZ77: 2038 | FA77: 2038 | FB77: 2038 | FC77: 2038 | FD77: 2039 | FE77: 2039 | FF77: 2039 | FG77: 2039 | FH77: 2039 | FI77: 2039 | FJ77: 2039 | FK77: 2039 | FL77: 2039 | FM77: 2039 | FN77: 2039 | FO77: 2039 | FP77: 2040 | FQ77: 2040 | FR77: 2040 | FS77: 2040 | FT77: 2040 | FU77: 2040 | FV77: 2040 | FW77: 2040 | FX77: 2040 | FY77: 2040 | FZ77: 2040 | GA77: 2040
C78: Month | D78: Jan | E78: Feb | F78: Mar | G78: Apr | H78: May | I78: Jun | J78: Jul | K78: Aug | L78: Sep | M78: Oct | N78: Nov | O78: Dec | P78: Jan | Q78: Feb | R78: Mar | S78: Apr | T78: May | U78: Jun | V78: Jul | W78: Aug | X78: Sep | Y78: Oct | Z78: Nov | AA78: Dec | AB78: Jan | AC78: Feb | AD78: Mar | AE78: Apr | AF78: May | AG78: Jun | AH78: Jul | AI78: Aug | AJ78: Sep | AK78: Oct | AL78: Nov | AM78: Dec | AN78: Jan | AO78: Feb | AP78: Mar | AQ78: Apr | AR78: May | AS78: Jun | AT78: Jul | AU78: Aug | AV78: Sep | AW78: Oct | AX78: Nov | AY78: Dec | AZ78: Jan | BA78: Feb | BB78: Mar | BC78: Apr | BD78: May | BE78: Jun | BF78: Jul | BG78: Aug | BH78: Sep | BI78: Oct | BJ78: Nov | BK78: Dec | BL78: Jan | BM78: Feb | BN78: Mar | BO78: Apr | BP78: May | BQ78: Jun | BR78: Jul | BS78: Aug | BT78: Sep | BU78: Oct | BV78: Nov | BW78: Dec | BX78: Jan | BY78: Feb | BZ78: Mar | CA78: Apr | CB78: May | CC78: Jun | CD78: Jul | CE78: Aug | CF78: Sep | CG78: Oct | CH78: Nov | CI78: Dec | CJ78: Jan | CK78: Feb | CL78: Mar | CM78: Apr | CN78: May | CO78: Jun | CP78: Jul | CQ78: Aug | CR78: Sep | CS78: Oct | CT78: Nov | CU78: Dec | CV78: Jan | CW78: Feb | CX78: Mar | CY78: Apr | CZ78: May | DA78: Jun | DB78: Jul | DC78: Aug | DD78: Sep | DE78: Oct | DF78: Nov | DG78: Dec | DH78: Jan | DI78: Feb | DJ78: Mar | DK78: Apr | DL78: May | DM78: Jun | DN78: Jul | DO78: Aug | DP78: Sep | DQ78: Oct | DR78: Nov | DS78: Dec | DT78: Jan | DU78: Feb | DV78: Mar | DW78: Apr | DX78: May | DY78: Jun | DZ78: Jul | EA78: Aug | EB78: Sep | EC78: Oct | ED78: Nov | EE78: Dec | EF78: Jan | EG78: Feb | EH78: Mar | EI78: Apr | EJ78: May | EK78: Jun | EL78: Jul | EM78: Aug | EN78: Sep | EO78: Oct | EP78: Nov | EQ78: Dec | ER78: Jan | ES78: Feb | ET78: Mar | EU78: Apr | EV78: May | EW78: Jun | EX78: Jul | EY78: Aug | EZ78: Sep | FA78: Oct | FB78: Nov | FC78: Dec | FD78: Jan | FE78: Feb | FF78: Mar | FG78: Apr | FH78: May | FI78: Jun | FJ78: Jul | FK78: Aug | FL78: Sep | FM78: Oct | FN78: Nov | FO78: Dec | FP78: Jan | FQ78: Feb | FR78: Mar | FS78: Apr | FT78: May | FU78: Jun | FV78: Jul | FW78: Aug | FX78: Sep | FY78: Oct | FZ78: Nov | GA78: Dec
C79: Quarter | D79: Q1 | E79: Q1 | F79: Q1 | G79: Q2 | H79: Q2 | I79: Q2 | J79: Q3 | K79: Q3 | L79: Q3 | M79: Q4 | N79: Q4 | O79: Q4 | P79: Q1 | Q79: Q1 | R79: Q1 | S79: Q2 | T79: Q2 | U79: Q2 | V79: Q3 | W79: Q3 | X79: Q3 | Y79: Q4 | Z79: Q4 | AA79: Q4 | AB79: Q1 | AC79: Q1 | AD79: Q1 | AE79: Q2 | AF79: Q2 | AG79: Q2 | AH79: Q3 | AI79: Q3 | AJ79: Q3 | AK79: Q4 | AL79: Q4 | AM79: Q4 | AN79: Q1 | AO79: Q1 | AP79: Q1 | AQ79: Q2 | AR79: Q2 | AS79: Q2 | AT79: Q3 | AU79: Q3 | AV79: Q3 | AW79: Q4 | AX79: Q4 | AY79: Q4 | AZ79: Q1 | BA79: Q1 | BB79: Q1 | BC79: Q2 | BD79: Q2 | BE79: Q2 | BF79: Q3 | BG79: Q3 | BH79: Q3 | BI79: Q4 | BJ79: Q4 | BK79: Q4 | BL79: Q1 | BM79: Q1 | BN79: Q1 | BO79: Q2 | BP79: Q2 | BQ79: Q2 | BR79: Q3 | BS79: Q3 | BT79: Q3 | BU79: Q4 | BV79: Q4 | BW79: Q4 | BX79: Q1 | BY79: Q1 | BZ79: Q1 | CA79: Q2 | CB79: Q2 | CC79: Q2 | CD79: Q3 | CE79: Q3 | CF79: Q3 | CG79: Q4 | CH79: Q4 | CI79: Q4 | CJ79: Q1 | CK79: Q1 | CL79: Q1 | CM79: Q2 | CN79: Q2 | CO79: Q2 | CP79: Q3 | CQ79: Q3 | CR79: Q3 | CS79: Q4 | CT79: Q4 | CU79: Q4 | CV79: Q1 | CW79: Q1 | CX79: Q1 | CY79: Q2 | CZ79: Q2 | DA79: Q2 | DB79: Q3 | DC79: Q3 | DD79: Q3 | DE79: Q4 | DF79: Q4 | DG79: Q4 | DH79: Q1 | DI79: Q1 | DJ79: Q1 | DK79: Q2 | DL79: Q2 | DM79: Q2 | DN79: Q3 | DO79: Q3 | DP79: Q3 | DQ79: Q4 | DR79: Q4 | DS79: Q4 | DT79: Q1 | DU79: Q1 | DV79: Q1 | DW79: Q2 | DX79: Q2 | DY79: Q2 | DZ79: Q3 | EA79: Q3 | EB79: Q3 | EC79: Q4 | ED79: Q4 | EE79: Q4 | EF79: Q1 | EG79: Q1 | EH79: Q1 | EI79: Q2 | EJ79: Q2 | EK79: Q2 | EL79: Q3 | EM79: Q3 | EN79: Q3 | EO79: Q4 | EP79: Q4 | EQ79: Q4 | ER79: Q1 | ES79: Q1 | ET79: Q1 | EU79: Q2 | EV79: Q2 | EW79: Q2 | EX79: Q3 | EY79: Q3 | EZ79: Q3 | FA79: Q4 | FB79: Q4 | FC79: Q4 | FD79: Q1 | FE79: Q1 | FF79: Q1 | FG79: Q2 | FH79: Q2 | FI79: Q2 | FJ79: Q3 | FK79: Q3 | FL79: Q3 | FM79: Q4 | FN79: Q4 | FO79: Q4 | FP79: Q1 | FQ79: Q1 | FR79: Q1 | FS79: Q2 | FT79: Q2 | FU79: Q2 | FV79: Q3 | FW79: Q3 | FX79: Q3 | FY79: Q4 | FZ79: Q4 | GA79: Q4
A80: Machine | B80: Capex Start | C80: Days | D80: 31 | E80: 28 | F80: 31 | G80: 30 | H80: 31 | I80: 30 | J80: 31 | K80: 31 | L80: 30 | M80: 31 | N80: 30 | O80: 31 | P80: 31 | Q80: 28 | R80: 31 | S80: 30 | T80: 31 | U80: 30 | V80: 31 | W80: 31 | X80: 30 | Y80: 31 | Z80: 30 | AA80: 31 | AB80: 31 | AC80: 28 | AD80: 31 | AE80: 30 | AF80: 31 | AG80: 30 | AH80: 31 | AI80: 31 | AJ80: 30 | AK80: 31 | AL80: 30 | AM80: 31 | AN80: 31 | AO80: 28 | AP80: 31 | AQ80: 30 | AR80: 31 | AS80: 30 | AT80: 31 | AU80: 31 | AV80: 30 | AW80: 31 | AX80: 30 | AY80: 31 | AZ80: 31 | BA80: 28 | BB80: 31 | BC80: 30 | BD80: 31 | BE80: 30 | BF80: 31 | BG80: 31 | BH80: 30 | BI80: 31 | BJ80: 30 | BK80: 31 | BL80: 31 | BM80: 28 | BN80: 31 | BO80: 30 | BP80: 31 | BQ80: 30 | BR80: 31 | BS80: 31 | BT80: 30 | BU80: 31 | BV80: 30 | BW80: 31 | BX80: 31 | BY80: 28 | BZ80: 31 | CA80: 30 | CB80: 31 | CC80: 30 | CD80: 31 | CE80: 31 | CF80: 30 | CG80: 31 | CH80: 30 | CI80: 31 | CJ80: 31 | CK80: 28 | CL80: 31 | CM80: 30 | CN80: 31 | CO80: 30 | CP80: 31 | CQ80: 31 | CR80: 30 | CS80: 31 | CT80: 30 | CU80: 31 | CV80: 31 | CW80: 28 | CX80: 31 | CY80: 30 | CZ80: 31 | DA80: 30 | DB80: 31 | DC80: 31 | DD80: 30 | DE80: 31 | DF80: 30 | DG80: 31 | DH80: 31 | DI80: 28 | DJ80: 31 | DK80: 30 | DL80: 31 | DM80: 30 | DN80: 31 | DO80: 31 | DP80: 30 | DQ80: 31 | DR80: 30 | DS80: 31 | DT80: 31 | DU80: 28 | DV80: 31 | DW80: 30 | DX80: 31 | DY80: 30 | DZ80: 31 | EA80: 31 | EB80: 30 | EC80: 31 | ED80: 30 | EE80: 31 | EF80: 31 | EG80: 28 | EH80: 31 | EI80: 30 | EJ80: 31 | EK80: 30 | EL80: 31 | EM80: 31 | EN80: 30 | EO80: 31 | EP80: 30 | EQ80: 31 | ER80: 31 | ES80: 28 | ET80: 31 | EU80: 30 | EV80: 31 | EW80: 30 | EX80: 31 | EY80: 31 | EZ80: 30 | FA80: 31 | FB80: 30 | FC80: 31 | FD80: 31 | FE80: 28 | FF80: 31 | FG80: 30 | FH80: 31 | FI80: 30 | FJ80: 31 | FK80: 31 | FL80: 30 | FM80: 31 | FN80: 30 | FO80: 31 | FP80: 31 | FQ80: 28 | FR80: 31 | FS80: 30 | FT80: 31 | FU80: 30 | FV80: 31 | FW80: 31 | FX80: 30 | FY80: 31 | FZ80: 30 | GA80: 31
A81: 1 | B81: =D24 -> 1 | D81: =IF($B81=D76, 1, IF(C81="", "", IF(C81<12, C81+1, ""))) -> 1 | E81: =IF($B81=Proforma!G$5, 1, IF(D81="", "", IF(D81<12, D81+1, ""))) -> 2 | F81: =IF($B81=Proforma!H$5, 1, IF(E81="", "", IF(E81<12, E81+1, ""))) -> 3 | G81: =IF($B81=Proforma!I$5, 1, IF(F81="", "", IF(F81<12, F81+1, ""))) -> 4 | H81: =IF($B81=Proforma!J$5, 1, IF(G81="", "", IF(G81<12, G81+1, ""))) -> 5 | I81: =IF($B81=Proforma!K$5, 1, IF(H81="", "", IF(H81<12, H81+1, ""))) -> 6 | J81: =IF($B81=Proforma!L$5, 1, IF(I81="", "", IF(I81<12, I81+1, ""))) -> 7 | K81: =IF($B81=Proforma!M$5, 1, IF(J81="", "", IF(J81<12, J81+1, ""))) -> 8 | L81: =IF($B81=Proforma!N$5, 1, IF(K81="", "", IF(K81<12, K81+1, ""))) -> 9 | ... GA81: =IF($B81=Proforma!GC$5, 1, IF(FZ81="", "", IF(FZ81<12, FZ81+1, "")))
A82: 2 | B82: 10 | D82: =IF(AND(ModelDescription!$D$23=$E$28, $B82=Proforma!F$5), 1, IF(C82="", "", IF(C82<12, C82+1, ""))) | E82: =IF(AND(ModelDescription!$D$23=$E$28, $B82=Proforma!G$5), 1, IF(D82="", "", IF(D82<12, D82+1, ""))) | F82: =IF(AND(ModelDescription!$D$23=$E$28, $B82=Proforma!H$5), 1, IF(E82="", "", IF(E82<12, E82+1, ""))) | G82: =IF(AND(ModelDescription!$D$23=$E$28, $B82=Proforma!I$5), 1, IF(F82="", "", IF(F82<12, F82+1, ""))) | H82: =IF(AND(ModelDescription!$D$23=$E$28, $B82=Proforma!J$5), 1, IF(G82="", "", IF(G82<12, G82+1, ""))) | I82: =IF(AND(ModelDescription!$D$23=$E$28, $B82=Proforma!K$5), 1, IF(H82="", "", IF(H82<12, H82+1, ""))) | J82: =IF(AND(ModelDescription!$D$23=$E$28, $B82=Proforma!L$5), 1, IF(I82="", "", IF(I82<12, I82+1, ""))) | K82: =IF(AND(ModelDescription!$D$23=$E$28, $B82=Proforma!M$5), 1, IF(J82="", "", IF(J82<12, J82+1, ""))) | ... GA82: =IF(AND(ModelDescription!$D$23=$E$28, $B82=Proforma!GC$5), 1, IF(FZ82="", "", IF(FZ82<12, FZ82+1, "")))
A83: 3 | B83: 11 | D83: =IF(AND(ModelDescription!$D$23=$E$28, $B83=Proforma!F$5), 1, IF(C83="", "", IF(C83<12, C83+1, ""))) | E83: =IF(AND(ModelDescription!$D$23=$E$28, $B83=Proforma!G$5), 1, IF(D83="", "", IF(D83<12, D83+1, ""))) | F83: =IF(AND(ModelDescription!$D$23=$E$28, $B83=Proforma!H$5), 1, IF(E83="", "", IF(E83<12, E83+1, ""))) | G83: =IF(AND(ModelDescription!$D$23=$E$28, $B83=Proforma!I$5), 1, IF(F83="", "", IF(F83<12, F83+1, ""))) | H83: =IF(AND(ModelDescription!$D$23=$E$28, $B83=Proforma!J$5), 1, IF(G83="", "", IF(G83<12, G83+1, ""))) | I83: =IF(AND(ModelDescription!$D$23=$E$28, $B83=Proforma!K$5), 1, IF(H83="", "", IF(H83<12, H83+1, ""))) | J83: =IF(AND(ModelDescription!$D$23=$E$28, $B83=Proforma!L$5), 1, IF(I83="", "", IF(I83<12, I83+1, ""))) | K83: =IF(AND(ModelDescription!$D$23=$E$28, $B83=Proforma!M$5), 1, IF(J83="", "", IF(J83<12, J83+1, ""))) | ... GA83: =IF(AND(ModelDescription!$D$23=$E$28, $B83=Proforma!GC$5), 1, IF(FZ83="", "", IF(FZ83<12, FZ83+1, "")))
A84: 4 | B84: 12 | D84: =IF(AND(ModelDescription!$D$23=$E$28, $B84=Proforma!F$5), 1, IF(C84="", "", IF(C84<12, C84+1, ""))) | E84: =IF(AND(ModelDescription!$D$23=$E$28, $B84=Proforma!G$5), 1, IF(D84="", "", IF(D84<12, D84+1, ""))) | F84: =IF(AND(ModelDescription!$D$23=$E$28, $B84=Proforma!H$5), 1, IF(E84="", "", IF(E84<12, E84+1, ""))) | G84: =IF(AND(ModelDescription!$D$23=$E$28, $B84=Proforma!I$5), 1, IF(F84="", "", IF(F84<12, F84+1, ""))) | H84: =IF(AND(ModelDescription!$D$23=$E$28, $B84=Proforma!J$5), 1, IF(G84="", "", IF(G84<12, G84+1, ""))) | I84: =IF(AND(ModelDescription!$D$23=$E$28, $B84=Proforma!K$5), 1, IF(H84="", "", IF(H84<12, H84+1, ""))) | J84: =IF(AND(ModelDescription!$D$23=$E$28, $B84=Proforma!L$5), 1, IF(I84="", "", IF(I84<12, I84+1, ""))) | K84: =IF(AND(ModelDescription!$D$23=$E$28, $B84=Proforma!M$5), 1, IF(J84="", "", IF(J84<12, J84+1, ""))) | ... GA84: =IF(AND(ModelDescription!$D$23=$E$28, $B84=Proforma!GC$5), 1, IF(FZ84="", "", IF(FZ84<12, FZ84+1, "")))
A85: 5 | B85: 13 | D85: =IF(AND(ModelDescription!$D$23=$E$28, $B85=Proforma!F$5), 1, IF(C85="", "", IF(C85<12, C85+1, ""))) | E85: =IF(AND(ModelDescription!$D$23=$E$28, $B85=Proforma!G$5), 1, IF(D85="", "", IF(D85<12, D85+1, ""))) | F85: =IF(AND(ModelDescription!$D$23=$E$28, $B85=Proforma!H$5), 1, IF(E85="", "", IF(E85<12, E85+1, ""))) | G85: =IF(AND(ModelDescription!$D$23=$E$28, $B85=Proforma!I$5), 1, IF(F85="", "", IF(F85<12, F85+1, ""))) | H85: =IF(AND(ModelDescription!$D$23=$E$28, $B85=Proforma!J$5), 1, IF(G85="", "", IF(G85<12, G85+1, ""))) | I85: =IF(AND(ModelDescription!$D$23=$E$28, $B85=Proforma!K$5), 1, IF(H85="", "", IF(H85<12, H85+1, ""))) | J85: =IF(AND(ModelDescription!$D$23=$E$28, $B85=Proforma!L$5), 1, IF(I85="", "", IF(I85<12, I85+1, ""))) | K85: =IF(AND(ModelDescription!$D$23=$E$28, $B85=Proforma!M$5), 1, IF(J85="", "", IF(J85<12, J85+1, ""))) | ... GA85: =IF(AND(ModelDescription!$D$23=$E$28, $B85=Proforma!GC$5), 1, IF(FZ85="", "", IF(FZ85<12, FZ85+1, "")))
A86: 6 | B86: 14 | D86: =IF(AND(ModelDescription!$D$23=$E$28, $B86=Proforma!F$5), 1, IF(C86="", "", IF(C86<12, C86+1, ""))) | E86: =IF(AND(ModelDescription!$D$23=$E$28, $B86=Proforma!G$5), 1, IF(D86="", "", IF(D86<12, D86+1, ""))) | F86: =IF(AND(ModelDescription!$D$23=$E$28, $B86=Proforma!H$5), 1, IF(E86="", "", IF(E86<12, E86+1, ""))) | G86: =IF(AND(ModelDescription!$D$23=$E$28, $B86=Proforma!I$5), 1, IF(F86="", "", IF(F86<12, F86+1, ""))) | H86: =IF(AND(ModelDescription!$D$23=$E$28, $B86=Proforma!J$5), 1, IF(G86="", "", IF(G86<12, G86+1, ""))) | I86: =IF(AND(ModelDescription!$D$23=$E$28, $B86=Proforma!K$5), 1, IF(H86="", "", IF(H86<12, H86+1, ""))) | J86: =IF(AND(ModelDescription!$D$23=$E$28, $B86=Proforma!L$5), 1, IF(I86="", "", IF(I86<12, I86+1, ""))) | K86: =IF(AND(ModelDescription!$D$23=$E$28, $B86=Proforma!M$5), 1, IF(J86="", "", IF(J86<12, J86+1, ""))) | ... GA86: =IF(AND(ModelDescription!$D$23=$E$28, $B86=Proforma!GC$5), 1, IF(FZ86="", "", IF(FZ86<12, FZ86+1, "")))
A87: 7 | D87: =IF(AND(ModelDescription!$D$23=$E$28, $B87=Proforma!F$5), 1, IF(C87="", "", IF(C87<12, C87+1, ""))) | E87: =IF(AND(ModelDescription!$D$23=$E$28, $B87=Proforma!G$5), 1, IF(D87="", "", IF(D87<12, D87+1, ""))) | F87: =IF(AND(ModelDescription!$D$23=$E$28, $B87=Proforma!H$5), 1, IF(E87="", "", IF(E87<12, E87+1, ""))) | G87: =IF(AND(ModelDescription!$D$23=$E$28, $B87=Proforma!I$5), 1, IF(F87="", "", IF(F87<12, F87+1, ""))) | H87: =IF(AND(ModelDescription!$D$23=$E$28, $B87=Proforma!J$5), 1, IF(G87="", "", IF(G87<12, G87+1, ""))) | I87: =IF(AND(ModelDescription!$D$23=$E$28, $B87=Proforma!K$5), 1, IF(H87="", "", IF(H87<12, H87+1, ""))) | J87: =IF(AND(ModelDescription!$D$23=$E$28, $B87=Proforma!L$5), 1, IF(I87="", "", IF(I87<12, I87+1, ""))) | K87: =IF(AND(ModelDescription!$D$23=$E$28, $B87=Proforma!M$5), 1, IF(J87="", "", IF(J87<12, J87+1, ""))) | ... GA87: =IF(AND(ModelDescription!$D$23=$E$28, $B87=Proforma!GC$5), 1, IF(FZ87="", "", IF(FZ87<12, FZ87+1, "")))
A88: 8 | D88: =IF(AND(ModelDescription!$D$23=$E$28, $B88=Proforma!F$5), 1, IF(C88="", "", IF(C88<12, C88+1, ""))) | E88: =IF(AND(ModelDescription!$D$23=$E$28, $B88=Proforma!G$5), 1, IF(D88="", "", IF(D88<12, D88+1, ""))) | F88: =IF(AND(ModelDescription!$D$23=$E$28, $B88=Proforma!H$5), 1, IF(E88="", "", IF(E88<12, E88+1, ""))) | G88: =IF(AND(ModelDescription!$D$23=$E$28, $B88=Proforma!I$5), 1, IF(F88="", "", IF(F88<12, F88+1, ""))) | H88: =IF(AND(ModelDescription!$D$23=$E$28, $B88=Proforma!J$5), 1, IF(G88="", "", IF(G88<12, G88+1, ""))) | I88: =IF(AND(ModelDescription!$D$23=$E$28, $B88=Proforma!K$5), 1, IF(H88="", "", IF(H88<12, H88+1, ""))) | J88: =IF(AND(ModelDescription!$D$23=$E$28, $B88=Proforma!L$5), 1, IF(I88="", "", IF(I88<12, I88+1, ""))) | K88: =IF(AND(ModelDescription!$D$23=$E$28, $B88=Proforma!M$5), 1, IF(J88="", "", IF(J88<12, J88+1, ""))) | ... GA88: =IF(AND(ModelDescription!$D$23=$E$28, $B88=Proforma!GC$5), 1, IF(FZ88="", "", IF(FZ88<12, FZ88+1, "")))

Sheet WACC
A2: =ModelDescription!A2 -> Economic Forecasting Model
A3: =ModelDescription!C4 -> Noble, OK 6 Processor Facility - Series A + Series B
A5: Cost of Equity:
B6: Cost of equity = Rf + Beta (Rm - Rf)
B7: Risk Free Rate (Rf) | C7: 0.035 | D7: Savings Bond Rate for 3 years
B8: Beta, share price movement | C8: 1 | D8: share moves in line with the market (excess of 1 = shares exagerate movement, less than 1 = shares more stable)
B9: Equity market risk premium (Rm - Rf) | C9: =0.2-C7 -> 0.165 | D9: difference between the risk free rate and investors expected return rate
A11: Cost of Debt
B12: Borrowing rate for debt (Rd) | C12: 0.08 | D12: total cost of debt
A14: Company Capital Structure
B15: Equity percent | C15: 1
B16: Debt percent | C16: =1-C15 -> 0
B18: Corporate tax rate | C18: =15%+6% -> 0.21 | D18: Assume 15% Federal Tax + 6% State Tax
A20: Weigted Average Cost of Capital
B21: Cost of Debt | C21: =C16*(C12*100-(1-C18)) -> 0
B22: Cost of Equity | C22: =C15*(C7*100+C8*C9*100) -> 20
B23: WACC (Discount Rate) | C23: =(C21+C22)/100 -> 0.2

Sheet 1 Machine Build
A2: =ModelDescription!A2 -> Economic Forecasting Model
A3: =ModelDescription!C4 -> Noble, OK 6 Processor Facility - Series A + Series B
B5: Period | F5: =Assumptions!D76 -> 1 | G5: =Assumptions!E76 -> 2 | H5: =Assumptions!F76 -> 3 | I5: =Assumptions!G76 -> 4 | J5: =Assumptions!H76 -> 5 | K5: =Assumptions!I76 -> 6 | L5: =Assumptions!J76 -> 7 | M5: =Assumptions!K76 -> 8 | ... Q5: =Assumptions!O76 -> 12
B6: Year | F6: =Assumptions!E77 -> 2026 | G6: =Assumptions!F77 -> 2026 | H6: =Assumptions!G77 -> 2026 | I6: =Assumptions!H77 -> 2026 | J6: =Assumptions!I77 -> 2026 | K6: =Assumptions!J77 -> 2026 | L6: =Assumptions!K77 -> 2026 | M6: =Assumptions!L77 -> 2026 | ... Q6: =Assumptions!P77 -> 2027
B7: Month | F7: =Assumptions!E78 -> Feb | G7: =Assumptions!F78 -> Mar | H7: =Assumptions!G78 -> Apr | I7: =Assumptions!H78 -> May | J7: =Assumptions!I78 -> Jun | K7: =Assumptions!J78 -> Jul | L7: =Assumptions!K78 -> Aug | M7: =Assumptions!L78 -> Sep | ... Q7: =Assumptions!P78 -> Jan
B8: Days | F8: =Assumptions!E80 -> 28 | G8: =Assumptions!F80 -> 31 | H8: =Assumptions!G80 -> 30 | I8: =Assumptions!H80 -> 31 | J8: =Assumptions!I80 -> 30 | K8: =Assumptions!J80 -> 31 | L8: =Assumptions!K80 -> 31 | M8: =Assumptions!L80 -> 30 | ... Q8: =Assumptions!P80 -> 31
A10: Summary
B11: Category | C11: Total | F11: 1 | G11: 2 | H11: 3 | I11: 4 | J11: 5 | K11: 6 | L11: 7 | M11: 8 | N11: 9 | O11: 10 | P11: 11 | Q11: 12
B12: Equipment & Materials | C12: =C58 -> 7290598 | F12: =F58 -> 4200199.3 | G12: =G58 -> 1698949.3 | H12: =H58 -> 1391449.3 | I12: =I58 -> 0 | J12: =J58 -> 0 | K12: =K58 -> 0 | L12: =L58 -> 0 | M12: =M58 -> 0 | ... Q12: =Q58 -> 0
B13: Facilities & Auxillary Support Systems | C13: =C81 -> 4697250 | F13: =F81 -> 1703250 | G13: =G81 -> 1309500 | H13: =H81 -> 1309500 | I13: =I81 -> 375000 | J13: =J81 -> 0 | K13: =K81 -> 0 | L13: =L81 -> 0 | M13: =M81 -> 0 | ... Q13: =Q81 -> 0
B14: Operating Costs | C14: =C112 -> 494850 | F14: =F112 -> 85450 | G14: =G112 -> 27950 | H14: =H112 -> 27950 | I14: =I112 -> 27950 | J14: =J112 -> 27950 | K14: =K112 -> 204016.67 | L14: =L112 -> 144616.67 | M14: =M112 -> 144616.67 | ... Q14: =Q112 -> 6000
B15: Professional Services | C15: 401400 | F15: =F126 -> 364550 | G15: =G126 -> 4550 | H15: =H126 -> 4550 | I15: =I126 -> 4550 | J15: =J126 -> 9550 | K15: =K126 -> 4550 | L15: =L126 -> 4550 | M15: =M126 -> 4550 | ... Q15: =Q126 -> 0
B16: Workforce - Role - Pay Rate | C16: 2775368 | F16: =F158 -> 343708.99 | G16: =G158 -> 296839.58 | H16: =H158 -> 343708.99 | I16: =I158 -> 328085.86 | J16: =J158 -> 360942.91 | K16: =K158 -> 344536.42 | L16: =L158 -> 360942.91 | M16: =M158 -> 360942.91 | ... Q16: =Q158 -> 0
B18: Total Cost Build 1 SENS Processor | C18: =SUM(F18:Q18) -> 15843457 | F18: =F16+F15+F14+F13+F12 -> 6697158.3 | G18: =G16+G15+G14+G13+G12 -> 3337788.9 | H18: =H16+H15+H14+H13+H12 -> 3077158.3 | I18: =I16+I15+I14+I13+I12 -> 735585.86 | J18: =J16+J15+J14+J13+J12 -> 398442.91 | K18: =K16+K15+K14+K13+K12 -> 553103.08 | L18: =L16+L15+L14+L13+L12 -> 510109.58 | M18: =M16+M15+M14+M13+M12 -> 510109.58 | ... Q18: =Q16+Q15+Q14+Q13+Q12 -> 6000
A20: Equipment & Materials
A21: Category | B21: Item | C21: Per Unit (Imported) | D21: Cap Schedule | E21: Cap Start | F21: 1 | G21: 2 | H21: 3 | I21: 4 | J21: 5 | K21: 6 | L21: 7 | M21: 8 | N21: 9 | O21: 10 | P21: 11 | Q21: 12
A22: Equipment & Materials
B23: Pack column, demister, liquid ring | C23: 233125 | D23: 3 | E23: 1 | F23: =IF(AND(F$21>=$E23, F$21<$E23+$D23), $C23/$D23, 0) -> 77708.333 | G23: =IF(AND(G$21>=$E23, G$21<$E23+$D23), $C23/$D23, 0) -> 77708.333 | H23: =IF(AND(H$21>=$E23, H$21<$E23+$D23), $C23/$D23, 0) -> 77708.333 | I23: =IF(AND(I$21>=$E23, I$21<$E23+$D23), $C23/$D23, 0) -> 0 | J23: =IF(AND(J$21>=$E23, J$21<$E23+$D23), $C23/$D23, 0) -> 0 | K23: =IF(AND(K$21>=$E23, K$21<$E23+$D23), $C23/$D23, 0) -> 0 | L23: =IF(AND(L$21>=$E23, L$21<$E23+$D23), $C23/$D23, 0) -> 0 | M23: =IF(AND(M$21>=$E23, M$21<$E23+$D23), $C23/$D23, 0) -> 0 | ... Q23: =IF(AND(Q$21>=$E23, Q$21<$E23+$D23), $C23/$D23, 0) -> 0
B24: Ovens | C24: 609375 | D24: 3 | E24: 1 | F24: =IF(AND(F$21>=$E24, F$21<$E24+$D24), $C24/$D24, 0) -> 203125 | G24: =IF(AND(G$21>=$E24, G$21<$E24+$D24), $C24/$D24, 0) -> 203125 | H24: =IF(AND(H$21>=$E24, H$21<$E24+$D24), $C24/$D24, 0) -> 203125 | I24: =IF(AND(I$21>=$E24, I$21<$E24+$D24), $C24/$D24, 0) -> 0 | J24: =IF(AND(J$21>=$E24, J$21<$E24+$D24), $C24/$D24, 0) -> 0 | K24: =IF(AND(K$21>=$E24, K$21<$E24+$D24), $C24/$D24, 0) -> 0 | L24: =IF(AND(L$21>=$E24, L$21<$E24+$D24), $C24/$D24, 0) -> 0 | M24: =IF(AND(M$21>=$E24, M$21<$E24+$D24), $C24/$D24, 0) -> 0 | ... Q24: =IF(AND(Q$21>=$E24, Q$21<$E24+$D24), $C24/$D24, 0) -> 0
B25: Pipe, fittings, auger tube shafts | C25: 516250 | D25: 3 | E25: 1 | F25: =IF(AND(F$21>=$E25, F$21<$E25+$D25), $C25/$D25, 0) -> 172083.33 | G25: =IF(AND(G$21>=$E25, G$21<$E25+$D25), $C25/$D25, 0) -> 172083.33 | H25: =IF(AND(H$21>=$E25, H$21<$E25+$D25), $C25/$D25, 0) -> 172083.33 | I25: =IF(AND(I$21>=$E25, I$21<$E25+$D25), $C25/$D25, 0) -> 0 | J25: =IF(AND(J$21>=$E25, J$21<$E25+$D25), $C25/$D25, 0) -> 0 | K25: =IF(AND(K$21>=$E25, K$21<$E25+$D25), $C25/$D25, 0) -> 0 | L25: =IF(AND(L$21>=$E25, L$21<$E25+$D25), $C25/$D25, 0) -> 0 | M25: =IF(AND(M$21>=$E25, M$21<$E25+$D25), $C25/$D25, 0) -> 0 | ... Q25: =IF(AND(Q$21>=$E25, Q$21<$E25+$D25), $C25/$D25, 0) -> 0
B26: Weight hopper feed system | C26: 582500 | D26: 3 | E26: 1 | F26: =IF(AND(F$21>=$E26, F$21<$E26+$D26), $C26/$D26, 0) -> 194166.67 | G26: =IF(AND(G$21>=$E26, G$21<$E26+$D26), $C26/$D26, 0) -> 194166.67 | H26: =IF(AND(H$21>=$E26, H$21<$E26+$D26), $C26/$D26, 0) -> 194166.67 | I26: =IF(AND(I$21>=$E26, I$21<$E26+$D26), $C26/$D26, 0) -> 0 | J26: =IF(AND(J$21>=$E26, J$21<$E26+$D26), $C26/$D26, 0) -> 0 | K26: =IF(AND(K$21>=$E26, K$21<$E26+$D26), $C26/$D26, 0) -> 0 | L26: =IF(AND(L$21>=$E26, L$21<$E26+$D26), $C26/$D26, 0) -> 0 | M26: =IF(AND(M$21>=$E26, M$21<$E26+$D26), $C26/$D26, 0) -> 0 | ... Q26: =IF(AND(Q$21>=$E26, Q$21<$E26+$D26), $C26/$D26, 0) -> 0
A27: National Tube sales
B28: Auger tubes | C28: 330000 | D28: 2 | E28: 1 | F28: =IF(AND(F$21>=$E28, F$21<$E28+$D28), $C28/$D28, 0) -> 165000 | G28: =IF(AND(G$21>=$E28, G$21<$E28+$D28), $C28/$D28, 0) -> 165000 | H28: =IF(AND(H$21>=$E28, H$21<$E28+$D28), $C28/$D28, 0) -> 0 | I28: =IF(AND(I$21>=$E28, I$21<$E28+$D28), $C28/$D28, 0) -> 0 | J28: =IF(AND(J$21>=$E28, J$21<$E28+$D28), $C28/$D28, 0) -> 0 | K28: =IF(AND(K$21>=$E28, K$21<$E28+$D28), $C28/$D28, 0) -> 0 | L28: =IF(AND(L$21>=$E28, L$21<$E28+$D28), $C28/$D28, 0) -> 0 | M28: =IF(AND(M$21>=$E28, M$21<$E28+$D28), $C28/$D28, 0) -> 0 | ... Q28: =IF(AND(Q$21>=$E28, Q$21<$E28+$D28), $C28/$D28, 0) -> 0
A29: Thomas Conveyor
B30: Auger flights | C30: 160000 | D30: 2 | E30: 1 | F30: =IF(AND(F$21>=$E30, F$21<$E30+$D30), $C30/$D30, 0) -> 80000 | G30: =IF(AND(G$21>=$E30, G$21<$E30+$D30), $C30/$D30, 0) -> 80000 | H30: =IF(AND(H$21>=$E30, H$21<$E30+$D30), $C30/$D30, 0) -> 0 | I30: =IF(AND(I$21>=$E30, I$21<$E30+$D30), $C30/$D30, 0) -> 0 | J30: =IF(AND(J$21>=$E30, J$21<$E30+$D30), $C30/$D30, 0) -> 0 | K30: =IF(AND(K$21>=$E30, K$21<$E30+$D30), $C30/$D30, 0) -> 0 | L30: =IF(AND(L$21>=$E30, L$21<$E30+$D30), $C30/$D30, 0) -> 0 | M30: =IF(AND(M$21>=$E30, M$21<$E30+$D30), $C30/$D30, 0) -> 0 | ... Q30: =IF(AND(Q$21>=$E30, Q$21<$E30+$D30), $C30/$D30, 0) -> 0
B31: Tapered Screw for weigh hopper | C31: 125000 | D31: 2 | E31: 1 | F31: =IF(AND(F$21>=$E31, F$21<$E31+$D31), $C31/$D31, 0) -> 62500 | G31: =IF(AND(G$21>=$E31, G$21<$E31+$D31), $C31/$D31, 0) -> 62500 | H31: =IF(AND(H$21>=$E31, H$21<$E31+$D31), $C31/$D31, 0) -> 0 | I31: =IF(AND(I$21>=$E31, I$21<$E31+$D31), $C31/$D31, 0) -> 0 | J31: =IF(AND(J$21>=$E31, J$21<$E31+$D31), $C31/$D31, 0) -> 0 | K31: =IF(AND(K$21>=$E31, K$21<$E31+$D31), $C31/$D31, 0) -> 0 | L31: =IF(AND(L$21>=$E31, L$21<$E31+$D31), $C31/$D31, 0) -> 0 | M31: =IF(AND(M$21>=$E31, M$21<$E31+$D31), $C31/$D31, 0) -> 0 | ... Q31: =IF(AND(Q$21>=$E31, Q$21<$E31+$D31), $C31/$D31, 0) -> 0
A32: Controls, motors and pumps
B33: Control Automation Component | C33: 478125 | D33: 1 | E33: 1 | F33: =IF(AND(F$21>=$E33, F$21<$E33+$D33), $C33/$D33, 0) -> 478125 | G33: =IF(AND(G$21>=$E33, G$21<$E33+$D33), $C33/$D33, 0) -> 0 | H33: =IF(AND(H$21>=$E33, H$21<$E33+$D33), $C33/$D33, 0) -> 0 | I33: =IF(AND(I$21>=$E33, I$21<$E33+$D33), $C33/$D33, 0) -> 0 | J33: =IF(AND(J$21>=$E33, J$21<$E33+$D33), $C33/$D33, 0) -> 0 | K33: =IF(AND(K$21>=$E33, K$21<$E33+$D33), $C33/$D33, 0) -> 0 | L33: =IF(AND(L$21>=$E33, L$21<$E33+$D33), $C33/$D33, 0) -> 0 | M33: =IF(AND(M$21>=$E33, M$21<$E33+$D33), $C33/$D33, 0) -> 0 | ... Q33: =IF(AND(Q$21>=$E33, Q$21<$E33+$D33), $C33/$D33, 0) -> 0
B34: Motors, gearboxes, drives, bucket elevators | C34: 356250 | D34: 1 | E34: 1 | F34: =IF(AND(F$21>=$E34, F$21<$E34+$D34), $C34/$D34, 0) -> 356250 | G34: =IF(AND(G$21>=$E34, G$21<$E34+$D34), $C34/$D34, 0) -> 0 | H34: =IF(AND(H$21>=$E34, H$21<$E34+$D34), $C34/$D34, 0) -> 0 | I34: =IF(AND(I$21>=$E34, I$21<$E34+$D34), $C34/$D34, 0) -> 0 | J34: =IF(AND(J$21>=$E34, J$21<$E34+$D34), $C34/$D34, 0) -> 0 | K34: =IF(AND(K$21>=$E34, K$21<$E34+$D34), $C34/$D34, 0) -> 0 | L34: =IF(AND(L$21>=$E34, L$21<$E34+$D34), $C34/$D34, 0) -> 0 | M34: =IF(AND(M$21>=$E34, M$21<$E34+$D34), $C34/$D34, 0) -> 0 | ... Q34: =IF(AND(Q$21>=$E34, Q$21<$E34+$D34), $C34/$D34, 0) -> 0
B35: Chiller Contols & Electrical | C35: 197500 | D35: 1 | E35: 1 | F35: =IF(AND(F$21>=$E35, F$21<$E35+$D35), $C35/$D35, 0) -> 197500 | G35: =IF(AND(G$21>=$E35, G$21<$E35+$D35), $C35/$D35, 0) -> 0 | H35: =IF(AND(H$21>=$E35, H$21<$E35+$D35), $C35/$D35, 0) -> 0 | I35: =IF(AND(I$21>=$E35, I$21<$E35+$D35), $C35/$D35, 0) -> 0 | J35: =IF(AND(J$21>=$E35, J$21<$E35+$D35), $C35/$D35, 0) -> 0 | K35: =IF(AND(K$21>=$E35, K$21<$E35+$D35), $C35/$D35, 0) -> 0 | L35: =IF(AND(L$21>=$E35, L$21<$E35+$D35), $C35/$D35, 0) -> 0 | M35: =IF(AND(M$21>=$E35, M$21<$E35+$D35), $C35/$D35, 0) -> 0 | ... Q35: =IF(AND(Q$21>=$E35, Q$21<$E35+$D35), $C35/$D35, 0) -> 0
B36: Myers (Flapper valves) | C36: 112500 | D36: 1 | E36: 1 | F36: =IF(AND(F$21>=$E36, F$21<$E36+$D36), $C36/$D36, 0) -> 112500 | G36: =IF(AND(G$21>=$E36, G$21<$E36+$D36), $C36/$D36, 0) -> 0 | H36: =IF(AND(H$21>=$E36, H$21<$E36+$D36), $C36/$D36, 0) -> 0 | I36: =IF(AND(I$21>=$E36, I$21<$E36+$D36), $C36/$D36, 0) -> 0 | J36: =IF(AND(J$21>=$E36, J$21<$E36+$D36), $C36/$D36, 0) -> 0 | K36: =IF(AND(K$21>=$E36, K$21<$E36+$D36), $C36/$D36, 0) -> 0 | L36: =IF(AND(L$21>=$E36, L$21<$E36+$D36), $C36/$D36, 0) -> 0 | M36: =IF(AND(M$21>=$E36, M$21<$E36+$D36), $C36/$D36, 0) -> 0 | ... Q36: =IF(AND(Q$21>=$E36, Q$21<$E36+$D36), $C36/$D36, 0) -> 0
B37: Myers Aubrey (Steam, and Gas Processing control valves) | C37: 335625 | D37: 1 | E37: 1 | F37: =IF(AND(F$21>=$E37, F$21<$E37+$D37), $C37/$D37, 0) -> 335625 | G37: =IF(AND(G$21>=$E37, G$21<$E37+$D37), $C37/$D37, 0) -> 0 | H37: =IF(AND(H$21>=$E37, H$21<$E37+$D37), $C37/$D37, 0) -> 0 | I37: =IF(AND(I$21>=$E37, I$21<$E37+$D37), $C37/$D37, 0) -> 0 | J37: =IF(AND(J$21>=$E37, J$21<$E37+$D37), $C37/$D37, 0) -> 0 | K37: =IF(AND(K$21>=$E37, K$21<$E37+$D37), $C37/$D37, 0) -> 0 | L37: =IF(AND(L$21>=$E37, L$21<$E37+$D37), $C37/$D37, 0) -> 0 | M37: =IF(AND(M$21>=$E37, M$21<$E37+$D37), $C37/$D37, 0) -> 0 | ... Q37: =IF(AND(Q$21>=$E37, Q$21<$E37+$D37), $C37/$D37, 0) -> 0
B38: Myers Aubrey (Flow meters) | C38: 170000 | D38: 1 | E38: 1 | F38: =IF(AND(F$21>=$E38, F$21<$E38+$D38), $C38/$D38, 0) -> 170000 | G38: =IF(AND(G$21>=$E38, G$21<$E38+$D38), $C38/$D38, 0) -> 0 | H38: =IF(AND(H$21>=$E38, H$21<$E38+$D38), $C38/$D38, 0) -> 0 | I38: =IF(AND(I$21>=$E38, I$21<$E38+$D38), $C38/$D38, 0) -> 0 | J38: =IF(AND(J$21>=$E38, J$21<$E38+$D38), $C38/$D38, 0) -> 0 | K38: =IF(AND(K$21>=$E38, K$21<$E38+$D38), $C38/$D38, 0) -> 0 | L38: =IF(AND(L$21>=$E38, L$21<$E38+$D38), $C38/$D38, 0) -> 0 | M38: =IF(AND(M$21>=$E38, M$21<$E38+$D38), $C38/$D38, 0) -> 0 | ... Q38: =IF(AND(Q$21>=$E38, Q$21<$E38+$D38), $C38/$D38, 0) -> 0
B39: Automatic Pump (Vacuum and Oil Water Separator) | C39: 172500 | D39: 1 | E39: 1 | F39: =IF(AND(F$21>=$E39, F$21<$E39+$D39), $C39/$D39, 0) -> 172500 | G39: =IF(AND(G$21>=$E39, G$21<$E39+$D39), $C39/$D39, 0) -> 0 | H39: =IF(AND(H$21>=$E39, H$21<$E39+$D39), $C39/$D39, 0) -> 0 | I39: =IF(AND(I$21>=$E39, I$21<$E39+$D39), $C39/$D39, 0) -> 0 | J39: =IF(AND(J$21>=$E39, J$21<$E39+$D39), $C39/$D39, 0) -> 0 | K39: =IF(AND(K$21>=$E39, K$21<$E39+$D39), $C39/$D39, 0) -> 0 | L39: =IF(AND(L$21>=$E39, L$21<$E39+$D39), $C39/$D39, 0) -> 0 | M39: =IF(AND(M$21>=$E39, M$21<$E39+$D39), $C39/$D39, 0) -> 0 | ... Q39: =IF(AND(Q$21>=$E39, Q$21<$E39+$D39), $C39/$D39, 0) -> 0
B40: Roberts & Spencer (Pressure transmitters, Vac Control Valves, level indicators) | C40: 168125 | D40: 1 | E40: 1 | F40: =IF(AND(F$21>=$E40, F$21<$E40+$D40), $C40/$D40, 0) -> 168125 | G40: =IF(AND(G$21>=$E40, G$21<$E40+$D40), $C40/$D40, 0) -> 0 | H40: =IF(AND(H$21>=$E40, H$21<$E40+$D40), $C40/$D40, 0) -> 0 | I40: =IF(AND(I$21>=$E40, I$21<$E40+$D40), $C40/$D40, 0) -> 0 | J40: =IF(AND(J$21>=$E40, J$21<$E40+$D40), $C40/$D40, 0) -> 0 | K40: =IF(AND(K$21>=$E40, K$21<$E40+$D40), $C40/$D40, 0) -> 0 | L40: =IF(AND(L$21>=$E40, L$21<$E40+$D40), $C40/$D40, 0) -> 0 | M40: =IF(AND(M$21>=$E40, M$21<$E40+$D40), $C40/$D40, 0) -> 0 | ... Q40: =IF(AND(Q$21>=$E40, Q$21<$E40+$D40), $C40/$D40, 0) -> 0
B41: Switch Gear and Generator | C41: 203125 | D41: 1 | E41: 1 | F41: =IF(AND(F$21>=$E41, F$21<$E41+$D41), $C41/$D41, 0) -> 203125 | G41: =IF(AND(G$21>=$E41, G$21<$E41+$D41), $C41/$D41, 0) -> 0 | H41: =IF(AND(H$21>=$E41, H$21<$E41+$D41), $C41/$D41, 0) -> 0 | I41: =IF(AND(I$21>=$E41, I$21<$E41+$D41), $C41/$D41, 0) -> 0 | J41: =IF(AND(J$21>=$E41, J$21<$E41+$D41), $C41/$D41, 0) -> 0 | K41: =IF(AND(K$21>=$E41, K$21<$E41+$D41), $C41/$D41, 0) -> 0 | L41: =IF(AND(L$21>=$E41, L$21<$E41+$D41), $C41/$D41, 0) -> 0 | M41: =IF(AND(M$21>=$E41, M$21<$E41+$D41), $C41/$D41, 0) -> 0 | ... Q41: =IF(AND(Q$21>=$E41, Q$21<$E41+$D41), $C41/$D41, 0) -> 0
B42: Control Valves, Modules, automation component | C42: 397500 | D42: 1 | E42: 1 | F42: =IF(AND(F$21>=$E42, F$21<$E42+$D42), $C42/$D42, 0) -> 397500 | G42: =IF(AND(G$21>=$E42, G$21<$E42+$D42), $C42/$D42, 0) -> 0 | H42: =IF(AND(H$21>=$E42, H$21<$E42+$D42), $C42/$D42, 0) -> 0 | I42: =IF(AND(I$21>=$E42, I$21<$E42+$D42), $C42/$D42, 0) -> 0 | J42: =IF(AND(J$21>=$E42, J$21<$E42+$D42), $C42/$D42, 0) -> 0 | K42: =IF(AND(K$21>=$E42, K$21<$E42+$D42), $C42/$D42, 0) -> 0 | L42: =IF(AND(L$21>=$E42, L$21<$E42+$D42), $C42/$D42, 0) -> 0 | M42: =IF(AND(M$21>=$E42, M$21<$E42+$D42), $C42/$D42, 0) -> 0 | ... Q42: =IF(AND(Q$21>=$E42, Q$21<$E42+$D42), $C42/$D42, 0) -> 0
A43: Oven
B44: Harbison-Walker (Refractory) | C44: 180000 | D44: 2 | E44: 2 | F44: =IF(AND(F$21>=$E44, F$21<$E44+$D44), $C44/$D44, 0) -> 0 | G44: =IF(AND(G$21>=$E44, G$21<$E44+$D44), $C44/$D44, 0) -> 90000 | H44: =IF(AND(H$21>=$E44, H$21<$E44+$D44), $C44/$D44, 0) -> 90000 | I44: =IF(AND(I$21>=$E44, I$21<$E44+$D44), $C44/$D44, 0) -> 0 | J44: =IF(AND(J$21>=$E44, J$21<$E44+$D44), $C44/$D44, 0) -> 0 | K44: =IF(AND(K$21>=$E44, K$21<$E44+$D44), $C44/$D44, 0) -> 0 | L44: =IF(AND(L$21>=$E44, L$21<$E44+$D44), $C44/$D44, 0) -> 0 | M44: =IF(AND(M$21>=$E44, M$21<$E44+$D44), $C44/$D44, 0) -> 0 | ... Q44: =IF(AND(Q$21>=$E44, Q$21<$E44+$D44), $C44/$D44, 0) -> 0
B45: GTI-Engineering (Eclipse Burner and controls) | C45: 357500 | D45: 3 | E45: 1 | F45: =IF(AND(F$21>=$E45, F$21<$E45+$D45), $C45/$D45, 0) -> 119166.67 | G45: =IF(AND(G$21>=$E45, G$21<$E45+$D45), $C45/$D45, 0) -> 119166.67 | H45: =IF(AND(H$21>=$E45, H$21<$E45+$D45), $C45/$D45, 0) -> 119166.67 | I45: =IF(AND(I$21>=$E45, I$21<$E45+$D45), $C45/$D45, 0) -> 0 | J45: =IF(AND(J$21>=$E45, J$21<$E45+$D45), $C45/$D45, 0) -> 0 | K45: =IF(AND(K$21>=$E45, K$21<$E45+$D45), $C45/$D45, 0) -> 0 | L45: =IF(AND(L$21>=$E45, L$21<$E45+$D45), $C45/$D45, 0) -> 0 | M45: =IF(AND(M$21>=$E45, M$21<$E45+$D45), $C45/$D45, 0) -> 0 | ... Q45: =IF(AND(Q$21>=$E45, Q$21<$E45+$D45), $C45/$D45, 0) -> 0
B46: Exothermics (Air to Air heat exchanger) | C46: 265000 | D46: 3 | E46: 1 | F46: =IF(AND(F$21>=$E46, F$21<$E46+$D46), $C46/$D46, 0) -> 88333.333 | G46: =IF(AND(G$21>=$E46, G$21<$E46+$D46), $C46/$D46, 0) -> 88333.333 | H46: =IF(AND(H$21>=$E46, H$21<$E46+$D46), $C46/$D46, 0) -> 88333.333 | I46: =IF(AND(I$21>=$E46, I$21<$E46+$D46), $C46/$D46, 0) -> 0 | J46: =IF(AND(J$21>=$E46, J$21<$E46+$D46), $C46/$D46, 0) -> 0 | K46: =IF(AND(K$21>=$E46, K$21<$E46+$D46), $C46/$D46, 0) -> 0 | L46: =IF(AND(L$21>=$E46, L$21<$E46+$D46), $C46/$D46, 0) -> 0 | M46: =IF(AND(M$21>=$E46, M$21<$E46+$D46), $C46/$D46, 0) -> 0 | ... Q46: =IF(AND(Q$21>=$E46, Q$21<$E46+$D46), $C46/$D46, 0) -> 0
B47: Hubbel Water heater | C47: 262500 | D47: 3 | E47: 1 | F47: =IF(AND(F$21>=$E47, F$21<$E47+$D47), $C47/$D47, 0) -> 87500 | G47: =IF(AND(G$21>=$E47, G$21<$E47+$D47), $C47/$D47, 0) -> 87500 | H47: =IF(AND(H$21>=$E47, H$21<$E47+$D47), $C47/$D47, 0) -> 87500 | I47: =IF(AND(I$21>=$E47, I$21<$E47+$D47), $C47/$D47, 0) -> 0 | J47: =IF(AND(J$21>=$E47, J$21<$E47+$D47), $C47/$D47, 0) -> 0 | K47: =IF(AND(K$21>=$E47, K$21<$E47+$D47), $C47/$D47, 0) -> 0 | L47: =IF(AND(L$21>=$E47, L$21<$E47+$D47), $C47/$D47, 0) -> 0 | M47: =IF(AND(M$21>=$E47, M$21<$E47+$D47), $C47/$D47, 0) -> 0 | ... Q47: =IF(AND(Q$21>=$E47, Q$21<$E47+$D47), $C47/$D47, 0) -> 0
B48: Emerson Thermal Couplers | C48: 120000 | D48: 3 | E48: 1 | F48: =IF(AND(F$21>=$E48, F$21<$E48+$D48), $C48/$D48, 0) -> 40000 | G48: =IF(AND(G$21>=$E48, G$21<$E48+$D48), $C48/$D48, 0) -> 40000 | H48: =IF(AND(H$21>=$E48, H$21<$E48+$D48), $C48/$D48, 0) -> 40000 | I48: =IF(AND(I$21>=$E48, I$21<$E48+$D48), $C48/$D48, 0) -> 0 | J48: =IF(AND(J$21>=$E48, J$21<$E48+$D48), $C48/$D48, 0) -> 0 | K48: =IF(AND(K$21>=$E48, K$21<$E48+$D48), $C48/$D48, 0) -> 0 | L48: =IF(AND(L$21>=$E48, L$21<$E48+$D48), $C48/$D48, 0) -> 0 | M48: =IF(AND(M$21>=$E48, M$21<$E48+$D48), $C48/$D48, 0) -> 0 | ... Q48: =IF(AND(Q$21>=$E48, Q$21<$E48+$D48), $C48/$D48, 0) -> 0
A49: Reactor
B50: Cappco Fabricators (rolling and endplates) | C50: 120000 | D50: 3 | E50: 1 | F50: =IF(AND(F$21>=$E50, F$21<$E50+$D50), $C50/$D50, 0) -> 40000 | G50: =IF(AND(G$21>=$E50, G$21<$E50+$D50), $C50/$D50, 0) -> 40000 | H50: =IF(AND(H$21>=$E50, H$21<$E50+$D50), $C50/$D50, 0) -> 40000 | I50: =IF(AND(I$21>=$E50, I$21<$E50+$D50), $C50/$D50, 0) -> 0 | J50: =IF(AND(J$21>=$E50, J$21<$E50+$D50), $C50/$D50, 0) -> 0 | K50: =IF(AND(K$21>=$E50, K$21<$E50+$D50), $C50/$D50, 0) -> 0 | L50: =IF(AND(L$21>=$E50, L$21<$E50+$D50), $C50/$D50, 0) -> 0 | M50: =IF(AND(M$21>=$E50, M$21<$E50+$D50), $C50/$D50, 0) -> 0 | ... Q50: =IF(AND(Q$21>=$E50, Q$21<$E50+$D50), $C50/$D50, 0) -> 0
B51: O&D Manufacturing (Brass seals and Bearings) | C51: 120000 | D51: 3 | E51: 1 | F51: =IF(AND(F$21>=$E51, F$21<$E51+$D51), $C51/$D51, 0) -> 40000 | G51: =IF(AND(G$21>=$E51, G$21<$E51+$D51), $C51/$D51, 0) -> 40000 | H51: =IF(AND(H$21>=$E51, H$21<$E51+$D51), $C51/$D51, 0) -> 40000 | I51: =IF(AND(I$21>=$E51, I$21<$E51+$D51), $C51/$D51, 0) -> 0 | J51: =IF(AND(J$21>=$E51, J$21<$E51+$D51), $C51/$D51, 0) -> 0 | K51: =IF(AND(K$21>=$E51, K$21<$E51+$D51), $C51/$D51, 0) -> 0 | L51: =IF(AND(L$21>=$E51, L$21<$E51+$D51), $C51/$D51, 0) -> 0 | M51: =IF(AND(M$21>=$E51, M$21<$E51+$D51), $C51/$D51, 0) -> 0 | ... Q51: =IF(AND(Q$21>=$E51, Q$21<$E51+$D51), $C51/$D51, 0) -> 0
B52: Machining-Shafts,drum bearings, exp joint etc | C52: 72500 | D52: 3 | E52: 1 | F52: =IF(AND(F$21>=$E52, F$21<$E52+$D52), $C52/$D52, 0) -> 24166.667 | G52: =IF(AND(G$21>=$E52, G$21<$E52+$D52), $C52/$D52, 0) -> 24166.667 | H52: =IF(AND(H$21>=$E52, H$21<$E52+$D52), $C52/$D52, 0) -> 24166.667 | I52: =IF(AND(I$21>=$E52, I$21<$E52+$D52), $C52/$D52, 0) -> 0 | J52: =IF(AND(J$21>=$E52, J$21<$E52+$D52), $C52/$D52, 0) -> 0 | K52: =IF(AND(K$21>=$E52, K$21<$E52+$D52), $C52/$D52, 0) -> 0 | L52: =IF(AND(L$21>=$E52, L$21<$E52+$D52), $C52/$D52, 0) -> 0 | M52: =IF(AND(M$21>=$E52, M$21<$E52+$D52), $C52/$D52, 0) -> 0 | ... Q52: =IF(AND(Q$21>=$E52, Q$21<$E52+$D52), $C52/$D52, 0) -> 0
A54: Engineering and EPC Fees | C54: 475598 | D54: 3 | E54: 1 | F54: =IF(AND(F$21>=$E54, F$21<$E54+$D54), $C54/$D54, 0) -> 158532.67 | G54: =IF(AND(G$21>=$E54, G$21<$E54+$D54), $C54/$D54, 0) -> 158532.67 | H54: =IF(AND(H$21>=$E54, H$21<$E54+$D54), $C54/$D54, 0) -> 158532.67 | I54: =IF(AND(I$21>=$E54, I$21<$E54+$D54), $C54/$D54, 0) -> 0 | J54: =IF(AND(J$21>=$E54, J$21<$E54+$D54), $C54/$D54, 0) -> 0 | K54: =IF(AND(K$21>=$E54, K$21<$E54+$D54), $C54/$D54, 0) -> 0 | L54: =IF(AND(L$21>=$E54, L$21<$E54+$D54), $C54/$D54, 0) -> 0 | M54: =IF(AND(M$21>=$E54, M$21<$E54+$D54), $C54/$D54, 0) -> 0 | ... Q54: =IF(AND(Q$21>=$E54, Q$21<$E54+$D54), $C54/$D54, 0) -> 0
A55: Commissioning | C55: 100000 | D55: 3 | E55: 1 | F55: =IF(AND(F$21>=$E55, F$21<$E55+$D55), $C55/$D55, 0) -> 33333.333 | G55: =IF(AND(G$21>=$E55, G$21<$E55+$D55), $C55/$D55, 0) -> 33333.333 | H55: =IF(AND(H$21>=$E55, H$21<$E55+$D55), $C55/$D55, 0) -> 33333.333 | I55: =IF(AND(I$21>=$E55, I$21<$E55+$D55), $C55/$D55, 0) -> 0 | J55: =IF(AND(J$21>=$E55, J$21<$E55+$D55), $C55/$D55, 0) -> 0 | K55: =IF(AND(K$21>=$E55, K$21<$E55+$D55), $C55/$D55, 0) -> 0 | L55: =IF(AND(L$21>=$E55, L$21<$E55+$D55), $C55/$D55, 0) -> 0 | M55: =IF(AND(M$21>=$E55, M$21<$E55+$D55), $C55/$D55, 0) -> 0 | ... Q55: =IF(AND(Q$21>=$E55, Q$21<$E55+$D55), $C55/$D55, 0) -> 0
A56: Certification and Testing | C56: 70000 | D56: 3 | E56: 1 | F56: =IF(AND(F$21>=$E56, F$21<$E56+$D56), $C56/$D56, 0) -> 23333.333 | G56: =IF(AND(G$21>=$E56, G$21<$E56+$D56), $C56/$D56, 0) -> 23333.333 | H56: =IF(AND(H$21>=$E56, H$21<$E56+$D56), $C56/$D56, 0) -> 23333.333 | I56: =IF(AND(I$21>=$E56, I$21<$E56+$D56), $C56/$D56, 0) -> 0 | J56: =IF(AND(J$21>=$E56, J$21<$E56+$D56), $C56/$D56, 0) -> 0 | K56: =IF(AND(K$21>=$E56, K$21<$E56+$D56), $C56/$D56, 0) -> 0 | L56: =IF(AND(L$21>=$E56, L$21<$E56+$D56), $C56/$D56, 0) -> 0 | M56: =IF(AND(M$21>=$E56, M$21<$E56+$D56), $C56/$D56, 0) -> 0 | ... Q56: =IF(AND(Q$21>=$E56, Q$21<$E56+$D56), $C56/$D56, 0) -> 0
B58: Total Equipment & Materials | C58: =SUM(F58:Q58) -> 7290598 | F58: =SUM(F23:F56) -> 4200199.3 | G58: =SUM(G23:G56) -> 1698949.3 | H58: =SUM(H23:H56) -> 1391449.3 | I58: =SUM(I23:I56) -> 0 | J58: =SUM(J23:J56) -> 0 | K58: =SUM(K23:K56) -> 0 | L58: =SUM(L23:L56) -> 0 | M58: =SUM(M23:M56) -> 0 | ... Q58: =SUM(Q23:Q56) -> 0
A60: Facilities & Auxillary Support Systems
A61: Facilities
B62: Shop
B63: Sq Ft Required | C63: 10000
B64: Rate | C64: 150
B65: Total Facilities | C65: 1500000 | D65: 4 | E65: 1 | F65: =IF(AND(F$21>=$E65, F$21<$E65+$D65), $C65/$D65, 0) -> 375000 | G65: =IF(AND(G$21>=$E65, G$21<$E65+$D65), $C65/$D65, 0) -> 375000 | H65: =IF(AND(H$21>=$E65, H$21<$E65+$D65), $C65/$D65, 0) -> 375000 | I65: =IF(AND(I$21>=$E65, I$21<$E65+$D65), $C65/$D65, 0) -> 375000 | J65: =IF(AND(J$21>=$E65, J$21<$E65+$D65), $C65/$D65, 0) -> 0 | K65: =IF(AND(K$21>=$E65, K$21<$E65+$D65), $C65/$D65, 0) -> 0 | L65: =IF(AND(L$21>=$E65, L$21<$E65+$D65), $C65/$D65, 0) -> 0 | M65: =IF(AND(M$21>=$E65, M$21<$E65+$D65), $C65/$D65, 0) -> 0 | ... Q65: =IF(AND(Q$21>=$E65, Q$21<$E65+$D65), $C65/$D65, 0) -> 0
A67: Aux Support Systems
B68: Process Mechanical | C68: 313500 | D68: 3 | E68: 1 | F68: =IF(AND(F$21>=$E68, F$21<$E68+$D68), $C68/$D68, 0) -> 104500 | G68: =IF(AND(G$21>=$E68, G$21<$E68+$D68), $C68/$D68, 0) -> 104500 | H68: =IF(AND(H$21>=$E68, H$21<$E68+$D68), $C68/$D68, 0) -> 104500 | I68: =IF(AND(I$21>=$E68, I$21<$E68+$D68), $C68/$D68, 0) -> 0 | J68: =IF(AND(J$21>=$E68, J$21<$E68+$D68), $C68/$D68, 0) -> 0 | K68: =IF(AND(K$21>=$E68, K$21<$E68+$D68), $C68/$D68, 0) -> 0 | L68: =IF(AND(L$21>=$E68, L$21<$E68+$D68), $C68/$D68, 0) -> 0 | M68: =IF(AND(M$21>=$E68, M$21<$E68+$D68), $C68/$D68, 0) -> 0 | ... Q68: =IF(AND(Q$21>=$E68, Q$21<$E68+$D68), $C68/$D68, 0) -> 0
B69: Process Civl | C69: 121875 | D69: 3 | E69: 1 | F69: =IF(AND(F$21>=$E69, F$21<$E69+$D69), $C69/$D69, 0) -> 40625 | G69: =IF(AND(G$21>=$E69, G$21<$E69+$D69), $C69/$D69, 0) -> 40625 | H69: =IF(AND(H$21>=$E69, H$21<$E69+$D69), $C69/$D69, 0) -> 40625 | I69: =IF(AND(I$21>=$E69, I$21<$E69+$D69), $C69/$D69, 0) -> 0 | J69: =IF(AND(J$21>=$E69, J$21<$E69+$D69), $C69/$D69, 0) -> 0 | K69: =IF(AND(K$21>=$E69, K$21<$E69+$D69), $C69/$D69, 0) -> 0 | L69: =IF(AND(L$21>=$E69, L$21<$E69+$D69), $C69/$D69, 0) -> 0 | M69: =IF(AND(M$21>=$E69, M$21<$E69+$D69), $C69/$D69, 0) -> 0 | ... Q69: =IF(AND(Q$21>=$E69, Q$21<$E69+$D69), $C69/$D69, 0) -> 0
B70: Chilled Water Plant | C70: 393750 | D70: 1 | E70: 1 | F70: =IF(AND(F$21>=$E70, F$21<$E70+$D70), $C70/$D70, 0) -> 393750 | G70: =IF(AND(G$21>=$E70, G$21<$E70+$D70), $C70/$D70, 0) -> 0 | H70: =IF(AND(H$21>=$E70, H$21<$E70+$D70), $C70/$D70, 0) -> 0 | I70: =IF(AND(I$21>=$E70, I$21<$E70+$D70), $C70/$D70, 0) -> 0 | J70: =IF(AND(J$21>=$E70, J$21<$E70+$D70), $C70/$D70, 0) -> 0 | K70: =IF(AND(K$21>=$E70, K$21<$E70+$D70), $C70/$D70, 0) -> 0 | L70: =IF(AND(L$21>=$E70, L$21<$E70+$D70), $C70/$D70, 0) -> 0 | M70: =IF(AND(M$21>=$E70, M$21<$E70+$D70), $C70/$D70, 0) -> 0 | ... Q70: =IF(AND(Q$21>=$E70, Q$21<$E70+$D70), $C70/$D70, 0) -> 0
B71: Gas & Oil Processing / Storage | C71: 737500 | D71: 3 | E71: 1 | F71: =IF(AND(F$21>=$E71, F$21<$E71+$D71), $C71/$D71, 0) -> 245833.33 | G71: =IF(AND(G$21>=$E71, G$21<$E71+$D71), $C71/$D71, 0) -> 245833.33 | H71: =IF(AND(H$21>=$E71, H$21<$E71+$D71), $C71/$D71, 0) -> 245833.33 | I71: =IF(AND(I$21>=$E71, I$21<$E71+$D71), $C71/$D71, 0) -> 0 | J71: =IF(AND(J$21>=$E71, J$21<$E71+$D71), $C71/$D71, 0) -> 0 | K71: =IF(AND(K$21>=$E71, K$21<$E71+$D71), $C71/$D71, 0) -> 0 | L71: =IF(AND(L$21>=$E71, L$21<$E71+$D71), $C71/$D71, 0) -> 0 | M71: =IF(AND(M$21>=$E71, M$21<$E71+$D71), $C71/$D71, 0) -> 0 | ... Q71: =IF(AND(Q$21>=$E71, Q$21<$E71+$D71), $C71/$D71, 0) -> 0
B72: Flare Stack | C72: 300000 | D72: 3 | E72: 1 | F72: =IF(AND(F$21>=$E72, F$21<$E72+$D72), $C72/$D72, 0) -> 100000 | G72: =IF(AND(G$21>=$E72, G$21<$E72+$D72), $C72/$D72, 0) -> 100000 | H72: =IF(AND(H$21>=$E72, H$21<$E72+$D72), $C72/$D72, 0) -> 100000 | I72: =IF(AND(I$21>=$E72, I$21<$E72+$D72), $C72/$D72, 0) -> 0 | J72: =IF(AND(J$21>=$E72, J$21<$E72+$D72), $C72/$D72, 0) -> 0 | K72: =IF(AND(K$21>=$E72, K$21<$E72+$D72), $C72/$D72, 0) -> 0 | L72: =IF(AND(L$21>=$E72, L$21<$E72+$D72), $C72/$D72, 0) -> 0 | M72: =IF(AND(M$21>=$E72, M$21<$E72+$D72), $C72/$D72, 0) -> 0 | ... Q72: =IF(AND(Q$21>=$E72, Q$21<$E72+$D72), $C72/$D72, 0) -> 0
B73: Carbon Black Processing / Storage | C73: 812500 | D73: 3 | E73: 1 | F73: =IF(AND(F$21>=$E73, F$21<$E73+$D73), $C73/$D73, 0) -> 270833.33 | G73: =IF(AND(G$21>=$E73, G$21<$E73+$D73), $C73/$D73, 0) -> 270833.33 | H73: =IF(AND(H$21>=$E73, H$21<$E73+$D73), $C73/$D73, 0) -> 270833.33 | I73: =IF(AND(I$21>=$E73, I$21<$E73+$D73), $C73/$D73, 0) -> 0 | J73: =IF(AND(J$21>=$E73, J$21<$E73+$D73), $C73/$D73, 0) -> 0 | K73: =IF(AND(K$21>=$E73, K$21<$E73+$D73), $C73/$D73, 0) -> 0 | L73: =IF(AND(L$21>=$E73, L$21<$E73+$D73), $C73/$D73, 0) -> 0 | M73: =IF(AND(M$21>=$E73, M$21<$E73+$D73), $C73/$D73, 0) -> 0 | ... Q73: =IF(AND(Q$21>=$E73, Q$21<$E73+$D73), $C73/$D73, 0) -> 0
B74: Steam Boiler | C74: 293125 | D74: 3 | E74: 1 | F74: =IF(AND(F$21>=$E74, F$21<$E74+$D74), $C74/$D74, 0) -> 97708.333 | G74: =IF(AND(G$21>=$E74, G$21<$E74+$D74), $C74/$D74, 0) -> 97708.333 | H74: =IF(AND(H$21>=$E74, H$21<$E74+$D74), $C74/$D74, 0) -> 97708.333 | I74: =IF(AND(I$21>=$E74, I$21<$E74+$D74), $C74/$D74, 0) -> 0 | J74: =IF(AND(J$21>=$E74, J$21<$E74+$D74), $C74/$D74, 0) -> 0 | K74: =IF(AND(K$21>=$E74, K$21<$E74+$D74), $C74/$D74, 0) -> 0 | L74: =IF(AND(L$21>=$E74, L$21<$E74+$D74), $C74/$D74, 0) -> 0 | M74: =IF(AND(M$21>=$E74, M$21<$E74+$D74), $C74/$D74, 0) -> 0 | ... Q74: =IF(AND(Q$21>=$E74, Q$21<$E74+$D74), $C74/$D74, 0) -> 0
B75: Dirty Water Treatment | C75: 93750 | D75: 3 | E75: 1 | F75: =IF(AND(F$21>=$E75, F$21<$E75+$D75), $C75/$D75, 0) -> 31250 | G75: =IF(AND(G$21>=$E75, G$21<$E75+$D75), $C75/$D75, 0) -> 31250 | H75: =IF(AND(H$21>=$E75, H$21<$E75+$D75), $C75/$D75, 0) -> 31250 | I75: =IF(AND(I$21>=$E75, I$21<$E75+$D75), $C75/$D75, 0) -> 0 | J75: =IF(AND(J$21>=$E75, J$21<$E75+$D75), $C75/$D75, 0) -> 0 | K75: =IF(AND(K$21>=$E75, K$21<$E75+$D75), $C75/$D75, 0) -> 0 | L75: =IF(AND(L$21>=$E75, L$21<$E75+$D75), $C75/$D75, 0) -> 0 | M75: =IF(AND(M$21>=$E75, M$21<$E75+$D75), $C75/$D75, 0) -> 0 | ... Q75: =IF(AND(Q$21>=$E75, Q$21<$E75+$D75), $C75/$D75, 0) -> 0
B76: Compressed Air Plant | C76: 100000 | D76: 3 | E76: 1 | F76: =IF(AND(F$21>=$E76, F$21<$E76+$D76), $C76/$D76, 0) -> 33333.333 | G76: =IF(AND(G$21>=$E76, G$21<$E76+$D76), $C76/$D76, 0) -> 33333.333 | H76: =IF(AND(H$21>=$E76, H$21<$E76+$D76), $C76/$D76, 0) -> 33333.333 | I76: =IF(AND(I$21>=$E76, I$21<$E76+$D76), $C76/$D76, 0) -> 0 | J76: =IF(AND(J$21>=$E76, J$21<$E76+$D76), $C76/$D76, 0) -> 0 | K76: =IF(AND(K$21>=$E76, K$21<$E76+$D76), $C76/$D76, 0) -> 0 | L76: =IF(AND(L$21>=$E76, L$21<$E76+$D76), $C76/$D76, 0) -> 0 | M76: =IF(AND(M$21>=$E76, M$21<$E76+$D76), $C76/$D76, 0) -> 0 | ... Q76: =IF(AND(Q$21>=$E76, Q$21<$E76+$D76), $C76/$D76, 0) -> 0
B77: Pressure wash system | C77: 31250 | D77: 3 | E77: 1 | F77: =IF(AND(F$21>=$E77, F$21<$E77+$D77), $C77/$D77, 0) -> 10416.667 | G77: =IF(AND(G$21>=$E77, G$21<$E77+$D77), $C77/$D77, 0) -> 10416.667 | H77: =IF(AND(H$21>=$E77, H$21<$E77+$D77), $C77/$D77, 0) -> 10416.667 | I77: =IF(AND(I$21>=$E77, I$21<$E77+$D77), $C77/$D77, 0) -> 0 | J77: =IF(AND(J$21>=$E77, J$21<$E77+$D77), $C77/$D77, 0) -> 0 | K77: =IF(AND(K$21>=$E77, K$21<$E77+$D77), $C77/$D77, 0) -> 0 | L77: =IF(AND(L$21>=$E77, L$21<$E77+$D77), $C77/$D77, 0) -> 0 | M77: =IF(AND(M$21>=$E77, M$21<$E77+$D77), $C77/$D77, 0) -> 0 | ... Q77: =IF(AND(Q$21>=$E77, Q$21<$E77+$D77), $C77/$D77, 0) -> 0
B79: Total Aux Supporty Systems | C79: =SUM(C68:C77) -> 3197250 | F79: =SUM(F68:F77) -> 1328250 | G79: =SUM(G68:G77) -> 934500 | H79: =SUM(H68:H77) -> 934500 | I79: =SUM(I68:I77) -> 0 | J79: =SUM(J68:J77) -> 0 | K79: =SUM(K68:K77) -> 0 | L79: =SUM(L68:L77) -> 0 | M79: =SUM(M68:M77) -> 0 | ... Q79: =SUM(Q68:Q77) -> 0
B81: Total Facilities & Aux | C81: =SUM(F81:Q81) -> 4697250 | F81: =SUM(F79,F65) -> 1703250 | G81: =SUM(G79,G65) -> 1309500 | H81: =SUM(H79,H65) -> 1309500 | I81: =SUM(I79,I65) -> 375000 | J81: =SUM(J79,J65) -> 0 | K81: =SUM(K79,K65) -> 0 | L81: =SUM(L79,L65) -> 0 | M81: =SUM(M79,M65) -> 0 | ... Q81: =SUM(Q79,Q65) -> 0
A83: Operating Costs
A84: Category | B84: Item | C84: Per Unit (Imported) | D84: Cap Schedule | E84: Cap Start | F84: 1 | G84: 2 | H84: 3 | I84: 4 | J84: 5 | K84: 6 | L84: 7 | M84: 8 | N84: 9 | O84: 10 | P84: 11 | Q84: 12
A85: Corporate Infrastructure
B86: Business Licenses & Memberships | C86: 2000 | D86: 8 | E86: 1 | F86: =IF(AND(F$21>=$E86, F$21<$E86+$D86), $C86, 0) -> 2000 | G86: =IF(AND(G$21>=$E86, G$21<$E86+$D86), $C86, 0) -> 2000 | H86: =IF(AND(H$21>=$E86, H$21<$E86+$D86), $C86, 0) -> 2000 | I86: =IF(AND(I$21>=$E86, I$21<$E86+$D86), $C86, 0) -> 2000 | J86: =IF(AND(J$21>=$E86, J$21<$E86+$D86), $C86, 0) -> 2000 | K86: =IF(AND(K$21>=$E86, K$21<$E86+$D86), $C86, 0) -> 2000 | L86: =IF(AND(L$21>=$E86, L$21<$E86+$D86), $C86, 0) -> 2000 | M86: =IF(AND(M$21>=$E86, M$21<$E86+$D86), $C86, 0) -> 2000 | ... Q86: =IF(AND(Q$21>=$E86, Q$21<$E86+$D86), $C86, 0) -> 0
B87: Software & Licenses | C87: 2500 | D87: 8 | E87: 1 | F87: =IF(AND(F$21>=$E87, F$21<$E87+$D87), $C87, 0) -> 2500 | G87: =IF(AND(G$21>=$E87, G$21<$E87+$D87), $C87, 0) -> 2500 | H87: =IF(AND(H$21>=$E87, H$21<$E87+$D87), $C87, 0) -> 2500 | I87: =IF(AND(I$21>=$E87, I$21<$E87+$D87), $C87, 0) -> 2500 | J87: =IF(AND(J$21>=$E87, J$21<$E87+$D87), $C87, 0) -> 2500 | K87: =IF(AND(K$21>=$E87, K$21<$E87+$D87), $C87, 0) -> 2500 | L87: =IF(AND(L$21>=$E87, L$21<$E87+$D87), $C87, 0) -> 2500 | M87: =IF(AND(M$21>=$E87, M$21<$E87+$D87), $C87, 0) -> 2500 | ... Q87: =IF(AND(Q$21>=$E87, Q$21<$E87+$D87), $C87, 0) -> 0
B88: Insurance - General | C88: 2000 | D88: 8 | E88: 1 | F88: =IF(AND(F$21>=$E88, F$21<$E88+$D88), $C88, 0) -> 2000 | G88: =IF(AND(G$21>=$E88, G$21<$E88+$D88), $C88, 0) -> 2000 | H88: =IF(AND(H$21>=$E88, H$21<$E88+$D88), $C88, 0) -> 2000 | I88: =IF(AND(I$21>=$E88, I$21<$E88+$D88), $C88, 0) -> 2000 | J88: =IF(AND(J$21>=$E88, J$21<$E88+$D88), $C88, 0) -> 2000 | K88: =IF(AND(K$21>=$E88, K$21<$E88+$D88), $C88, 0) -> 2000 | L88: =IF(AND(L$21>=$E88, L$21<$E88+$D88), $C88, 0) -> 2000 | M88: =IF(AND(M$21>=$E88, M$21<$E88+$D88), $C88, 0) -> 2000 | ... Q88: =IF(AND(Q$21>=$E88, Q$21<$E88+$D88), $C88, 0) -> 0
B89: Interest & Bank Charges | C89: 250 | D89: 8 | E89: 1 | F89: =IF(AND(F$21>=$E89, F$21<$E89+$D89), $C89, 0) -> 250 | G89: =IF(AND(G$21>=$E89, G$21<$E89+$D89), $C89, 0) -> 250 | H89: =IF(AND(H$21>=$E89, H$21<$E89+$D89), $C89, 0) -> 250 | I89: =IF(AND(I$21>=$E89, I$21<$E89+$D89), $C89, 0) -> 250 | J89: =IF(AND(J$21>=$E89, J$21<$E89+$D89), $C89, 0) -> 250 | K89: =IF(AND(K$21>=$E89, K$21<$E89+$D89), $C89, 0) -> 250 | L89: =IF(AND(L$21>=$E89, L$21<$E89+$D89), $C89, 0) -> 250 | M89: =IF(AND(M$21>=$E89, M$21<$E89+$D89), $C89, 0) -> 250 | ... Q89: =IF(AND(Q$21>=$E89, Q$21<$E89+$D89), $C89, 0) -> 0
B90: Web Hosting/Domains/Azure | C90: 1200 | D90: 8 | E90: 1 | F90: =IF(AND(F$21>=$E90, F$21<$E90+$D90), $C90, 0) -> 1200 | G90: =IF(AND(G$21>=$E90, G$21<$E90+$D90), $C90, 0) -> 1200 | H90: =IF(AND(H$21>=$E90, H$21<$E90+$D90), $C90, 0) -> 1200 | I90: =IF(AND(I$21>=$E90, I$21<$E90+$D90), $C90, 0) -> 1200 | J90: =IF(AND(J$21>=$E90, J$21<$E90+$D90), $C90, 0) -> 1200 | K90: =IF(AND(K$21>=$E90, K$21<$E90+$D90), $C90, 0) -> 1200 | L90: =IF(AND(L$21>=$E90, L$21<$E90+$D90), $C90, 0) -> 1200 | M90: =IF(AND(M$21>=$E90, M$21<$E90+$D90), $C90, 0) -> 1200 | ... Q90: =IF(AND(Q$21>=$E90, Q$21<$E90+$D90), $C90, 0) -> 0
B91: L1 Visas - 7500 / person (5 people) | C91: 37500 | D91: 1 | E91: 1 | F91: =IF(AND(F$21>=$E91, F$21<$E91+$D91), $C91, 0) -> 37500 | G91: =IF(AND(G$21>=$E91, G$21<$E91+$D91), $C91, 0) -> 0 | H91: =IF(AND(H$21>=$E91, H$21<$E91+$D91), $C91, 0) -> 0 | I91: =IF(AND(I$21>=$E91, I$21<$E91+$D91), $C91, 0) -> 0 | J91: =IF(AND(J$21>=$E91, J$21<$E91+$D91), $C91, 0) -> 0 | K91: =IF(AND(K$21>=$E91, K$21<$E91+$D91), $C91, 0) -> 0 | L91: =IF(AND(L$21>=$E91, L$21<$E91+$D91), $C91, 0) -> 0 | M91: =IF(AND(M$21>=$E91, M$21<$E91+$D91), $C91, 0) -> 0 | ... Q91: =IF(AND(Q$21>=$E91, Q$21<$E91+$D91), $C91, 0) -> 0
B93: Total Corporate Infrastructure | C93: =SUM(C86:C91) -> 45450 | F93: =SUM(F86:F91) -> 45450 | G93: =SUM(G86:G91) -> 7950 | H93: =SUM(H86:H91) -> 7950 | I93: =SUM(I86:I91) -> 7950 | J93: =SUM(J86:J91) -> 7950 | K93: =SUM(K86:K91) -> 7950 | L93: =SUM(L86:L91) -> 7950 | M93: =SUM(M86:M91) -> 7950 | ... Q93: =SUM(Q86:Q91) -> 0
A95: Travel & Accommodations
B96: Travel | C96: 5000 | D96: 8 | E96: 1 | F96: =IF(AND(F$21>=$E96, F$21<$E96+$D96), $C96, 0) -> 5000 | G96: =IF(AND(G$21>=$E96, G$21<$E96+$D96), $C96, 0) -> 5000 | H96: =IF(AND(H$21>=$E96, H$21<$E96+$D96), $C96, 0) -> 5000 | I96: =IF(AND(I$21>=$E96, I$21<$E96+$D96), $C96, 0) -> 5000 | J96: =IF(AND(J$21>=$E96, J$21<$E96+$D96), $C96, 0) -> 5000 | K96: =IF(AND(K$21>=$E96, K$21<$E96+$D96), $C96, 0) -> 5000 | L96: =IF(AND(L$21>=$E96, L$21<$E96+$D96), $C96, 0) -> 5000 | M96: =IF(AND(M$21>=$E96, M$21<$E96+$D96), $C96, 0) -> 5000 | ... Q96: =IF(AND(Q$21>=$E96, Q$21<$E96+$D96), $C96, 0) -> 0
B97: Home Lease + Utilities | C97: 6000 | D97: 12 | E97: 1 | F97: =IF(AND(F$21>=$E97, F$21<$E97+$D97), $C97, 0) -> 6000 | G97: =IF(AND(G$21>=$E97, G$21<$E97+$D97), $C97, 0) -> 6000 | H97: =IF(AND(H$21>=$E97, H$21<$E97+$D97), $C97, 0) -> 6000 | I97: =IF(AND(I$21>=$E97, I$21<$E97+$D97), $C97, 0) -> 6000 | J97: =IF(AND(J$21>=$E97, J$21<$E97+$D97), $C97, 0) -> 6000 | K97: =IF(AND(K$21>=$E97, K$21<$E97+$D97), $C97, 0) -> 6000 | L97: =IF(AND(L$21>=$E97, L$21<$E97+$D97), $C97, 0) -> 6000 | M97: =IF(AND(M$21>=$E97, M$21<$E97+$D97), $C97, 0) -> 6000 | ... Q97: =IF(AND(Q$21>=$E97, Q$21<$E97+$D97), $C97, 0) -> 6000
B98: Home Lease + Furnishing | C98: 20000 | D98: 1 | E98: 1 | F98: =IF(AND(F$21>=$E98, F$21<$E98+$D98), $C98, 0) -> 20000 | G98: =IF(AND(G$21>=$E98, G$21<$E98+$D98), $C98, 0) -> 0 | H98: =IF(AND(H$21>=$E98, H$21<$E98+$D98), $C98, 0) -> 0 | I98: =IF(AND(I$21>=$E98, I$21<$E98+$D98), $C98, 0) -> 0 | J98: =IF(AND(J$21>=$E98, J$21<$E98+$D98), $C98, 0) -> 0 | K98: =IF(AND(K$21>=$E98, K$21<$E98+$D98), $C98, 0) -> 0 | L98: =IF(AND(L$21>=$E98, L$21<$E98+$D98), $C98, 0) -> 0 | M98: =IF(AND(M$21>=$E98, M$21<$E98+$D98), $C98, 0) -> 0 | ... Q98: =IF(AND(Q$21>=$E98, Q$21<$E98+$D98), $C98, 0) -> 0
B99: Lodging | C99: 1000 | D99: 8 | E99: 1 | F99: =IF(AND(F$21>=$E99, F$21<$E99+$D99), $C99, 0) -> 1000 | G99: =IF(AND(G$21>=$E99, G$21<$E99+$D99), $C99, 0) -> 1000 | H99: =IF(AND(H$21>=$E99, H$21<$E99+$D99), $C99, 0) -> 1000 | I99: =IF(AND(I$21>=$E99, I$21<$E99+$D99), $C99, 0) -> 1000 | J99: =IF(AND(J$21>=$E99, J$21<$E99+$D99), $C99, 0) -> 1000 | K99: =IF(AND(K$21>=$E99, K$21<$E99+$D99), $C99, 0) -> 1000 | L99: =IF(AND(L$21>=$E99, L$21<$E99+$D99), $C99, 0) -> 1000 | M99: =IF(AND(M$21>=$E99, M$21<$E99+$D99), $C99, 0) -> 1000 | ... Q99: =IF(AND(Q$21>=$E99, Q$21<$E99+$D99), $C99, 0) -> 0
B100: Meals | C100: 5000 | D100: 8 | E100: 1 | F100: =IF(AND(F$21>=$E100, F$21<$E100+$D100), $C100, 0) -> 5000 | G100: =IF(AND(G$21>=$E100, G$21<$E100+$D100), $C100, 0) -> 5000 | H100: =IF(AND(H$21>=$E100, H$21<$E100+$D100), $C100, 0) -> 5000 | I100: =IF(AND(I$21>=$E100, I$21<$E100+$D100), $C100, 0) -> 5000 | J100: =IF(AND(J$21>=$E100, J$21<$E100+$D100), $C100, 0) -> 5000 | K100: =IF(AND(K$21>=$E100, K$21<$E100+$D100), $C100, 0) -> 5000 | L100: =IF(AND(L$21>=$E100, L$21<$E100+$D100), $C100, 0) -> 5000 | M100: =IF(AND(M$21>=$E100, M$21<$E100+$D100), $C100, 0) -> 5000 | ... Q100: =IF(AND(Q$21>=$E100, Q$21<$E100+$D100), $C100, 0) -> 0
B101: Vehicle Rent | C101: 3000 | D101: 8 | E101: 1 | F101: =IF(AND(F$21>=$E101, F$21<$E101+$D101), $C101, 0) -> 3000 | G101: =IF(AND(G$21>=$E101, G$21<$E101+$D101), $C101, 0) -> 3000 | H101: =IF(AND(H$21>=$E101, H$21<$E101+$D101), $C101, 0) -> 3000 | I101: =IF(AND(I$21>=$E101, I$21<$E101+$D101), $C101, 0) -> 3000 | J101: =IF(AND(J$21>=$E101, J$21<$E101+$D101), $C101, 0) -> 3000 | K101: =IF(AND(K$21>=$E101, K$21<$E101+$D101), $C101, 0) -> 3000 | L101: =IF(AND(L$21>=$E101, L$21<$E101+$D101), $C101, 0) -> 3000 | M101: =IF(AND(M$21>=$E101, M$21<$E101+$D101), $C101, 0) -> 3000 | ... Q101: =IF(AND(Q$21>=$E101, Q$21<$E101+$D101), $C101, 0) -> 0
B103: Total Travel & Accommodations | C103: =SUM(C96:C101) -> 40000 | F103: =SUM(F96:F101) -> 40000 | G103: =SUM(G96:G101) -> 20000 | H103: =SUM(H96:H101) -> 20000 | I103: =SUM(I96:I101) -> 20000 | J103: =SUM(J96:J101) -> 20000 | K103: =SUM(K96:K101) -> 20000 | L103: =SUM(L96:L101) -> 20000 | M103: =SUM(M96:M101) -> 20000 | ... Q103: =SUM(Q96:Q101) -> 6000
A105: Lab Testing & Sampling
B106: Lab Fees | C106: 350000 | D106: 3 | E106: 6 | F106: =IF(AND(F$21>=$E106, F$21<$E106+$D106), $C106/$D106, 0) -> 0 | G106: =IF(AND(G$21>=$E106, G$21<$E106+$D106), $C106/$D106, 0) -> 0 | H106: =IF(AND(H$21>=$E106, H$21<$E106+$D106), $C106/$D106, 0) -> 0 | I106: =IF(AND(I$21>=$E106, I$21<$E106+$D106), $C106/$D106, 0) -> 0 | J106: =IF(AND(J$21>=$E106, J$21<$E106+$D106), $C106/$D106, 0) -> 0 | K106: =IF(AND(K$21>=$E106, K$21<$E106+$D106), $C106/$D106, 0) -> 116666.67 | L106: =IF(AND(L$21>=$E106, L$21<$E106+$D106), $C106/$D106, 0) -> 116666.67 | M106: =IF(AND(M$21>=$E106, M$21<$E106+$D106), $C106/$D106, 0) -> 116666.67 | ... Q106: =IF(AND(Q$21>=$E106, Q$21<$E106+$D106), $C106/$D106, 0) -> 0
B107: Feedstock - Coal (220 Tons $50 / ton) | C107: 11000 | D107: 1 | E107: 6 | F107: =IF(AND(F$21>=$E107, F$21<$E107+$D107), $C107/$D107, 0) -> 0 | G107: =IF(AND(G$21>=$E107, G$21<$E107+$D107), $C107/$D107, 0) -> 0 | H107: =IF(AND(H$21>=$E107, H$21<$E107+$D107), $C107/$D107, 0) -> 0 | I107: =IF(AND(I$21>=$E107, I$21<$E107+$D107), $C107/$D107, 0) -> 0 | J107: =IF(AND(J$21>=$E107, J$21<$E107+$D107), $C107/$D107, 0) -> 0 | K107: =IF(AND(K$21>=$E107, K$21<$E107+$D107), $C107/$D107, 0) -> 11000 | L107: =IF(AND(L$21>=$E107, L$21<$E107+$D107), $C107/$D107, 0) -> 0 | M107: =IF(AND(M$21>=$E107, M$21<$E107+$D107), $C107/$D107, 0) -> 0 | ... Q107: =IF(AND(Q$21>=$E107, Q$21<$E107+$D107), $C107/$D107, 0) -> 0
B108: Feedstock - Tires (220 Tons .10/lb) | C108: 48400 | D108: 1 | E108: 6 | F108: =IF(AND(F$21>=$E108, F$21<$E108+$D108), $C108/$D108, 0) -> 0 | G108: =IF(AND(G$21>=$E108, G$21<$E108+$D108), $C108/$D108, 0) -> 0 | H108: =IF(AND(H$21>=$E108, H$21<$E108+$D108), $C108/$D108, 0) -> 0 | I108: =IF(AND(I$21>=$E108, I$21<$E108+$D108), $C108/$D108, 0) -> 0 | J108: =IF(AND(J$21>=$E108, J$21<$E108+$D108), $C108/$D108, 0) -> 0 | K108: =IF(AND(K$21>=$E108, K$21<$E108+$D108), $C108/$D108, 0) -> 48400 | L108: =IF(AND(L$21>=$E108, L$21<$E108+$D108), $C108/$D108, 0) -> 0 | M108: =IF(AND(M$21>=$E108, M$21<$E108+$D108), $C108/$D108, 0) -> 0 | ... Q108: =IF(AND(Q$21>=$E108, Q$21<$E108+$D108), $C108/$D108, 0) -> 0
B110: Total Lab Testing & Sampling | C110: =SUM(C106:C108) -> 409400 | F110: =SUM(F106:F108) -> 0 | G110: =SUM(G106:G108) -> 0 | H110: =SUM(H106:H108) -> 0 | I110: =SUM(I106:I108) -> 0 | J110: =SUM(J106:J108) -> 0 | K110: =SUM(K106:K108) -> 176066.67 | L110: =SUM(L106:L108) -> 116666.67 | M110: =SUM(M106:M108) -> 116666.67 | ... Q110: =SUM(Q106:Q108) -> 0
B112: Total Operating Costs | C112: =SUM(C93+C103+C110) -> 494850 | F112: =SUM(F93+F103+F110) -> 85450 | G112: =SUM(G93+G103+G110) -> 27950 | H112: =SUM(H93+H103+H110) -> 27950 | I112: =SUM(I93+I103+I110) -> 27950 | J112: =SUM(J93+J103+J110) -> 27950 | K112: =SUM(K93+K103+K110) -> 204016.67 | L112: =SUM(L93+L103+L110) -> 144616.67 | M112: =SUM(M93+M103+M110) -> 144616.67 | ... Q112: =SUM(Q93+Q103+Q110) -> 6000
A114: Professional Services
A115: Category | B115: Item | C115: Per Unit (Imported) | D115: Cap Schedule | E115: Cap Start | F115: 1 | G115: 2 | H115: 3 | I115: 4 | J115: 5 | K115: 6 | L115: 7 | M115: 8
A116: Accounting
B117: HGA Accounting Services | C117: 1000 | D117: 8 | E117: 1 | F117: =IF(AND(F$21>=$E117, F$21<$E117+$D117), $C117, 0) -> 1000 | G117: 1000 | H117: 1000 | I117: 1000 | J117: 1000 | K117: 1000 | L117: 1000 | M117: 1000
A118: Legal
B119: HGA - Vendor / Employee Contracts | C119: 1000 | D119: 8 | E119: 1 | F119: =IF(AND(F$21>=$E119, F$21<$E119+$D119), $C119, 0) -> 1000 | G119: 1000 | H119: 1000 | I119: 1000 | J119: 1000 | K119: 1000 | L119: 1000 | M119: 1000
...

Sheet Site Construction Budget
A2: =ModelDescription!A2 -> Economic Forecasting Model
A3: =ModelDescription!C4 -> Noble, OK 6 Processor Facility - Series A + Series B
A5: Scope Assumptions:
A6: 1 | B6: Will develop approximately 13 of the 20 acres balance for fire control and Storage
A7: 2 | B7: Approximatel 8 acres will be gravel covered
A8: 3 | B8: Oil storage tanks and distribution
A9: 4 | B9: Carbon black will be pelletized stored in super sacks shrink wrapped in suitable sized lots
A10: 5 | B10: All costs are in $US
A11: 6 | B11: Includes Carbon Black Handling Equipment
A12: 7 | B12: Includes Power Generation Station
E13: =_xlfn.XLOOKUP("Series B", Proforma!$F$21:$BM$21, Proforma!$F$5:$BM$5) -> #N/A | F13: =E13+1 -> #N/A | G13: =F13+1 -> #N/A | H13: =G13+1 -> #N/A | I13: =H13+1 -> #N/A | J13: =I13+1 -> #N/A | K13: =J13+1 -> #N/A | L13: =K13+1 -> #N/A | M13: =L13+1 -> #N/A | ... Z13: =Y13+1 -> #N/A
E14: =_xlfn.XLOOKUP(E$13, Assumptions!$D$76:$GA$76, Assumptions!$D77:$GA77) -> #N/A | F14: =_xlfn.XLOOKUP(F$13, Assumptions!$D$76:$GA$76, Assumptions!$D77:$GA77) -> #N/A | G14: =_xlfn.XLOOKUP(G$13, Assumptions!$D$76:$GA$76, Assumptions!$D77:$GA77) -> #N/A | H14: =_xlfn.XLOOKUP(H$13, Assumptions!$D$76:$GA$76, Assumptions!$D77:$GA77) -> #N/A | I14: =_xlfn.XLOOKUP(I$13, Assumptions!$D$76:$GA$76, Assumptions!$D77:$GA77) -> #N/A | J14: =_xlfn.XLOOKUP(J$13, Assumptions!$D$76:$GA$76, Assumptions!$D77:$GA77) -> #N/A | K14: =_xlfn.XLOOKUP(K$13, Assumptions!$D$76:$GA$76, Assumptions!$D77:$GA77) -> #N/A | L14: =_xlfn.XLOOKUP(L$13, Assumptions!$D$76:$GA$76, Assumptions!$D77:$GA77) -> #N/A | ... Z14: =_xlfn.XLOOKUP(Z$13, Assumptions!$D$76:$GA$76, Assumptions!$D77:$GA77) -> #N/A
E15: =_xlfn.XLOOKUP(E$13, Assumptions!$D$76:$GA$76, Assumptions!$D78:$GA78) -> #N/A | F15: =_xlfn.XLOOKUP(F$13, Assumptions!$D$76:$GA$76, Assumptions!$D78:$GA78) -> #N/A | G15: =_xlfn.XLOOKUP(G$13, Assumptions!$D$76:$GA$76, Assumptions!$D78:$GA78) -> #N/A | H15: =_xlfn.XLOOKUP(H$13, Assumptions!$D$76:$GA$76, Assumptions!$D78:$GA78) -> #N/A | I15: =_xlfn.XLOOKUP(I$13, Assumptions!$D$76:$GA$76, Assumptions!$D78:$GA78) -> #N/A | J15: =_xlfn.XLOOKUP(J$13, Assumptions!$D$76:$GA$76, Assumptions!$D78:$GA78) -> #N/A | K15: =_xlfn.XLOOKUP(K$13, Assumptions!$D$76:$GA$76, Assumptions!$D78:$GA78) -> #N/A | L15: =_xlfn.XLOOKUP(L$13, Assumptions!$D$76:$GA$76, Assumptions!$D78:$GA78) -> #N/A | ... Z15: =_xlfn.XLOOKUP(Z$13, Assumptions!$D$76:$GA$76, Assumptions!$D78:$GA78) -> #N/A
B16: Budget | E16: =_xlfn.XLOOKUP(E$13, Assumptions!$D$76:$GA$76, Assumptions!$D80:$GA80) -> #N/A | F16: =_xlfn.XLOOKUP(F$13, Assumptions!$D$76:$GA$76, Assumptions!$D80:$GA80) -> #N/A | G16: =_xlfn.XLOOKUP(G$13, Assumptions!$D$76:$GA$76, Assumptions!$D80:$GA80) -> #N/A | H16: =_xlfn.XLOOKUP(H$13, Assumptions!$D$76:$GA$76, Assumptions!$D80:$GA80) -> #N/A | I16: =_xlfn.XLOOKUP(I$13, Assumptions!$D$76:$GA$76, Assumptions!$D80:$GA80) -> #N/A | J16: =_xlfn.XLOOKUP(J$13, Assumptions!$D$76:$GA$76, Assumptions!$D80:$GA80) -> #N/A | K16: =_xlfn.XLOOKUP(K$13, Assumptions!$D$76:$GA$76, Assumptions!$D80:$GA80) -> #N/A | L16: =_xlfn.XLOOKUP(L$13, Assumptions!$D$76:$GA$76, Assumptions!$D80:$GA80) -> #N/A | ... Z16: =_xlfn.XLOOKUP(Z$13, Assumptions!$D$76:$GA$76, Assumptions!$D80:$GA80) -> #N/A
A17: Div 1 | B17: Site Works / Engineering Final | C17: =SUM(E17:Z17) -> 1975000 | E17: 250000 | F17: 250000 | G17: 300000 | H17: 350000 | I17: 250000 | J17: 275000 | K17: 150000 | L17: 150000
A18: Div 2 | B18: UnderGround and Site Utilities | C18: =SUM(E18:Z18) -> 608510 | G18: 100000 | H18: 100000 | I18: 83510 | J18: 175000 | K18: 150000
A19: Div 3 | B19: Warehouse 2 @10,000 Sq Ft | C19: =SUM(E19:Z19) -> 1250000 | G19: 250000 | H19: 150000 | I19: 275000 | J19: 150000 | K19: 175000 | L19: 250000
A20: Div 4 | B20: OfficeBuilding | C20: =SUM(E20:Z20) -> 1908000 | H20: 100000 | I20: 100000 | J20: 150000 | K20: 250000 | L20: 300000 | M20: 250000 | N20: 250000 | O20: 208000 | P20: 200000 | Q20: 100000
A21: Div 5 | B21: Process Mechanical | C21: =SUM(E21:Z21) -> 4708000 | F21: 450000 | G21: 350000 | H21: 300000 | I21: 250000 | J21: 250000 | K21: 208000 | L21: 200000 | M21: 350000 | N21: 250000 | O21: 175000 | P21: 200000 | Q21: 300000 | R21: 300000 | S21: 200000 | T21: 200000 | U21: 150000 | V21: 100000 | W21: 100000 | X21: 125000 | Y21: 100000 | Z21: 150000
A22: Div 6 | B22: Process Civil | C22: =SUM(E22:Z22) -> 975000 | F22: 250000 | G22: 250000 | H22: 150000 | I22: 100000 | J22: 75000 | K22: 50000 | L22: 50000 | M22: 50000
A23: Div 7 | B23: Chilled Water Plant | C23: =SUM(E23:Z23) -> 3150000 | F23: 450000 | I23: 450000 | L23: 450000 | O23: 450000 | R23: 450000 | U23: 450000 | W23: 450000
A24: Div 8 | B24: Gas /Oil Processing and Storage | C24: =SUM(E24:Z24) -> 5900000 | F24: 950000 | G24: 150000 | H24: 550000 | I24: 550000 | J24: 150000 | K24: 150000 | L24: 500000 | M24: 175000 | N24: 150000 | O24: 450000 | P24: 250000 | Q24: 150000 | R24: 175000 | S24: 450000 | T24: 175000 | U24: 300000 | V24: 175000 | W24: 450000
A25: Div 9 | B25: Flare Stack | C25: =SUM(E25:Z25) -> 300000 | W25: 150000 | Z25: 150000
A26: Div 10 | B26: Carbon Black Processing/ Storage | C26: =SUM(E26:Z26) -> 6500000 | F26: 3250000 | G26: 150000 | H26: 250000 | I26: 75000 | J26: 100000 | K26: 50000 | L26: 550000 | M26: 50000 | N26: 75000 | O26: 350000 | P26: 150000 | Q26: 250000 | R26: 350000 | S26: 100000 | T26: 50000 | U26: 100000 | V26: 200000 | W26: 150000 | X26: 100000 | Y26: 150000
A27: Div 11 | B27: Steam Boiler | C27: =SUM(E27:Z27) -> 2345000 | F27: 350000 | G27: 30000 | H27: 25000 | I27: 15000 | J27: 350000 | K27: 30000 | L27: 25000 | M27: 350000 | N27: 30000 | O27: 25000 | P27: 350000 | Q27: 30000 | R27: 25000 | S27: 250000 | T27: 30000 | U27: 25000 | V27: 350000 | W27: 30000 | X27: 25000
A28: Div 12 | B28: Dirty Water Treatment | C28: =SUM(E28:Z28) -> 750000 | G28: 250000 | K28: 250000 | O28: 250000
A29: Div 13 | B29: R/O Water Treatment | C29: =SUM(E29:Z29) -> 1480000 | H29: 675000 | I29: 65000 | S29: 675000 | T29: 65000
A30: Div 14 | B30: Back Up Generator | C30: =SUM(E30:Z30) -> 1200000 | G30: 600000 | R30: 600000
A31: Div 15 | B31: Compressed Air Plant | C31: =SUM(E31:Z31) -> 800000 | G31: 350000 | Q31: 350000 | V31: 100000
A32: Div 16 | B32: Pressure Wash System | C32: =SUM(E32:Z32) -> 250000 | F32: 250000
B33: Carbon Black Pellitizer | C33: =SUM(E33:Z33) -> 2050000 | F33: 1800000 | M33: 250000
B34: Material Handling Equip - Site | C34: =SUM(E34:Z34) -> 2100000 | G34: 350000 | I34: 400000 | K34: 450000 | Q34: 450000 | V34: 450000
B35: Permits and Consulting Fees - Site | C35: =SUM(E35:Z35) -> 120000 | E35: 65000 | G35: 35000 | I35: 20000
B36: Mobilization Costs | C36: =SUM(E36:Z36) -> 65000 | E36: 65000
B40: Subtotal | C40: =SUM(C17:C36) -> 38434510 | E40: =SUM(E17:E36) -> 380000 | F40: =SUM(F17:F36) -> 8000000 | G40: =SUM(G17:G36) -> 3165000 | H40: =SUM(H17:H36) -> 2650000 | I40: =SUM(I17:I36) -> 2633510 | J40: =SUM(J17:J36) -> 1675000 | K40: =SUM(K17:K36) -> 1913000 | L40: =SUM(L17:L36) -> 2475000 | ... Z40: =SUM(Z17:Z36) -> 300000
B41: Contractor's Fee Included | C41: =C40*0 -> 0 | E41: =E40*0 -> 0 | F41: =F40*0 -> 0 | G41: =G40*0 -> 0 | H41: =H40*0 -> 0 | I41: =I40*0 -> 0 | J41: =J40*0 -> 0 | K41: =K40*0 -> 0 | L41: =L40*0 -> 0 | ... Z41: =Z40*0 -> 0
B42: Engineering Included | C42: =0*(C40+C41) -> 0 | E42: =0*(E40+E41) -> 0 | F42: =0*(F40+F41) -> 0 | G42: =0*(G40+G41) -> 0 | H42: =0*(H40+H41) -> 0 | I42: =0*(I40+I41) -> 0 | J42: =0*(J40+J41) -> 0 | K42: =0*(K40+K41) -> 0 | L42: =0*(L40+L41) -> 0 | ... Z42: =0*(Z40+Z41) -> 0
C43: =SUM(C40:C42) -> 38434510 | E43: =SUM(E40:E42) -> 380000 | F43: =SUM(F40:F42) -> 8000000 | G43: =SUM(G40:G42) -> 3165000 | H43: =SUM(H40:H42) -> 2650000 | I43: =SUM(I40:I42) -> 2633510 | J43: =SUM(J40:J42) -> 1675000 | K43: =SUM(K40:K42) -> 1913000 | L43: =SUM(L40:L42) -> 2475000 | ... Z43: =SUM(Z40:Z42) -> 300000

Sheet OpCost
A2: =ModelDescription!A2 -> Economic Forecasting Model
A3: =ModelDescription!C4 -> Noble, OK 6 Processor Facility - Series A + Series B
B5: Monthly Operating Cost Estimate | C5: Actual | D5: Model | E5: $/Feed Ton
B6: Based on Actuals from Previous Plants
B7: Rubber lbs per day | C7: =C8*2000 -> 96000 | D7: =D8*2000 -> 96000
B8: Rubber tons per day | C8: =Assumptions!D47 -> 48 | D8: =C8 -> 48
B9: Rubber tons per month | C9: =C8*30 -> 1440 | D9: =D8*30 -> 1440
A12: EQUIPMENT EXPENSE | B12: Fuel | C12: 3500 | D12: =C12*(1+Assumptions!$D$43) -> 3850 | E12: =D12/D$9 -> 2.6736111
B13: Process Equip Maintenance | C13: 8000 | D13: =C13*(1+Assumptions!$D$43) -> 8800 | E13: =D13/D$9 -> 6.1111111
B14: Equipment Lease | C14: 0 | D14: =C14*(1+Assumptions!$D$43) -> 0 | E14: =D14/D$9 -> 0
B15: Tools | C15: 200 | D15: =C15*(1+Assumptions!$D$43) -> 220 | E15: =D15/D$9 -> 0.15277778
B16: Vehicles | C16: 1200 | D16: =C16*(1+Assumptions!$D$43) -> 1320 | E16: 0
A17: TRAVEL | B17: Ground Transport | C17: 400 | D17: =C17*(1+Assumptions!$D$43) -> 440 | E17: =D17/D$9 -> 0.30555556
B18: Airfare | C18: 1000 | D18: =C18*(1+Assumptions!$D$43) -> 1100 | E18: =D18/D$9 -> 0.76388889
B19: Lodging | C19: 1600 | D19: =C19*(1+Assumptions!$D$43) -> 1760 | E19: =D19/D$9 -> 1.2222222
B20: Meals/Entertainment | C20: 500 | D20: =C20*(1+Assumptions!$D$43) -> 550 | E20: =D20/D$9 -> 0.38194444
A21: MISC EXPENSES | B21: Product Packaging Carbon | C21: 10498.86 | D21: =C21*(1+Assumptions!$D$43) -> 11548.746 | E21: =D21/D$9 -> 8.0199625
B22: Plant Supplies | C22: 3500 | D22: =C22*(1+Assumptions!$D$43) -> 3850 | E22: =D22/D$9 -> 2.6736111
B23: Plant Office Supplies | C23: 900 | D23: =C23*(1+Assumptions!$D$43) -> 990 | E23: =D23/D$9 -> 0.6875
B24: Plant Shipping | C24: 450 | D24: =C24*(1+Assumptions!$D$43) -> 495 | E24: =D24/D$9 -> 0.34375
B25: State Compliance | C25: 3000 | D25: =C25*(1+Assumptions!$D$43) -> 3300 | E25: =D25/D$9 -> 2.2916667
B26: Plant Maintenance and Consumables | C26: 4875 | D26: =C26*(1+Assumptions!$D$43) -> 5362.5 | E26: =D26/D$9 -> 3.7239583
A27: INSURANCE | B27: General Liability Insurance | C27: 5000 | D27: =C27*(1+Assumptions!$D$43) -> 5500 | E27: =D27/D$9 -> 3.8194444
B28: Plant & Equipment Insurance | C28: 3000 | D28: =C28*(1+Assumptions!$D$43) -> 3300 | E28: =D28/D$9 -> 2.2916667
B29: Workers Comp | C29: 16616 | D29: =C29*(1+Assumptions!$D$43) -> 18277.6 | E29: =D29/D$9 -> 12.692778
B30: Pollution Insurnace | C30: 2000 | D30: =C30*(1+Assumptions!$D$43) -> 2200 | E30: =D30/D$9 -> 1.5277778
B31: Insurance - Vehicles | C31: 750 | D31: =C31*(1+Assumptions!$D$43) -> 825 | E31: =D31/D$9 -> 0.57291667
A32: PROFESSIONAL FEES | B32: 3rd Party Consulting | C32: 3000 | D32: =C32*(1+Assumptions!$D$43) -> 3300 | E32: =D32/D$9 -> 2.2916667
B33: Accounting | C33: 4000 | D33: =C33*(1+Assumptions!$D$43) -> 4400 | E33: =D33/D$9 -> 3.0555556
B34: Professional Fees/Dues | C34: 250 | D34: =C34*(1+Assumptions!$D$43) -> 275 | E34: =D34/D$9 -> 0.19097222
B35: Legal Expense | C35: 1500 | D35: =C35*(1+Assumptions!$D$43) -> 1650 | E35: =D35/D$9 -> 1.1458333
A36: Quality Control OFFICE | B36: IT Computer Support | C36: 3000 | D36: =C36*(1+Assumptions!$D$43) -> 3300 | E36: =D36/D$9 -> 2.2916667
B37: Office Supplies | C37: 600 | D37: =C37*(1+Assumptions!$D$43) -> 660 | E37: =D37/D$9 -> 0.45833333
B38: Contract Services | C38: 200 | D38: =C38*(1+Assumptions!$D$43) -> 220 | E38: =D38/D$9 -> 0.15277778
A39: TELEPHONE | B39: Cellular | C39: 600 | D39: =C39*(1+Assumptions!$D$43) -> 660 | E39: =D39/D$9 -> 0.45833333
B40: Local Phone | C40: 650 | D40: =C40*(1+Assumptions!$D$43) -> 715 | E40: =D40/D$9 -> 0.49652778
B41: Long Distance | C41: 500 | D41: =C41*(1+Assumptions!$D$43) -> 550 | E41: =D41/D$9 -> 0.38194444
A42: UTILITIES | B42: Gas | C42: 700 | D42: =C42*(1+Assumptions!$D$43) -> 770 | E42: =D42/D$9 -> 0.53472222
B43: Electricity | C43: 1400 | D43: =C43*(1+Assumptions!$D$43) -> 1540 | E43: =D43/D$9 -> 1.0694444
B44: Water | C44: 600 | D44: =C44*(1+Assumptions!$D$43) -> 660 | E44: =D44/D$9 -> 0.45833333

Sheet MthCashSum
A2: =ModelDescription!A2 -> Economic Forecasting Model
A3: =ModelDescription!C4 -> Noble, OK 6 Processor Facility - Series A + Series B
B5: Period | F5: =Assumptions!D76 -> 1 | G5: =Assumptions!E76 -> 2 | H5: =Assumptions!F76 -> 3 | I5: =Assumptions!G76 -> 4 | J5: =Assumptions!H76 -> 5 | K5: =Assumptions!I76 -> 6 | L5: =Assumptions!J76 -> 7 | M5: =Assumptions!K76 -> 8 | ... GC5: =Assumptions!GA76 -> 180
B6: Year | F6: =Assumptions!D77 -> 2026 | G6: =Assumptions!E77 -> 2026 | H6: =Assumptions!F77 -> 2026 | I6: =Assumptions!G77 -> 2026 | J6: =Assumptions!H77 -> 2026 | K6: =Assumptions!I77 -> 2026 | L6: =Assumptions!J77 -> 2026 | M6: =Assumptions!K77 -> 2026 | ... GC6: =Assumptions!GA77 -> 2040
B7: Month | F7: =Assumptions!D78 -> Jan | G7: =Assumptions!E78 -> Feb | H7: =Assumptions!F78 -> Mar | I7: =Assumptions!G78 -> Apr | J7: =Assumptions!H78 -> May | K7: =Assumptions!I78 -> Jun | L7: =Assumptions!J78 -> Jul | M7: =Assumptions!K78 -> Aug | ... GC7: =Assumptions!GA78 -> Dec
B8: Days | F8: =Assumptions!D80 -> 31 | G8: =Assumptions!E80 -> 28 | H8: =Assumptions!F80 -> 31 | I8: =Assumptions!G80 -> 30 | J8: =Assumptions!H80 -> 31 | K8: =Assumptions!I80 -> 30 | L8: =Assumptions!J80 -> 31 | M8: =Assumptions!K80 -> 31 | ... GC8: =Assumptions!GA80 -> 31
B9: Revenue | C9: R | E9: =SUM(F9:BM9) -> 95127828 | F9: =SUMPRODUCT((F$22:F$99)*($C$22:$C$99=$C9)) -> 0 | G9: =SUMPRODUCT((G$22:G$99)*($C$22:$C$99=$C9)) -> 0 | H9: =SUMPRODUCT((H$22:H$99)*($C$22:$C$99=$C9)) -> 0 | I9: =SUMPRODUCT((I$22:I$99)*($C$22:$C$99=$C9)) -> 0 | J9: =SUMPRODUCT((J$22:J$99)*($C$22:$C$99=$C9)) -> 0 | K9: =SUMPRODUCT((K$22:K$99)*($C$22:$C$99=$C9)) -> 0 | L9: =SUMPRODUCT((L$22:L$99)*($C$22:$C$99=$C9)) -> 0 | M9: =SUMPRODUCT((M$22:M$99)*($C$22:$C$99=$C9)) -> 1762387.2 | ... GC9: =SUMPRODUCT((GC$22:GC$99)*($C$22:$C$99=$C9)) -> 1829857.6
B10: Loan | C10: L | E10: =SUM(F10:BM10) -> 15000000 | F10: =SUMPRODUCT((F$22:F$99)*($C$22:$C$99=$C10)) -> 15000000 | G10: =SUMPRODUCT((G$22:G$99)*($C$22:$C$99=$C10)) -> 0 | H10: =SUMPRODUCT((H$22:H$99)*($C$22:$C$99=$C10)) -> 0 | I10: =SUMPRODUCT((I$22:I$99)*($C$22:$C$99=$C10)) -> 0 | J10: =SUMPRODUCT((J$22:J$99)*($C$22:$C$99=$C10)) -> 0 | K10: =SUMPRODUCT((K$22:K$99)*($C$22:$C$99=$C10)) -> 0 | L10: =SUMPRODUCT((L$22:L$99)*($C$22:$C$99=$C10)) -> 0 | M10: =SUMPRODUCT((M$22:M$99)*($C$22:$C$99=$C10)) -> 0 | ... GC10: =SUMPRODUCT((GC$22:GC$99)*($C$22:$C$99=$C10)) -> 0
B11: Costs | C11: C | E11: =SUM(F11:BM11) -> 33896207 | F11: =SUMPRODUCT((F$22:F$99)*($C$22:$C$99=$C11)) -> 0 | G11: =SUMPRODUCT((G$22:G$99)*($C$22:$C$99=$C11)) -> 0 | H11: =SUMPRODUCT((H$22:H$99)*($C$22:$C$99=$C11)) -> 0 | I11: =SUMPRODUCT((I$22:I$99)*($C$22:$C$99=$C11)) -> 0 | J11: =SUMPRODUCT((J$22:J$99)*($C$22:$C$99=$C11)) -> 0 | K11: =SUMPRODUCT((K$22:K$99)*($C$22:$C$99=$C11)) -> 0 | L11: =SUMPRODUCT((L$22:L$99)*($C$22:$C$99=$C11)) -> 0 | M11: =SUMPRODUCT((M$22:M$99)*($C$22:$C$99=$C11)) -> 651421.46 | ... GC11: =SUMPRODUCT((GC$22:GC$99)*($C$22:$C$99=$C11)) -> 651421.46
B12: Business Overhead | C12: O | E12: =SUM(F12:BM12) -> 5587146.3 | F12: =SUMPRODUCT((F$22:F$99)*($C$22:$C$99=$C12)) -> 0 | G12: =SUMPRODUCT((G$22:G$99)*($C$22:$C$99=$C12)) -> 0 | H12: =SUMPRODUCT((H$22:H$99)*($C$22:$C$99=$C12)) -> 0 | I12: =SUMPRODUCT((I$22:I$99)*($C$22:$C$99=$C12)) -> 0 | J12: =SUMPRODUCT((J$22:J$99)*($C$22:$C$99=$C12)) -> 0 | K12: =SUMPRODUCT((K$22:K$99)*($C$22:$C$99=$C12)) -> 0 | L12: =SUMPRODUCT((L$22:L$99)*($C$22:$C$99=$C12)) -> 0 | M12: =SUMPRODUCT((M$22:M$99)*($C$22:$C$99=$C12)) -> 106266.3 | ... GC12: =SUMPRODUCT((GC$22:GC$99)*($C$22:$C$99=$C12)) -> 106266.3
B13: Investment Capital | C13: CAP | E13: =SUM(F13:BM13) -> 15843457 | F13: =SUMPRODUCT((F$22:F$99)*($C$22:$C$99=$C13)) -> 6697158.3 | G13: =SUMPRODUCT((G$22:G$99)*($C$22:$C$99=$C13)) -> 3337788.9 | H13: =SUMPRODUCT((H$22:H$101)*($C$22:$C$101=$C13)) -> 3077158.3 | I13: =SUMPRODUCT((I$22:I$101)*($C$22:$C$101=$C13)) -> 735585.86 | J13: =SUMPRODUCT((J$22:J$101)*($C$22:$C$101=$C13)) -> 398442.91 | K13: =SUMPRODUCT((K$22:K$101)*($C$22:$C$101=$C13)) -> 553103.08 | L13: =SUMPRODUCT((L$22:L$101)*($C$22:$C$101=$C13)) -> 510109.58 | M13: =SUMPRODUCT((M$22:M$101)*($C$22:$C$101=$C13)) -> 510109.58 | N13: =SUMPRODUCT((N$22:N$101)*($C$22:$C$101=$C13)) -> 6000 | O13: =SUMPRODUCT((O$22:O$101)*($C$22:$C$101=$C13)) -> 6000 | ... GC13: =SUMPRODUCT((GC$22:GC$101)*($C$22:$C$101=$C13)) -> 0
B14: Loan Payment | C14: LP | E14: =SUM(F14:BM14) -> 0 | F14: =SUMPRODUCT((F$22:F$99)*($C$22:$C$99=$C14)) -> 0 | G14: =SUMPRODUCT((G$22:G$99)*($C$22:$C$99=$C14)) -> 0 | H14: =SUMPRODUCT((H$22:H$101)*($C$22:$C$101=$C14)) -> 0 | I14: =SUMPRODUCT((I$22:I$101)*($C$22:$C$101=$C14)) -> 0 | J14: =SUMPRODUCT((J$22:J$101)*($C$22:$C$101=$C14)) -> 0 | K14: =SUMPRODUCT((K$22:K$101)*($C$22:$C$101=$C14)) -> 0 | L14: =SUMPRODUCT((L$22:L$101)*($C$22:$C$101=$C14)) -> 0 | M14: =SUMPRODUCT((M$22:M$101)*($C$22:$C$101=$C14)) -> 0 | N14: =SUMPRODUCT((N$22:N$101)*($C$22:$C$101=$C14)) -> 0 | O14: =SUMPRODUCT((O$22:O$101)*($C$22:$C$101=$C14)) -> 0 | ... GC14: =SUMPRODUCT((GC$22:GC$101)*($C$22:$C$101=$C14)) -> 0
B15: Depreciation | C15: DEP | E15: =SUM(F15:BM15) -> 4243665.2 | F15: =SUMPRODUCT((F$22:F$99)*($C$22:$C$99=$C15)) -> 0 | G15: =SUMPRODUCT((G$22:G$99)*($C$22:$C$99=$C15)) -> 0 | H15: =SUMPRODUCT((H$22:H$101)*($C$22:$C$101=$C15)) -> 0 | I15: =SUMPRODUCT((I$22:I$101)*($C$22:$C$101=$C15)) -> 0 | J15: =SUMPRODUCT((J$22:J$101)*($C$22:$C$101=$C15)) -> 0 | K15: =SUMPRODUCT((K$22:K$101)*($C$22:$C$101=$C15)) -> 0 | L15: =SUMPRODUCT((L$22:L$101)*($C$22:$C$101=$C15)) -> 0 | M15: =SUMPRODUCT((M$22:M$101)*($C$22:$C$101=$C15)) -> 0 | N15: =SUMPRODUCT((N$22:N$101)*($C$22:$C$101=$C15)) -> 4685.8699 | O15: =SUMPRODUCT((O$22:O$101)*($C$22:$C$101=$C15)) -> 4685.8699 | ... GC15: =SUMPRODUCT((GC$22:GC$101)*($C$22:$C$101=$C15)) -> 88019.203
B16: Taxes | C16: =WACC!C18 -> 0.21 | E16: =SUM(F16:BM16) -> -12576509 | F16: =IF(F9<=0,0,-(F9-F11-F12+F15)*$C16) -> 0 | G16: =IF(G9<=0,0,-(G9-G11-G12+G15)*$C16) -> 0 | H16: =IF(H9<=0,0,-(H9-H11-H12+H15)*$C16) -> 0 | I16: =IF(I9<=0,0,-(I9-I11-I12+I15)*$C16) -> 0 | J16: =IF(J9<=0,0,-(J9-J11-J12+J15)*$C16) -> 0 | K16: =IF(K9<=0,0,-(K9-K11-K12+K15)*$C16) -> 0 | L16: =IF(L9<=0,0,-(L9-L11-L12+L15)*$C16) -> 0 | M16: =IF(M9<=0,0,-(M9-M11-M12+M15)*$C16) -> -210986.88 | ... GC16: =IF(GC9<=0,0,-(GC9-GC11-GC12+GC15)*$C16) -> -243639.69
B17: Working Capital | C17: 0.15 | F17: =$C17*(F9) -> 0 | G17: =$C17*(F9-G9) -> 0 | H17: =$C17*(G9-H9) -> 0 | I17: =$C17*(H9-I9) -> 0 | J17: =$C17*(I9-J9) -> 0 | K17: =$C17*(J9-K9) -> 0 | L17: =$C17*(K9-L9) -> 0 | M17: =$C17*(L9-M9) -> -264358.08 | N17: =$C17*(M9-N9) -> 1182.1146 | ... GC17: =$C17*(GB9-GC9) -> -8854.1496
B18: Cash Flow | F18: =SUM(F9:F10)-SUM(F11:F14)+F16+F17 -> 8302841.7 | G18: =SUM(G9:G10)-SUM(G11:G14)+G16+G17 -> -3337788.9 | H18: =SUM(H9:H10)-SUM(H11:H14)+H16+H17 -> -3077158.3 | I18: =SUM(I9:I10)-SUM(I11:I14)+I16+I17 -> -735585.86 | J18: =SUM(J9:J10)-SUM(J11:J14)+J16+J17 -> -398442.91 | K18: =SUM(K9:K10)-SUM(K11:K14)+K16+K17 -> -553103.08 | L18: =SUM(L9:L10)-SUM(L11:L14)+L16+L17 -> -510109.58 | M18: =SUM(M9:M10)-SUM(M11:M14)+M16+M17 -> 19244.9 | ... GC18: =SUM(GC9:GC10)-SUM(GC11:GC14)+GC16+GC17 -> 819675.98
B19: Cumulative Cash Flow | F19: =E19+F18 -> 8302841.7 | G19: =F19+G18 -> 4965052.8 | H19: =G19+H18 -> 1887894.4 | I19: =H19+I18 -> 1152308.6 | J19: =I19+J18 -> 753865.66 | K19: =J19+K18 -> 200762.58 | L19: =K19+L18 -> -309347 | M19: =L19+M18 -> -290102.1 | ... GC19: =GB19+GC18 -> 1.39352e+08
A23: TiPs1000 Plants
B24: Revenue | C24: R | E24: =SUM(F24:BM24) -> 95127828 | F24: =Proforma!F9 -> 0 | G24: =Proforma!G9 -> 0 | H24: =Proforma!H9 -> 0 | I24: =Proforma!I9 -> 0 | J24: =Proforma!J9 -> 0 | K24: =Proforma!K9 -> 0 | L24: =Proforma!L9 -> 0 | M24: =Proforma!M9 -> 1762387.2 | ... GC24: =Proforma!GC9 -> 1829857.6
B25: Capital Investment | C25: L | E25: =SUM(F25:BM25) -> 15000000 | F25: =Proforma!F10 -> 15000000 | G25: =Proforma!G10 -> 0 | H25: =Proforma!H10 -> 0 | I25: =Proforma!I10 -> 0 | J25: =Proforma!J10 -> 0 | K25: =Proforma!K10 -> 0 | L25: =Proforma!L10 -> 0 | M25: =Proforma!M10 -> 0 | ... GC25: =Proforma!GC10 -> 0
B26: Costs | C26: C | E26: =SUM(F26:BM26) -> 33896207 | F26: =Proforma!F11 -> 0 | G26: =Proforma!G11 -> 0 | H26: =Proforma!H11 -> 0 | I26: =Proforma!I11 -> 0 | J26: =Proforma!J11 -> 0 | K26: =Proforma!K11 -> 0 | L26: =Proforma!L11 -> 0 | M26: =Proforma!M11 -> 651421.46 | ... GC26: =Proforma!GC11 -> 651421.46
B27: Business Overhead | C27: O | E27: =SUM(F27:BM27) -> 5587146.3 | F27: =Proforma!F12 -> 0 | G27: =Proforma!G12 -> 0 | H27: =Proforma!H12 -> 0 | I27: =Proforma!I12 -> 0 | J27: =Proforma!J12 -> 0 | K27: =Proforma!K12 -> 0 | L27: =Proforma!L12 -> 0 | M27: =Proforma!M12 -> 106266.3 | ... GC27: =Proforma!GC12 -> 106266.3
B28: Investment Capital | C28: CAP | E28: =SUM(F28:BM28) -> 15843457 | F28: =Proforma!F13 -> 6697158.3 | G28: =Proforma!G13 -> 3337788.9 | H28: =Proforma!H13 -> 3077158.3 | I28: =Proforma!I13 -> 735585.86 | J28: =Proforma!J13 -> 398442.91 | K28: =Proforma!K13 -> 553103.08 | L28: =Proforma!L13 -> 510109.58 | M28: =Proforma!M13 -> 510109.58 | ... GC28: =Proforma!GC13 -> 0
B29: Loan Payment | C29: LP | E29: =SUM(F29:BM29) -> 0 | F29: =Proforma!F14 -> 0 | G29: =Proforma!G14 -> 0 | H29: =Proforma!H14 -> 0 | I29: =Proforma!I14 -> 0 | J29: =Proforma!J14 -> 0 | K29: =Proforma!K14 -> 0 | L29: =Proforma!L14 -> 0 | M29: =Proforma!M14 -> 0 | ... GC29: =Proforma!GC14 -> 0
B30: Depreciation | C30: DEP | E30: =SUM(F30:BM30) -> 4243665.2 | F30: =Proforma!F15 -> 0 | G30: =Proforma!G15 -> 0 | H30: =Proforma!H15 -> 0 | I30: =Proforma!I15 -> 0 | J30: =Proforma!J15 -> 0 | K30: =Proforma!K15 -> 0 | L30: =Proforma!L15 -> 0 | M30: =Proforma!M15 -> 0 | ... GC30: =Proforma!GC15 -> 88019.203

Sheet Graphs - HIDE
A2: =ModelDescription!A2 -> Economic Forecasting Model
A3: =ModelDescription!C4 -> Noble, OK 6 Processor Facility - Series A + Series B
A5: Monthly Cash Flow
A23: Tire Oil Production (bbls)
B41: Period | F41: =Assumptions!D76 -> 1 | G41: =Assumptions!E76 -> 2 | H41: =Assumptions!F76 -> 3 | I41: =Assumptions!G76 -> 4 | J41: =Assumptions!H76 -> 5 | K41: =Assumptions!I76 -> 6 | L41: =Assumptions!J76 -> 7 | M41: =Assumptions!K76 -> 8 | ... BL41: =Assumptions!BJ76 -> 59 | BM41: c | BN41: =Assumptions!BL76 -> 61 | BO41: =Assumptions!BM76 -> 62 | BP41: =Assumptions!BN76 -> 63 | BQ41: =Assumptions!BO76 -> 64 | BR41: =Assumptions!BP76 -> 65 | BS41: =Assumptions!BQ76 -> 66 | BT41: =Assumptions!BR76 -> 67 | BU41: =Assumptions!BS76 -> 68 | ... GC41: =Assumptions!GA76 -> 180
B42: Year | F42: =Assumptions!D77 -> 2026 | G42: =Assumptions!E77 -> 2026 | H42: =Assumptions!F77 -> 2026 | I42: =Assumptions!G77 -> 2026 | J42: =Assumptions!H77 -> 2026 | K42: =Assumptions!I77 -> 2026 | L42: =Assumptions!J77 -> 2026 | M42: =Assumptions!K77 -> 2026 | ... GC42: =Assumptions!GA77 -> 2040
B43: Month | F43: =Assumptions!D78 -> Jan | G43: =Assumptions!E78 -> Feb | H43: =Assumptions!F78 -> Mar | I43: =Assumptions!G78 -> Apr | J43: =Assumptions!H78 -> May | K43: =Assumptions!I78 -> Jun | L43: =Assumptions!J78 -> Jul | M43: =Assumptions!K78 -> Aug | ... GC43: =Assumptions!GA78 -> Dec
B44: Day | F44: =Assumptions!D80 -> 31 | G44: =Assumptions!E80 -> 28 | H44: =Assumptions!F80 -> 31 | I44: =Assumptions!G80 -> 30 | J44: =Assumptions!H80 -> 31 | K44: =Assumptions!I80 -> 30 | L44: =Assumptions!J80 -> 31 | M44: =Assumptions!K80 -> 31 | ... GC44: =Assumptions!GA80 -> 31
A46: Tire Oil Production
B47: TiPs Plants (gallons) | E47: =SUM(F47:GC47) -> 606297.6 | F47: =Proforma!F165 -> 0 | G47: =Proforma!G165 -> 0 | H47: =Proforma!H165 -> 0 | I47: =Proforma!I165 -> 0 | J47: =Proforma!J165 -> 0 | K47: =Proforma!K165 -> 0 | L47: =Proforma!L165 -> 0 | M47: =Proforma!M165 -> 3571.2 | ... GC47: =Proforma!GC165 -> 3571.2
